Workbook
Name data: #REF!
Name rapel: #REF!
Name Slicer_APPLICATION_YEAR: #N/A
Name Slicer_Kategori_Sumber_Dana: #N/A
Name Slicer_Kategori_Sumber_Dana1: #N/A
Name Slicer_Prodi1: #N/A
Name Slicer_Prodi21: #N/A
Name Slicer_Prodi51: #N/A
Name Slicer_Prodi81: #N/A
Name Slicer_Tahun_Usulan: #N/A
Name Slicer_Tahun_Usulan1: #N/A

Sheet Dashboard_Pengmas_08082024
A1: Kategori Sumber Dana | B1: (All)
A2: Tahun Usulan | B2: 2023
A4: Tahun/Nama Skema | B4: Total
A5: Pengmas penugasan | B5: 1
A6: pkm reguler | B6: 1
A7: Grand Total | B7: 2

Sheet Dashboard_penelitian_08082024
A2: Sumber Dana | B2: (All)
A3: Kategori Sumber Dana | B3: Internal
A5: Tahun / Skema Penelitian | B5: Sum of Tahun Usulan
A6: Penelitian Dasar | B6: 2021
A7: Rizqa Amelia Zunaidi | B7: 2021
A8: Penelitian Dana Internal (PDI) | B8: 62603
A9: Abduh Sayid Albana | B9: 2019
A10: Bernadus Anggo Seno Aji | B10: 2019
A11: Billy Montolalu | B11: 2019
A12: Dewi Rahmawati | B12: 4039
A13: Dimas Adiputra | B13: 4039
A14: Dominggo Bayu Baskara | B14: 2020
A15: Dwi Edi Setyawan | B15: 2019
A16: Farah Zakiyah Rahmanti | B16: 4039
A17: Hamzah Ulinuha Mustakim | B17: 2019
... A259: Grand Total | B259: 513678

Sheet Data Sitasi Scopus
A1: Citation Per Researchers Scopus Per September 2024 | J1: Citation Per Researchers Scopus Tahun 2024
A3: No | B3: NAMA | C3: NAMA DEPAN | D3: NAMA TENGAH | E3: NAMA BELAKANG | F3: PRODI | G3: FAKULTAS | H3: Sitasi | J3: No. | K3: Nama Lengkap | L3: Program Studi | M3: Sitasi Scopus | N3: Afiliasi
A4: 1 | B4: Dwi Edi Setyawan | C4: Dwi | D4: Edi | E4: Setyawan | F4: Teknik Komputer | G4: Fakultas Teknik Elektro | H4: 9 | J4: 1 | K4: Tri Agus Djoko Kuntjoro | L4: Teknik Telekomunikasi | M4: 0
A5: 2 | B5: Moch. Iskandar Riansyah | C5: Moch. | D5: Iskandar | E5: Riansyah | F5: Teknik Elektro | G5: Fakultas Teknik Elektro | H5: 10 | J5: 2 | K5: Dwi Edi Setyawan | L5: Teknik Komputer | M5: 10
A6: 3 | B6: Khodijah Amiroh | C6: Khodijah | D6: Amiroh | F6: Teknologi Informasi | G6: Fakultas Informatika | H6: 4 | J6: 3 | K6: Moch. Iskandar Riansyah | L6: Teknik Elektro | M6: 11
A7: 4 | B7: Dimas Adiputra | C7: Dimas | D7: Adiputra | F7: Teknik Elektro | G7: Fakultas Teknik Elektro | H7: 197 | J7: 4 | K7: Khodijah Amiroh | L7: Teknologi Informasi | M7: 7
A8: 5 | B8: Isa Hafidz | C8: Isa | D8: Hafidz | F8: Teknik Elektro | G8: Fakultas Teknik Elektro | H8: 51 | J8: 5 | K8: Dimas Adiputra | L8: Teknik Elektro | M8: 209
A9: 6 | B9: Walid Maulana Hadiansyah | C9: Walid | D9: Maulana | E9: Hadiansyah | F9: Teknik Telekomunikasi | G9: Fakultas Teknik Elektro | H9: 17 | J9: 6 | K9: Isa Hafidz | L9: Teknik Elektro | M9: 58
A10: 7 | B10: Farah Zakiyah Rahmanti | C10: Farah | D10: Zakiyah | E10: Rahmanti | F10: Teknologi Informasi | G10: Fakultas Informatika | H10: 72 | J10: 7 | K10: Walid Maulana Hadiansyah | L10: Teknik Telekomunikasi | M10: 17 | N10: Institut Teknologi Sepuluh Nopember
A11: 8 | B11: Helmy Widyantara | C11: Helmy | D11: Widyantara | F11: Teknologi Informasi | G11: Fakultas Informatika | H11: 38 | J11: 8 | K11: Farah Zakiyah Rahmanti | L11: Teknologi Informasi | M11: 75
A12: 9 | B12: Wahyu Andy Prastyabudi | C12: Wahyu | D12: Andy | E12: Prastyabudi | F12: Teknik Industri | G12: Fakultas Rekayasa Industri | H12: 10 | J12: 9 | K12: Helmy Widyantara | L12: Teknologi Informasi | M12: 39
A13: 10 | B13: Fidi Wincoko Putro | C13: Fidi | D13: Wincoko | E13: Putro | F13: RPL | G13: Fakultas Informatika | H13: 0 | J13: 10 | K13: Wahyu Andy Prastyabudi | L13: Teknik Industri | M13: 13
A14: 11 | B14: Philip Tobianto Daely | C14: Philip | D14: Tobianto | E14: Daely | F14: Teknologi Informasi | G14: Fakultas Informatika | H14: 287 | J14: 11 | K14: Fidi Wincoko Putro | L14: Rekayasa Perangkat Lunak | N14: Tidak ada
A15: 12 | B15: Anifatul Faricha | C15: Anifatul | D15: Faricha | F15: Teknik Elektro | G15: Fakultas Teknik Elektro | H15: 86 | J15: 12 | K15: Philip Tobianto Daely | L15: Teknologi Informasi | M15: 287
A16: 13 | B16: Mohammad Sholik | C16: Mohammad | D16: Sholik | F16: RPL | G16: Fakultas Informatika | H16: 2 | J16: 13 | K16: Anifatul Faricha | L16: Teknik Elektro | M16: 91
A17: 14 | B17: Anfazul Faridatul Azizah | C17: Anfazul | D17: Faridatul | E17: Azizah | F17: Sistem Informasi | G17: Fakultas Rekayasa Industri | H17: 0 | J17: 14 | K17: Mohammad Sholik | L17: Rekayasa Perangkat Lunak | M17: 3
A18: 15 | B18: Hamzah Ulinuha Mustakim | C18: Hamzah | D18: Ulinuha | E18: Mustakim | F18: Teknik Telekomunikasi | G18: Fakultas Teknik Elektro | H18: 1 | J18: 15 | K18: Anfazul Faridatul Azizah | L18: Sistem Informasi | M18: 1 | N18: Institut Teknologi Sepuluh Nopember
A19: 16 | B19: Mohamad Yani | C19: Mohamad | D19: Yani | F19: Teknik Komputer | G19: Fakultas Teknik Elektro | H19: 14 | J19: 16 | K19: Hamzah Ulinuha Mustakim | L19: Teknik Telekomunikasi | M19: 1
A20: 17 | B20: Muhsin | C20: Muhsin | F20: Teknik Telekomunikasi | G20: Fakultas Teknik Elektro | H20: 35 | J20: 17 | K20: Mohamad Yani | L20: Teknik Komputer | M20: 14
A21: 18 | B21: Nilla Rachmaningrum | C21: Nilla | D21: Rachmaningrum | F21: Teknik Telekomunikasi | G21: Fakultas Teknik Elektro | H21: 1 | J21: 18 | K21: Muhsin | L21: Teknik Telekomunikasi | M21: 36
A22: 19 | B22: Noerma Pudji Istyanto | C22: Noerma | D22: Pudji | E22: Istyanto | F22: Sistem Informasi | G22: Fakultas Rekayasa Industri | H22: 0 | J22: 19 | K22: Nilla Rachmaningrum | L22: Teknik Telekomunikasi | M22: 1
A23: 20 | B23: Lora Khaula Amifia | C23: Lora | D23: Khaula | E23: Amifia | F23: Teknik Elektro | G23: Fakultas Teknik Elektro | H23: 16 | J23: 20 | K23: Noerma Pudji Istyanto | L23: Sistem Informasi | M23: 0
A24: 21 | B24: Ully Asfari | C24: Ully | D24: Asfari | F24: Sistem Informasi | G24: Fakultas Rekayasa Industri | H24: 57 | J24: 21 | K24: Lora Khaula Amifia | L24: Teknik Elektro | M24: 16
A25: 22 | B25: Ubaidillah Umar | C25: Ubaidillah | D25: Umar | F25: Teknik Komputer | G25: Fakultas Teknik Elektro | H25: 14 | J25: 22 | K25: Ully Asfari | L25: Sistem Informasi | M25: 73
A26: 23 | B26: Oktavia Ayu Permata | C26: Oktavia | D26: Ayu | E26: Permata | F26: Teknologi Informasi | G26: Fakultas Informatika | H26: 1 | J26: 23 | K26: Ubaidillah Umar | L26: Teknik Komputer | M26: 16
A27: 24 | B27: Dominggo Bayu Baskara | C27: Dominggo | D27: Bayu | E27: Baskara | F27: Digital Bisnis | G27: Fakultas Ekonomi dan Bisnis | H27: 2 | J27: 24 | K27: Oktavia Ayu Permata | L27: Teknologi Informasi | M27: 2
A28: 25 | B28: Billy Montolalu | C28: Billy | D28: Montolalu | F28: RPL | G28: Fakultas Informatika | H28: 11 | J28: 25 | K28: Dominggo Bayu Baskara | L28: Digital Bisnis | N28: Tidak ada
A29: 26 | B29: Yupit Sudianto | C29: Yupit | D29: Sudianto | F29: Sistem Informasi | G29: Fakultas Rekayasa Industri | H29: 0 | J29: 26 | K29: Billy Montolalu | L29: Rekayasa Perangkat Lunak | M29: 11
A30: 27 | B30: Dewi Rahmawati | C30: Dewi | D30: Rahmawati | F30: RPL | G30: Fakultas Informatika | H30: 120 | J30: 27 | K30: Yupit Sudianto | L30: Sistem Informasi | M30: 0
A31: 28 | B31: Ardiansyah Al Farouq | C31: Ardiansyah | D31: Al | E31: Farouq | F31: Teknik Komputer | G31: Fakultas Teknik Elektro | H31: 17 | J31: 28 | K31: Dewi Rahmawati | L31: Rekayasa Perangkat Lunak | M31: 139
A32: 29 | B32: Ardian Yusuf Wicaksono | C32: Ardian | D32: Yusuf | E32: Wicaksono | F32: Informatika | G32: Fakultas Informatika | H32: 35 | J32: 29 | K32: Ardiansyah Al Farouq | L32: Teknik Komputer | M32: 17
A33: 30 | B33: Rahaditya Dimas Prihadianto | C33: Rahaditya | D33: Dimas | E33: Prihadianto | F33: Teknik Industri | G33: Fakultas Rekayasa Industri | H33: 3 | J33: 30 | K33: Ardian Yusuf Wicaksono | L33: Informatika | M33: 35
A34: 31 | B34: Rizqa Amelia Zunaidi | C34: Rizqa | D34: Amelia | E34: Zunaidi | F34: Teknik Industri | G34: Fakultas Rekayasa Industri | H34: 4 | J34: 31 | K34: Rahaditya Dimas Prihadianto | L34: Teknik Industri | M34: 3 | N34: Institut Teknologi Sepuluh Nopember
A35: 32 | B35: Titus Kristanto | C35: Titus | D35: Kristanto | F35: Digital Bisnis | G35: Fakultas Ekonomi dan Bisnis | H35: 27 | J35: 32 | K35: Rizqa Amelia Zunaidi | L35: Teknik Industri | M35: 7
A36: 33 | B36: Pangestu Widodo | C36: Pangestu | D36: Widodo | F36: Teknik Komputer | G36: Fakultas Teknik Elektro | H36: 0 | J36: 33 | K36: Titus Kristanto | L36: Digital Bisnis | M36: 28
A37: 34 | B37: Abduh Sayid Albana | C37: Abduh | D37: Sayid | E37: Albana | F37: Teknik Logistik | G37: Fakultas Rekayasa Industri | H37: 68 | J37: 34 | K37: Pangestu Widodo | L37: Teknik Komputer | M37: 0
A38: 35 | B38: Hawwin Mardhiana | C38: Hawwin | D38: Mardhiana | F38: Sistem Informasi | G38: Fakultas Rekayasa Industri | H38: 4 | J38: 35 | K38: Abduh Sayid Albana | L38: Teknik Logistik | M38: 69
A39: 36 | B39: Benazir Imam Arif Muttaqin | C39: Benazir | D39: Imam | E39: Muttaqin | F39: Teknik Industri | G39: Fakultas Rekayasa Industri | H39: 16 | J39: 36 | K39: Hawwin Mardhiana | L39: Sistem Informasi | M39: 4
A40: 37 | B40: Bernadus Anggo Seno Aji | C40: Bernadus | D40: Anggo | E40: Aji | F40: Teknologi Informasi | G40: Fakultas Informatika | H40: 9 | J40: 37 | K40: Benazir Imam Arif Muttaqin | L40: Teknik Industri | M40: 20
A41: 38 | B41: Rokhmatul Insani | C41: Rokhmatul | D41: Insani | F41: Sistem Informasi | G41: Fakultas Rekayasa Industri | H41: 7 | J41: 38 | K41: Bernadus Anggo Seno Aji | L41: Teknologi Informasi | M41: 10
A42: 39 | B42: Risdilah Mimma Untsa | C42: Risdilah | D42: Mimma | E42: Untsa | F42: Teknik Telekomunikasi | G42: Fakultas Teknik Elektro | H42: 0 | J42: 39 | K42: Rokhmatul Insani | L42: Sistem Informasi | M42: 7 | N42: Institut Teknologi Bandung
A43: 40 | B43: Susijanto Tri Rasmana | C43: Susijanto | D43: Tri | E43: Rasmana | F43: Teknik Elektro | G43: Fakultas Teknik Elektro | H43: 8 | J43: 40 | K43: Agus Sulistya | L43: Sistem Informasi | N43: perbantuan
A44: 41 | B44: Ayu Endah Wahyuni | C44: Ayu | D44: Endah | E44: Wahyuni | F44: Teknik Industri | G44: Fakultas Rekayasa Industri | H44: 0 | J44: 41 | K44: Risdilah Mimma Untsa | L44: Teknik Telekomunikasi | M44: 0
A45: 42 | B45: Muhamad Nasrullah | C45: Muhamad | D45: Nasrullah | F45: Sistem Informasi | G45: Fakultas Rekayasa Industri | H45: 0 | J45: 42 | K45: Susijanto Tri Rasmana | L45: Teknik Elektro | N45: Tidak ada
A46: 43 | B46: Sekar Widyasari Putri | C46: Sekar | D46: Widyasari | E46: Putri | F46: Digital Bisnis | G46: Fakultas Ekonomi dan Bisnis | H46: 0 | J46: 43 | K46: Ayu Endah Wahyuni | L46: Teknik Industri | N46: Faculty of Engineering
A47: 44 | B47: Ahmad Wali Satria Bahari Johan | C47: Ahmad | D47: Wali | E47: Johan | F47: Informatika | G47: Fakultas Informatika | H47: 26 | J47: 44 | K47: Muhamad Nasrullah | L47: Sistem Informasi | N47: Tidak ada
A48: 45 | B48: Muhammad Dzulfikar Fauzi | C48: Muhammad | D48: Dzulfikar | E48: Fauzi | F48: Informatika | G48: Fakultas Informatika | H48: 4 | J48: 45 | K48: Sekar Widyasari Putri | L48: Digital Bisnis | N48: Tidak ada
A49: 46 | B49: Kharisma Monika Dian Pertiwi | C49: Kharisma | D49: Monika | E49: Pertiwi | F49: Informatika | G49: Fakultas Informatika | H49: 6 | J49: 46 | K49: Ahmad Wali Satria Bahari Johan | L49: Informatika | M49: 28
A50: 47 | B50: Rizky Fenaldo Maulana | C50: Rizky | D50: Fenaldo | E50: Maulana | F50: Informatika | G50: Fakultas Informatika | H50: 0 | J50: 47 | K50: Muhammad Dzulfikar Fauzi | L50: Informatika | M50: 6
A51: 48 | B51: Amalia Nur Alifah | C51: Amalia | D51: Nur | E51: Alifah | F51: Sains Data | G51: Fakultas Informatika | H51: 7 | J51: 48 | K51: Kharisma Monika Dian Pertiwi | L51: Informatika | M51: 6 | N51: Institut Teknologi Sepuluh Nopember
A52: 49 | B52: Helisyah Nur Fadhilah | C52: Helisyah | D52: Nur | E52: Fadhilah | F52: Sains Data | G52: Fakultas Informatika | H52: 15 | J52: 49 | K52: Rizky Fenaldo Maulana | L52: Informatika | N52: Tidak ada
A53: 50 | B53: Moh. Hamim Zajuli Al Faroby | C53: Moh. | D53: Hamim | E53: Al Faroby | F53: Sains Data | G53: Fakultas Informatika | H53: 1 | J53: 50 | K53: Amalia Nur Alifah | L53: Sains Data | M53: 7
A54: 51 | B54: Desita Nur Rachmaniar | C54: Desita | D54: Nur | E54: Rachmaniar | F54: Teknik Logistik | G54: Fakultas Rekayasa Industri | H54: 0 | J54: 51 | K54: Helisyah Nur Fadhilah | L54: Sains Data | M54: 16
A55: 52 | B55: Granita Hajar | C55: Granita | D55: Hajar | F55: Teknik Logistik | G55: Fakultas Rekayasa Industri | H55: 12 | J55: 52 | K55: Moh. Hamim Zajuli Al Faroby | L55: Sains Data | N55: Tidak ada
A56: 53 | B56: Nisa Isrofi | C56: Nisa | D56: Isrofi | F56: Teknik Logistik | G56: Fakultas Rekayasa Industri | H56: 1 | J56: 53 | K56: Desita Nur Rachmaniar | L56: Teknik Logistik | N56: Tidak ada
A57: 54 | B57: Fannush Shofi Akbar | C57: Fannush | D57: Shofi | E57: Akbar | F57: Teknik Telekomunikasi | G57: Fakultas Teknik Elektro | H57: 39 | J57: 54 | K57: Granita Hajar | L57: Teknik Logistik | M57: 13 | N57: Institut Teknologi Sepuluh Nopember
A58: 55 | B58: Aulia Rahma Annisa | C58: Aulia | D58: Rahma | E58: Annisa | F58: Teknik Komputer | G58: Fakultas Teknik Elektro | H58: 30 | J58: 55 | K58: Nisa Isrofi | L58: Teknik Logistik | M58: 1
A59: 56 | B59: Aris Kusumawati | C59: Aris | D59: Kusumawati | F59: Sistem Informasi | G59: Fakultas Rekayasa Industri | H59: 0 | J59: 56 | K59: Fannush Shofi Akbar | L59: Teknik Telekomunikasi | M59: 42
A60: 57 | B60: Mochamad Nizar Palefi Ma'ady | C60: Mochamad | D60: Nizar | E60: Ma'ady | F60: Sistem Informasi | G60: Fakultas Rekayasa Industri | H60: 13 | J60: 57 | K60: Aris Kusumawati | L60: Sistem Informasi | M60: 0
A61: 58 | B61: Purnama Anaking | C61: Purnama | D61: Anaking | F61: Sistem Informasi | G61: Fakultas Rekayasa Industri | H61: 1 | J61: 58 | K61: Mochamad Nizar Palefi Ma'ady | L61: Sistem Informasi | M61: 15
A62: 59 | B62: Arrizky Ayu Faradila Purnama | C62: Arrizky | D62: Ayu | E62: Purnama | F62: Teknik Telekomunikasi | G62: Fakultas Teknik Elektro | H62: 39 | J62: 59 | K62: Purnama Anaking | L62: Sistem Informasi | M62: 1
A63: 60 | B63: Regita Putri Permata | C63: Regita | D63: Putri | E63: Permata | F63: Sains Data | G63: Fakultas Informatika | H63: 12 | J63: 60 | K63: Arrizky Ayu Faradila Purnama | L63: Teknik Telekomunikasi | M63: 41
A64: 61 | B64: Rifdatun Ni'mah | C64: Rifdatun | D64: Ni'mah | F64: Sains Data | G64: Fakultas Informatika | H64: 0 | J64: 61 | K64: Regita Putri Permata | L64: Sains Data | M64: 14
A65: 62 | B65: Muhammad Adib Kamali | C65: Muhammad | D65: Adib | E65: Kamali | F65: Teknologi Informasi | G65: Fakultas Informatika | H65: 12 | J65: 62 | K65: Rifdatun Ni'mah | L65: Sains Data | N65: Tidak ada
A66: 63 | B66: Raulia Riski | C66: Raulia | D66: Riski | F66: Sistem Informasi | G66: Fakultas Rekayasa Industri | H66: 2 | J66: 63 | K66: Muhammad Adib Kamali | L66: Teknologi Informasi | M66: 16
A67: 64 | B67: Sri Hidayati | C67: Sri | D67: Hidayati | F67: Sistem Informasi | G67: Fakultas Rekayasa Industri | H67: 9 | J67: 64 | K67: Raulia Riski | L67: Sistem Informasi | M67: 3
A68: 65 | B68: Caesareano Lafado Yesa | C68: Caesareano | D68: Lafado | E68: Yesa | F68: Digital Bisnis | G68: Fakultas Ekonomi dan Bisnis | H68: 0 | J68: 65 | K68: Sri Hidayati | L68: Sistem Informasi | M68: 2
A69: 66 | B69: Achmad Muzakki | C69: Achmad | D69: Muzakki | F69: RPL | G69: Fakultas Informatika | H69: 0 | J69: 66 | K69: Caesareano Lafado Yesa | L69: Digital Bisnis | N69: Tidak ada
A70: 67 | B70: Silvi Istiqomah | C70: Silvi | D70: Istiqomah | F70: Teknik Industri | G70: Fakultas Rekayasa Industri | H70: 14 | J70: 67 | K70: Achmad Muzakki | L70: Rekayasa Perangkat Lunak | M70: 0
A71: 68 | B71: Darlin Aulia | C71: Darlin | D71: Aulia | F71: Digital Bisnis | G71: Fakultas Ekonomi dan Bisnis | H71: 3 | J71: 68 | K71: Silvi Istiqomah | L71: Teknik Industri | M71: 15
A72: 69 | B72: Perdana Suteja Putra | C72: Perdana | D72: Suteja | E72: Putra | F72: Teknik Industri | G72: Fakultas Rekayasa Industri | H72: 10 | J72: 69 | K72: Darlin Aulia | L72: Digital Bisnis | M72: 3 | N72: Sekolah Tinggi Ilmu Ekonomi MNC
A73: 70 | B73: Adzanil Rachmadhi Putra | C73: Adzanil | D73: Rachmadhi | E73: Putra | F73: Sistem Informasi | G73: Fakultas Rekayasa Industri | H73: 1 | J73: 70 | K73: Agoes Windarto | L73: Digital Bisnis | N73: Tidak ada
A74: 71 | B74: Affifiana Prisyanti | C74: Affifiana | D74: Prisyanti | F74: Sistem Informasi | G74: Fakultas Rekayasa Industri | H74: 2 | J74: 71 | K74: Adzanil Rachmadhi Putra | L74: Sistem Informasi | M74: 1
A75: 72 | B75: Alifiansyah Arrizqy Hidayat | C75: Alifiansyah | D75: Arrizqy | E75: Hidayat | F75: Sistem Informasi | G75: Fakultas Rekayasa Industri | H75: 18 | J75: 72 | K75: Affifiana Prisyanti | L75: Sistem Informasi | N75: Tidak ada
A76: 73 | B76: Anisa Dzulkarnain | C76: Anisa | D76: Dzulkarnain | F76: Sistem Informasi | G76: Fakultas Rekayasa Industri | H76: 25 | J76: 73 | K76: Alifiansyah Arrizqy Hidayat | L76: Sistem Informasi | M76: 18
A77: 74 | B77: Anita Hakim Nasution | C77: Anita | D77: Hakim | E77: Nasution | F77: Sistem Informasi | G77: Fakultas Rekayasa Industri | H77: 0 | J77: 74 | K77: Anisa Dzulkarnain | L77: Sistem Informasi | M77: 25
A78: 75 | B78: Arip Ramadan | C78: Arip | D78: Ramadan | F78: Sistem Informasi | G78: Fakultas Rekayasa Industri | H78: 0 | J78: 75 | K78: Anita Hakim Nasution | L78: Sistem Informasi | M78: 0
A79: 76 | B79: Wachda Yuniar Rochmah | C79: Wachda | D79: Yuniar | E79: Rochmah | F79: Digital Bisnis | G79: Fakultas Ekonomi dan Bisnis | H79: 5 | J79: 76 | K79: Arip Ramadan | L79: Sistem Informasi | M79: 2
A80: 77 | B80: Mustafa Kamal | C80: Mustafa | D80: Kamal | F80: Teknologi Informasi | G80: Fakultas Informatika | H80: 3 | J80: 77 | K80: Wachda Yuniar Rochmah | L80: Digital Bisnis | M80: 6
A81: 78 | B81: Yohanes Setiawan | C81: Yohanes | D81: Setiawan | F81: Teknologi Informasi | G81: Fakultas Informatika | H81: 9 | J81: 78 | K81: Mustafa Kamal | L81: Teknologi Informasi | N81: Tidak ada
A82: 79 | B82: Rosyid Abdillah | C82: Rosyid | D82: Abdillah | F82: Sistem Informasi | G82: Fakultas Rekayasa Industri | H82: 7 | J82: 79 | K82: Yohanes Setiawan | L82: Teknologi Informasi | M82: 11 | N82: Institut Teknologi Sepuluh Nopember
A83: 80 | B83: Vessa Rizky Oktavia | C83: Vessa | D83: Rizky | E83: Oktavia | F83: Informatika | G83: Fakultas Informatika | H83: 1 | J83: 80 | K83: Rosyid Abdillah | L83: Sistem Informasi | M83: 7 | N83: Institut Teknologi Sepuluh Nopember
A84: 81 | B84: Alqis Rausanfita | C84: Alqis | D84: Rausanfita | F84: Informatika | G84: Fakultas Informatika | H84: 0 | J84: 81 | K84: Vessa Rizky Oktavia | L84: Informatika | M84: 1 | N84: Institut Teknologi Sepuluh Nopember
A85: 82 | B85: Rifki Dwi Putranto | C85: Rifki | D85: Dwi | E85: Putranto | F85: Teknik Elektro | G85: Fakultas Teknik Elektro | H85: 0 | J85: 82 | K85: Alqis Rausanfita | L85: Informatika | M85: 0 | N85: Institut Teknologi Sepuluh Nopember
A86: 83 | B86: Huki Chandra | C86: Huki | D86: Chandra | F86: Teknik Industri | G86: Fakultas Rekayasa Industri | H86: 0 | J86: 83 | K86: Rifki Dwi Putranto | L86: Teknik Elektro | M86: 1 | N86: Institut Teknologi Sepuluh Nopember
A87: 84 | B87: Tita Ayu Rospricilia | C87: Tita | D87: Ayu | E87: Rospricilia | F87: Sistem Informasi | G87: Fakultas Rekayasa Industri | H87: 1 | J87: 84 | K87: Huki Chandra | L87: Teknik Industri | M87: 0 | N87: Tidak ada
A88: 85 | B88: Dahliar Ananda | C88: Dahliar | D88: Ananda | F88: RPL | G88: Fakultas Informatika | H88: 11 | J88: 85 | K88: Tita Ayu Rospricilia | L88: Sistem Informasi | M88: 2 | N88: Institut Teknologi Sepuluh Nopember
A89: 86 | B89: Hendy Briantoro | C89: Hendy | D89: Briantoro | F89: Teknik Komputer | G89: Fakultas Teknik Elektro | H89: 37 | J89: 86 | K89: Dahliar Ananda | L89: Rekayasa Perangkat Lunak | M89: 15
A90: 87 | B90: Berlian Rahmy Lidiawaty | C90: Berlian | D90: Rahmy | E90: Lidiawaty | F90: Sistem Informasi | G90: Fakultas Rekayasa Industri | H90: 10 | J90: 87 | K90: Hendy Briantoro | L90: Teknik Komputer | M90: 38
A91: 88 | B91: Mohammad Yanuar Hariyawan | C91: Mohammad | D91: Yanuar | E91: Hariyawan | F91: Teknik Komputer | G91: Fakultas Teknik Elektro | H91: 57 | J91: 88 | K91: Berlian Rahmy Lidiawaty | L91: Sistem Informasi | M91: 12
A92: 89 | B92: Chaironi Latif | C92: Chaironi | D92: Latif | F92: Teknik Elektro | G92: Fakultas Teknik Elektro | H92: 24 | J92: 89 | K92: Mohammad Yanuar Hariyawan | L92: Teknik Komputer | M92: 57
A93: 90 | B93: Aufar Fikri Dimyati | C93: Aufar | D93: Fikri | E93: Dimyati | F93: Teknik Industri | G93: Fakultas Rekayasa Industri | H93: 0 | J93: 90 | K93: Chaironi Latif | L93: Teknik Elektro | M93: 24
A94: 91 | B94: Muhammad Ilham Alhari | C94: Muhammad | D94: Ilham | E94: Alhari | F94: Sistem Informasi | G94: Fakultas Rekayasa Industri | H94: 30 | J94: 91 | K94: Aufar Fikri Dimyati | L94: Teknik Industri | M94: 0 | N94: Institut Teknologi Sepuluh Nopember
A95: 92 | B95: Adisya Resti Rahmadanti | C95: Adisya | D95: Resti | E95: Rahmadanti | F95: Digital Bisnis | G95: Fakultas Ekonomi dan Bisnis | H95: 0 | J95: 92 | K95: Muhammad Ilham Alhari | L95: Sistem Informasi | M95: 40
A96: 93 | B96: Arni Muarifah Amri | C96: Arni | D96: Muarifah | E96: Amri | F96: RPL | G96: Fakultas Informatika | H96: 2 | J96: 93 | K96: Adisya Resti Rahmadanti | L96: Digital Bisnis | M96: 0 | N96: Tidak ada
A97: 94 | B97: Daud Muhajir | C97: Daud | D97: Muhajir | F97: Informatika | G97: Fakultas Informatika | H97: 17 | J97: 94 | K97: Arni Muarifah Amri | L97: Rekayasa Perangkat Lunak | M97: 2
A98: 95 | B98: Dyah Putri Rahmawati | C98: Dyah | D98: Putri | E98: Rahmawati | F98: Informatika | G98: Fakultas Informatika | H98: 55 | J98: 95 | K98: Daud Muhajir | L98: Informatika | M98: 20 | N98: Institut Teknologi Sepuluh Nopember
A99: 96 | B99: Eka Sari Oktarina | C99: Eka | D99: Sari | E99: Oktarina | F99: Teknik Komputer | G99: Fakultas Teknik Elektro | H99: 4 | J99: 96 | K99: Dyah Putri Rahmawati | L99: Informatika | M99: 60 | N99: Institut Teknologi Sepuluh Nopember
A100: 97 | B100: Krisnayanti Aditasari | C100: Krisnayanti | D100: Aditasari | F100: Digital Bisnis | G100: Fakultas Ekonomi dan Bisnis | H100: 0 | J100: 97 | K100: Eka Sari Oktarina | L100: Teknik Komputer | M100: 4 | N100: Universitas Gadjah Mada
A101: 98 | B101: Pima Hani Safitri | C101: Pima | D101: Hani | E101: Safitri | F101: Informatika | G101: Fakultas Informatika | H101: 4 | J101: 98 | K101: Krisnayanti Aditasari | L101: Digital Bisnis | M101: 0 | N101: tidak ada
...

Sheet Grafik PNLT
A2: Tahun Usulan | B2: 2024
A4: Nama Skema | B4: Count of Nama Skema
A5: PENELITIAN DASAR PERIODE 1 | B5: 29
A6: PENELITIAN DASAR PERIODE 2 | B6: 7
A7: PENELITIAN KEMITRAAN DALAM NEGERI PERIODE 1 | B7: 1
A8: PENELITIAN KEMITRAAN LUAR NEGERI PERIODE 1 | B8: 1
A9: PENELITIAN MANDIRI PERIODE 1 | B9: 3
A10: PENELITIAN STRATEGIS PERIODE 1 | B10: 3
A11: PENELITIAN TERAPAN PERIODE 1 | B11: 3
A12: Grand Total | B12: 47
A45: SDG | B45: Count of SDG
A46: 2 | B46: 1
A47: 3 | B47: 4
A48: 4 | B48: =4+E52 -> 4
A49: 5 | B49: 1
A50: 6 | B50: 1
A51: 7 | B51: =1+E49 -> 1
A52: 8 | B52: =1+E50 -> 1
A53: 9 | B53: =9+E46 -> 9
A54: 11 | B54: 1
A55: 14 | B55: 1
A56: 17 | B56: =1+E47 -> 1
A57: 13 | B57: 2
A58: 16 | B58: 2
A59: 12 | B59: 1
A60: 11 | B60: 1
B61: =SUM(B46:B60) -> 31

Sheet Grafik SDG PNLT
A1: Tahun Usulan | B1: 2024-2025 | E1: Tahun Usulan | F1: 2024
A3: SDG | B3: Keterangan | C3: Jumlah | E3: SDG | F3: Keterangan | G3: Jumlah
A4: 1 | B4: Tanpa Kemiskinan | C4: =COUNTIF(#REF!,"1") -> #REF! | E4: 1 | F4: Tanpa Kemiskinan | G4: =COUNTIF(#REF!,"1") -> #REF!
A5: 2 | B5: Tanpa Kelaparan | C5: =COUNTIF(#REF!,"2") -> #REF! | E5: 2 | F5: Tanpa Kelaparan | G5: =COUNTIF(#REF!,"2") -> #REF!
A6: 3 | B6: Kehidupan Sehat dan Sejahtera | C6: =COUNTIF(#REF!,"3") -> #REF! | E6: 3 | F6: Kehidupan Sehat dan Sejahtera | G6: =COUNTIF(#REF!,"3") -> #REF!
A7: 4 | B7: Pendidikan Berkualitas | C7: =COUNTIF(#REF!,"4") -> #REF! | E7: 4 | F7: Pendidikan Berkualitas | G7: =COUNTIF(#REF!,"4") -> #REF!
A8: 5 | B8: Kesetaraan Gender | C8: =COUNTIF(#REF!,"5") -> #REF! | E8: 5 | F8: Kesetaraan Gender | G8: =COUNTIF(#REF!,"5") -> #REF!
A9: 6 | B9: Air Bersih dan Sanitasi Layak | C9: =COUNTIF(#REF!,"6") -> #REF! | E9: 6 | F9: Air Bersih dan Sanitasi Layak | G9: =COUNTIF(#REF!,"6") -> #REF!
A10: 7 | B10: Energi Bersih dan Terjangkau | C10: =COUNTIF(#REF!,"7") -> #REF! | E10: 7 | F10: Energi Bersih dan Terjangkau | G10: =COUNTIF(#REF!,"7") -> #REF!
A11: 8 | B11: Pekerjaan Layak dan Pertumbuhan Ekonomi | C11: =COUNTIF(#REF!,"8") -> #REF! | E11: 8 | F11: Pekerjaan Layak dan Pertumbuhan Ekonomi | G11: =COUNTIF(#REF!,"8") -> #REF!
A12: 9 | B12: Industri, Inovasi dan Infrastruktur | C12: =COUNTIF(#REF!,"9") -> #REF! | E12: 9 | F12: Industri, Inovasi dan Infrastruktur | G12: =COUNTIF(#REF!,"9") -> #REF!
A13: 10 | B13: Berkurangnya Kesenjangan | C13: =COUNTIF(#REF!,"10") -> #REF! | E13: 10 | F13: Berkurangnya Kesenjangan | G13: =COUNTIF(#REF!,"10") -> #REF!
A14: 11 | B14: Kota dan Permukiman yang Berkelanjutan | C14: =COUNTIF(#REF!,"11") -> #REF! | E14: 11 | F14: Kota dan Permukiman yang Berkelanjutan | G14: =COUNTIF(#REF!,"11") -> #REF!
A15: 12 | B15: Konsumsi dan Produksi yang Bertanggung Jawab | C15: =COUNTIF(#REF!,"12") -> #REF! | E15: 12 | F15: Konsumsi dan Produksi yang Bertanggung Jawab | G15: =COUNTIF(#REF!,"12") -> #REF!
A16: 13 | B16: Penanganan Perubahan Iklim | C16: =COUNTIF(#REF!,"13") -> #REF! | E16: 13 | F16: Penanganan Perubahan Iklim | G16: =COUNTIF(#REF!,"13") -> #REF!
A17: 14 | B17: Ekosistem Lautan | C17: =COUNTIF(#REF!,"14") -> #REF! | E17: 14 | F17: Ekosistem Lautan | G17: =COUNTIF(#REF!,"14") -> #REF!
A18: 15 | B18: Ekosistem Daratan | C18: =COUNTIF(#REF!,"15") -> #REF! | E18: 15 | F18: Ekosistem Daratan | G18: =COUNTIF(#REF!,"15") -> #REF!
A19: 16 | B19: Perdamaian, Keadilan, dan Kelembagaan yang Tangguh | C19: =COUNTIF(#REF!,"16") -> #REF! | E19: 16 | F19: Perdamaian, Keadilan, dan Kelembagaan yang Tangguh | G19: =COUNTIF(#REF!,"16") -> #REF!
A20: 17 | B20: Kemitraan untuk Mencapai Tujuan | C20: =COUNTIF(#REF!,"17") -> #REF! | E20: 17 | F20: Kemitraan untuk Mencapai Tujuan | G20: =COUNTIF(#REF!,"17") -> #REF!
E23: Tahun Usulan | F23: 2025
E25: SDG | F25: Keterangan | G25: Jumlah
E26: 1 | F26: Tanpa Kemiskinan | G26: =COUNTIF(#REF!,"1") -> #REF!
E27: 2 | F27: Tanpa Kelaparan | G27: =COUNTIF(#REF!,"2") -> #REF!
E28: 3 | F28: Kehidupan Sehat dan Sejahtera | G28: =COUNTIF(#REF!,"3") -> #REF!
E29: 4 | F29: Pendidikan Berkualitas | G29: =COUNTIF(#REF!,"4") -> #REF!
E30: 5 | F30: Kesetaraan Gender | G30: =COUNTIF(#REF!,"5") -> #REF!
E31: 6 | F31: Air Bersih dan Sanitasi Layak | G31: =COUNTIF(#REF!,"6") -> #REF!
E32: 7 | F32: Energi Bersih dan Terjangkau | G32: =COUNTIF(#REF!,"7") -> #REF!
E33: 8 | F33: Pekerjaan Layak dan Pertumbuhan Ekonomi | G33: =COUNTIF(#REF!,"8") -> #REF!
E34: 9 | F34: Industri, Inovasi dan Infrastruktur | G34: =COUNTIF(#REF!,"9") -> #REF!
E35: 10 | F35: Berkurangnya Kesenjangan | G35: =COUNTIF(#REF!,"10") -> #REF!
E36: 11 | F36: Kota dan Permukiman yang Berkelanjutan | G36: =COUNTIF(#REF!,"11") -> #REF!
E37: 12 | F37: Konsumsi dan Produksi yang Bertanggung Jawab | G37: =COUNTIF(#REF!,"12") -> #REF!
E38: 13 | F38: Penanganan Perubahan Iklim | G38: =COUNTIF(#REF!,"13") -> #REF!
E39: 14 | F39: Ekosistem Lautan | G39: =COUNTIF(#REF!,"14") -> #REF!
E40: 15 | F40: Ekosistem Daratan | G40: =COUNTIF(#REF!,"15") -> #REF!
E41: 16 | F41: Perdamaian, Keadilan, dan Kelembagaan yang Tangguh | G41: =COUNTIF(#REF!,"16") -> #REF!
E42: 17 | F42: Kemitraan untuk Mencapai Tujuan | G42: =COUNTIF(#REF!,"17") -> #REF!

Sheet Grafik PKM
A1: Tahun Usulan | B1: 2024
A3: Nama Skema | B3: Count of Nama Skema
A4: KOLABORASI DALAM NEGERI | B4: 5
A5: PENDAMPINGAN/PELATIHAN PERIODE 1 | B5: 5
A6: PENDAMPINGAN/PELATIHAN PERIODE 2 | B6: 1
A7: TEKNOLOGI TEPAT GUNA (TTG) PERIODE 1 | B7: 16
A8: TEKNOLOGI TEPAT GUNA (TTG) PERIODE 2 | B8: 5
A9: Grand Total | B9: 32

Sheet Grafik SDG PKM
A1: Tahun Pelaksanaan Kegiatan | B1: 2024
A3: SDG | B3: Count of SDG
A4: 1 | B4: 2
A5: 2 | B5: 4
A6: 3 | B6: 10
A7: 4 | B7: 7
A8: 5 | B8: 1
A9: 6 | B9: 5
A10: 7 | B10: 2
A11: 9 | B11: 1
A12: Grand Total | B12: 32

Sheet Publikasi implementasi
A1: DATA PUBLIKASI | I1: DATA PENULIS KORESPONDING | N1: DATA PENULIS (1) | S1: DATA PENULIS (2) | X1: DATA PENULIS (3) | AC1: DATA PENULIS (4) | AH1: DATA PENULIS (5) | AM1: DATA PENULIS (6) | AR1: DATA PENULIS LAINNYA
A2: Judul Publikasi | B2: Nama Jurnal | C2: Implementasi | D2: Akreditasi/ Index Jurnal | E2: Lembaga Pengindeks | F2: Tahun Submit | G2: Tahun Accepted | H2: Tahun Published | I2: Nama Penulis Koresponding | J2: Sinta ID | K2: NIDN | L2: Prodi | M2: Afiliasi | N2: Nama Penulis (1) | O2: Prodi2 | P2: Afiliasi3 | Q2: Sinta ID4 | R2: NIDN5 | S2: Nama Penulis (2) | T2: Prodi6 | U2: Afiliasi7 | V2: Sinta ID8 | W2: NIDN9 | X2: Nama Penulis (3) | Y2: Prodi10 | Z2: Afiliasi11 | AA2: Sinta ID12 | AB2: NIDN13 | AC2: Nama Penulis (4) | AD2: Prodi14 | AE2: Afiliasi15 | AF2: Sinta ID16 | AG2: NIDN17 | AH2: Nama Penulis (5) | AI2: Prodi18 | AJ2: Afiliasi19 | AK2: Sinta ID20 | AL2: NIDN21 | AM2: Nama Penulis (6) | AN2: Prodi22 | AO2: Afiliasi23 | AP2: Sinta ID24 | AQ2: NIDN25 | AR2: Nama Penulis Lain | AS2: Prodi26 | AT2: Afiliasi27 | AU2: Sinta ID28 | AV2: NIDN29
A3: Low-cost Transverse Electromagnetic (TEM) cell design for radiated emission measurement | B3: IOP Conference Series: Materials Science and Engineering 1073 (1), 012040, 2021 | D3: Prosiding Internasional | H3: 2021 | I3: Muhammad Yanuar Hariawan | L3: TK | M3: ITTELKOM Surabaya | N3: Muhammad Yanuar Hariawan | O3: TK | P3: ITTELKOM Surabaya | S3: Rizadi Sasmita Darwis | U3: Politeknik Caltex Riau | X3: B A Habibi | Z3: Politeknik Caltex Riau
A4: Simulasi Efisiensi dan Akurasi Shielding Effectiveness pada Kabel Coaxial | B4: ABEC Indonesia 9, 1263-1274, 2021 | D4: Prosiding Nasional | H4: 2021 | I4: Putri Cahyanda | M4: Politeknik Caltex Riau | N4: Putri Cahyanda | P4: Politeknik Caltex Riau | S4: Rizadi Sasmita Darwis | U4: Politeknik Caltex Riau | X4: Muhammad Yanuar Hariawan | Y4: TK | Z4: ITTELKOM Surabaya
A5: RANCANG MAGNETIC NEAR FIELD PROBE UNTUK PENGUJIAN RADIATED EMISSION PADA FREKUENSI RENDAH | B5: ABEC Indonesia 9, 1040-1049, 2021 | D5: Prosiding Nasional | H5: 2021 | I5: Yospet Pradika | M5: Politeknik Caltex Riau | N5: Yospet Pradika | P5: Politeknik Caltex Riau | S5: Muhammad Yanuar Hariawan | T5: TK | U5: ITTELKOM Surabaya
A6: RANCANG BANGUN ALAT MONITORING KUALITAS UDARA BERBASIS NODEMCU ESP8266 (HARDWARE) | B6: ABEC Indonesia 9, 837-846, 2021 | D6: Prosiding Nasional | H6: 2021 | I6: Raywanda Affandi Harahap | M6: Politeknik Caltex Riau | N6: Raywanda Affandi Harahap | P6: Politeknik Caltex Riau | S6: Muhammad Yanuar Hariawan | T6: TK | U6: ITTELKOM Surabaya
A7: Filter EMI Aktif menggunakan Op-Amp untuk Mereduksi Near-Field EMI pada PCB | B7: ABEC Indonesia 9, 847-856, 2021 | D7: Prosiding Nasional | H7: 2021 | I7: Wahyudi Nasrianza1 | M7: Politeknik Caltex Riau | N7: Wahyudi Nasrianza1 | P7: Politeknik Caltex Riau | S7: Muhammad Yanuar Hariawan | T7: TK | U7: ITTELKOM Surabaya
A8: SISTEM MONITORING KUALITAS UDARA BERBASIS NODEMCU ESP8266 DENGAN METODE FUZZY LOGIC (SOFTWARE) | B8: ABEC Indonesia 9, 1050-1062, 2021 | D8: Prosiding Nasional | H8: 2021 | I8: Diemas Ibnus Pasedja | M8: Politeknik Caltex Riau | N8: Diemas Ibnus Pasedja | P8: Politeknik Caltex Riau | S8: Muhammad Yanuar Hariawan | T8: TK | U8: ITTELKOM Surabaya
A9: Pengaruh Ketebalan Material Terhadap Shielding effectiveness pada Frekuensi Rendah | B9: Jurnal Elektro dan Mesin Terapan 7 (2), 18-24, 2021 | D9: S4 | E9: SINTA | H9: 2021 | I9: Muhammad Yanuar Hariawan | L9: TK | M9: ITTELKOM Surabaya | N9: Muhammad Yanuar Hariawan | O9: TK | P9: ITTELKOM Surabaya | S9: Rizadi Sasmita Darwis | U9: Politeknik Caltex Riau
A10: Prediksi Jarak Bola Pada Citra Kamera Katadioptrik Menggunakan Metode Artifical Neural Network | B10: ELKOMIKA: Jurnal Teknik Energi Elektrik, Teknik Telekomunikasi, &amp; Teknik Elektronika | D10: S2 | E10: SINTA | H10: 2021 | I10: ZENDI ZAKARIA RAGA PERMANA | M10: Universitas Dinamika | N10: ZENDI ZAKARIA RAGA PERMANA | P10: Universitas Dinamika | S10: Susijanto Tri Rasmana | T10: TE | U10: ITTELKOM Surabaya | X10: IRA PUSPASARI | Z10: Universitas Dinamika
A11: A Systematic Review on the Autonomous Emergency Steering Assessments and Tests Methodology in ASEAN | B11: Journal of the Society of Automotive Engineers Malaysia 5 (2), 185-193, 2021 | D11: Jurnal ber-ISSN | H11: 2021 | I11: M.A.Abdul Rahman | M11: UTM | N11: Susijanto Tri Rasmana | O11: TE | P11: ITTELKOM Surabaya | S11: Dimas Adiputra | T11: TE | U11: ITTELKOM Surabaya | X11: M.A.Abdul Rahman | Z11: UTM | AC11: A.Dwijotomo | AE11: UTM | AH11: M.H.Mohammed Ariff | AJ11: UTM | AM11: N.Abu Husain | AO11: UTM
A12: Pengendali Tingkat Keasaman Air Kolam untuk Peternak Ikan Lele | B12: JMM (Jurnal Masyarakat Mandiri) 5 (6), 3135-3144, 2021 | D12: S3 | E12: SINTA | H12: 2021 | N12: Susijanto Tri Rasmana | O12: TE | P12: ITTELKOM Surabaya | S12: Mochammad Iskandar Riansyah | T12: TE | U12: ITTELKOM Surabaya | X12: Chaironi Latif | Y12: TE | Z12: ITTELKOM Surabaya | AC12: Muhammad Dwi Hariyanto | AD12: TE | AE12: ITTELKOM Surabaya | AH12: Anak Agung Kusuma Jaya Ningrat | AI12: TE | AJ12: ITTELKOM Surabaya | AM12: Jesica Febriani Nura | AN12: TE | AO12: ITTELKOM Surabaya
A13: KINERJA KARYAWAN (KONSEP PENILAIAN KINERJA DI PERUSAHAAN) | B13: CV WIDINA MEDIA UTAMA, 2021 | D13: Buku | H13: 2021 | N13: Hartini Hartini | S13: Alnisa Min Fadlillah | X13: Hetty Ismainar | AC13: Retno Setyorini | AH13: Ahmad Bairizki | AM13: Afdol Muftiasa | AR13: Titus Kristanto | AS13: RPL | AT13: ITTELKOM Surabaya
A14: Kewirausahaan (Teori dan Praktis) | B14: CV WIDINA MEDIA UTAMA, 2021 | D14: Buku | H14: 2021 | N14: Agus Alimuddin | S14: Adih Supriadi | X14: Ujang Enas | AC14: Fauzan Aziz | AH14: Komang Trisna Sari Dewi | AM14: Nikmatul Khoiriyah | AR14: Titus Kristanto | AS14: RPL | AT14: ITTELKOM Surabaya
A15: Marketing Digital Usaha Mikro | B15: CV WIDINA MEDIA UTAMA, 2021 | D15: Buku | H15: 2021 | N15: Rudy Irwansyah | S15: Danil Syahputra | X15: Supiah Ningsih | AC15: Muhammad Hasan | AH15: Titus Kristanto | AI15: RPL | AJ15: ITTELKOM Surabaya | AM15: Lucky Nugroho | AR15: Diana Triwardhani
A16: Pelatihan Dan Pendampingan Pemasaran Online Produk Nasi Tiwul Di Masa Pandemi Covid-19 | B16: JMM (Jurnal Masyarakat Mandiri) 5 (4), 1681-1688, 2021 | D16: S3 | E16: SINTA | H16: 2021 | N16: Titus Kristanto | O16: RPL | P16: ITTELKOM Surabaya | S16: Dewi Rahmawati | T16: RPL | U16: ITTELKOM Surabaya | X16: Ayu Endah Wahyuni | Y16: TI | Z16: ITTELKOM Surabaya | AC16: Muhammad Nasrullah | AD16: SI | AE16: ITTELKOM Surabaya | AH16: Reza Arindra Fadillah | AI16: RPL | AJ16: ITTELKOM Surabaya | AM16: Amanda Amalia | AN16: RPL | AO16: ITTELKOM Surabaya
A17: PELATIHAN PENINGKATAN KEMAMPUAN MENGGUNAKAN MICROSOFT DYNAMICS 365 BUSINESS CENTRAL | B17: Prosiding Konferensi Nasional Pengabdian Kepada Masyarakat dan Corporate &#8230;, 2021 | D17: Prosiding Nasional | H17: 2021 | I17: Muhammad Nasrullah | L17: SI | M17: ITTELKOM Surabaya | N17: Muhammad Nasrullah | O17: SI | P17: ITTELKOM Surabaya | S17: Titus Kristanto | T17: RPL | U17: ITTELKOM Surabaya
A18: Pengujian Black Box Menggunakan Teknik Equivalence Partitions Pada Aplikasi E-Learning Berbasis Web | B18: Building of Informatics, Technology and Science (BITS) 3 (3), 269-274, 2021 | D18: S3 | E18: SINTA | H18: 2021 | I18: Titus Kristanto | L18: RPL | M18: ITTELKOM Surabaya | N18: Titus Kristanto | O18: RPL | P18: ITTELKOM Surabaya | S18: Amanda Amalia | U18: ITTELKOM Surabaya | X18: Salva Wanda Putri Hamidah | Z18: ITTELKOM Surabaya
A19: PENGARUH KREATIVITAS DAN MOTIVASI TERHADAP KARAKTERISTIK KINERJA MANAJERIAL PT PAL INDONESIA (PERSERO) MENGGUNAKAN METODE GRAPHIC RATING SCALE | B19: Prosiding Seminar Nasional MIPATI 1 (1), 2021 | D19: Prosiding Nasional | H19: 2021 | N19: Titus Kristanto | O19: RPL | P19: ITTELKOM Surabaya | S19: Rosdiana Marpaung | U19: Sekolah Tinggi Ilmu Ekonomi Indonesia | X19: Dwi Mustika Kusumawardani | Z19: ITTP | AC19: Dewi Rahmawati | AD19: RPL | AE19: ITTELKOM Surabaya
A20: EndorseGram: Interactive Visualization of Influencer Endorsement Marketplace | B20: 2021 International Conference on Computer Science, Information Technology and Electrical Engineering (ICOMITEE), 2021 | D20: Prosiding Internasional | H20: 2021 | N20: Mochamad Nizar Palefi Ma’Ady | O20: SI | P20: ITTELKOM Surabaya | S20: Shinta Amalia Kusuma Wardhani | U20: Universitas Nahdlatul Ulama Sunan Giri
A21: EFFECTIVE MANAGEMENT OF ONLINE LEARNING DURING PANDEMIC AT SDN 1 TANAH TINGGI | B21: PROGRES PENDIDIKAN 2 (2), 115-118, 2021 | D21: S5 | E21: SINTA | H21: 2021 | I21: Ina Magdalena | M21: Universitas Muhammadiyah Tangerang | N21: Ina Magdalena | P21: Universitas Muhammadiyah Tangerang | S21: Ayu Endah Wahyuni | T21: TI | U21: ITTELKOM Surabaya | X21: Davina Dewi Hartana | Z21: Universitas Muhammadiyah Tangerang
A22: The Development of TRAM Model for Blockchain Use Readiness Among MSMEs in Indonesia | B22: Ninth International Conference on Entrepreneurship and Business Management (ICEBM 2020) | D22: Prosiding Internasional | H22: 2021 | I22: Ayu Endah Wahyuni | L22: TI | M22: ITTELKOM Surabaya | N22: Ayu Endah Wahyuni | O22: TI | P22: ITTELKOM Surabaya | S22: Anita Juraida | U22: Universitas Widyatama | X22: Asep Anwar | Z22: Universitas Widyatama
A23: Readiness factor identification Bandung city MSMEs use blockchain technology | B23: Jurnal Sistem dan Manajemen Industri 5 (2), 53-62, 2021 | D23: S2 | E23: SINTA | H23: 2021 | I23: Ayu Endah Wahyuni | L23: TI | M23: ITTELKOM Surabaya | N23: Ayu Endah Wahyuni | O23: TI | P23: ITTELKOM Surabaya | S23: Anita Juraida | U23: Universitas Widyatama | X23: Asep Anwar | Z23: Universitas Widyatama
A24: Pembuatan Film Animasi Permainan Tradisional Anak-Anak Berbasis 3 Dimensi | B24: eProceeding of TIK 1 (1), 2021 | D24: Jurnal ber-ISSN | H24: 2021 | I24: Ayu Endah Wahyuni | L24: TI | M24: ITTELKOM Surabaya | N24: Ayu Endah Wahyuni | O24: TI | P24: ITTELKOM Surabaya | S24: Mursyidah | U24: Politeknik Negeri Lhokseumawe | X24: Muhammad Nasir | Z24: Politeknik Negeri Lhokseumawe
A25: PEMBUATAN WORKBENCH ERGONOMIS UNTUK MENDUKUNG AKTIVITAS PEMILAHAN, PENGEPRESAN, DAN PENGARUNGAN SAMPAH AIR MINUM DALAM KEMASAN DI KELURAHAN WONKUSUMO SURABAYA | B25: LOGISTA-Jurnal Ilmiah Pengabdian kepada Masyarakat 5 (2), 330-335, 2021 | D25: S4 | E25: SINTA | H25: 2021 | N25: Rahaditya Dimas Prihadianto | O25: TI | P25: ITTELKOM Surabaya | S25: Abduh Sayid Albana | T25: TI | U25: ITTELKOM Surabaya | X25: Ayu Endah Wahyuni | Y25: TI | Z25: ITTELKOM Surabaya | AC25: Hendrawan Widianto | AD25: TI | AE25: ITTELKOM Surabaya
A26: MENGGAGAS MEJA DIGITAL PRIBADI (DIGITALLY PERSONALIZED DESKS) UNTUK ANAK USIA DINI DALAM SISTEM PEMBELAJARAN | B26: Lomba Karya Tulis Ilmiah 2 (1), 109-114, 2021 | D26: Jurnal tidak ber-ISSN | H26: 2021 | N26: Amarrangga Kumara Prada | P26: ITTELKOM Surabaya | S26: Iftitah Kurnia | U26: ITTELKOM Surabaya | X26: Mohammad Robi Maulana | Z26: ITTELKOM Surabaya | AC26: Ayu Endah Wahyuni | AD26: TI | AE26: ITTELKOM Surabaya
A27: Fuzzy Gain Scheduling for Cascaded PI-Control for DC Motor | B27: 2021 IEEE Conference on Energy Conversion (CENCON), 158-162, 2021 | D27: Prosiding Internasional | H27: 2021 | N27: Deany Putri Aulia | P27: Universitas Pertamina | S27: Alfiyah Shaldzabila Yustin | U27: Universitas Pertamina | X27: Amien Marzuq Hilman | Z27: Universitas Pertamina | AC27: Aulia Rahma Annisa | AD27: TK | AE27: ITTELKOM Surabaya | AH27: Eng Wahyu Kunto Wibowo | AJ27: Universitas Pertamina
A28: Rancang Bangun Sistem Alat Fototerapi Untuk Bayi Hiperbilirubinemia Berbasis Internet Of Things (IoT) | B28: Kilat 11 (2), 111-188, 2022 | D28: S4 | E28: SINTA | H28: 2021 | I28: Annida Sakinah Ramadhani | M28: Universitas Pertamina | N28: Annida Sakinah Ramadhani | P28: Universitas Pertamina | S28: Herminarto Nugroho | U28: Universitas Pertamina | X28: Aulia Rahma Annisa | Y28: TK | Z28: ITTELKOM Surabaya
A29: Implementasi Virtual Reality Berbasis Foto 360o Untuk Memvisualisasikan Fasilitas Perguruan Tinggi Surabaya | B29: Jurnal RESTI (Rekayasa Sistem Dan Teknologi Informasi) 5 (1), 155-162, 2021 | D29: S2 | E29: SINTA | H29: 2021 | I29: Nadiah Ratnaduhita | L29: SI | M29: ITTELKOM Surabaya | N29: Nadiah Ratnaduhita | O29: SI | P29: ITTELKOM Surabaya | S29: Ian Mahendra Putra | T29: SI | U29: ITTELKOM Surabaya | X29: Ully Asfari | Y29: SI | Z29: ITTELKOM Surabaya | AC29: Yupit Sudianto | AD29: SI | AE29: ITTELKOM Surabaya | AH29: Benazir Imam Arif Muttaqin | AI29: TI | AJ29: ITTELKOM Surabaya
A30: Modeling of salt supply chains to achieve competitive salt prices | B30: International Journal on Food System Dynamics 12 (1), 51-67, 2021 | D30: Q2 | H30: 2021 | N30: Isnaini Muhandhis | P30: Universitas Wijaya Putra | S30: Budisantoso Wirjodirdjo | U30: ITS | X30: Erma Suryani | Z30: ITS | AC30: Heri Susanto | AE30: Universitas Wijaya Putra | AH30: Ully Asfari | AI30: SI | AJ30: ITTELKOM Surabaya
A31: System Dynamic Framework: Increasing Productivity Of Sugarcane To Support Sustainable Cultivation | B31: Sustainability in Food and Agriculture (SFNA) 2 (2), 105-109, 2021 | D31: Jurnal ber-ISSN | H31: 2021 | I31: Hawwin Mardhiana | L31: SI | M31: ITTELKOM Surabaya | N31: Hawwin Mardhiana | O31: SI | P31: ITTELKOM Surabaya | S31: Erma Suryani | U31: ITS | X31: Ully Asfari | Y31: SI | Z31: ITTELKOM Surabaya | AC31: Muhammad Nasrullah | AD31: SI | AE31: ITTELKOM Surabaya
A32: 3D Virtual prototyping dalam Perbaikan Desain Fasilitas Tempat Kerja: Studi Kasus CV. XYZ | B32: Jurnal IPTEK 25 (1), 69-76, 2021 | D32: S3 | E32: SINTA | H32: 2021 | N32: Benazir Imam Arif Muttaqin | O32: TI | P32: ITTELKOM Surabaya | S32: Ully Asfari | T32: SI | U32: ITTELKOM Surabaya | X32: Hawwin Mardhiana | Y32: SI | Z32: ITTELKOM Surabaya | AC32: Shanggabuana Adhitya Shamaradewa | AD32: TI | AE32: ITTELKOM Surabaya | AH32: Gagas Putra Dawangga | AI32: SI | AJ32: ITTELKOM Surabaya
A33: Faktor yang Mempengaruhi Implementasi Green Human Resource Management pada Ormawa: Model Konseptual: Indonesia | B33: Journal of Advances in Information and Industrial Technology 3 (1), 11-18, 2021 | D33: Jurnal ber-ISSN | H33: 2021 | I33: Moch. Yusuf Fathussalam | L33: SI | M33: ITTELKOM Surabaya | N33: Moch. Yusuf Fathussalam | O33: SI | P33: ITTELKOM Surabaya | S33: I G Ag Kom Agnam M | T33: SI | U33: ITTELKOM Surabaya | X33: Irene Dyah Ayuwati | Y33: SI | Z33: ITTELKOM Surabaya | AC33: Desy Fitri A. L. | AD33: SI | AE33: ITTELKOM Surabaya | AH33: Yuniar Revi A. L | AI33: SI | AJ33: ITTELKOM Surabaya | AM33: Geraldo Brata Hiroshi P. | AN33: SI | AO33: ITTELKOM Surabaya | AR33: Ully Asfari | AS33: SI | AT33: ITTELKOM Surabaya
A34: Pengaruh Pelatihan dan Pengembangan SDM Pada ABA Collection Terhadap Kinerja Pegawai Menggunakan Metode Regresi Linear Berganda | B34: Journal of Advances in Information and Industrial Technology 3 (1), 19-30, 2021 | D34: Jurnal ber-ISSN | H34: 2021 | I34: Nadiah Ratnaduhita | L34: SI | M34: ITTELKOM Surabaya | N34: Nadiah Ratnaduhita | O34: SI | P34: ITTELKOM Surabaya | S34: Rio Armando | T34: SI | U34: ITTELKOM Surabaya | X34: Salsabila Qatrunnada | Y34: SI | Z34: ITTELKOM Surabaya | AC34: Tanang Satriyo Adi | AD34: SI | AE34: ITTELKOM Surabaya | AH34: Tanfirul Roibafi | AI34: SI | AJ34: ITTELKOM Surabaya | AM34: Wan Azizah Sri Nuraini | AN34: SI | AO34: ITTELKOM Surabaya | AR34: Ully Asfari | AS34: SI | AT34: ITTELKOM Surabaya
A35: INOVASI KINERJA PRODUKSI KOPI UNTUK MENINGKATKAN KEUNTUNGAN MELALUI KEGIATAN PENGABDIAN MASYARAKAT KE UKM KOPI ARABICA TRADISIONAL | B35: Prosiding Seminar Nasional &amp; Call for Paper&quot; Peran Perempuan Sebagai &#8230;, 2021 | D35: Prosiding Nasional | H35: 2021 | N35: Ully Asfari | O35: SI | P35: ITTELKOM Surabaya | S35: Isnaini Muhandhis | U35: Universitas Wijaya Putra | X35: Imam Kholik | Z35: Universitas Wijaya Putra
A36: Edge Computing Based Pickup and Delivery Optimization for Warehouse | B36: KICS Winter Conference 2021, 323-324, 2021 | D36: Prosiding Internasional | H36: 2021 | N36: Philip Tobianto Daely | O36: IT | P36: ITTELKOM Surabaya | S36: Jae-Woo Kim | U36: Kumoh National Institute of Technology | X36: Jae Min Lee | Z36: Kumoh National Institute of Technology | AC36: Dong-Seong Kim | AE36: Kumoh National Institute of Technology
A37: Dynamic VRP optimization using discrete PSO in edge computing environment | B37: 2021 International Conference on Information and Communication Technology Convergence (ICTC);, 2021 | D37: Prosiding Internasional | H37: 2021 | N37: Philip Tobianto Daely | O37: IT | P37: ITTELKOM Surabaya | S37: Yohana Jayanti Aruan | U37: Kumoh National Institute of Technology | X37: Jae Min Lee | Z37: Kumoh National Institute of Technology | AC37: Dong-Seong Kim | AE37: Kumoh National Institute of Technology
A38: The design of the emerging 5g using hybrid gpon and xgs-pon technology | B38: 2022 International Conference on Information and Communication Technology Convergence (ICTC);, 2021 | D38: Prosiding Internasional | H38: 2021 | N38: Yohana Jayanti Aruan | P38: Kumoh National Institute of Technology | S38: Philip Tobianto Daely | T38: IT | U38: ITTELKOM Surabaya | X38: Gabriel Avelino Ramos Sampedro | Z38: Kumoh National Institute of Technology | AC38: Jae Min Lee | AE38: Kumoh National Institute of Technology | AH38: Dong-Seong Kim | AJ38: Kumoh National Institute of Technology
A39: Battery Insulation Performance Analysis in Electric Vehicles for the Improvement of Battery Lifetime | B39: Jurnal Ilmiah Teknik Elektro Komputer dan Informatika (JITEKI) 7 (3), 412-422, 2021 | D39: S2 | E39: SINTA | H39: 2021 | I39: Lora Khaula Amifia | L39: TE | M39: ITTELKOM Surabaya | N39: Lora Khaula Amifia | O39: TE | P39: ITTELKOM Surabaya | S39: Nuansa Dipa Bismoko | U39: PT. Telekomunikasi Seluler | X39: Philip Tobianto Daely | Y39: IT | Z39: ITTELKOM Surabaya
A40: Prediction Point of Fault Location on Its Campus Power Grid by using Neural Artificial Method | B40: IOP Conference Series: Materials Science and Engineering 1096 (1), 012068, 2021 | D40: Prosiding Internasional | H40: 2021 | I40: A Syamsudin | M40: ITS | N40: A Syamsudin | P40: ITS | S40: Isa Hafidz | T40: TE | U40: ITTELKOM Surabaya | X40: D Rahmatullah | Z40: Universitas Hang Tuah | AC40: D A Asfani | AE40: ITS | AH40: I M Y Negara | AJ40: ITS
A41: Upaya Peningkatan Kualitas Pendidikan melalui Penerapan ICT di Sekolah Menengah Atas | B41: E-Dimas: Jurnal Pengabdian kepada Masyarakat 12 (2), 329-334, 2021 | D41: S4 | E41: SINTA | H41: 2021 | I41: Isa Hafidz | L41: TE | M41: ITTELKOM Surabaya | N41: Isa Hafidz | O41: TE | P41: ITTELKOM Surabaya | S41: Helmy Widyantara | T41: IT | U41: ITTELKOM Surabaya | X41: Ubaidillah Umar | Y41: TK | Z41: ITTELKOM Surabaya | AC41: Dwi Edi Setyawan | AD41: TK | AE41: ITTELKOM Surabaya | AH41: Billy Montolalu | AI41: TK | AJ41: ITTELKOM Surabaya
A42: Development of Digital Ventilator with Internet of Things for Preparation of the Next Outbreak in Indonesia | B42: Kinetik: Game Technology, Information System, Computer Network, Computing &#8230;, 2021 | D42: S2 | E42: SINTA | H42: 2021 | I42: Dimas Adiputra | L42: TE | M42: ITTELKOM Surabaya | N42: Dimas Adiputra | O42: TE | P42: ITTELKOM Surabaya | S42: Isa Hafidz | T42: TE | U42: ITTELKOM Surabaya | X42: Billy Montolalu | Y42: TK | Z42: ITTELKOM Surabaya | AC42: Fauzan Rasyid | AE42: ITTELKOM Surabaya
A43: Modified Critical Trajectory Algorithm to Determine the Critical Clearing Time for Unbalanced Fault | B43: 2021 International Electronics Symposium (IES), 36-40, 2021 | D43: Prosiding Internasional | H43: 2021 | N43: Isa Hafidz | O43: TE | P43: ITTELKOM Surabaya | S43: Ardyono Priyadi | U43: ITS | X43: Margo Pujiantara | Z43: ITS | AC43: Sjamsjul Anam | AE43: ITS | AH43: Naoto Yorino | AJ43: Hiroshima University | AM43: Mauridhi Hery Purnomo | AO43: ITS
A44: Power Monitoring and Passanger Classification on Logistics Elevator | B44: Elinvo (Electronics, Informatics, and Vocational Education) 6 (2), 2021 | D44: S2 | E44: SINTA | H44: 2021 | I44: Isa Hafidz | L44: TE | M44: ITTELKOM Surabaya | N44: Isa Hafidz | O44: TE | P44: ITTELKOM Surabaya | S44: Aldhitiansyah Putra | U44: ITTELKOM Surabaya | X44: Billy Montolalu | Y44: TK | Z44: ITTELKOM Surabaya | AC44: Dimas Adiputra | AD44: TE | AE44: ITTELKOM Surabaya | AH44: Rifky Dwi Putranto | AI44: TE | AJ44: ITTELKOM Surabaya | AM44: Rafly Daffaldi | AO44: ITTELKOM Surabaya | AR44: Dinda Karisma Ulfa | AT44: ITTELKOM Surabaya
A45: 5G Network as a Technology to Fight Covid-19 Pan-demic in Indonesia: a Review | B45: Journal of Computer, Electronic, and Telecommunication (COMPLETE) 2 (2), 2021 | D45: Jurnal ber-ISSN | H45: 2021 | I45: Hamzah U. Mustakim | L45: TT | M45: ITTELKOM Surabaya | N45: Hamzah U. Mustakim | O45: TT | P45: ITTELKOM Surabaya | S45: Billy Montolalu | T45: TK | U45: ITTELKOM Surabaya | X45: Isa Hafidz | Y45: TE | Z45: ITTELKOM Surabaya
A46: Ulcerative colitis in hemophilia a patient: case report | B46: Materia Socio-medica 33 (1), 75, 2021 | D46: Buku | H46: 2021 | N46: Fauzi Yusuf | P46: Universitas Syiah Kuala | S46: Reno Keumalazia Kamarlis | U46: Universitas Syiah Kuala | X46: Muhsin | Y46: TT | Z46: ITTELKOM Surabaya
A47: Alterations of Gut Microbiota Composition in Severe Acute Respiratory Syndrome Coronavirus 2 Infection: A Brief Review | B47: Annals of the Romanian Society for Cell Biology 25 (6), 13136-13143, 2021 | D47: Q4 | H47: 2021 | I47: Fauzi Yusuf | M47: Universitas Syiah Kuala | N47: Fauzi Yusuf | P47: Universitas Syiah Kuala | S47: Azzaki Abubakar | U47: Universitas Syiah Kuala | X47: Desi Maghfirah | Z47: Universitas Syiah Kuala | AC47: Muhsin | AD47: TT | AE47: ITTELKOM Surabaya | AH47: Marhami Fahriani | AJ47: Universitas Syiah Kuala | AM47: Muhammad Iqhrammullah | AO47: Universitas Syiah Kuala
A48: Anxiety to COVID-19 pandemic amongst university students is related with gastrointestinal symptoms | B48: Bali Medical Journal 10 (2), 847-850, 2021 | D48: Q4 | H48: 2021 | I48: Azzaki Abubakar | M48: Universitas Syiah Kuala | N48: Azzaki Abubakar | P48: Universitas Syiah Kuala | S48: Muhammad Fadhlan Ma'ruf | U48: Universitas Syiah Kuala | X48: Muhammad Mizfaruddin | Z48: Universitas Syiah Kuala | AC48: Fauzi Yusuf | AE48: Universitas Syiah Kuala | AH48: Desi Maghfirah | AJ48: Universitas Syiah Kuala | AM48: Muhsin | AN48: TT | AO48: ITTELKOM Surabaya
A49: Implementasi Process Mining pada Proses Praktik Kerja Lapangan (PKL) | B49: Techno. Com 20 (4), 579-587, 2021 | D49: S3 | E49: SINTA | H49: 2021 | N49: Afina Lina Nurlaili | P49: UPN Veteran Jatim | S49: Muhsin | T49: TT | U49: ITTELKOM Surabaya | X49: Eristya Maya Safitri | Z49: UPN Veteran Jatim
A50: Performance Evaluation of Inductive Miner for Internship Program Workflow | B50: Jurnal Mantik 5 (3), 1619-1624, 2021 | D50: S4 | E50: SINTA | H50: 2021 | N50: Afina Lina Nurlaili | P50: UPN Veteran Jatim | S50: Muhsin | T50: TT | U50: ITTELKOM Surabaya | X50: Dhian Satria Yudha Kartika | Z50: UPN Veteran Jatim
A51: Analisis Desain Eksperimen Perbandingan Aplikasi Pencarian Lokasi | B51: Scan: Jurnal Teknologi Informasi dan Komunikasi 16 (2), 29-33, 2021 | D51: Jurnal ber-ISSN | H51: 2021 | I51: Afina Lina Nurlaili | M51: UPN Veteran Jatim | N51: Afina Lina Nurlaili | P51: UPN Veteran Jatim | S51: Mochammad Arief Ridwan | U51: ITS | X51: Muhsin | Y51: TT | Z51: ITTELKOM Surabaya
A52: Sectoral dual-polarized MIMO antenna for 5G-NR band N77 base station | B52: Indonesian Journal of Electrical Engineering and Computer Sciences 21 (3), 2021 | D52: Q2 | H52: 2021 | I52: Muhsin | L52: TT | M52: ITTELKOM Surabaya | N52: Muhsin | O52: TT | P52: ITTELKOM Surabaya | S52: Afina Lina Nurlaili | U52: UPN Veteran Jatim | X52: Aulia Saharani | Y52: TT | Z52: ITTELKOM Surabaya | AC52: Indah Rahmawati Utami | AD52: TT | AE52: ITTELKOM Surabaya
A53: Anomaly detection using control flow pattern and fuzzy regression in port container handling | B53: Journal of King Saud University-Computer and Information Sciences 33 (1), 11-20, 2021 | D53: Q1 | H53: 2021 | I53: Dewi Rahmawati | L53: RPL | M53: ITTELKOM Surabaya | N53: Dewi Rahmawati | O53: RPL | P53: ITTELKOM Surabaya | S53: Riyanarto Sarno | U53: ITS
A54: A New Hybrid Region-Based Segmentation for 2D Corpus Callosum Segmentation | B54: 2021 5th International Conference on Informatics and Computational Sciences &#8230;, 2021 | D54: Prosiding Internasional | H54: 2021 | N54: Dewi Rahmawati | O54: RPL | P54: ITTELKOM Surabaya | S54: Riyanarto Sarno | U54: ITS | X54: Chastine Fatichah | Z54: ITS
A55: Intelligent System for Fall Prediction Based on Accelerometer and Gyroscope of Fatal Injury in Geriatric | B55: JURNAL NASIONAL TEKNIK ELEKTRO, 2021 | D55: S2 | E55: SINTA | H55: 2021 | I55: Dewi Rahmawati | L55: RPL | M55: ITTELKOM Surabaya | N55: Khodijah Amiroh | O55: IT | P55: ITTELKOM Surabaya | S55: Dewi Rahmawati | T55: RPL | U55: ITTELKOM Surabaya | X55: Ardian Yusuf Wicaksono | Y55: RPL | Z55: ITTELKOM Surabaya
A56: Desain Arsitektur IoT untuk Budidaya Gurami | B56: Jurnal Teknologi Informasi dan Ilmu Komputer 8 (1), 111-118, 2021 | D56: S2 | E56: SINTA | H56: 2021 | I56: Yupit Sudianto | L56: SI | M56: ITTELKOM Surabaya | O56: SI | P56: ITTELKOM Surabaya
A57: Polyaniline-atomic Au modified platinum electrode with ionic liquid as configuration for enhanced electrochemical sensing | B57: 2021 IEEE Sensors, 1-4, 2021 | D57: Prosiding Internasional | H57: 2021 | N57: Parthojit Chakraborty | P57: Tokyo Institute of Technology | S57: Hiroki Kawakami | U57: Tokyo Institute of Technology | X57: Anifatul Faricha | Y57: TE | Z57: ITTELKOM Surabaya | AC57: Tso-Fu Mark Chang | AE57: Tokyo Institute of Technology | AH57: Masato Sone | AJ57: Tokyo Institute of Technology | AM57: Takamichi Nakamoto | AO57: Tokyo Institute of Technology
A58: Study of gas sensing measurement using room temperature ionic liquid coated on interdigitated array electrodes and quartz crystal microbalance | B58: 「センサ・マイクロマシンと応用システム」 シンポジウム論文集 電気学会センサ・マイクロマシン部門 [編] 38 (2021) | D58: Prosiding Internasional | H58: 2021 | N58: Anifatul Faricha | O58: TE | P58: ITTELKOM Surabaya | S58: Parthojit Chakraborty | U58: Tokyo Institute of Technology | X58: Tso-Fu Mark Chang | Z58: Tokyo Institute of Technology | AC58: Masato Sone | AE58: Tokyo Institute of Technology | AH58: Takamichi Nakamoto | AJ58: Tokyo Institute of Technology
A59: Unmanned Aerial Vehicle Robot untuk Pemadam Api dengan Rancangan Alat Pemadam yang Efisien | B59: Jurnal Nasional Teknik Elektro | D59: S2 | E59: SINTA | H59: 2021 | I59: Ardiansyah Al Farouq | L59: TK | M59: ITTELKOM Surabaya | N59: Ardiansyah Al Farouq | O59: TK | P59: ITTELKOM Surabaya | S59: Moch. Iskandar Riansyah | T59: TE | U59: ITTELKOM Surabaya | X59: Ahmad Habibi | Y59: TK | Z59: ITTELKOM Surabaya
A60: Customer rejection to guide lead time quotation and pricing decisions | B60: Journal of the Operational Research Society 72 (6), 1358-1372, 2021 | D60: Q1 | H60: 2021 | I60: Ramzi Hammami | M60: Rennes School of Business | N60: Ramzi Hammami | P60: Rennes School of Business | S60: Yannick Frein | U60: University of Grenoble Alpes | X60: Abduh Sayid Albana | Y60: TI | Z60: ITTELKOM Surabaya
A61: PENGARUH PEMBELAJARAN DIGITAL DENGAN MODEL BLANDED POE2WE BAGI SISWA/MAHASISWA | B61: Lomba Karya Tulis Ilmiah 2 (1), 139-148, 2021 | D61: Jurnal tidak ber-ISSN | H61: 2021 | N61: Yesika Purba | P61: ITTELKOM Surabaya | S61: Nur Rizki Madani | U61: ITTELKOM Surabaya | X61: Farrel Abednego Darea | Z61: ITTELKOM Surabaya | AC61: Abduh Sayid Albana | AD61: TI | AE61: ITTELKOM Surabaya
A62: A Parallel Permutation Flow-Shop Scheduling Model by Using a Two-Step Evolutionary Algorithm to Minimize Intermediate Storage with Tolerable Maximum Completion Time | B62: International Journal of Intelligent Engineering and Systems 14 (6), 464-475, 2021 | D62: Q2 | H62: 2021 | I62: Purba Daru Kusuma | M62: Universitas Telkom | N62: Purba Daru Kusuma | P62: Universitas Telkom | S62: Abduh Sayid Albana | T62: TI | U62: ITTELKOM Surabaya
A63: University course timetabling model in joint courses program to minimize the number of unserved requests | B63: International Journal of Advanced Computer Science and Applications 12 (10), 2021 | D63: Q3 | H63: 2021 | N63: Purba Daru Kusuma | P63: Universitas Telkom | S63: Abduh Sayid Albana | T63: TI | U63: ITTELKOM Surabaya
A64: An improved spectral temporal average method for mitigating Doppler effects in V2V communications | B64: International Journal of Vehicle Information and Communication Systems 6 (3 &#8230;, 2021 | D64: Q4 | H64: 2021 | N64: Wahyu Pamungkas | P64: ITTP | S64: Jans Hendry | U64: UGM | X64: Walid Maulana Hadiansyah | Y64: TE | Z64: ITTELKOM Surabaya
A65: Implementation of Importance-Performance Analysis on Integrated Information System Institut Teknologi Telkom Purwokerto | B65: Jurnal Ilmiah Teknik Industri 20 (2), 184-194, 2021 | D65: S2 | E65: SINTA | H65: 2021 | I65: Dina Rachmawaty | M65: ITTP | N65: Dina Rachmawaty | P65: ITTP | S65: Achmad Zaki Yamani | U65: ITTP | X65: Famila Dwi Winati | Z65: ITTP | AC65: Hawwin Mardhiana | AD65: SI | AE65: ITTELKOM Surabaya
A66: USABILITY TESTING OF THE ONLINE PLATFORM FOR SELLING FOODSTUFFS IN INDONESIA | B66: Journal of Industrial Engineering Management 6 (3), 183-193, 2021 | D66: S3 | E66: SINTA | H66: 2021 | N66: Rizqa Amelia Zunaidi | O66: TI | P66: ITTELKOM Surabaya | S66: Adek Dhea Resmi Purbantari | T66: TI | U66: ITTELKOM Surabaya | X66: Hawwin Mardhiana | Y66: SI | Z66: ITTELKOM Surabaya
A67: Analysis of EMG Signals during Stance and Swing Phases for Controlling Magnetorheological Brake applications | B67: Open Engineering 11 (1), 112-119, 2021 | D67: Q2 | H67: 2021 | I67: Nurhazimah Nazmi | M67: Malaysia-Japan International Institute of Technology | N67: Nurhazimah Nazmi | P67: Malaysia-Japan International Institute of Technolog | S67: Mohd Azizi Abdul Rahman | U67: Malaysia-Japan International Institute of Technolog | X67: Saiful Amri Mazlan | Z67: Malaysia-Japan International Institute of Technolog | AC67: Dimas Adiputra | AD67: TE | AE67: ITTELKOM Surabaya | AH67: Irfan Bahiuddin | AJ67: Malaysia-Japan International Institute of Technolog | AM67: Muhammad Kashfi Shabdin | AO67: Malaysia-Japan International Institute of Technolog | AR67: Nurul Afifah Abdul Razak, Mohd Hatta Mohammed Ariff | AT67: Malaysia-Japan International Institute of Technolog
A68: Sensor number optimization using neural network for ankle foot orthosis equipped with magnetorheological brake | B68: Open Engineering 11 (1), 91-101, 2021 | D68: Q2 | H68: 2021 | I68: Mohd Azizi Abdul Rahman | M68: Malaysia-Japan International Institute of Technology | N68: Dimas Adiputra | O68: TE | P68: ITTELKOM Surabaya | S68: Mohd Azizi Abdul Rahman | U68: Malaysia-Japan International Institute of Technolog | X68: Irfan Bahiuddin | Z68: Malaysia-Japan International Institute of Technolog | AC68: Ubaidillah | AE68: Malaysia-Japan International Institute of Technolog | AH68: Nurhazimah Nazmi | AJ68: Malaysia-Japan International Institute of Technolog
A69: Personalized Gait Treatment Using Passive Controllable Ankle Foot Orthosis | B69: IOP Conference Series: Materials Science and Engineering 1096 (1), 012002, 2021 | D69: Prosiding Internasional | H69: 2021 | N69: Mohd Azizi Abdul Rahman | P69: Malaysia-Japan International Institute of Technology | S69: Dimas Adiputra | T69: TE | U69: ITTELKOM Surabaya
A70: IMPLEMENTASI KAHOOT! DALAM MENUNJANG PEMBELAJARAN DARING INTERAKTIF | B70: Lomba Karya Tulis Ilmiah 2 (1), 123-138, 2021 | D70: Jurnal tidak ber-ISSN | H70: 2021 | N70: Muhammad Nasrulloh Mubarak | P70: ITTELKOM Surabaya | S70: Jesica Febriani Nura | U70: ITTELKOM Surabaya | X70: Dimas Adiputra | Y70: TE | Z70: ITTELKOM Surabaya
A71: Simplified Walking Simulation for Tuning a Passive Controllable Ankle Foot Orthosis | B71: Journal of Computer, Electronic, and Telecommunication (COMPLETE) 2 (2), 2021 | D71: Jurnal ber-ISSN | H71: 2021 | I71: Dimas Adiputra | L71: TE | M71: ITTELKOM Surabaya | N71: Dimas Adiputra | O71: TE | P71: ITTELKOM Surabaya
A72: Dasar Pemrograman Dalam Bahasa C | B72: Deepublish, 2021 | D72: Buku | H72: 2021 | N72: Bernadus Anggo Seno Aji | O72: IT | P72: ITTELKOM Surabaya | S72: Farah Zakiyah Rahmanti | T72: IT | U72: ITTELKOM Surabaya
A73: Undergraduate Thesis System Information Service Evaluation Using UTAUT–5 Factors Based Chatbot | B73: 2021 International Seminar on Application for Technology of Information and Communication (iSemantic) | D73: Prosiding Internasional | H73: 2021 | N73: Septian Enggar Sukmana | P73: Politeknik Negeri Malang | S73: Rokhimatul Wakhidah | U73: Politeknik Negeri Malang | X73: Putri Khoirin Nashiroh | Z73: Universitas Negeri Semarang | AC73: Farah Zakiyah Rahmanti | AD73: IT | AE73: ITTELKOM Surabaya
A74: A Study of Conveyor System with UV Light for Vegetable and Fruit Sterilization for Farmer | B74: 2021 International Conference on Computer Science, Information Technology &#8230;, 2021 | D74: Prosiding Internasional | H74: 2021 | N74: Farah Zakiyah Rahmanti | O74: IT | P74: ITTELKOM Surabaya | S74: Bernadus Anggo Seno Aji | T74: IT | U74: ITTELKOM Surabaya | X74: Arliyanti Nurdin | Y74: IT | Z74: ITTELKOM Surabaya | AC74: Wiranti Maharani | AD74: IT | AE74: ITTELKOM Surabaya | AH74: Riska Aprilia | AI74: IT | AJ74: ITTELKOM Surabaya | AM74: Mochammad Rafi Adityawarman | AN74: IT | AO74: ITTELKOM Surabaya
A75: ANALISIS KONTEN PEMBELAJARAN DIGITAL UNTUK MENGUKUR TINGKAT INTERAKSI DAN PEMAHAMAN MAHASISWA | B75: Lomba Karya Tulis Ilmiah 2 (1), 115-122, 2021 | D75: Jurnal tidak ber-ISSN | H75: 2021 | N75: Muhammad Bayu Prasetyo | P75: ITTELKOM Surabaya | S75: Adrianus Satria Pinandita | U75: ITTELKOM Surabaya | X75: Yakfi Zamzami Achmad | Z75: ITTELKOM Surabaya | AC75: Wahyu Andy Prastyabudi | AD75: TI | AE75: ITTELKOM Surabaya
A76: Penerapan System Thinking Untuk Peningkatan Branding dan Optimalisasi Manajemen Usaha Pada UKM Handy Craft Az-Zahra | B76: Prosiding Konferensi Nasional Pengabdian Kepada Masyarakat dan Corporate &#8230;, 2021 | D76: Prosiding Nasional | H76: 2021 | N76: Arda Erico Yuda | P76: ITTELKOM Surabaya | S76: Wahyu Andy Prastyabudi | T76: TI | U76: ITTELKOM Surabaya | X76: Muhammad Dzulfikar Fauzi | Y76: IF | Z76: ITTELKOM Surabaya | AC76: Arliyanti Nurdin | AD76: IT | AE76: ITTELKOM Surabaya
A77: An Inventory Policy On Agroindustry Supply Chain: A Case Study Of Fruit Seasonal In East Java | B77: Food &amp; Agribusiness Management (FABM) 2 (2), 46-50, 2021 | D77: Jurnal ber-ISSN | H77: 2021 | I77: Paramaditya Arismawati | L77: TI | M77: ITTELKOM Surabaya | N77: Paramaditya Arismawati | O77: TI | P77: ITTELKOM Surabaya | S77: Wahyu Andy Prastyabudi | T77: TI | U77: ITTELKOM Surabaya
A78: A CONCEPTUAL DESIGN OF WASTE MANAGEMENT: SMART BIN DEPLOYMENT IN SURABAYA SMART CITY | B78: Acta Mechanica Malaysia | D78: Jurnal ber-ISSN | H78: 2021 | I78: Wahyu Andy Prastyabudi | L78: TI | M78: ITTELKOM Surabaya | N78: Wahyu Andy Prastyabudi | O78: TI | P78: ITTELKOM Surabaya | S78: Oktavia Ayu Permata | T78: IT | U78: ITTELKOM Surabaya
A79: PERLUASAN PLATFORM E-LEARNING UNTUK MENUNJANG PEMBELAJARAN DI DAERAH TERPENCIL | B79: Lomba Karya Tulis Ilmiah 2 (1), 99-108, 2021 | D79: Jurnal tidak ber-ISSN | H79: 2021 | N79: Rafi Juniar Saputra | P79: ITTELKOM Surabaya | S79: Asri Kartika Dewi | U79: ITTELKOM Surabaya | X79: Era Anzha Naelil Munna | Z79: ITTELKOM Surabaya | AC79: Wahyu Andy Prastyabudi | AD79: TI | AE79: ITTELKOM Surabaya
A80: Notifikasi Real-time Pada Sistem Nurse Call Nirkabel Berbasis Zigbee Menggunakan Protokol WebSocket | B80: SYSTEMIC (Information System and Informatic Journal) 7 (1), 49-54, 2021 | D80: S4 | E80: SINTA | H80: 2021 | N80: Billy Montolalu | O80: TK | P80: ITTELKOM Surabaya | S80: Hamzah Ulinuha Mustakim | T80: TT | U80: ITTELKOM Surabaya | X80: Nilla Rachmaningrum | Y80: TT | Z80: ITTELKOM Surabaya
A81: A Study of Human State Pattern Acquisition Method for Partner Robots | B81: 2021 International Symposium on Micro-NanoMehatronics and Human Science (MHS &#8230;, 2021 | D81: Prosiding Internasional | H81: 2021 | N81: Nao Yamada | P81: Tokyo Metropolitan University | S81: Yani Mohamad | T81: TK | U81: ITTELKOM Surabaya | X81: Naoyuki Kubota | Z81: Tokyo Metropolitan University
A82: Gradient-Free Deep Q-Networks Reinforcement learning: Benchmark and Evaluation | B82: 2021 IEEE Symposium Series on Computational Intelligence (SSCI), 1-5, 2021 | D82: Prosiding Internasional | H82: 2021 | N82: Yani Mohamad | O82: TK | P82: ITTELKOM Surabaya | S82: Fernando Ardilla | U82: PENS | X82: Azhar Aulia Saputra | Z82: Tokyo Metropolitan University | AC82: Naoyuki Kubota | AE82: Tokyo Metropolitan University
A83: Deep Convolutional Networks with Genetic Algorithm for Reinforcement Learning Problem | B83: The 7th International Workshop on Advanced Computational Intelligence and &#8230;, 2021 | D83: Prosiding Internasional | H83: 2021 | N83: Yani Mohamad | O83: TK | P83: ITTELKOM Surabaya | S83: Naoyuki Kubota | U83: Tokyo Metropolitan University
A84: Pengembangan Sistem Penukaran Tiket Suroboyo Bus Melalui Digitalisasi Pencatatan Penukaran Sampah Berbasis Android | B84: JEPIN (Jurnal Edukasi dan Penelitian Informatika) 7 (1), 100-105, 2021 | D84: S2 | E84: SINTA | H84: 2021 | N84: Oktavia Ayu Permata | O84: IT | P84: ITTELKOM Surabaya | S84: Khodijah Amiroh | T84: IT | U84: ITTELKOM Surabaya | X84: Auldy Ansya Rullah | Y84: IT | Z84: ITTELKOM Surabaya
A85: CARITA: PENDIDIKAN KARAKTER ANAK USIA DINI MELALUI SERIAL WEBTOON INTERAKTIF | B85: Lomba Karya Tulis Ilmiah 2 (1), 177-190, 2021 | D85: Jurnal tidak ber-ISSN | H85: 2021 | N85: Berliana Amelia Aryanti Zain | P85: ITTELKOM Surabaya | S85: Alfito De Vaga Mayavanny | U85: ITTELKOM Surabaya | X85: Muhammad Ma`'sum Juniyanto | Z85: ITTELKOM Surabaya | AC85: Oktavia Ayu Permata | AD85: IT | AE85: ITTELKOM Surabaya
A86: Implementation of dosimetry protocol for radionuclide therapy in Indonesia: Collaborative works in nuclear medicine | B86: AIP Conference Proceedings 2346 (1), 030007, 2021 | D86: Prosiding Internasional | H86: 2021 | I86: N. R. Hidayati | M86: Center for Technology of Radiation Safety and Metrology | N86: N. R. Hidayati | P86: Center for Technology of Radiation Safety and Metrology | S86: W. Mailana | U86: Center for Technology of Radiation Safety and Metrology | X86: Pangestu Widodo | Y86: RPL | Z86: ITTELKOM Surabaya | AC86: A. R. Dewi | AE86: Dharmais National Cancer Hospital | AH86: E. Rosilawaty | AJ86: Hasan Sadikin General Hospital | AM86: E. Rosilawaty | AO86: Hasan Sadikin General Hospital | AR86: R. Shintawati H. Budiawan A. H. S. Kartamihardja I. A. S. Mu'minah | AT86: Hasan Sadikin General Hospital Hasan Sadikin General Hospital Hasan Sadikin General Hospital Universitas Indonesia Depok
A87: Sidelobe level suppression and scan-loss compensation in a wide-angular scanning linear array using subarrays amplitude control | B87: 2020 50th European Microwave Conference (EuMC), 352-355, 2021 | D87: Prosiding Internasional | H87: 2021 | N87: Fannush S. Akbar | O87: TT | P87: ITTELKOM Surabaya | S87: Leo Ligthart | U87: Delft University of Technology | X87: Gamantyo Hendrantoro | Z87: ITS | AC87: Ioan E. Lager | AE87: Delft University of Technology
A88: Linear Array Thinning with Cavity backed U-slot Patch Antenna using Genetic Algorithm | B88: Journal of Science and Applicative Technology 5 (1), 9-16, 2021 | D88: S4 | E88: SINTA | H88: 2021 | I88: Novalia Pertiwi | M88: nstitut Teknologi Sumatera | N88: Novalia Pertiwi | P88: Institut Teknologi Sumatera | S88: Fannush S. Akbar | T88: TT | U88: ITTELKOM Surabaya | X88: Eko Setijadi | Z88: ITS | AC88: Gamantyo Hendrantoro | AE88: ITS
A89: A Toolbox of Subarrays for Optimizing Wide-Angular Scanning Arrays Using Trade-Offs Between Scan Loss and Side Lobe Level | B89: IEEE Access 9, 16337-16359, 2021 | D89: Q1 | H89: 2021 | I89: Gamantyo Hendrantoro | M89: ITS | N89: Fannush S. Akbar | O89: TT | P89: ITTELKOM Surabaya | S89: Leo Ligthart | U89: Delft University of Technology | X89: Gamantyo Hendrantoro | Z89: ITS
A90: The Use Of Subarrays In Sparse Phased Array Antenna For Wide-Angular Scanning Radar Applications | B90: Institut Teknologi Sepuluh Nopember, 2021 | D90: Doctoral Thesis | H90: 2021 | I90: Fannush S. Akbar | L90: TT | M90: ITTELKOM Surabaya | N90: Fannush S. Akbar | O90: TT | P90: ITTELKOM Surabaya
A91: Dampak Pandemi Covid-19 Terhadap Pengangguran Di Indonesia | B91: JISIP (Jurnal Ilmu Sosial dan Pendidikan) 5 (4), 2021 | D91: S5 | E91: SINTA | H91: 2021 | I91: Verina Ruth Krisnandika | M91: Sekolah Tinggi Media Nusantara Citra | N91: Verina Ruth Krisnandika | P91: Sekolah Tinggi Media Nusantara Citra | S91: Darlin Aulia | T91: DB | U91: ITTELKOM Surabaya | X91: Luluul Jannah | Z91: Sekolah Tinggi Media Nusantara Citra
A92: Pengaruh Covid-19 Terhadap Perekonomian Di Negara Asean | B92: JISIP (Jurnal Ilmu Sosial Dan Pendidikan) 5 (3), 2021 | D92: S5 | E92: SINTA | H92: 2021 | I92: Azzahra Aulia Dewi | M92: Sekolah Tinggi Media Nusantara Citra | N92: Azzahra Aulia Dewi | P92: Sekolah Tinggi Media Nusantara Citra | S92: Darlin Aulia | T92: DB | U92: ITTELKOM Surabaya | X92: Kurnia Indah Sumunar | Z92: Sekolah Tinggi Media Nusantara Citra | AC92: Erni Hernawati | AE92: Sekolah Tinggi Media Nusantara Citra
A93: Pengaruh Female Independent Directors dan Family Ownership terhadap Financial Reporting Quality dengan Financial Irregulaties sebagai Variabel Moderasi | B93: JISIP (Jurnal Ilmu Sosial dan Pendidikan) 5 (4), 2021 | D93: S5 | E93: SINTA | H93: 2021 | I93: Darlin Aulia | L93: DB | M93: ITTELKOM Surabaya | N93: Darlin Aulia | O93: DB | P93: ITTELKOM Surabaya | S93: Kurnia Indah Sumunar | U93: Sekolah Tinggi Media Nusantara Citra | X93: Luluul Jannah | Z93: Sekolah Tinggi Media Nusantara Citra
A94: Pengaruh Female Tainted Director Terhadap Biaya Audit dan Kualitas Laporan Keuangan dengan Variabel Moderasi Political Connection | B94: JISIP (Jurnal Ilmu Sosial dan Pendidikan) 5 (4), 2021 | D94: S5 | E94: SINTA | H94: 2021 | I94: Budi S. Kramadibrata | M94: Sekolah Tinggi Media Nusantara Citra | N94: Budi S. Kramadibrata | P94: Sekolah Tinggi Media Nusantara Citra | S94: Darlin Aulia | T94: DB | U94: ITTELKOM Surabaya | X94: Rizal Kamsurya | Z94: Sekolah Tinggi Ilmu Keguruan dan Ilmu Pendidikan Media Nusantara Citra
A95: Dampak Financial Technology (Fintech) Dan Intellectual Capital Terhadap Kinerja Keuangan Perbankan Komersial di Indonesia | B95: SEIKO: Journal of Management &amp; Business 4 (2), 198-202, 2021 | D95: S4 | E95: SINTA | H95: 2021 | I95: Muhammad Fauzan Tanjung | M95: Sekolah Tinggi Media Nusantara Citra | N95: Muhammad Fauzan Tanjung | P95: Sekolah Tinggi Media Nusantara Citra | S95: Darlin Aulia | T95: DB | U95: ITTELKOM Surabaya
A96: Kegiatan Pengabdian Masyarakat IT Telkom Purwokerto Berupa Optimasi Produk Kopi Di Desa Melung Pasca Pandemi Corona Virus Disease (COVID-19) | B96: Magistrorum et Scholarium: Jurnal Pengabdian Masyarakat 1 (3), 347-360, 2021 | D96: Jurnal ber-ISSN | H96: 2021 | I96: Kholidiyah Masykuroh | M96: ITTP | N96: Nanda Iryani | O96: TK | P96: ITTELKOM Surabaya | S96: Sarah Astiti | U96: ITTP | X96: Kholidiyah Masykuroh | Z96: ITTP
A97: Prototype smart door lock by using wireless network based on arduino uno | B97: 2021 IEEE International Conference on Communication, Networks and Satellite &#8230;, 2021 | D97: Prosiding Internasional | H97: 2021 | N97: Kholidiyah Masykuroh | P97: ITTP | S97: Fikra Titan Syifa | U97: ITTP | X97: Gatot Rizky Setiyanto | Z97: ITTP | AC97: Afifah Dwi Ramadhani | AE97: ITTP | AH97: Danny Kurnianto | AJ97: ITTP | AM97: Nanda Iryani | AN97: TK | AO97: ITTELKOM Surabaya
A98: Analisis Performansi Routing OSPF menggunakan RYU Controller dan POX Controller pada Software Defined Networking | B98: InComTech: Jurnal Telekomunikasi dan Komputer 11 (1), 73-84, 2021 | D98: S3 | E98: SINTA | H98: 2021 | I98: Nanda Iryani | L98: TK | M98: ITTELKOM Surabaya | N98: Nanda Iryani | O98: TK | P98: ITTELKOM Surabaya | S98: Afifah Dwi Ramadhani | U98: ITTP | X98: Mayang Karmila Sari | Z98: ITTP
A99: Analisis Performansi Dynamic Multipoint Virtual Private Network pada Routing Protocol BGP dengan FRRouting. 6 (1) | B99: JTERA (Jurnal Teknologi Rekayasa), 6(1), 61-66 | D99: S3 | E99: SINTA | H99: 2021 | I99: Nanda Iryani | L99: TK | M99: ITTELKOM Surabaya | N99: Nanda Iryani | O99: TK | P99: ITTELKOM Surabaya | S99: Dyas Dendi Andika | U99: ITTP
A100: Analisis Perbandingan Performansi Eksternal Border Gateway Protocol (EBGP) pada Jaringan Konvensional dan Jaringan Software Defined Network | B100: RESISTOR (Elektronika Kendali Telekomunikasi Tenaga Listrik Komputer) 4 (2 &#8230;, 2021 | D100: S4 | E100: SINTA | H100: 2021 | N100: Lu’lu’ Hasna’ Mahdiyah | P100: ITTP | S100: Jafaruddin Gusti Amri Ginting | U100: ITTP | X100: Nanda Iryani | Y100: TK | Z100: ITTELKOM Surabaya
...

Sheet Pivot Publikasi
A1: Tahun Published | B1: 2025
A2: Lembaga Pengindeks | B2: (Beberapa Item)
A4: Akreditasi/ Index Jurnal | B4: Count of Akreditasi/ Index Jurnal
A5: Jurnal ber-ISSN | B5: 2
A6: S2 | B6: 2
A7: S3 | B7: 13
A8: S4 | B8: 10
A9: S5 | B9: 3
A10: S6 | B10: 1
A11: (kosong)
A12: Total Keseluruhan | B12: 31

Sheet Pivot Data KI
A1: APPLICATION YEAR | B1: 2025
A3: Count of Kategori | C3: Status
A4: Kategori | B4: Jenis HKI | C4: (PA) Diberi Paten | D4: Granted | E4: (PA) Pemeriksaan Formalitas | F4: Grand Total
A5: Hak Cipta | B5: Karya Lainnya (Program Komputer) | D5: 58 | F5: 58
B6: Karya Tulis | D6: 33 | F6: 33
B7: Buku Panduan/Petunjuk | D7: 1 | F7: 1
B8: Karya Rekaman Video | D8: 1 | F8: 1
B9: Modul | D9: 1 | F9: 1
A10: Hak Cipta Total | D10: 94 | F10: 94
A11: Paten | B11: Alat / Sistem | E11: 1 | F11: 1
A12: Paten Total | E12: 1 | F12: 1
A13: Paten Sederhana | B13: Alat / Sistem | C13: 2 | F13: 2
B14: Metode | C14: 3 | E14: 4 | F14: 7
A15: Paten Sederhana Total | C15: 5 | E15: 4 | F15: 9
A16: DESAIN INDUSTRI | B16: Satu Kesatuan Desain (Set) | E16: 1 | F16: 1
A17: DESAIN INDUSTRI Total | E17: 1 | F17: 1
A18: Grand Total | C18: 5 | D18: 94 | E18: 6 | F18: 105

Sheet Program start Up
A2: No | B2: Prodi | C2: Nama Tim | D2: Kategori Program
A3: 1 | B3: Digital Bisnis | C3: Kustompedia | D3: Faculty Joint Incubation Program (FJIP)
A4: 2 | B4: Teknik Industri | C4: Etechting | D4: Faculty Joint Incubation Program (FJIP)
A5: 3 | B5: Teknik Komputer | C5: EsTehAnget | D5: Faculty Joint Incubation Program (FJIP)
A6: 4 | B6: Teknik Komputer | C6: LokaThings | D6: Faculty Joint Incubation Program (FJIP)
A7: 5 | B7: Sistem Informasi | C7: Devinit | D7: WRAP Entrepreneurship
A8: 6 | B8: Informatika | C8: Solusi Ketenagakerjaan | D8: WRAP Entrepreneurship
A9: 7 | B9: Informatika | C9: Berdaya | D9: WRAP Entrepreneurship
A10: 8 | B10: Digital Bisnis | C10: Mesti Minum | D10: WRAP Entrepreneurship
A11: 9 | B11: Informatika | C11: Sistem Informasi Koperasi | D11: WRAP Entrepreneurship

Sheet DATA PNLT KHUSUS AKRE 2025
A1: No | B1: No. SK | C1: No. Kontrak | D1: Judul Penelitian | E1: Nama Skema | F1: Tahun Usulan | G1: Tahun Pelaksanaan Kegiatan | H1: Lama Kegiatan (bulan) | I1: Bidang Fokus | J1: Dana Disetujui | K1: Nama Institusi Penerima Dana | L1: Target TKT | M1: Nama Program Hibah | N1: Kategori Sumber Dana | O1: Negara Sumber Dana | P1: Sumber Dana | Q1: Sinta ID Ketua | R1: Nama Ketua | S1: NIDN Ketua | T1: DANA KETUA | U1: Prodi Ketua | V1: Prodi Ketua (2) | W1: Prodi Ketua (3) | X1: Fakultas Ketua | Y1: Institusi Ketua | Z1: Sinta ID Institusi Ketua | AA1: Kode PT Ketua | AB1: Sinta ID Member1 | AC1: NIDN Member1 | AD1: Nama Anggota 1 | AE1: Dana Anggota 1 | AF1: Prodi Member 1 | AG1: Prodi Member 1 (2) | AH1: Prodi Anggota 1 (3) | AI1: Fakultas | AJ1: PT | AK1: Sinta ID Member2 | AL1: NIDN Member2 | AM1: Nama Anggota 2 | AN1: Dana Anggota 2 | AO1: Prodi Anggota 2 | AP1: Prodi Anggota 2 (2) | AQ1: Prodi Anggota 2 (3) | AR1: Fakultas3 | AS1: PT4 | AT1: Sinta ID Member3 | AU1: NIDN Member3 | AV1: Nama Anggota 3 | AW1: Dana Anggota 3 | AX1: Prodi Anggota 3 | AY1: Prodi Anggota 3 (2) | AZ1: Fakultas Anggota 3 | BA1: PT Anggota 3 | BB1: Sinta ID Member4 | BC1: NIDN Member4 | BD1: Nama Member4 | BE1: Dana Anggota 4 | BF1: Prodi Anggota 4 | BG1: Prodi Anggota 4 (2) | BH1: Fakultas Anggota 4 | BI1: PT Anggota 4 | BJ1: Sinta ID Member5 | BK1: NIDN Member5 | BL1: Nama Member5 | BM1: Prodi Anggota 5 | BN1: Fakultas Anggota 5 | BO1: Dana Anggota 5 | BP1: SDG | BQ1: Proposal | BR1: Laporan Akhir | BS1: Nama Mh | BT1: Prodi, Fak, PT Mhs1 | BU1: Nama Mhs2 | BV1: Prodi, Fak, PT Mhs2 | BW1: Nama Mhs3 | BX1: Prodi, Fak, PT Mhs3 | BY1: Nama Mhs4 | BZ1: Prodi Mhs4 | CA1: Nama Mhs5 | CB1: Prodi Mhs5 | CC1: Nama Mhs6 | CD1: Prodi Mhs6 | CE1: Nama Mhs7 | CF1: Prodi Mhs7 | CG1: Luaran Wajib | CH1: Capaian Luaran Wajib | CI1: Luaran Tambahan | CJ1: Capaian Luaran Tambahan
C2: 10/KP/LPPM-UWP/K-1/II/2018 | D2: RANCANGAN TEORI BAPAKISME TERHADAP PRODUKTIFITAS KADER POSYANDU SEBAGAI PENGGUNA SISTEM INFORMASI KMS | E2: Penelitian Hibah Eksternal | F2: 2018 | G2: 2018 | I2: Teknologi Informasi dan Komunikasi | J2: 16750000 | K2: Institut Teknologi Telkom Surabaya | O2: ID | P2: ITTelkom Surabaya | R2: Ully Asfari | T2: =J2 -> 16750000 | U2: Sistem Informasi | X2: FTII | AD2: Ir SUBADERI M.M | AE2: =J2 -> 16750000
C4: 214/PNLT3/PPM/III/2019 | D4: PENGEMBANGAN SISTEM KENDALI KUANTITAS AIR PADA TANAMAN HIDROPONIK BERBASIS INTERNET OF THINGS (IOT) | E4: Penelitian Dana Internal (PDI) | F4: 2019 | G4: 2019 | H4: 10 | J4: 8880000 | K4: Institut Teknologi Telkom Surabaya | L4: 4 | M4: Penelitian Kompetitif Internal | N4: Internal | O4: ID | P4: ITTelkom Surabaya | R4: Ubaidillah Umar | T4: =J4 -> 8880000 | U4: Teknik Komputer | X4: FTE | AD4: Helmy Widyantara | AE4: =J4 -> 8880000 | AF4: Teknologi Informasi | AG4: Sistem Informasi | AI4: FTII | BQ4: Proposal | BR4: Laporan Akhir | BS4: Rizal Fathurrahman | BU4: Alfrido Ramadhana KP
C5: 214/PNLT3/PPM/III/2019 | D5: Superposisi Gelombang Sinus Sebagai Media Pembelajaran Gelombang Dan Bunyi Pada Matakuliah Fisika Dasar Screen reader support enabled. | E5: Penelitian Dana Internal (PDI) | F5: 2019 | G5: 2019 | H5: 6 | J5: 4114000 | K5: Institut Teknologi Telkom Surabaya | L5: 3 | M5: Penelitian Kompetitif Internal | N5: Internal | O5: ID | P5: ITTelkom Surabaya | R5: Dwi Edi Setyawan | T5: =J5 -> 4114000 | U5: Teknik Komputer | X5: FTE | AD5: Billy Montolalu | AE5: =J5 -> 4114000 | AF5: Teknik Komputer | AI5: FTE | BQ5: Proposal | BR5: Laporan Akhir | BS5: Danang Taufik Kurnianto | BU5: Muhammad Syaiful Islam
C6: 214/PNLT3/PPM/III/2019 | D6: Rancang Bangun Modul Praktikum Harmonisasi Nada Sebagai Media Pembelajaran Gelombang Dan Bunyi Pada Matakuliah Fisika Dasar | E6: Penelitian Dana Internal (PDI) | F6: 2019 | G6: 2019 | H6: 6 | J6: 4752000 | K6: Institut Teknologi Telkom Surabaya | L6: 3 | M6: Penelitian Kompetitif Internal | N6: Internal | O6: ID | P6: ITTelkom Surabaya | R6: Dwi Edi Setyawan | T6: =J6 -> 4752000 | U6: Teknik Komputer | X6: FTE | AD6: Ardiansyah Al farouq | AE6: =J6 -> 4752000 | AF6: Teknik Komputer | AI6: FTE | BQ6: Proposal | BR6: Laporan Akhir | BS6: Muhammad Yanuar Muhaimin | BU6: Muhammad Huzaimi Maulana
C7: 214/PNLT3/PPM/III/2019 | D7: Analisis Kepuasan Pelanggan Terhadap Layanan Penyedia Jasa Transportasi Online Menggunakan Fuzzy Service Quality | E7: Penelitian Dana Internal (PDI) | F7: 2019 | G7: 2019 | H7: 8 | J7: 9627000 | K7: Institut Teknologi Telkom Surabaya | M7: Penelitian Kompetitif Internal | N7: Internal | O7: ID | P7: ITTelkom Surabaya | R7: Hawwin Mardhiana | T7: =J7 -> 9627000 | U7: Sistem Informasi | X7: FTII | AD7: Ully Asfari | AE7: =J7 -> 9627000 | AF7: Sistem Informasi | AI7: FTII | AM7: Anfazul Faridatul Azizah | AN7: =J7 -> 9627000 | AO7: Sistem Informasi | AR7: FTII | AV7: Rizqa Amelia Zunaidi | AW7: =J7 -> 9627000 | AX7: Teknik Industri | AZ7: FTII | BQ7: Proposal | BR7: Laporan Akhir | BS7: Tanang Satrio Adi
C8: 214/PNLT3/PPM/III/2019 | D8: Sistem Akuaponik Berbasis IOT pada Urban Farming | E8: Penelitian Dana Internal (PDI) | F8: 2019 | G8: 2019 | H8: 6 | J8: 11120000 | K8: Institut Teknologi Telkom Surabaya | L8: 6 | M8: Penelitian Kompetitif Internal | N8: Internal | O8: ID | P8: ITTelkom Surabaya | R8: Yupit Sudianto | T8: =J8 -> 11120000 | U8: Sistem Informasi | X8: FTII | AD8: Dimas Adiputra | AE8: =J8 -> 11120000 | AF8: Teknik Elektro | AI8: FTE | AM8: Fidi Wincoko Putro | AN8: =J8 -> 11120000 | AO8: Rekayasa Perangkat Lunak | AR8: FTII | AV8: Dominggo Bayu Baskara | AW8: =J8 -> 11120000 | AX8: Teknik Industri | AZ8: FTII | BD8: Noerma Pudji Istyanto | BE8: =J8 -> 11120000 | BF8: Sistem Informasi | BH8: FTII | BQ8: Proposal | BR8: Laporan Akhir | BS8: Tanfirul Roibafi Muhammad | BT8: SI, FTII, ITTS | BU8: Dhimas Bintang Bagaskara | BV8: RPL, FTII, ITTS
C9: 214/PNLT3/PPM/III/2019 | D9: Antena Dengan Beamforming Sederhana Untuk Komunikasi Robot Bergerak | E9: Penelitian Dana Internal (PDI) | F9: 2019 | G9: 2019 | H9: 9 | J9: 11400000 | K9: Institut Teknologi Telkom Surabaya | L9: 4 | M9: Penelitian Kompetitif Internal | N9: Internal | O9: ID | P9: ITTelkom Surabaya | R9: Muhsin | T9: =J9 -> 11400000 | U9: Teknik Telekomunikasi | V9: Teknik Elektro | X9: FTE | AD9: Walid Maulana Hadiansyah | AE9: =J9 -> 11400000 | AF9: Teknik Telekomunikasi | AI9: FTE | AM9: Tri Agus Djoko Kuntjoro | AN9: =J9 -> 11400000 | AO9: Teknik Telekomunikasi | AR9: FTE | BQ9: Proposal | BR9: Laporan Akhir | BS9: Aulia Putri Pramita | BU9: Riski Dwi Nur Cahyanti | BW9: Prasasti Desta Srihadi
C10: 214/PNLT3/PPM/III/2019 | D10: Identifikasi Posisi Kapal Mengunakan Internet Of Thing Sistem Untuk Mengurangi Antrian Kendaraan Truk Di Pelabuhan | E10: Penelitian Dana Internal (PDI) | F10: 2019 | G10: 2019 | H10: 10 | J10: 10125000 | K10: Institut Teknologi Telkom Surabaya | L10: Publikasi paper seminar | M10: Penelitian Kompetitif Internal | N10: Internal | O10: ID | P10: ITTelkom Surabaya | R10: Nilla Rachmaningrum | T10: =J10 -> 10125000 | U10: Teknik Telekomunikasi | X10: FTE | AD10: Hamzah Ulinuha Mustakim | AE10: =J10 -> 10125000 | AF10: Teknik Telekomunikasi | AI10: FTE | AM10: Tri Agus Djoko Kuntjoro | AN10: =J10 -> 10125000 | AO10: Teknik Telekomunikasi | AR10: FTE | BQ10: Proposal | BR10: Laporan Akhir | BS10: RM. Bagastyo Anggoro | BU10: Utami Ika Sulistya Rini
C11: 214/PNLT3/PPM/III/2019 | D11: Transporter Logistik Cerdas "SROBOT" | E11: Penelitian Dana Internal (PDI) | F11: 2019 | G11: 2019 | H11: 5 | J11: 11875000 | K11: Institut Teknologi Telkom Surabaya | L11: 4 | M11: Penelitian Kompetitif Internal | N11: Internal | O11: ID | P11: ITTelkom Surabaya | R11: Moch. Iskandar Riansyah | T11: =J11 -> 11875000 | U11: Teknik Elektro | X11: FTE | AD11: Lora Khaula Amifia | AE11: =J11 -> 11875000 | AF11: Teknik Elektro | AI11: FTE | BQ11: Proposal | BR11: Laporan Akhir | BS11: Putu Duta Hasta Putra | BU11: Getsemani Adi Bagus Maranata H
C12: 214/PNLT3/PPM/III/2019 | D12: Analisis Dan Deteksi Anomali Pada Perubahan Total Electron Content (Tec) Di Lapisan Ionosphare Sebelum Terjadi Gempa Bumi Menggunakan Ensemble Method. (Studi Kasus Gempa Bumi Palu Dan Lombok) | E12: Penelitian Dana Internal (PDI) | F12: 2019 | G12: 2019 | H12: 8 | J12: 3748000 | K12: Institut Teknologi Telkom Surabaya | L12: Jurnal Nasional Terakreditasi | M12: Penelitian Kompetitif Internal | N12: Internal | O12: ID | P12: ITTelkom Surabaya | R12: Bernadus Anggo Seno Aji | T12: =J12 -> 3748000 | U12: Teknologi Informasi | X12: FTII | AD12: Pangestu Widodo | AE12: =J12 -> 3748000 | AF12: Teknik Komputer | AI12: FTE | AM12: Arliyanti Nurdin | AN12: =J12 -> 3748000 | AO12: Teknologi Informasi | AR12: FTII | BQ12: Proposal | BR12: Laporan Akhir | BS12: Muhamad Rizal Dwi Adhipramana
C13: 214/PNLT3/PPM/III/2019 | D13: Simple Digital Wireless Transmitter & Receiver | E13: Penelitian Dana Internal (PDI) | F13: 2019 | G13: 2019 | H13: 10 | J13: 9400000 | K13: Institut Teknologi Telkom Surabaya | L13: HAKI | M13: Penelitian Kompetitif Internal | N13: Internal | O13: ID | P13: ITTelkom Surabaya | R13: Hamzah Ulinuha Mustakim | T13: =J13 -> 9400000 | U13: Teknik Telekomunikasi | X13: FTE | AD13: Nilla Rachmaningrum | AE13: =J13 -> 9400000 | AF13: Teknik Telekomunikasi | AI13: FTE | AM13: Walid Maulana Hadiansyah | AN13: =J13 -> 9400000 | AO13: Teknik Telekomunikasi | AR13: FTE | BQ13: Proposal | BR13: Laporan Akhir | BS13: Ahmad Maulana Rozaq
C14: 214/PNLT3/PPM/III/2019 | D14: Model Lokasi Spatial Dengan Fungsi Permintaan Yang Bergantung Pada Harga, Lokasi, Dan Diskon | E14: Penelitian Dana Internal (PDI) | F14: 2019 | G14: 2019 | H14: 8 | J14: 5296000 | K14: Institut Teknologi Telkom Surabaya | L14: 3 | M14: Penelitian Kompetitif Internal | N14: Internal | O14: ID | P14: ITTelkom Surabaya | R14: Abduh Sayid Albana | T14: =J14 -> 5296000 | U14: Teknik Industri | V14: Teknik Logistik | X14: FTII | AD14: Rahaditya Dimas Prihadianto | AE14: =J14 -> 5296000 | AF14: Teknik Industri | AI14: FTII | AM14: Sinta Dewi | AN14: =J14 -> 5296000 | BQ14: Proposal | BR14: Laporan Akhir | BS14: Muhammad Narendroduto Rokhyadi
C15: 214/PNLT3/PPM/III/2019 | D15: Pengawasan Dan Klasifikasi Kualitas Air Pdam Surabaya Berbasis Internet Of Things | E15: Penelitian Dana Internal (PDI) | F15: 2019 | G15: 2019 | H15: 6 | J15: 10250000 | K15: Institut Teknologi Telkom Surabaya | L15: 4 | M15: Penelitian Kompetitif Internal | N15: Internal | O15: ID | P15: ITTelkom Surabaya | R15: Dimas Adiputra | T15: =J15 -> 10250000 | U15: Teknik Elektro | X15: FTE | AD15: Anifatul Faricha | AE15: =J15 -> 10250000 | AF15: Teknik Elektro | AI15: FTE | AM15: Moch. Iskandar Riansyah | AN15: =J15 -> 10250000 | AO15: Teknik Elektro | AR15: FTE | AV15: Billy Montolalu | AW15: =J15 -> 10250000 | AX15: Teknik Komputer | AZ15: FTE | BQ15: Proposal | BR15: Laporan Akhir | BS15: Fauzan Abdul Rasyid | BU15: Moch. Bagus Indrastata
C16: 214/PNLT3/PPM/III/2019 | D16: Permodelan Permintaan Yang Mempertimbangkan Harga, Lokasi Dan Rebate | E16: Penelitian Dana Internal (PDI) | F16: 2019 | G16: 2019 | H16: 6 | J16: 6800000 | K16: Institut Teknologi Telkom Surabaya | L16: 2 | M16: Penelitian Kompetitif Internal | N16: Internal | O16: ID | P16: ITTelkom Surabaya | R16: Wahyu Andy Prastyabudi | T16: =J16 -> 6800000 | U16: Teknik Industri | X16: FTII | AD16: Sinta Dewi | AE16: =J16 -> 6800000 | AM16: Rizqa Amelia Zunaidi | AN16: =J16 -> 6800000 | AO16: Teknik Industri | AR16: FTII | BQ16: Proposal | BR16: Laporan Akhir | BS16: Nisrina Salsabila
C17: 214/PNLT3/PPM/III/2019 | D17: Koordinasi vd Kompetisi: Aplikasi Hotelling Model Pada Pelabuhan Peti Kemas Surabaya | E17: Penelitian Dana Internal (PDI) | F17: 2019 | G17: 2019 | H17: 10 | J17: 4800000 | K17: Institut Teknologi Telkom Surabaya | L17: 3 | M17: Penelitian Kompetitif Internal | N17: Internal | O17: ID | P17: ITTelkom Surabaya | R17: Rahaditya Dimas Prihadianto | T17: =J17 -> 4800000 | U17: Teknik Industri | X17: FTII | AD17: Abduh Sayid Albana | AE17: =J17 -> 4800000 | AF17: Teknik Industri | AG17: Teknik Logistik | AI17: FTII | AM17: Dominggo Bayu Baskara | AN17: =J17 -> 4800000 | AO17: Teknik Industri | AR17: FTII | BQ17: Proposal | BR17: Laporan Akhir | BS17: Shanggabuana Adhitya Shamaradewa
C18: 214/PNLT3/PPM/III/2019 | D18: Rancang Bangun Sistem Informasi Transportasi Umum Di Surabaya Mengguanakan Google Maps APIs Dan Firebase Pada Perangkat | E18: Penelitian Dana Internal (PDI) | F18: 2019 | G18: 2019 | H18: 10 | J18: 10748000 | K18: Institut Teknologi Telkom Surabaya | L18: Aplikasi Android, Jurnal Nasional Terakreditasi, Seminar Internasional Terindeks IEEE | M18: Penelitian Kompetitif Internal | N18: Internal | O18: ID | P18: ITTelkom Surabaya | R18: Farah Zakiyah Rahmanti | T18: =J18 -> 10748000 | U18: Teknologi Informasi | X18: FTII | AD18: Khodijah Amiroh | AE18: =J18 -> 10748000 | AF18: Teknologi Informasi | AI18: FTII | AM18: Oktavia Ayu Permata | AN18: =J18 -> 10748000 | AO18: Teknologi Informasi | AR18: FTII | AV18: Philip Tobianto Daely | AW18: =J18 -> 10748000 | AX18: Teknologi Informasi | AZ18: FTII | BQ18: Proposal | BR18: Laporan Akhir | BS18: Anas Ittaqullah
C19: 214/PNLT3/PPM/III/2019 | D19: Voice Command Dalam Rumah Pintar Berbasis Internet Of Things | E19: Penelitian Dana Internal (PDI) | F19: 2019 | G19: 2019 | H19: 3 | J19: 8681500 | K19: Institut Teknologi Telkom Surabaya | L19: Artikel Ilmiah dimuat di Jurnal | M19: Penelitian Kompetitif Internal | N19: Internal | O19: ID | P19: ITTelkom Surabaya | R19: Billy Montolalu | T19: =J19 -> 8681500 | U19: Teknik Komputer | X19: FTE | AD19: Ardiansyah Al farouq | AE19: =J19 -> 8681500 | AF19: Teknik Komputer | AI19: FTE | BQ19: Proposal | BR19: Laporan Akhir | BS19: Danu Diningrat | BU19: Alvin Tamado Cahaya
C20: 214/PNLT3/PPM/III/2019 | D20: Pengembangan Sistem Cerdas Untuk Prediksi Jatuh Berbasis Accelerometer Dan Gyroscope Dalam Rangka Pencegahan Cedera Fatal Pada Geriatri | E20: Penelitian Dana Internal (PDI) | F20: 2019 | G20: 2019 | H20: 10 | J20: 10025000 | K20: Institut Teknologi Telkom Surabaya | L20: 3 | M20: Penelitian Kompetitif Internal | N20: Internal | O20: ID | P20: ITTelkom Surabaya | R20: Dewi Rahmawati | T20: =J20 -> 10025000 | U20: Rekayasa Perangkat Lunak | X20: FTII | AD20: Ardian Yusuf Wicaksono | AE20: =J20 -> 10025000 | AF20: Informatika | AI20: FTII | AM20: Khodijah Amiroh | AN20: =J20 -> 10025000 | AO20: Teknologi Informasi | AR20: FTII | AV20: Titus Kristanto | AW20: =J20 -> 10025000 | AX20: Rekayasa Perangkat Lunak | AY20: Sistem Informasi | AZ20: FTII | BQ20: Proposal | BR20: Laporan Akhir
C21: 214/PNLT3/PPM/III/2019 | D21: Manajemen Energi Menggunakan Internet Of Things Untuk Smart Home | E21: Penelitian Dana Internal (PDI) | F21: 2019 | G21: 2019 | H21: 6 | J21: 6574000 | K21: Institut Teknologi Telkom Surabaya | L21: Paper Scopus | M21: Penelitian Kompetitif Internal | N21: Internal | O21: ID | P21: ITTelkom Surabaya | R21: Isa Hafidz | T21: =J21 -> 6574000 | U21: Teknik Elektro | X21: FTE | AD21: Moch. Iskandar Riansyah | AE21: =J21 -> 6574000 | AF21: Teknik Elektro | AI21: FTE | AM21: Dimas Adiputra | AN21: =J21 -> 6574000 | AO21: Teknik Elektro | AR21: FTE | BQ21: Proposal | BR21: Laporan Akhir | BS21: Fathur Alfariz | BU21: Nova H. M. Soetarno
A23: 1 | B23: REK.623/PNLT3/PPM/III/2020 | C23: 544/PNLT3/PPM/III/2020 | D23: PENGARUH TIPE MEDIA SOSIAL TERHADAP HUBUNGAN ANTARA INFORMASI PADA IKLAN PRODUK UKM INDUSTRI SANDANG DENGAN INTENSI MEMBELI PADA INFORMATION ACCEPTANCE MODEL (IACM) | E23: Penelitian Dana Internal (PDI) | F23: 2020 | G23: 2020 | H23: 10 | I23: Manajemen Industri | J23: 4563200 | K23: Institut Teknologi Telkom Surabaya | L23: 1 | N23: Internal | O23: ID | P23: ITTelkom Surabaya | Q23: 6681051 | R23: Rizqa Amelia Zunaidi | S23: 0711069301 | T23: =J23 -> 4563200 | U23: Teknik Industri | X23: FTEIC | AB23: 6680627 | AC23: 0703119301 | AD23: Benazir Imam Arif Muttaqin | AE23: =J23 -> 4563200 | AF23: Teknik Industri | AI23: FTEIC | AJ23: ITTelkom Surabaya | BQ23: Proposal | BR23: Laporan Akhir | CG23: Jurnal Nasional Terakreditasi | CI23: Seminar Internasional
A24: 2 | B24: REK.623/PNLT3/PPM/III/2020 | C24: 545/PNLT3/PPM/III/2020 | D24: Studi Kelayakan Teknologi Klasifikasi Otomatis Berbasis Convolutional Neural Network Pada Sistem Penerimaan Mahasiswa Baru | E24: Penelitian Dana Internal (PDI) | F24: 2020 | G24: 2020 | H24: 10 | I24: Studi Kelayakan | J24: 5820000 | K24: Institut Teknologi Telkom Surabaya | L24: 3 | N24: Internal | O24: ID | P24: ITTelkom Surabaya | Q24: 6682237 | R24: Dominggo Bayu Baskara | S24: 0722069004 | T24: =J24 -> 5820000 | U24: Bisnis Digital | X24: FTIB | AB24: 6680626 | AC24: 0727099201 | AD24: Ardian Yusuf Wicaksono | AE24: =J24 -> 5820000 | AF24: Informatika | AI24: FTIB | AJ24: ITTelkom Surabaya | AK24: 6680628 | AL24: 0730058702 | AM24: Fidi Wincoko Putro | AN24: =J24 -> 5820000 | AO24: Rekayasa Perangkat Lunak | AR24: FTIB | AS24: ITTelkom Surabaya | BQ24: Proposal | BR24: Laporan Akhir | CG24: Jurnal Nasional
A25: 3 | B25: REK.623/PNLT3/PPM/III/2020 | C25: 546/PNLT3/PPM/III/2020 | D25: 2D TO 3D MRI BRAIN SEGMENTATION MENGGUNAKAN U-NET AND MASK R-CNN METHOD UNTUK PENDUDUK DAERAH MARITIM | E25: Penelitian Dana Internal (PDI) | F25: 2020 | G25: 2020 | H25: 10 | I25: Machine Learning | J25: 13337500 | K25: Institut Teknologi Telkom Surabaya | L25: 3 | M25: Penelitian Kompetitif Internal | N25: Internal | O25: ID | P25: ITTelkom Surabaya | Q25: 6680622 | R25: Dewi Rahmawati | S25: 0709039401 | T25: =J25 -> 13337500 | U25: Rekayasa Perangkat Lunak | X25: FTIB | Y25: ITTelkom Surabaya | Z25: 8140 | AA25: 072019 | AB25: 6680626 | AC25: 0727099201 | AD25: Ardian Yusuf Wicaksono | AE25: =J25 -> 13337500 | AF25: Informatika | AI25: FTIB | AJ25: ITTelkom Surabaya | BQ25: Proposal | BR25: Laporan Akhir | CG25: Jurnal Nasional Terakreditasi | CI25: Seminar Internasional
A26: 4 | B26: REK.623/PNLT3/PPM/III/2020 | C26: 547/PNLT3/PPM/III/2020 | D26: Water Monitoring Using Internet of Things (IoT) Gen. 1 | E26: Penelitian Dana Internal (PDI) | F26: 2020 | G26: 2020 | H26: 10 | I26: Kemaritiman | J26: 15883750 | K26: Institut Teknologi Telkom Surabaya | L26: 4 | N26: Internal | O26: ID | P26: ITTelkom Surabaya | Q26: 6680651 | R26: Dimas Adiputra | S26: 0725059301 | T26: =J26 -> 15883750 | U26: Teknik Elektro | X26: FTEIC | AB26: 6680631 | AC26: 0704069202 | AD26: Anifatul Faricha | AE26: =J26 -> 15883750 | AF26: Teknik Elektro | AI26: FTEIC | AJ26: ITTelkom Surabaya | AK26: 6680685 | AL26: 0721068802 | AM26: Moch. Iskandar Riansyah | AN26: =J26 -> 15883750 | AO26: Teknik Elektro | AR26: FTEIC | AS26: ITTelkom Surabaya | BQ26: Proposal | BR26: Laporan Akhir | CG26: Jurnal | CI26: Proseding internasional, Prototype
A27: 5 | B27: REK.623/PNLT3/PPM/III/2020 | C27: 548/PNLT3/PPM/III/2020 | D27: Simulasi Model Hoteliing Pada Pelabuhan Peti Kemas Surabaya | E27: Penelitian Dana Internal (PDI) | F27: 2020 | G27: 2020 | H27: 10 | I27: Simulasi Industri | J27: 5796000 | K27: Institut Teknologi Telkom Surabaya | L27: 3 | N27: Internal | O27: ID | P27: ITTelkom Surabaya | Q27: 6680618 | R27: Rahaditya Dimas Prihadianto | S27: 0725059202 | T27: =J27 -> 5796000 | U27: Teknik Industri | X27: FTEIC | AB27: 6680643 | AC27: 0702039003 | AD27: Abduh Sayid Albana | AE27: =J27 -> 5796000 | AF27: Teknik Logistik | AG27: Teknik Industri | AI27: FTEIC | AJ27: ITTelkom Surabaya | AK27: 6682237 | AL27: 722069004 | AM27: Dominggo Bayu | AN27: =J27 -> 5796000 | AO27: Bisnis Digital | AR27: FTIB | AS27: ITTelkom Surabaya | BQ27: Proposal | BR27: Laporan Akhir | CG27: Jurnal Nasional Terakreditasi | CI27: Seminar Internasional
A28: 6 | B28: REK.623/PNLT3/PPM/III/2020 | C28: 549/PNLT3/PPM/III/2020 | D28: Desain Sistem Monitoring Solar Farm dengan Menggunakan PV Inverter pada Bangunan | E28: Penelitian Dana Internal (PDI) | F28: 2020 | G28: 2020 | H28: 10 | I28: Teknologi Informasi dan Komunikasi | J28: 15035000 | K28: Institut Teknologi Telkom Surabaya | L28: 2 | N28: Internal | O28: ID | P28: ITTelkom Surabaya | Q28: 6680612 | R28: Isa Hafidz | S28: 0728059203 | T28: =J28 -> 15035000 | U28: Teknik Elektro | X28: FTEIC | AB28: 6680683 | AC28: 0729088704 | AD28: Billy Montolalu | AE28: =J28 -> 15035000 | AF28: Rekayasa Perangkat Lunak | AI28: FTIB | AJ28: ITTelkom Surabaya | AK28: 6680741 | AL28: 727059002 | AM28: Hamzah Ulinuha Mustakim | AN28: =J28 -> 15035000 | AO28: Teknik Telekomunikasi | AR28: FTEIC | AS28: ITTelkom Surabaya | BQ28: Proposal | BR28: Laporan Akhir | CG28: Jurnal | CI28: Modul Pelatihan, Modul Praktikum
A29: 7 | B29: REK.623/PNLT3/PPM/III/2020 | C29: 550/PNLT3/PPM/III/2020 | D29: EVAN (Emergency Vehiche Automatic Notification) | E29: Penelitian Dana Internal (PDI) | F29: 2020 | G29: 2020 | H29: 10 | I29: Transportasi | J29: 12530400 | K29: Institut Teknologi Telkom Surabaya | L29: 2 | N29: Internal | O29: ID | P29: ITTelkom Surabaya | Q29: 6682174 | R29: Khodijah Amiroh | S29: 0708069202 | T29: =J29 -> 12530400 | U29: Teknologi Informasi | X29: FTIB | AB29: 6680664 | AC29: 0715128708 | AD29: Farah Zakiyah Rahmanti | AE29: =J29 -> 12530400 | AF29: Teknologi Informasi | AI29: FTIB | AJ29: ITTelkom Surabaya | AK29: 6680680 | AL29: 704039202 | AM29: Bernadus Anggo Seno Aji | AN29: =J29 -> 12530400 | AO29: Teknologi Informasi | AR29: FTIB | AS29: ITTelkom Surabaya | BQ29: Proposal | BR29: Laporan Akhir | CG29: Jurnal Nasional Terakreditasi | CI29: HKI
A30: 8 | B30: REK.623/PNLT3/PPM/III/2020 | C30: 551/PNLT3/PPM/III/2020 | D30: Analisis Karakteristik Peniaian Kinerja Manajerial Terhadap Pengaruh Motivasi Dan Kreativitas Menggunakan Metode Graphic Rating Scale Pada Instansi XYZ | E30: Penelitian Dana Internal (PDI) | F30: 2020 | G30: 2020 | H30: 10 | I30: Teknologi Informasi dan Komunikasi | J30: 6661475 | K30: Institut Teknologi Telkom Surabaya | L30: 3 | N30: Internal | O30: ID | P30: ITTelkom Surabaya | Q30: 259781 | R30: Titus Kristanto | S30: 0710028604 | T30: =J30 -> 6661475 | U30: Bisnis Digital | V30: Sistem Informasi | X30: FTIB | AB30: 6680698 | AC30: 0709128101 | AD30: Mohammad Sholik | AE30: =J30 -> 6661475 | AF30: Rekayasa Perangkat Lunak | AI30: FTIB | AJ30: ITTelkom Surabaya | AK30: 6744406 | AL30: 0709059004 | AM30: Muhamad Nasrullah | AN30: =J30 -> 6661475 | AO30: Sistem Informasi | AR30: FTIB | AS30: ITTelkom Surabaya | BQ30: Proposal | BR30: Laporan Akhir | CG30: Jurnal Nasional Terakreditasi | CI30: Seminar Internasional, Hak Cipta
A31: 9 | B31: REK.623/PNLT3/PPM/III/2020 | C31: 552/PNLT3/PPM/III/2020 | D31: Perancangan Data Warehouse untuk Menunjang Akreditasi Program Studi | E31: Penelitian Dana Internal (PDI) | F31: 2020 | G31: 2020 | H31: 6 | I31: Warehouse Management System | J31: 4600000 | K31: Institut Teknologi Telkom Surabaya | L31: 3 | N31: Internal | O31: ID | P31: ITTelkom Surabaya | Q31: 6764236 | R31: Rokhmatul Insani | S31: 0704068902 | T31: =J31 -> 4600000 | U31: Sistem Informasi | X31: FTIB | AB31: 6665306 | AC31: 0703129001 | AD31: Ully Asfari | AE31: =J31 -> 4600000 | AF31: Sistem Informasi | AI31: FTIB | AJ31: ITTelkom Surabaya | BQ31: Proposal | BR31: Laporan Akhir | CG31: Jurnal Sinta 2 | CI31: Seminar Internasional
A32: 10 | B32: REK.623/PNLT3/PPM/III/2020 | C32: 553/PNLT3/PPM/III/2020 | D32: Penelusuran Sumber Gas Pada Kondisi Turbulensi Mekanis Menggunakan Mobile Robot | E32: Penelitian Dana Internal (PDI) | F32: 2020 | G32: 2020 | H32: 7 | I32: Transportasi | J32: 11932940 | K32: Institut Teknologi Telkom Surabaya | L32: 4 | N32: Internal | O32: ID | P32: ITTelkom Surabaya | Q32: 6680633 | R32: Helmy Widyantara | S32: 0717017902 | T32: =J32 -> 11932940 | U32: Teknologi Informasi | V32: Sistem Informasi | X32: FTIB | AB32: 6680629 | AC32: 0727048809 | AD32: Ubaidillah Umar | AE32: =J32 -> 11932940 | AF32: Teknik Komputer | AI32: FTEIC | AJ32: ITTelkom Surabaya | BQ32: Proposal | BR32: Laporan Akhir | CG32: Jurnal Internasional
A33: 11 | B33: REK.623/PNLT3/PPM/III/2020 | C33: 554/PNLT3/PPM/III/2020 | D33: Antenna MIMO 5G-NR Band N77 dengan Korelasi Rendah untuk Base Station Komunikasi Robot Bergerak | E33: Penelitian Dana Internal (PDI) | F33: 2020 | G33: 2020 | H33: 10 | I33: Teknologi Informasi dan Komunikasi | J33: 11270000 | K33: Institut Teknologi Telkom Surabaya | L33: 4 | N33: Internal | O33: ID | P33: ITTelkom Surabaya | Q33: 6680615 | R33: Muhsin | S33: 0703049401 | T33: =J33 -> 11270000 | U33: Teknik Telekomunikasi | V33: Teknik Elektro | X33: FTEIC | AB33: 6680645 | AC33: 0713108902 | AD33: Walid Maulana Hadiansyah | AE33: =J33 -> 11270000 | AF33: Teknik Telekomunikasi | AI33: FTEIC | AJ33: ITTelkom Surabaya | BQ33: Proposal | BR33: Laporan Akhir | CG33: Jurnal Internasional
A34: 12 | B34: REK.623/PNLT3/PPM/III/2020 | C34: 555/PNLT3/PPM/III/2020 | D34: Transporter Logistik Cerdas dengan Kemampuan Obstacle Avoidance dan Path Planning | E34: Penelitian Dana Internal (PDI) | F34: 2020 | G34: 2020 | H34: 10 | I34: Transportasi | J34: 13337500 | K34: Institut Teknologi Telkom Surabaya | L34: 4 | N34: Internal | O34: ID | P34: ITTelkom Surabaya | Q34: 6680685 | R34: Moch. Iskandar Riansyah | S34: 0721068802 | T34: =J34 -> 13337500 | U34: Teknik Elektro | X34: FTEIC | AB34: 6680708 | AC34: 0706069201 | AD34: Lora Khaula Amifia | AE34: =J34 -> 13337500 | AF34: Teknik Elektro | AI34: FTEIC | AJ34: ITTelkom Surabaya | BQ34: Proposal | BR34: Laporan Akhir | CG34: Jurnal | CI34: Proseding internasional, Prototype
A35: 13 | B35: REK.623/PNLT3/PPM/III/2020 | C35: 556/PNLT3/PPM/III/2020 | D35: Sistem Pelacakan Aset Menggunakan RFID pada ITTelkom Surabaya | E35: Penelitian Dana Internal (PDI) | F35: 2020 | G35: 2020 | H35: 10 | I35: Logistik | J35: 13579200 | K35: Institut Teknologi Telkom Surabaya | L35: 2 | N35: Internal | O35: ID | P35: ITTelkom Surabaya | Q35: 6680664 | R35: Farah Zakiyah Rahmanti | S35: 0715128708 | T35: =J35 -> 13579200 | U35: Teknologi Informasi | X35: FTIB | AB35: 6682174 | AC35: 0708069202 | AD35: Khodijah Amiroh | AE35: =J35 -> 13579200 | AF35: Teknologi Informasi | AI35: FTIB | AJ35: ITTelkom Surabaya | AK35: 6679083 | AL35: 0728069401 | AM35: Philip Tobianto Daely | AN35: =J35 -> 13579200 | AO35: Teknologi Informasi | AR35: FTIB | AS35: ITTelkom Surabaya | BQ35: Proposal | BR35: Laporan Akhir | CG35: Jurnal Nasional Terakreditasi | CI35: HKI
A36: 14 | B36: REK.623/PNLT3/PPM/III/2020 | C36: 557/PNLT3/PPM/III/2020 | D36: Menyelidiki Hasil Pembelajaran dan Menghasilkan Subyektif Mendalam Dalam Pengalaman Logistic Dengan Video 360 | E36: Penelitian Dana Internal (PDI) | F36: 2020 | G36: 2020 | H36: 10 | I36: Virtual Reality, Budaya Organisasi | J36: 8320250 | K36: Institut Teknologi Telkom Surabaya | L36: 2 | N36: Internal | O36: ID | P36: ITTelkom Surabaya | Q36: 6665306 | R36: Ully Asfari | S36: 0703129001 | T36: =J36 -> 8320250 | U36: Sistem Informasi | X36: FTIB | AB36: 6680623 | AC36: 0721088602 | AD36: Yupit Sudianto | AE36: =J36 -> 8320250 | AF36: Sistem Informasi | AI36: FTIB | AJ36: ITTelkom Surabaya | AK36: 6680627 | AL36: 0703119301 | AM36: Benazir Imam Arif Muttaqin | AN36: =J36 -> 8320250 | AO36: Teknik Industri | AR36: FTEIC | AS36: ITTelkom Surabaya | BQ36: Proposal | BR36: Laporan Akhir | CG36: Jurnal Nasional | CI36: Hak Cipta
A37: 15 | B37: REK.661/PNLT3/PPM/III/2020 | C37: 534/SAM4/PPM/III/2020 | D37: Pengembangan sistem kendali kuantitas air pada tanaman hidroponik berbasis Internet of Things (IoT) | E37: Penelitian Dosen Pemula (PDP) | F37: 2020 | G37: 2020 | H37: 10 | I37: Kemaritiman | J37: 19765000 | K37: Institut Teknologi Telkom Surabaya | L37: 2 | M37: Penelitian Kompetitif Nasional | N37: eksternal | O37: ID | Q37: 6680629 | R37: Ubaidillah Umar | S37: 0727048809 | T37: =J37 -> 19765000 | U37: Teknik Komputer | X37: FTEIC | AB37: 6680633 | AC37: 0717017902 | AD37: Helmy Widyantara | AE37: =J37 -> 19765000 | AF37: Teknologi Informasi | AG37: Sistem Informasi | AI37: FTIB | AJ37: ITTelkom Surabaya | BQ37: Proposal | BR37: Proposal | CG37: Jurnal | CI37: Proseding internasional, Prototype
A38: 16 | B38: REK.661/PNLT3/PPM/III/2020 | C38: 535/SAM4/PPM/III/2020 | D38: Implementasi Framework Performance System (PMS) pada Perusahaan Penyedia Jasa Logistik di Indonesia | E38: Penelitian Dosen Pemula (PDP) | F38: 2020 | G38: 2020 | H38: 12 | J38: 19355000 | K38: Institut Teknologi Telkom Surabaya | L38: 2 | N38: eksternal | O38: ID | Q38: 6681051 | R38: Rizqa Amelia Zunaidi | S38: 0711069301 | T38: =J38 -> 19355000 | U38: Teknik Industri | X38: FTEIC | AB38: 6680687 | AC38: 0702048705 | AD38: Wahyu Andy Prastyabudi | AE38: =J38 -> 19355000 | AF38: Teknik Industri | AI38: FTEIC | AJ38: ITTelkom Surabaya | BQ38: Proposal | BR38: Laporan Akhir | CG38: Jurnal Nasional Terakreditasi | CI38: Seminar Internasional,
A39: 17 | B39: REK.661/PNLT3/PPM/III/2020 | C39: 536/SAM4/PPM/III/2020 | D39: Adopsi dan Implementasi I-Gracias di Lemdikti Yayasan Pendidikan Telkom berbasis Knowledge Management System (Studi Kasus: ITTelkom Surabaya) | E39: Penelitian Dosen Pemula (PDP) | F39: 2020 | G39: 2020 | H39: 12 | J39: 18860000 | K39: Institut Teknologi Telkom Surabaya | L39: 2 | N39: eksternal | O39: ID | Q39: 6680634 | R39: Noerma Pudji Istyanto | S39: 0725059004 | T39: =J39 -> 18860000 | U39: Sistem Informasi | X39: FTIB | AB39: 6680622 | AC39: 0709039401 | AD39: Dewi Rahmawati | AE39: =J39 -> 18860000 | AF39: Rekayasa Perangkat Lunak | AI39: FTIB | AJ39: ITTelkom Surabaya | BQ39: Proposal | BR39: Laporan Akhir | CG39: Jurnal Nasional Terakreditasi
A40: 18 | B40: REK.661/PNLT3/PPM/III/2020 | C40: 537/SAM4/PPM/III/2020 | D40: Analisis dan Perancangan Framewrork Sistem Informasi Manajemen Data Perguruan Tinggi di Surabaya | E40: Penelitian Dosen Pemula (PDP) | F40: 2020 | G40: 2020 | H40: 12 | J40: 19721000 | K40: Institut Teknologi Telkom Surabaya | L40: 2 | N40: eksternal | O40: ID | Q40: 259781 | R40: Titus Kristanto | S40: 0710028604 | T40: =J40 -> 19721000 | U40: Bisnis Digital | V40: Sistem Informasi | X40: FTIB | AB40: 6680645 | AC40: 0713108902 | AD40: Walid Maulana Hadiansyah | AE40: =J40 -> 19721000 | AF40: Teknik Telekomunikasi | AI40: FTEIC | AJ40: ITTelkom Surabaya | BQ40: Proposal | BR40: Laporan Akhir | CG40: Jurnal Nasional Terakreditasi | CI40: Buku (berupa buku ajar, monograf, atau buku referensi)
A41: 19 | B41: REK.661/PNLT3/PPM/III/2020 | C41: 538/SAM4/PPM/III/2020 | D41: Deteksi Kerusakan Jalan Raya secara Real Time berbasis perangkat bergerak dengan convolutional neural network | E41: Penelitian Dosen Pemula (PDP) | F41: 2020 | G41: 2020 | H41: 12 | J41: 16000000 | K41: Institut Teknologi Telkom Surabaya | N41: eksternal | O41: ID | Q41: 6680628 | R41: Fidi Wincoko Putro | S41: 0730058702 | T41: =J41 -> 16000000 | U41: Rekayasa Perangkat Lunak | X41: FTIB | Y41: ITTelkom Surabaya | Z41: 8140 | AA41: 072019 | AB41: 6680626 | AC41: 0727099201 | AD41: Ardian Yusuf Wicaksono | AE41: =J41 -> 16000000 | AF41: Informatika | AI41: FTIB | AJ41: ITTelkom Surabaya | AK41: 6680698 | AL41: 0709128101 | AM41: Mohammad Sholik | AN41: =J41 -> 16000000 | AO41: Rekayasa Perangkat Lunak | AR41: FTIB | AS41: ITTelkom Surabaya | BQ41: Proposal | BR41: Laporan Akhir
A42: 20 | B42: REK.661/PNLT3/PPM/III/2020 | C42: 539/SAM4/PPM/III/2020 | D42: Pengembangan sistem penukaran tiket suroboyobus melalui digitalisasi pencatatan penukaran sampah berbasis android | E42: Penelitian Dosen Pemula (PDP) | F42: 2020 | G42: 2020 | J42: 19770000 | K42: Institut Teknologi Telkom Surabaya | N42: eksternal | O42: ID | Q42: 6681205 | R42: Oktavia Ayu Permata | S42: 0705109002 | T42: =J42 -> 19770000 | U42: Teknologi Informasi | X42: FTIB | AB42: 6682174 | AC42: 0708069202 | AD42: Khodijah Amiroh | AE42: =J42 -> 19770000 | AF42: Teknologi Informasi | AI42: FTIB | AJ42: ITTelkom Surabaya | BQ42: Proposal | BR42: Laporan Akhir
A43: 21 | B43: REK.661/PNLT3/PPM/III/2020 | C43: 540/SAM4/PPM/III/2020 | D43: Pengembangan Sistem Nurse Call Nirkabael Berbasis ZigBee untuk Pasien Rawat Inap di RS Umum Daerah Tongas | E43: Penelitian Dosen Pemula (PDP) | F43: 2020 | G43: 2020 | H43: 12 | I43: Teknologi Informasi dan Komunikasi | J43: 16097000 | K43: Institut Teknologi Telkom Surabaya | L43: 2 | N43: eksternal | O43: ID | Q43: 6680683 | R43: Billy Montolalu | S43: 0729088704 | T43: =J43 -> 16097000 | U43: Rekayasa Perangkat Lunak | X43: FTIB | Y43: ITTelkom Surabaya | Z43: 8140 | AA43: 072019 | AB43: 6680741 | AC43: 0727059002 | AD43: Hamzah Ulinuha Mustakim | AE43: =J43 -> 16097000 | AF43: Teknik Telekomunikasi | AI43: FTEIC | AJ43: ITTelkom Surabaya | BQ43: Proposal | BR43: Laporan Akhir | CG43: Jurnal Nasional Terakreditasi
A44: 22 | B44: REK.661/PNLT3/PPM/III/2020 | C44: 541/SAM4/PPM/III/2020 | D44: Pemanfaatan VR dalam perancangan desain tempat kerja dan pengaruhnya terhadap produktivitas | E44: Penelitian Dosen Pemula (PDP) | F44: 2020 | G44: 2020 | H44: 12 | I44: Kemaritiman | J44: 19431000 | K44: Institut Teknologi Telkom Surabaya | L44: 3 | N44: eksternal | O44: ID | Q44: 6680627 | R44: Benazir Imam Arif Muttaqin | S44: 0703119301 | T44: =J44 -> 19431000 | U44: Teknik Industri | X44: FTEIC | AB44: 6665306 | AC44: 0703129001 | AD44: Ully Asfari | AE44: =J44 -> 19431000 | AF44: Sistem Informasi | AI44: FTIB | AJ44: ITTelkom Surabaya | AK44: 6680648 | AL44: 724089201 | AM44: Hawwin Mardhiana | AN44: =J44 -> 19431000 | AO44: Sistem Informasi | AR44: FTIB | AS44: ITTelkom Surabaya | BQ44: Proposal | BR44: Laporan Akhir | CG44: Jurnal Nasional Terakreditasi | CI44: Karya arsitektur
A45: 23 | B45: REK.661/PNLT3/PPM/III/2020 | C45: 542/SAM4/PPM/III/2020 | D45: Deteksi Kecelakaan Lalu Lintas pada Real Time Video | E45: Penelitian Dosen Pemula (PDP) | F45: 2020 | G45: 2020 | H45: 12 | I45: Transportasi | J45: 19990000 | K45: Institut Teknologi Telkom Surabaya | L45: 2 | N45: eksternal | O45: ID | Q45: 6680726 | R45: Arliyanti Nurdin | S45: 0719069101 | T45: =J45 -> 19990000 | U45: Teknologi Informasi | X45: FTIB | AB45: 6680680 | AC45: 0704039202 | AD45: Bernandus Anggo Seno Aji | AE45: =J45 -> 19990000 | AF45: Teknologi Informasi | AI45: FTIB | AJ45: ITTelkom Surabaya | AK45: 6680623 | AL45: 721088602 | AM45: Yupit Sudianto | AN45: =J45 -> 19990000 | AO45: Sistem Informasi | AR45: FTIB | AS45: ITTelkom Surabaya | BQ45: Proposal | BR45: Laporan Akhir | CG45: Jurnal Nasional Terakreditasi
A46: 24 | B46: REK.661/PNLT3/PPM/III/2020 | C46: 543/SAM4/PPM/III/2020 | D46: Pengembangan robot pesawat tanpa awak untuk pemadam kebakaran di lingkungan yang berbahaya | E46: Penelitian Dosen Pemula (PDP) | F46: 2020 | G46: 2020 | H46: 12 | J46: 19800000 | K46: Institut Teknologi Telkom Surabaya | L46: 3 | N46: eksternal | O46: ID | Q46: 6680641 | R46: Ardiansyah Al Farouq | S46: 0714029301 | T46: =J46 -> 19800000 | U46: Teknik Komputer | X46: FTEIC | AB46: 6680685 | AC46: 0721068802 | AD46: Moch.Iskandar Riansyah | AE46: =J46 -> 19800000 | AF46: Teknik Elektro | AI46: FTEIC | AJ46: ITTelkom Surabaya | BQ46: Proposal | BR46: Laporan Akhir | CG46: Jurnal Nasional Terakreditasi | CI46: Program Komputer
A47: 25 | B47: REK. 754/PNLT1/WRI/IV/2020 | C47: 1298/PNLT3/LPPM/VIII/2020 | D47: Lorong Sterilisasi Untuk Membersihkan Virus Corona pada Pakaian Luar Tubuh Manusia | E47: Penelitian Penugasan | F47: 2020 | G47: 2020 | H47: 12 | J47: 85000000 | K47: Institut Teknologi Telkom Surabaya | N47: Internal | O47: ID | Q47: 6680628 | R47: Fidi Wincoko Putro | S47: 0730058702 | T47: =J47 -> 85000000 | U47: Rekayasa Perangkat Lunak | X47: FTIB | Y47: ITTelkom Surabaya | Z47: 8140 | AA47: 072019 | AB47: 6680685 | AC47: 0721068802 | AD47: Moch.Iskandar Riansyah | AE47: =J47 -> 85000000 | AF47: Teknik Elektro | AI47: FTEIC | AJ47: ITTelkom Surabaya | AK47: 6680648 | AL47: 724089201 | AM47: Hawwin Mardhiana | AN47: =J47 -> 85000000 | AO47: Sistem Informasi | AR47: FTIB | AS47: ITTelkom Surabaya | AT47: 6680678 | AU47: 0713068702 | AV47: Dwi Edi Setyawan | AW47: =J47 -> 85000000 | AX47: Teknik Komputer | AZ47: FTEIC | BA47: ITTelkom Surabaya | BQ47: Proposal | BR47: Laporan Akhir
A48: 26 | B48: REK. 754/PNLT1/WRI/IV/2020 | C48: 1299/PNLT3/LPPM/VIII/2020 | D48: Rancang bangun sterillisasi chamber untuk meminimalisir risiko paparan virus COVID-19 | E48: Penelitian Penugasan | F48: 2020 | G48: 2020 | H48: 5 | J48: 50000000 | K48: Institut Teknologi Telkom Surabaya | L48: 3 | N48: Internal | O48: ID | Q48: 6680678 | R48: Dwi Edi Setyawan | S48: 0713068702 | T48: =J48 -> 50000000 | U48: Teknik Komputer | X48: FTEIC | AB48: 6680741 | AC48: 727059002 | AD48: Hamzah Ulinuha Mustakim | AE48: =J48 -> 50000000 | AF48: Teknik Telekomunikasi | AI48: FTEIC | AJ48: ITTelkom Surabaya | AK48: 6682794 | AL48: 721058310 | AM48: Pangestu Widodo | AN48: =J48 -> 50000000 | AO48: Teknik Komputer | AR48: FTEIC | AS48: ITTelkom Surabaya | AT48: 6764236 | AU48: 0704068902 | AV48: Rokhmatul Insani | AW48: =J48 -> 50000000 | AX48: Sistem Informasi | AZ48: FTIB | BA48: ITTelkom Surabaya | BQ48: Proposal | BR48: Laporan Akhir | CG48: Produk
A49: 27 | B49: REK. 754/PNLT1/WRI/IV/2020 | C49: 1300/PNLT3/LPPM/VIII/2020 | D49: Desain Robot Logistik Pembantu Tenaga Medis di Rumah Sakit | E49: Penelitian Penugasan | F49: 2020 | G49: 2020 | H49: 10 | I49: Teknologi Informasi dan Komunikasi | J49: 7500000 | K49: Institut Teknologi Telkom Surabaya | L49: 2 | N49: Internal | O49: ID | Q49: 6680683 | R49: Billy Montolalu | S49: 0729088704 | T49: =J49 -> 7500000 | U49: Rekayasa Perangkat Lunak | X49: FTIB | Y49: ITTelkom Surabaya | Z49: 8140 | AA49: 072019 | AB49: 6680612 | AC49: 728059203 | AD49: Isa Hafidz | AE49: =J49 -> 7500000 | AF49: Teknik Elektro | AI49: FTEIC | AJ49: ITTelkom Surabaya | AK49: 6680633 | AL49: 0717017902 | AM49: Helmy Widyantara | AN49: =J49 -> 7500000 | AO49: Teknologi Informasi | AP49: Sistem Informasi | AR49: FTIB | AS49: ITTelkom Surabaya | BQ49: Proposal | BR49: Laporan Akhir | CG49: Jurnal
A50: 28 | B50: REK. 754/PNLT1/WRI/IV/2020 | C50: 1301/PNLT3/LPPM/VIII/2020 | D50: Robot Sterillisasi Ruang Isolasi/ICU | E50: Penelitian Penugasan | F50: 2020 | G50: 2020 | H50: 3 | J50: 45000000 | K50: Institut Teknologi Telkom Surabaya | L50: 2 | N50: Internal | O50: ID | Q50: 6680633 | R50: Helmy Widyantara | S50: 0717017902 | T50: =J50 -> 45000000 | U50: Teknologi Informasi | V50: Sistem Informasi | X50: FTIB | AB50: 6680685 | AC50: 0721068802 | AD50: Moch.Iskandar Riansyah | AE50: =J50 -> 45000000 | AF50: Teknik Elektro | AI50: FTEIC | AJ50: ITTelkom Surabaya | AK50: 6680683 | AL50: 729088704 | AM50: Billy Montolalu | AN50: =J50 -> 45000000 | AO50: Rekayasa Perangkat Lunak | AR50: FTIB | AS50: ITTelkom Surabaya | BQ50: Proposal | BR50: Laporan Akhir | CG50: HAKI | CI50: Jurnal
A51: 29 | B51: REK. 754/PNLT1/WRI/IV/2020 | C51: 1302/PNLT3/LPPM/VIII/2020 | D51: Swab Chamber untuk Pencegahan Penularan COVID-19 pada Petugas Medis | E51: Penelitian Penugasan | F51: 2020 | G51: 2020 | H51: 12 | I51: Elektronika | J51: 40000000 | K51: Institut Teknologi Telkom Surabaya | N51: Internal | O51: ID | Q51: 6680741 | R51: Hamzah Ulinuha Mustakim | S51: 0727059002 | T51: =J51 -> 40000000 | U51: Teknik Telekomunikasi | X51: FTEIC | AB51: 6680627 | AC51: 0703119301 | AD51: Benazir Imam Arif Muttaqin | AE51: =J51 -> 40000000 | AF51: Teknik Industri | AI51: FTEIC | AJ51: ITTelkom Surabaya | BQ51: Proposal | BR51: Laporan Akhir | CG51: Prototype, HKI
A52: 30 | B52: REK. 754/PNLT1/WRI/IV/2020 | C52: 1303/PNLT3/LPPM/VIII/2020 | D52: Pengembangan portable Non-Invasive Ventilator untuk menghadapi wabah COVID-19 di Jawa Timur, Indonesia | E52: Penelitian Penugasan | F52: 2020 | G52: 2020 | H52: 5 | I52: COVID-19 | J52: 23317000 | K52: Institut Teknologi Telkom Surabaya | L52: 4 | N52: Internal | O52: ID | Q52: 6680651 | R52: Dimas Adiputra | S52: 0725059301 | T52: =J52 -> 23317000 | U52: Teknik Elektro | X52: FTEIC | AB52: 6680633 | AC52: 0717017902 | AD52: Helmy Widyantara | AE52: =J52 -> 23317000 | AF52: Teknologi Informasi | AG52: Sistem Informasi | AI52: FTIB | AJ52: ITTelkom Surabaya | AK52: 6680683 | AL52: 729088704 | AM52: Billy Montolalu | AN52: =J52 -> 23317000 | AO52: Rekayasa Perangkat Lunak | AR52: FTIB | AT52: 6680627 | AU52: 0703119301 | AV52: Benazir Imam Arif Muttaqin | AW52: =J52 -> 23317000 | AX52: Teknik Industri | AZ52: FTEIC | BA52: ITTelkom Surabaya | BB52: 6680612 | BC52: 0728059203 | BD52: Isa Hafidz | BE52: =J52 -> 23317000 | BF52: Teknik Industri | BH52: FTEIC | BI52: ITTelkom Surabaya | BQ52: Proposal | BR52: Laporan Akhir | CG52: Prototype
A53: 31 | B53: REK. 754/PNLT1/WRI/IV/2020 | C53: 1304/PNLT3/LPPM/VIII/2020 | D53: Pengembangan desain APD Face Shield dengan teknologi cetak tridimensi untuk mengatasi kekurangan APD Tenaga Medis COVID-19 | E53: Penelitian Penugasan | F53: 2020 | G53: 2020 | H53: 2 | J53: 2067000 | K53: Institut Teknologi Telkom Surabaya | L53: 6 | N53: Internal | O53: ID | Q53: 6680627 | R53: Benazir Imam Arif Muttaqin | S53: 0703119301 | T53: =J53 -> 2067000 | U53: Teknik Industri | X53: FTEIC | AB53: 6682237 | AC53: 0722069004 | AD53: Dominggo Bayu Baskara | AE53: =J53 -> 2067000 | AF53: Bisnis Digital | AI53: FTIB | AJ53: ITTelkom Surabaya | AK53: 6681051 | AL53: 711069301 | AM53: Rizqa Amelia Zunaidi | AN53: =J53 -> 2067000 | AO53: Teknik Industri | AR53: FTEIC | AT53: 6665306 | AU53: 0703129001 | AV53: Ully Asfari | AW53: =J53 -> 2067000 | AX53: Sistem Informasi | AZ53: FTIB | BA53: ITTelkom Surabaya | BQ53: Proposal | BR53: Laporan Akhir | CG53: Hak Cipta | CI53: Desain Industri
A54: 32 | B54: REK. 941/SAM4/REK/VI/2020 | D54: Cairan Antiseptik untuk Pencegahan Penyebaran Covid -19 | E54: Penelitian kerjasama | F54: 2020 | G54: 2020 | J54: 100000000 | K54: Institut Teknologi Telkom Surabaya | N54: eksternal | O54: ID | Q54: 6680651 | R54: Dimas Adiputra | S54: 0725059301 | T54: =J54 -> 100000000 | U54: Teknik Elektro | X54: FTEIC | AB54: 6805206 | AC54: 8920230021 | AD54: Agus Sulistya | AE54: =J54 -> 100000000 | AF54: Sistem Informasi | AI54: FTIB | AJ54: ITTelkom Surabaya | AT54: 6859016 | AU54: 0727069503 | AV54: Rifki Dwi Putranto | AW54: =J54 -> 100000000 | AX54: Teknik Elektro | AZ54: FTEIC | BA54: ITTelkom Surabaya | BQ54: Proposal | BR54: Laporan Akhir
A55: 33 | B55: REK.1287/PNLT3/REK/VIII/2020 | C55: 1305/PNLT3/LPPM/VIII/2020 | D55: Sterilisasi Udara Pada Ruangan Tertutup Menggunakan Filter Aktif | E55: Penelitian Penugasan | F55: 2020 | G55: 2020 | H55: 3 | J55: 10055000 | K55: Institut Teknologi Telkom Surabaya | N55: Internal | O55: ID | Q55: 6682174 | R55: Khodijah Amiroh | S55: 0708069202 | T55: =J55 -> 10055000 | U55: Teknologi Informasi | X55: FTIB | BQ55: Proposal | BR55: Laporan Akhir | CG55: Prototype | CI55: HAKI
A56: 34 | B56: REK.1287/PNLT3/REK/VIII/2020 | C56: 1306/PNLT3/LPPM/VIII/2020 | D56: Sterilisasi Udara pada AC Untuk Menghadapi Kondisi New Normal | E56: Penelitian Penugasan | F56: 2020 | G56: 2020 | H56: 3 | J56: 9145000 | K56: Institut Teknologi Telkom Surabaya | N56: Internal | O56: ID | Q56: 6680633 | R56: Helmy Widyantara | S56: 0717017902 | T56: =J56 -> 9145000 | U56: Teknologi Informasi | V56: Sistem Informasi | X56: FTIB | BQ56: Proposal | BR56: Laporan Akhir | CG56: Prototype
A57: 35 | B57: REK.1287/PNLT3/REK/VIII/2020 | C57: 1307/PNLT3/LPPM/VIII/2020 | D57: Sterilisasi Udara Portable Untuk Olahragawan Menggunakan Filter Aktif | E57: Penelitian Penugasan | F57: 2020 | G57: 2020 | H57: 3 | J57: 8555000 | K57: Institut Teknologi Telkom Surabaya | N57: Internal | O57: ID | Q57: 6680680 | R57: Bernadus Anggo Seno Aji | S57: 0704039202 | T57: =J57 -> 8555000 | U57: Teknologi Informasi | X57: FTIB | BQ57: Proposal | BR57: Laporan Akhir | CG57: Prototype
A58: 36 | B58: REK. 2031/SAM4/REK/VI/2020 | D58: Penelitian dan Pengembangan Digital Ventilator | E58: Penelitian kerjasama | F58: 2020 | G58: 2020 | J58: 86400000 | K58: Institut Teknologi Telkom Surabaya | N58: eksternal | O58: ID | Q58: 6665306 | R58: Ully Asfari | S58: 0703129001 | T58: =J58 -> 86400000 | U58: Sistem Informasi | X58: FTIB | AK58: 6859016 | AL58: 0727069503 | AM58: Rifki Dwi Putranto | AN58: =J58 -> 86400000 | AO58: Teknik Elektro | AR58: FTEIC | AS58: ITTelkom Surabaya | BQ58: Proposal | BR58: Laporan Akhir
A59: 37 | B59: REK. 925/SAM4/REK/VI/2020 | D59: Crane Pemulasaraan Jenazah Pasien COVID-19 | E59: Penelitian kerjasama | F59: 2020 | G59: 2020 | J59: 200000000 | K59: Institut Teknologi Telkom Surabaya | N59: eksternal | O59: ID | Q59: 6680633 | R59: Helmy Widyantara | S59: 0717017902 | T59: =J59 -> 200000000 | U59: Teknologi Informasi | V59: Sistem Informasi | X59: FTIB | AB59: 6665306 | AC59: 0703129001 | AD59: Ully Asfari | AE59: =T59 -> 200000000 | AF59: Sistem Informasi | AI59: FTIB | AJ59: ITTelkom Surabaya | AT59: 6665306 | AU59: 0703129001 | AV59: Ully Asfari | AW59: =J59 -> 200000000 | AX59: Sistem Informasi | AZ59: FTIB | BA59: ITTelkom Surabaya | BQ59: Proposal | BR59: Laporan Akhir
A61: 1 | B61: REK.086/PNLT1/REK/III/2021 | C61: 997/PNLT1/LPPM/III/2021 | D61: Evaluasi Platform Penjualan Produk Hidroponik dan Aqua ponik | E61: Penelitian Dasar | F61: 2021 | G61: 2021 | H61: 12 | I61: Teknologi Informasi dan Komunikasi | J61: 6750000 | K61: Institut Teknologi Telkom Surabaya | L61: 1 | M61: Penelitian Kompetitif Internal | N61: Internal | O61: ID | P61: ITTelkom Surabaya | Q61: 6681051 | R61: Rizqa Amelia Zunaidi | S61: 0711069301 | T61: =J61 -> 6750000 | U61: Teknik Industri | X61: FTII | Y61: ITTelkom Surabaya | Z61: 8140 | AA61: 072019 | AB61: 6680648 | AC61: 0724089201 | AD61: Hawwin Mardhiana | AE61: =T61 -> 6750000 | AF61: Sistem Informasi | AI61: FTII | AJ61: ITTelkom Surabaya | BQ61: Proposal | BR61: Laporan Akhir | BS61: ADEK DHEA RESMI PURBANTARI | CG61: Jurnal Nasional Terakreditasi | CH61: Accepted | CI61: Seminar Internasional | CJ61: Presented
A62: 2 | B62: REK.086/PNLT1/REK/III/2021 | C62: 998/PNLT1/LPPM/III/2021 | D62: Penerapan Data Mining untuk Menunjang Proses Seleksi Calon Mahasiswa pada ITTelkom Surabaya | E62: Penelitian Dasar | F62: 2021 | G62: 2021 | H62: 10 | I62: Teknologi Informasi dan Komunikasi | J62: 3750000 | K62: Institut Teknologi Telkom Surabaya | L62: 3 | M62: Penelitian Kompetitif Internal | N62: Internal | O62: ID | P62: ITTelkom Surabaya | Q62: 6764236 | R62: Rokhmatul Insani | S62: 0704068902 | T62: =J62 -> 3750000 | U62: Sistem Informasi | X62: FTII | Y62: ITTelkom Surabaya | Z62: 8140 | AA62: 072019 | AB62: 6744406 | AC62: 0709059004 | AD62: Muhammad Nasrullah | AE62: =T62 -> 3750000 | AF62: Sistem Informasi | AI62: FTII | AJ62: ITTelkom Surabaya | AK62: 6681032 | AL62: 0715039004 | AM62: Anfazul Faridatul Azizah | AN62: =T62 -> 3750000 | AO62: Sistem Informasi | AR62: FTII | AS62: ITTelkom Surabaya | BQ62: Proposal | BR62: Laporan Akhir | BS62: BONNIE FERDINAND AKBAR | BU62: EDRIAND IMENS RAYGRANDI | BW62: RAHMAT ANDIKA LAKSANA | CG62: Jurnal Nasional Terakreditasi | CH62: - | CI62: HKI
A63: 3 | B63: REK.086/PNLT1/REK/III/2021 | C63: 999/PNLT1/LPPM/III/2021 | D63: Strategi Optimalisasi Kegiatan Petani Garam dan Peningkatan Produktivitas Garam dengan Pendekatan Simulasi Sistem Dinamik (Studi kasus: Kawasan Tambak Cemandi Sidoarjo) | E63: Penelitian Dasar | F63: 2021 | G63: 2021 | H63: 10 | I63: Kemaritiman | J63: 7000000 | K63: Institut Teknologi Telkom Surabaya | L63: 1 | M63: Penelitian Kompetitif Internal | N63: Internal | O63: ID | P63: ITTelkom Surabaya | Q63: 6680648 | R63: Hawwin Mardhiana | S63: 0724089201 | T63: =J63 -> 7000000 | U63: Sistem Informasi | X63: FTII | Y63: ITTelkom Surabaya | Z63: 8140 | AA63: 072019 | AB63: 6681051 | AC63: 0711069301 | AD63: Rizqa Amelia Zunaidi | AE63: =T63 -> 7000000 | AF63: Teknik Industri | AI63: FTII | AJ63: ITTelkom Surabaya | AK63: 6680627 | AL63: 0703119301 | AM63: Benazir Imam Arif Muttaqin | AN63: =T63 -> 7000000 | AO63: Teknik Industri | AR63: FTII | AS63: ITTelkom Surabaya | BQ63: Proposal | BR63: Laporan Akhir | BS63: SITI AMINAH | BU63: WIDAYATULLAH RA | BW63: ACHMAD DAFA FIRDAUS | CG63: - | CH63: - | CI63: -
A64: 4 | B64: REK.086/PNLT1/REK/III/2021 | C64: 1000/PNLT1/LPPM/III/2021 | D64: Pakan Ikan Otomatis Menggunakan Fuzzy Logic Berbasis IoT | E64: Penelitian Dasar | F64: 2021 | G64: 2021 | H64: 10 | I64: Pangan-Pertanian | J64: 6995000 | K64: Institut Teknologi Telkom Surabaya | L64: 3 | M64: Penelitian Kompetitif Internal | N64: Internal | O64: ID | P64: ITTelkom Surabaya | Q64: 6680680 | R64: Bernadus Anggo Seno Aji | S64: 0704039202 | T64: =J64 -> 6995000 | U64: Teknologi Informasi | X64: FTII | Y64: ITTelkom Surabaya | Z64: 8140 | AA64: 072019 | AB64: 6681205 | AC64: 0705109002 | AD64: Oktavia Ayu Permata | AE64: =T64 -> 6995000 | AF64: Teknologi Informasi | AI64: FTII | AJ64: ITTelkom Surabaya | AK64: 6680664 | AL64: 0715128708 | AM64: Farah Zakiyah Rahmanti | AN64: =T64 -> 6995000 | AO64: Teknologi Informasi | AR64: FTII | AS64: ITTelkom Surabaya | BQ64: Proposal | BR64: Laporan Akhir | BS64: CHINTYA TRIBHUANA UTAMI | BU64: BAYU KRISNA MUKTI | CG64: Jurnal Nasional S3 | CH64: -
A65: 5 | B65: REK.086/PNLT1/REK/III/2021 | C65: 1001/PNLT1/LPPM/III/2021 | D65: Analisis Efektivitas Pembelajaran Daring Pada Anak Usia Sekolah Dasar Hingga Perguruan Tinggi | E65: Penelitian Dasar | F65: 2021 | G65: 2021 | H65: 10 | I65: Teknologi Informasi dan Komunikasi | J65: 6316000 | K65: Institut Teknologi Telkom Surabaya | L65: 3 | M65: Penelitian Kompetitif Internal | N65: Internal | O65: ID | P65: ITTelkom Surabaya | Q65: 6744406 | R65: Muhammad Nasrullah | S65: 0709059004 | T65: =J65 -> 6316000 | U65: Sistem Informasi | X65: FTII | Y65: ITTelkom Surabaya | Z65: 8140 | AA65: 072019 | AB65: 6764236 | AC65: 0704068902 | AD65: Rokhmatul Insani | AE65: =T65 -> 6316000 | AF65: Sistem Informasi | AI65: FTII | AJ65: ITTelkom Surabaya | AK65: 6680634 | AL65: 0725059004 | AM65: Noerma Pudji Istyanto | AN65: =T65 -> 6316000 | AO65: Sistem Informasi | AR65: FTII | AS65: ITTelkom Surabaya | BQ65: Proposal | BR65: Laporan Akhir | BS65: RIO ARMANDO | BU65: RAIHAN FEBRIANTO GRAHADI | BW65: NATASYA AMELIA SUKMAWATI | CG65: Jurnal Nasional Terakreditasi | CH65: Submitted | CI65: Seminar Internasional | CJ65: Submit Abstrak
A66: 6 | B66: REK.086/PNLT1/REK/III/2021 | C66: 1004/PNLT1/LPPM/III/2021 | D66: Model Prediksi Point of Interest Berdasarkan Data Log Perjalanan Taksi | E66: Penelitian Dasar | F66: 2021 | G66: 2021 | H66: 10 | I66: Teknologi Informasi dan Komunikasi | J66: 6750000 | K66: Institut Teknologi Telkom Surabaya | L66: 3 | M66: Penelitian Kompetitif Internal | N66: Internal | O66: ID | P66: ITTelkom Surabaya | Q66: 6680687 | R66: Wahyu Andy Prastyabudi | S66: 0702048705 | T66: =J66 -> 6750000 | U66: Teknik Industri | X66: FTE | Y66: ITTelkom Surabaya | Z66: 8140 | AA66: 072019 | AB66: 6778837 | AC66: 0711039403 | AD66: Muhammad Dzulfikar Fauzi | AE66: =T66 -> 6750000 | AF66: Informatika | AI66: FTII | AJ66: ITTelkom Surabaya | BQ66: Proposal | BR66: Laporan Akhir | BS66: ARDA ERICO YUDA | BU66: AYU PREMA LAKSMI | CG66: Publikasi Jurnal Internasional | CH66: - | CI66: -
A67: 7 | B67: REK.086/PNLT1/REK/III/2021 | C67: 1005/PNLT1/LPPM/III/2021 | D67: Segmentasi Jalan Raya dengan CNN Unet untuk Asisten Pengemudi | E67: Penelitian Dasar | F67: 2021 | G67: 2021 | H67: 12 | I67: ITTS: Transportasi | J67: 6800000 | K67: Institut Teknologi Telkom Surabaya | L67: 3 | M67: Penelitian Kompetitif Internal | N67: Internal | O67: ID | P67: ITTelkom Surabaya | Q67: 6680626 | R67: Ardian Yusuf Wicaksono | S67: 0727099201 | T67: =J67 -> 6800000 | U67: Rekayasa Perangkat Lunak | X67: FTII | Y67: ITTelkom Surabaya | Z67: 8140 | AA67: 072019 | AB67: 6680628 | AC67: 0730058702 | AD67: Fidi Wincoko Putro | AE67: =T67 -> 6800000 | AF67: Rekayasa Perangkat Lunak | AI67: FTII | AJ67: ITTelkom Surabaya | AK67: 6767777 | AL67: 0713059501 | AM67: Ahmad Wali Satria | AN67: =T67 -> 6800000 | AO67: Informatika | AR67: FTII | AS67: ITTelkom Surabaya | BQ67: Proposal | BR67: Laporan Akhir | BS67: MOCH YUSUF FAISAL AKBAR ANWARI | BU67: SYAHFRIL NIZAMMUDIN | BW67: AULIYA RAHMAN PAKARTI | CG67: Jurnal Nasional S3 | CH67: - | CI67: -
A68: 8 | B68: REK.086/PNLT1/REK/III/2021 | C68: 1006/PNLT1/LPPM/III/2021 | D68: Analisis Pengaruh Adopsi Teknologi Big Data terhadap Keunggulan Bersaing dan Performansi pada UMKM (Study case: UMKM Kota Surabaya) | E68: Penelitian Dasar | F68: 2021 | G68: 2021 | H68: 12 | I68: Teknologi Informasi dan Komunikasi | J68: 6750000 | K68: Institut Teknologi Telkom Surabaya | L68: 3 | M68: Penelitian Kompetitif Internal | N68: Internal | O68: ID | P68: ITTelkom Surabaya | Q68: 6658545 | R68: Ayu Endah Wahyuni | S68: 0401078801 | T68: =J68 -> 6750000 | U68: Teknik Industri | X68: FTII | Y68: ITTelkom Surabaya | Z68: 8140 | AA68: 072019 | AB68: 6658545 | AC68: 0401078801 | AD68: Ayu Endah Wahyuni | AE68: =T68 -> 6750000 | AF68: Teknik Industri | AI68: FTII | AJ68: ITTelkom Surabaya | AK68: 6682237 | AL68: 0722069004 | AM68: Dominggo Bayu Baskara | AN68: =T68 -> 6750000 | AO68: Bisnis Digital | AR68: FTII | AS68: ITTelkom Surabaya | BQ68: Proposal | BR68: Laporan Akhir | BS68: ABIYYAS DAFFA SURYADI | BU68: MUHAMMAD HANIF RAIHAN | BW68: YAKFI ZAMZAMI ACHMAD | CG68: Jurnal Nasional Terakreditasi | CH68: Submitted | CI68: Seminar Internasional
A69: 9 | B69: REK.086/PNLT1/REK/III/2021 | C69: 1009/PNLT1/LPPM/III/2021 | D69: Hydroponic Monitoring System Based On LoRa Technology | E69: Penelitian Dasar | F69: 2021 | G69: 2021 | H69: 8 | I69: Teknologi Informasi dan Komunikasi | J69: 6750000 | K69: Institut Teknologi Telkom Surabaya | L69: 2 | M69: Penelitian Kompetitif Internal | N69: Internal | O69: ID | P69: ITTelkom Surabaya | Q69: 6681205 | R69: Oktavia Ayu Permata | S69: 0705109002 | T69: =J69 -> 6750000 | U69: Teknologi Informasi | X69: FTII | Y69: ITTelkom Surabaya | Z69: 8140 | AA69: 072019 | AB69: 6680664 | AC69: 0715128708 | AD69: Farah Zakiyah Rahmanti | AE69: =T69 -> 6750000 | AF69: Teknologi Informasi | AI69: FTII | AJ69: ITTelkom Surabaya | AK69: 6680680 | AL69: 0704039202 | AM69: Bernadus Anggo Seno Aji | AN69: =T69 -> 6750000 | AO69: Teknologi Informasi | AR69: FTII | AS69: ITTelkom Surabaya | BQ69: Proposal | BR69: Laporan Akhir | BS69: RISKA APRILIA | BU69: GALIH DIMAS PRASTOWO | CG69: Publikasi Jurnal Internasional | CH69: - | CI69: HKI
A70: 10 | B70: REK.086/PNLT1/REK/III/2021 | C70: 1010/PNLT1/LPPM/III/2021 | D70: Integrasi IT dengan Proses Bisnis dengan Studi Kasus di Institut Teknologi Telkom Surabaya | E70: Penelitian Dasar | F70: 2021 | G70: 2021 | H70: 10 | I70: Teknologi Informasi dan Komunikasi | J70: 6500000 | K70: Institut Teknologi Telkom Surabaya | L70: 1 | M70: Penelitian Kompetitif Internal | N70: Internal | O70: ID | P70: ITTelkom Surabaya | Q70: 6680623 | R70: Yupit Sudianto | S70: 0721088602 | T70: =J70 -> 6500000 | U70: Sistem Informasi | X70: FTII | Y70: ITTelkom Surabaya | Z70: 8140 | AA70: 072019 | AB70: 6680626 | AC70: 0727099201 | AD70: Ardian Yusuf Wicaksono | AE70: =T70 -> 6500000 | AF70: Rekayasa Perangkat Lunak | AI70: FTII | AJ70: ITTelkom Surabaya | AK70: 6787821 | AL70: 0707029303 | AM70: Desinta Nur Rachmaniar | AN70: =T70 -> 6500000 | AO70: Teknik Logistik | AR70: FTE | AS70: ITTelkom Surabaya | BQ70: Proposal | BR70: Laporan Akhir | BS70: ARDA ERICO YUDA | BU70: ARDANU ADANG SAPUTRA | BW70: REKSA ALDIAN RAHMANDY PUTRA | CG70: Jurnal Nasional S4 | CH70: - | CI70: -
A71: 11 | B71: REK.086/PNLT1/REK/III/2021 | C71: 1008/PNLT1/LPPM/III/2021 | D71: Evaluasi Efektivitas Penerapan metode Pengenalan marka Jalan Raya Untuk Mengenali Rel Listrik pada Jalan Raya Berlistrik | E71: Penelitian Dasar | F71: 2021 | G71: 2021 | H71: 10 | I71: ITTS: Transportasi | J71: 6750000 | K71: Institut Teknologi Telkom Surabaya | L71: 2 | M71: Penelitian Kompetitif Internal | N71: Internal | O71: ID | P71: ITTelkom Surabaya | Q71: 6682794 | R71: Pangestu Widodo | S71: 0721058310 | T71: =J71 -> 6750000 | U71: Rekayasa Perangkat Lunak | X71: FTII | Y71: ITTelkom Surabaya | Z71: 8140 | AA71: 072019 | AB71: 6778837 | AC71: 0711039403 | AD71: Muhammad Dzulfikar Fauzi | AE71: =T71 -> 6750000 | AF71: Informatika | AI71: FTII | AJ71: ITTelkom Surabaya | BQ71: Proposal | BR71: Laporan Akhir | BS71: MOCH YUSUF FAISAL AKBAR ANWARI | CG71: Jurnal Nasional Terakreditasi | CH71: - | CI71: -
A72: 12 | B72: REK.086/PNLT1/REK/III/2021 | C72: 1011/PNLT1/LPPM/III/2021 | D72: Monitoring Daya Cargo Elevator berbasis IoT | E72: Penelitian Terapan | F72: 2021 | G72: 2021 | H72: 6 | I72: ITTS: Sistem Logistik Cerdas | J72: 12137500 | K72: Institut Teknologi Telkom Surabaya | L72: 3 | M72: Penelitian Kompetitif Internal | N72: Internal | O72: ID | P72: ITTelkom Surabaya | Q72: 6680612 | R72: Isa Hafidz | S72: 0728059203 | T72: =J72 -> 12137500 | U72: Teknik Elektro | X72: FTE | Y72: ITTelkom Surabaya | Z72: 8140 | AA72: 072019 | AB72: 6680683 | AC72: 0729088704 | AD72: Billy Montolalu | AE72: =T72 -> 12137500 | AF72: Teknik Kopmputer | AI72: FTE | AJ72: ITTelkom Surabaya | AK72: 6859016 | AL72: 0727069503 | AM72: Rifki Dwi Putranto | AN72: =T72 -> 12137500 | AO72: Teknik Elektro | AR72: FTE | AS72: ITTelkom Surabaya | BQ72: Proposal | BR72: Laporan Akhir | BS72: ALDHITIANSYAH PUTRA | BU72: MOCHAMMAD RAFLY PUTRA DAFFALDI | BV72: Teknik Elektro,FTEIC, ITTelkom Surabaya | BW72: DINDA KARISMA ULFA | BX72: Teknik Komputer, FTEIC, ITTelkom Surabaya | CG72: JURNAL NASIONAL TERINDEKS | CH72: Submitted | CI72: -
A73: 13 | B73: REK.086/PNLT1/REK/III/2021 | C73: 1012/PNLT1/LPPM/III/2021 | D73: Smart BLDC Motor Control for Smooth Efficient Initial Movement of an Electric Vehicle | E73: Penelitian Terapan | F73: 2021 | G73: 2021 | H73: 12 | I73: ITTS: Transportasi | J73: 16750000 | K73: Institut Teknologi Telkom Surabaya | L73: 5 | M73: Penelitian Kompetitif Internal | N73: Internal | O73: ID | P73: ITTelkom Surabaya | Q73: 6680651 | R73: Dimas Adiputra | S73: 0725059301 | T73: =J73 -> 16750000 | U73: Teknik Elektro | X73: FTE | Y73: ITTelkom Surabaya | Z73: 8140 | AA73: 072019 | AB73: 6682794 | AC73: 0721058310 | AD73: Pangestu Widodo | AE73: =T73 -> 16750000 | AF73: Rekaqyasa Perangkat Lunak | AI73: FTII | AJ73: ITTelkom Surabaya | BQ73: Proposal | BR73: Laporan Akhir | BS73: Aldo Juan Widodo | BT73: Teknik Elektro, FTEIC, ITTelkom Surabaya | BU73: YOSEFAN ALFEUS BAYUAJI | BV73: Teknik Elektro,FTEIC, ITTelkom Surabaya | BW73: NADIA DINDA PRATAMA PUTRI_x000D_ | BX73: Teknik Elektro,FTEIC, ITTelkom Surabaya | CG73: JURNAL NASIONAL TERINDEKS | CH73: Submitted | CI73: HAKI Prototype | CJ73: Submitted
A74: 14 | B74: REK.086/PNLT1/REK/III/2021 | C74: 1014/PNLT1/LPPM/III/2021 | D74: Desain dan Verifikasi keamanan Sistem Manajemen Baterai sebagai Pendukung Kendaraan Listrik | E74: Penelitian Terapan | F74: 2021 | G74: 2021 | H74: 12 | I74: ITTS: Transportasi | J74: 17000000 | K74: Institut Teknologi Telkom Surabaya | L74: 3 | M74: Penelitian Kompetitif Internal | N74: Internal | O74: ID | P74: ITTelkom Surabaya | Q74: 6680708 | R74: Lora Khaula Amifia | S74: 0706069201 | T74: =J74 -> 17000000 | U74: Teknik Elektro | X74: FTE | Y74: ITTelkom Surabaya | Z74: 8140 | AA74: 072019 | AB74: 6680685 | AC74: 0721068802 | AD74: Moch. Iskandar Riansyah | AE74: =T74 -> 17000000 | AF74: Teknik Elektro | AI74: FTE | AJ74: ITTelkom Surabaya | AK74: 6680627 | AL74: 0703119301 | AM74: Benazir Imam Arif Muttaqin | AN74: =T74 -> 17000000 | AO74: Teknik Induustri | AR74: FTE | AS74: ITTelkom Surabaya | BQ74: Proposal | BR74: Laporan Akhir | BS74: Adellia Puspita Ratri_x000D_ | BT74: Teknik Elektro, FTEIC, ITTelkom Surabaya | BU74: Bagas Wahyu Prakoso_x000D_ | BV74: Teknik Elektro, FTEIC, ITTelkom Surabaya | BW74: Firman Adi Rifansyah | BX74: Teknik Elektro, FTEIC, ITTelkom Surabaya | CG74: Jurnal Internasional Terindeks | CH74: In Review | CI74: Jurnal Nasional S2 | CJ74: Accepted
A75: 15 | B75: REK.086/PNLT1/REK/III/2021 | C75: 1015/PNLT1/LPPM/III/2021 | D75: Desain Antena Phased Array untuk Radar Kendaraan Otonom | E75: Penelitian Terapan | F75: 2021 | G75: 2021 | H75: 12 | I75: ITTS: Transportasi | J75: 17000000 | K75: Institut Teknologi Telkom Surabaya | L75: 6 | M75: Penelitian Kompetitif Internal | N75: Internal | O75: ID | P75: ITTelkom Surabaya | Q75: 6680645 | R75: Walid Maulana Hadiansyah | S75: 0713108902 | T75: =J75 -> 17000000 | U75: Teknik Telekomunikasi | X75: FTE | Y75: ITTelkom Surabaya | Z75: 8140 | AA75: 072019 | AB75: 6724784 | AC75: 0722119101 | AD75: Fannush Shofi Akbar | AE75: =T75 -> 17000000 | AF75: Teknik Telekomunikasi | AI75: FTE | AJ75: ITTelkom Surabaya | AK75: 6680741 | AL75: 0727059002 | AM75: Hamzah Ulinuha Mustakim | AN75: =T75 -> 17000000 | AO75: Teknik Telekomunikasi | AR75: FTE | AS75: ITTelkom Surabaya | BQ75: Proposal | BR75: Laporan Akhir | CG75: 1 Jurnal Terindeks | CH75: Submitted | CI75: -
A76: 16 | B76: REK.086/PNLT1/REK/III/2021 | C76: 1017/PNLT1/LPPM/III/2021 | D76: Simultanous Localization and Mapping pada Robot Cerdas Pemadam Kebakaran di Gudang | E76: Penelitian Terapan | F76: 2021 | G76: 2021 | H76: 12 | I76: ITTS: Kebencanaan | J76: 16976100 | K76: Institut Teknologi Telkom Surabaya | L76: 4 | M76: Penelitian Kompetitif Internal | N76: Internal | O76: ID | P76: ITTelkom Surabaya | Q76: 258471 | R76: Susijanto Tri Rasmana | S76: 0727097302 | T76: =J76 -> 16976100 | U76: Teknik Elektro | X76: FTE | Y76: ITTelkom Surabaya | Z76: 8140 | AA76: 072019 | AB76: 6680641 | AC76: 0714029301 | AD76: Ardiansyah Al farouq | AE76: =T76 -> 16976100 | AF76: Teknik Kopmputer | AI76: FTE | AJ76: ITTelkom Surabaya | BQ76: Proposal | BR76: Laporan Akhir | BS76: Moch Syamfallah Anwar | BT76: Teknik Elektro, FTEIC, ITTelkom Surabaya | BU76: Verina Elista Malik | BV76: Teknik Elektro, FTEIC, ITTelkom Surabaya | BW76: Rizqika Ibnu Khattab | CG76: Jurnal Nasional Terakreditasi Sinta | CH76: - | CI76: HAKI (Hak Cipta)
A77: 17 | B77: REK.086/PNLT1/REK/III/2021 | C77: 1018/PNLT1/LPPM/III/2021 | D77: Built in Scale For Estimating Truck Capacity | E77: Penelitian Terapan | F77: 2021 | G77: 2021 | H77: 12 | I77: ITTS: Transportasi | J77: 14500000 | K77: Institut Teknologi Telkom Surabaya | L77: 4 | M77: Penelitian Kompetitif Internal | N77: Internal | O77: ID | P77: ITTelkom Surabaya | Q77: 6680618 | R77: Rahaditya Dimas Prihadianto | S77: 0725059202 | T77: =J77 -> 14500000 | U77: Teknik Industri | X77: FTII | Y77: ITTelkom Surabaya | Z77: 8140 | AA77: 072019 | AB77: 6680651 | AC77: 0725059301 | AD77: Dimas Adiputra | AE77: =T77 -> 14500000 | AF77: Teknik Elektro | AI77: FTE | AJ77: ITTelkom Surabaya | AK77: 6658545 | AL77: 0401078801 | AM77: Ayu Endah Wahyuni | AN77: =T77 -> 14500000 | AO77: Teknik Industri | AR77: FTE | AS77: ITTelkom Surabaya | BQ77: Proposal | BR77: Laporan Akhir | BS77: SULAIMAN ASHARI | BU77: M. BAGUS INDRASTATA_x000D_ | CG77: Jurnal Nasional Terakreditasi Sinta 4_x000D_ | CH77: - | CI77: Prosiding Seminar Nasional
A78: 18 | B78: REK.086/PNLT1/REK/III/2021 | C78: 1019/PNLT1/LPPM/III/2021 | D78: Pemodelan Machine Learning untuk Analisis Kredit Pembayaran Biaya Kuliah | E78: Penelitian Terapan | F78: 2021 | G78: 2021 | H78: 12 | I78: ITTS: Teknologi Informasi dan Komunikasi | J78: 16750000 | K78: Institut Teknologi Telkom Surabaya | L78: 3 | M78: Penelitian Kompetitif Internal | N78: Internal | O78: ID | P78: ITTelkom Surabaya | Q78: 6680726 | R78: Arliyanti Nurdin | S78: 0719069101 | T78: =J78 -> 16750000 | U78: Teknologi Informasi | X78: FTE | Y78: ITTelkom Surabaya | Z78: 8140 | AA78: 072019 | AB78: 6681051 | AC78: 0711069301 | AD78: Rizqa Amelia Zunaidi | AE78: =T78 -> 16750000 | AF78: Teknik Industri | AI78: FTE | AJ78: ITTelkom Surabaya | AM78: Rasyidi Faiz Akbar | BQ78: Proposal | BR78: Laporan Akhir | BS78: MUHAMMAD ARKAN FAUZAN WICAKSONO | BU78: DONI FRIANDY | BW78: AGI LOBITA JAPTARA MARTADINATA | CG78: Jurnal Nasional Terakreditasi | CH78: - | CI78: HKI
A79: 19 | B79: REK.086/PNLT1/REK/III/2021 | C79: 1021/PNLT1/LPPM/III/2021 | D79: Feasibility Study for Conversion of Diesel Powered into Electric Truck | E79: Penelitian Terapan | F79: 2021 | G79: 2021 | H79: 12 | I79: ITTS: Transportasi | J79: 13980000 | K79: Institut Teknologi Telkom Surabaya | L79: 3 | M79: Penelitian Kompetitif Internal | N79: Internal | O79: ID | P79: ITTelkom Surabaya | Q79: 6680627 | R79: Benazir Imam Arif Muttawin | S79: 0703119301 | T79: =J79 -> 13980000 | U79: Teknik Industri | X79: FTII | Y79: ITTelkom Surabaya | Z79: 8140 | AA79: 072019 | AB79: 6682237 | AC79: 0722069004 | AD79: Dominggo Bayu Baskara | AE79: =T79 -> 13980000 | AF79: Bisnis Digital | AI79: FTII | AJ79: ITTelkom Surabaya | BQ79: Proposal | BR79: Laporan Akhir | BS79: TERRESA INDRAJANI KUSUMA | BU79: HENDRAWAN WIDIANTO | BW79: MUHAMMAD MIFTAHUL ABIDIN | BY79: YUDITH IQBAL DIKA PERMANA | CG79: 1 Jurnal Nasional S3; 1 Prosiding Internasional_x000D_ | CH79: Published | CI79: 1 Blueprint KI
A80: 20 | B80: REK.086/PNLT1/REK/III/2021 | C80: 1825/PNLT1/LPPM/III/2021 | D80: Optimalisasi Daya Turbin Angin Proses Vertikal Menggunakan Sistem Kendli Adaptif Pada Diffusert Penyearah Angin | E80: Penelitian Terapan | F80: 2021 | G80: 2021 | H80: 24 | I80: Nasional: Energi-Energi Baru dan Terbarukan | J80: 17000000 | K80: Institut Teknologi Telkom Surabaya | L80: 3 | M80: Penelitian Kompetitif Internal | N80: Internal | O80: ID | P80: ITTelkom Surabaya | Q80: 6680633 | R80: Helmy Widyantara | S80: 0717017902 | T80: =J80 -> 17000000 | U80: Teknologi Informasi | V80: Sistem Informasi | X80: FTII | Y80: ITTelkom Surabaya | Z80: 8140 | AA80: 072019 | BQ80: Proposal | BR80: Laporan Akhir | CG80: Prototype | CH80: - | CI80: Jurnal Internasional | CJ80: Submitted
A81: 21 | B81: REK.086/PNLT1/REK/III/2021 | C81: 1020/PNLT1/LPPM/III/2021 | D81: Desain dan Impelementasi Sistem Informasi Manajemen Cerdas Kerja Praktik dan Magang Mahasiswa dengan Decision Tree (Study kasus: ITTelkom Surabaya) | E81: Penelitian Terapan | F81: 2021 | G81: 2021 | H81: 12 | I81: ITTS: Teknologi Informasi dan Komunikasi | J81: 14500000 | K81: Institut Teknologi Telkom Surabaya | L81: 6 | M81: Penelitian Kompetitif Internal | N81: Internal | O81: ID | P81: ITTelkom Surabaya | Q81: 6680628 | R81: Fidi Wincoko Putro | S81: 0730058702 | T81: =J81 -> 14500000 | U81: Rekayasa Perangkat Lunak | X81: FTII | Y81: ITTelkom Surabaya | Z81: 8140 | AA81: 072019 | AB81: 6682174 | AC81: 0708069202 | AD81: Khodijah Amiroh | AE81: =T81 -> 14500000 | AF81: Teknologi Informasi | AI81: FTII | AJ81: ITTelkom Surabaya | AK81: 6764236 | AL81: 0704068902 | AM81: Rokhmatul Insani | AN81: =T81 -> 14500000 | AO81: Sistem Informasi | AR81: FTII | AS81: ITTelkom Surabaya | BQ81: Proposal | BR81: Laporan Akhir | BS81: ZULKARNAIN (1201190004) | BU81: AQIL MUSTAQIM (1201190017) | BW81: MUHAMAD IQBAL MAULANA (1202190023) | CG81: Jurnal Nasional S3; HAKI | CH81: - | CI81: Seminar Internasional
A82: 22 | B82: REK.086/PNLT1/REK/III/2021 | C82: 1024/PNLT1/LPPM/III/2021 | D82: Hybrid Renewble Energy and Smart Management for Office Building | E82: Penelitian Pengembangan | F82: 2021 | G82: 2021 | H82: 6 | I82: Nasional: Energi-Energi Baru dan Terbarukan | J82: 23600000 | K82: Institut Teknologi Telkom Surabaya | L82: 6 | M82: Penelitian Kompetitif Internal | N82: Internal | O82: ID | P82: ITTelkom Surabaya | Q82: 6680683 | R82: Billy Montolalu | S82: 0729088704 | T82: =J82 -> 23600000 | U82: Teknik Komputer | X82: FTE | Y82: ITTelkom Surabaya | Z82: 8140 | AA82: 072019 | AB82: 6680651 | AC82: 0725059301 | AD82: Dimas Adiputra | AE82: =T82 -> 23600000 | AF82: Teknik Elektro | AI82: FTE | AJ82: ITTelkom Surabaya | AK82: 6859016 | AL82: 0727069503 | AM82: Rifki Dwi Putranto | AN82: =T82 -> 23600000 | AO82: Teknik Elektro | AR82: FTE | AS82: ITTelkom Surabaya | AT82: 6680612 | AU82: 728059203 | AV82: Isa Hafidz | AW82: =T82 -> 23600000 | AX82: Teknik Elektro | AZ82: FTEIC | BA82: ITTelkom Surabaya | BQ82: Proposal | BR82: Laporan Akhir | BS82: Muh Syahwal M | BU82: Jesica F Nura | BW82: Royzaldo Aser Elegius Logo | CG82: Submit Jurnal Ber-ISSN | CH82: - | CI82: -
A83: 23 | B83: REK.136/PNLT1/REK/V/2021 | C83: 1275/PNLT1/LPPM/IV/2021 | D83: Pembuatan Prototipe Anjungan Kesehatan mandiri | E83: Penelitian Kerjasama Institusi | F83: 2021 | G83: 2021 | H83: 8 | I83: Nasional: Kesehatan-Obat | J83: 40000000 | K83: Institut Teknologi Telkom Surabaya | L83: 4 | M83: Penelitian Kemitraan | N83: Internal | O83: ID | P83: ITTelkom Surabaya | Q83: 258471 | R83: Susijanto Tri Rasmana | S83: 0727097302 | T83: =J83 -> 40000000 | U83: Teknik Elektro | X83: FTE | Y83: ITTelkom Surabaya | Z83: 8140 | AA83: 072019 | BQ83: Proposal | BR83: Laporan Akhir | BS83: Nova Herlina Mila Soetarno | BT83: Teknik Elektro, FTEIC, ITTelkom Surabaya | BU83: Muhammad Dwi Hariyanto | BV83: Teknik Elektro, FTEIC, ITTelkom Surabaya | BW83: Andi Nur Halisyah | BX83: Teknik Elektro, FTEIC, ITTelkom Surabaya | BY83: Riyo Oktavian Pradana | BZ83: Teknik Elektro, FTEIC, ITTelkom Surabaya | CA83: Robin Addwiyansyah Alvaro | CB83: Teknik Elektro, FTEIC, ITTelkom Surabaya | CC83: Bagas Wahyu Prakoso | CD83: Teknik Elektro, FTEIC, ITTelkom Surabaya | CG83: Anjungan Pemeriksa Kesehatan | CH83: Submitted | CI83: PATEN | CJ83: Diterima
A84: 24 | B84: REK.136/PNLT1/REK/V/2021 | C84: - | D84: Implementasi Java Interface Pada Anjungan Kesehatan Mandiri | E84: Penelitian Kerjasama Institusi | F84: 2021 | G84: 2021 | H84: 12 | I84: Nasional: Kesehatan-Obat | J84: 40000000 | K84: Institut Teknologi Telkom Surabaya | L84: 4 | M84: Penelitian Kemitraan | N84: Internal | O84: ID | P84: ITTelkom Surabaya | Q84: 6680683 | R84: Billy Montolalu | S84: 0729088704 | T84: =J84 -> 40000000 | U84: Teknik Komputer | X84: FTE | Y84: ITTelkom Surabaya | Z84: 8140 | AA84: 072019 | AB84: 6778837 | AC84: 0711039403 | AD84: Muhammad Dzulfikar Fauzi | AE84: =T84 -> 40000000 | AF84: Informatika | AI84: FTII | AJ84: ITTelkom Surabaya | AK84: 6767777 | AL84: 0713059501 | AM84: Ahmad Wali Satria Bhari Johan | AN84: =T84 -> 40000000 | AO84: Informatika | AR84: FTII | AS84: ITTelkom Surabaya | BQ84: Proposal | BR84: Laporan Akhir | BS84: Dimas Bagas Wicaksono | BT84: Teknik Elektro, FTEIC, ITTelkom Surabaya | BU84: Fathur Alfariz | BV84: Teknik Elektro, FTEIC, ITTelkom Surabaya | BW84: Adellia Puspita Ratri | BX84: Teknik Elektro, FTEIC, ITTelkom Surabaya | BY84: Getsemani Adi Bagus Maranata Hartono | BZ84: Teknik Elektro, FTEIC, ITTelkom Surabaya | CA84: Abdullaoh Hamid Nushfi | CB84: Teknik Elektro, FTEIC, ITTelkom Surabaya | CD84: Teknik Elektro, FTEIC, ITTelkom Surabaya | CG84: Prototipe perangkat lunak berupa program untukmembaca alat ukur, mengolah data pengukuran, menyajikan informasi ke perangkat luara, dan transferdata ke database rumah sakit. | CH84: - | CI84: Publikasi ilmiah yang diterbitkan pada jurnal nasionalatau internasional terindek
A85: 25 | B85: REK.139/PNLT1/REK/V/2021 | C85: 1274/PNLT1/LPPM/V/2021 | D85: Perbaikan Sustem I-gracias Institut Teknologi Telkom Purwokerto dengan Metode Quality Function Deployment (QFD) | E85: Penelitian Kerjasama Perguruan Tinggi (PEKERTI) | F85: 2021 | G85: 2021 | H85: 8 | I85: Teknologi Informasi dan Komunikasi | J85: =8103000+12474000 -> 20577000 | K85: Institut Teknologi Telkom Surabaya | L85: 2 | N85: Internal | Q85: 6070770 | R85: Achmad Zaki Yamani | S85: 0613118701 | T85: =J85 -> 20577000 | U85: Teknik Industri | Y85: ITTelkom Purwokerto | Z85: 228 | AA85: 062003 | AB85: 6699792 | AC85: 0615089201 | AD85: Dina Rachmawaty | AF85: Teknik Industri | AJ85: ITTelkom Purwokerto | AK85: 6753293 | AL85: 0601049501 | AM85: Famila Dwi Winati | AO85: Teknik Industri | AS85: ITTelkom Purwokerto | AT85: 6680648 | AU85: 0724089201 | AV85: Hawwin Mardhiana | AW85: =J85 -> 20577000 | AX85: Sistem Informasi | AZ85: FTII | BA85: ITTelkom Surabaya | BQ85: Proposal | BR85: Laporan Akhir | CG85: 2 Jurnal Nasional Terakreditasi S2 | CH85: Submitted – In review | CI85: Seminar Internasional | CJ85: Accepted, Presented
A86: 26 | B86: REK.001/PNLT1/REK/I/2021 | C86: 1273/PNLT1/LPPM/I/2021 | D86: Pengembangan Metode Advanced Feature Selection Untuk Sensor Array Optimization Pada Electronic Nose (Tel U) | E86: Penelitian Kerjasama Perguruan Tinggi (PEKERTI) | F86: 2021 | G86: 2021 | H86: 12 | I86: - | J86: 40000000 | K86: Institut Teknologi Telkom Surabaya | L86: 4 | N86: Internal | Q86: 6680622 | R86: Dewi RahmawatI | S86: 0709039401 | T86: =J86 -> 40000000 | U86: Rekayasa Perangkat Lunak | X86: FTII | Y86: ITTelkom Surabaya | Z86: 8140 | AA86: 072019 | BQ86: Proposal | BR86: Laporan Akhir | BS86: Zaki Al Faridzi | BU86: Muhammad Abizard Al Thareq | BW86: Indah Mayang Sari | CG86: Jurnal Internasional | CH86: - | CI86: Prosiding Internasional
A87: 27 | B87: REK.193/PNLT1/REK/IX/2021 | C87: 1660/PNLT1/LPPM/X/2021 | D87: Mengkonstruksi Defini dari Startup (Sebuah Kajian Systematic Literatur Review) | E87: Penelitian Kerjasama Perguruan Tinggi (PEKERTI) | F87: 2021 | G87: 2021 | H87: 11 | I87: - | J87: =16750000*2 -> 33500000 | L87: 6 | N87: Internal | R87: Kiki Sudiana | T87: =J87 -> 33500000 | AD87: Fajar Sidiq Prabowo | AM87: Agus Sulistya | AV87: Riza Akhsani Setyo Prayoga | BQ87: Proposal | BR87: Laporan Akhir | BS87: MUHAMMAD RAFLI RAMADHAN | CG87: Jurnal Internasional, Prosiding conference, Hak Cipta | CH87: - | CI87: -
A88: 28 | B88: REK.090/PNLT1/REK/III/2021 | C88: 1110/PNLT1/LPPM/IV/2021 | D88: Pengembangan Purwarupa truk bertenaga listrik | E88: Penelitian Research Center | F88: 2021 | G88: 2021 | H88: 12 | I88: Nasional: Transportasi | J88: 100000000 | K88: Institut Teknologi Telkom Surabaya | L88: 4 | M88: Penelitian Kompetitif Internal | N88: Internal | O88: ID | P88: ITTelkom Surabaya | Q88: 6680685 | R88: Moch. Iskandar Riansyah | S88: 0721068802 | T88: =J88 -> 100000000 | U88: Teknik Elektro | X88: FTE | Y88: ITTelkom Surabaya | Z88: 8140 | AA88: 072019 | BQ88: Proposal | BR88: Laporan Akhir | BS88: Aditya Yudhistira | BT88: Teknologi Informasi, FTIB, ITTelkom Surabaya | BU88: Moch. Syamfallah Anwar | BW88: Nova Herlina Mila Soetarno | BY88: M Fariz Rahmadany | BZ88: Teknik Elektro, FTEIC, ITTelkom Surabaya | CA88: Muhammad Fauzan Rasyid | CC88: Henko kholima | CE88: Ishak Rizaldy Eka Kurnia | CG88: Jurnal Nasional Sinta2 | CH88: - | CI88: Prototype, HKI
A89: 29 | B89: REK.090/PNLT1/REK/III/2021 | C89: 1111/PNLT1/LPPM/IV/2021 | D89: Sistem Pemberdayaan Rooftop Terintegrasi | E89: Penelitian Research Center | F89: 2021 | G89: 2021 | H89: 12 | I89: Nasional: Pangan-Pertanian | J89: 100000000 | K89: Institut Teknologi Telkom Surabaya | L89: 4 | M89: Penelitian Kompetitif Internal | N89: Internal | O89: ID | P89: ITTelkom Surabaya | Q89: 6680633 | R89: Helmy Widyantara | S89: 0717017902 | T89: =J89 -> 100000000 | U89: Teknologi Informasi | V89: Sistem Informasi | X89: FTII | Y89: ITTelkom Surabaya | Z89: 8140 | AA89: 072019 | BQ89: Proposal | BR89: Laporan Akhir | BS89: Muhammad Rafi Irzam | BT89: Teknologi Informasi, FTIB, ITTelkom Surabaya | BU89: Danang Taufik Kurnianto | BW89: Denza Tanzilda | BX89: Teknologi Informasi, FTIB, ITTelkom Surabaya | BY89: Muhammad Yanuar Muhaimin | CA89: Danu Diningrat | CB89: Teknik Komputer, FTEIC, ITTelkom Surabaya | CC89: Naufal Ammar Badr | CD89: Teknologi Informasi, FTIB, ITTelkom Surabaya | CG89: Jurnal Internasional | CH89: - | CI89: Prototype sistem monitoring dan pengendalian green house berbasis IoT dan Prototype sistem monitoring dan pengendalian kualitas air pada pemijahan wader
A90: 30 | B90: REK.086/PNLT1/REK/III/2021 | C90: 1038/PNLT1/LPPM/III/2021 | D90: Pengantar Teknik Industri | E90: Penulisan Buku Ajar | F90: 2021 | G90: 2021 | H90: 10 | I90: Nasional: Sosial Humaniora-Seni Budaya Pendidikan | J90: 3500000 | K90: Institut Teknologi Telkom Surabaya | L90: Terbit | M90: Penelitian Kompetitif Internal | N90: Internal | O90: ID | P90: ITTelkom Surabaya | Q90: 6682237 | R90: Dominggo Bayu Baskara | S90: 0722069004 | T90: =J90 -> 3500000 | U90: Teknik Industri | X90: FTII | Y90: ITTelkom Surabaya | Z90: 8140 | AA90: 072019 | AB90: 6680618 | AC90: 0725059202 | AD90: Rahaditya Dimas Prihadianto | AE90: =T90 -> 3500000 | AF90: Teknik Industri | AI90: FTE | AJ90: ITTelkom Surabaya | AK90: 6680627 | AL90: 0703119301 | AM90: Benazir Imam Arif Muttawin | AN90: =T90 -> 3500000 | AO90: Teknik Industri | AR90: FTE | AS90: ITTelkom Surabaya | BQ90: Proposal | BR90: Laporan Akhir | CG90: Buku Ajar | CH90: - | CI90: -
A91: 31 | B91: REK.086/PNLT1/REK/III/2021 | C91: 1039/PNLT1/LPPM/III/2021 | D91: Pengenalan Sistem Enterprise Menggunkan Odoo (Studi Kasus:Logistik) | E91: Penulisan Buku Ajar | F91: 2021 | G91: 2021 | H91: 8 | I91: ITTS: Sistem Logistik Cerdas | J91: 3000000 | K91: Institut Teknologi Telkom Surabaya | L91: - | M91: Penelitian Kompetitif Internal | N91: Internal | O91: ID | P91: ITTelkom Surabaya | Q91: 6665306 | R91: Ully Asfari | S91: 0703129001 | T91: =J91 -> 3000000 | U91: Sistem Informasi | X91: FTII | Y91: ITTelkom Surabaya | Z91: 8140 | AA91: 072019 | AB91: 6680648 | AC91: 0724089201 | AD91: Hawwin Mardhiana | AE91: =T91 -> 3000000 | AF91: Sistem Informasi | AI91: FTII | AJ91: ITTelkom Surabaya | AK91: 6744406 | AL91: 0709059004 | AM91: Muhammad Nasrullah | AN91: =T91 -> 3000000 | AO91: Sistem Informasi | AR91: FTII | AS91: ITTelkom Surabaya | BQ91: Proposal | BR91: Laporan Akhir | CG91: Buku Ajar ISSBN | CH91: Terealisasi | CI91: -
A92: 32 | B92: REK.086/PNLT1/REK/III/2021 | C92: 1013/PNLT1/LPPM/III/2021 | D92: Prototype Sistem Kendali Cerdas untuk Ground Vehicle di Jalan Raya | E92: Penelitian Terapan | F92: 2021 | G92: 2021 | H92: 12 | I92: ITTS: Transportasi | J92: 16800000 | K92: Institut Teknologi Telkom Surabaya | L92: 3 | M92: Penelitian Kompetitif Internal | N92: Internal | O92: ID | P92: ITTelkom Surabaya | Q92: 6680641 | R92: Ardiansyah Al Farouq | S92: 0714029301 | T92: =J92 -> 16800000 | U92: Teknik Komputer | X92: FTE | Y92: ITTelkom Surabaya | Z92: 8140 | AA92: 072019 | AB92: 6680678 | AC92: 0713068702 | AD92: Dwi Edi Setyawan | AE92: =T92 -> 16800000 | AF92: Teknik Kopmputer | AI92: FTE | AJ92: ITTelkom Surabaya | BQ92: Proposal | BR92: Laporan Akhir | BS92: Ahmad Habibi | BT92: Teknik Komputer, FTEIC, ITTelkom Surabaya | BU92: Dito Hewi Julianto | BV92: Teknik Komputer, FTEIC, ITTelkom Surabaya | CG92: Konference | CH92: Accepted | CI92: Prototype Robot UGV
A93: 33 | B93: REK.094/PNLT1/REK/III/2021 | C93: - | D93: TEKNIK KOMPUTASI DENGAN MEMPERTIMBANGKAN STABILITAS TRANSIEN PADA SMART GRID | E93: Penelitian Mandiri | F93: 2021 | G93: 2021 | H93: 6 | I93: ITTS: Sistem Logistik Cerdas | J93: 0 | K93: Institut Teknologi Telkom Surabaya | L93: 2 | M93: Penelitian Dana Mandiri | N93: Internal | O93: ID | P93: ITTelkom Surabaya | Q93: 6680612 | R93: Isa Hafidz | S93: 0728059203 | T93: =J93 -> 0 | U93: Teknik Elektro | X93: FTE | Y93: ITTelkom Surabaya | Z93: 8140 | AA93: 072019 | BQ93: Proposal | BR93: Laporan Akhir | BS93: ALDHITIANSYAH PUTRA | BT93: Teknik Elektro, FTEIC, ITTelkom Surabaya | BU93: Rafly Daffaldi | BV93: Teknik Elektro, FTEIC, ITTelkom Surabaya | CG93: Seminar Internasional | CH93: Accepted | CI93: -
A94: 34 | B94: REK.094/PNLT1/REK/III/2021 | C94: - | D94: Aplying Machine Learning Algorithm in Time Series Forecasting on Financial Prediction | E94: Penelitian Mandiri | F94: 2021 | G94: 2021 | H94: 6 | I94: Teknologi Informasi dan Komunikasi | J94: 0 | K94: Institut Teknologi Telkom Surabaya | L94: 3 | M94: Penelitian Dana Mandiri | N94: Internal | O94: ID | P94: ITTelkom Surabaya | Q94: 6680631 | R94: Anifatul Faricha | S94: 0704069202 | T94: =J94 -> 0 | U94: Teknik Elektro | X94: FTE | Y94: ITTelkom Surabaya | Z94: 8140 | AA94: 072019 | AB94: 6680648 | AC94: 0724089201 | AD94: Hawwin Mardhiana | AE94: =T94 -> 0 | AF94: Sistem Informasi | AI94: FTII | AJ94: ITTelkom Surabaya | AK94: 6718390 | AL94: 0001069203 | AM94: Siti Maghfirotul Ulyah | AN94: =T94 -> 0 | AO94: Statistika | AR94: FST | AS94: Universitas Airlangga | AT94: 5999348 | AU94: 0031077602 | AV94: Rika Susanti | AW94: =T94 -> 0 | AX94: Obstetori dan Gineklogi Peminatan | AZ94: FK | BA94: Universitas Andalas | BQ94: Proposal | BR94: Laporan Akhir | BS94: Christoper Andreas | BU94: Firman Adi Rifansyah | BV94: Teknik Elektro, FTEIC, ITTelkom Surabaya | CG94: Jurnal Sinta 1 | CH94: Submitted | CI94: Procsiding Internasional | CJ94: Accepted
A95: 35 | B95: REK.094/PNLT1/REK/III/2021 | C95: - | D95: Sistem Kendali dan Monitoring Suhu Kolam Pemijahan Wader Pari Ikan Wader berbasis IoT | E95: Penelitian Mandiri | F95: 2021 | G95: 2021 | H95: 12 | I95: ITTS: Teknologi Informasi dan Komunikasi | J95: 0 | K95: Institut Teknologi Telkom Surabaya | L95: 3 | M95: Penelitian Dana Mandiri | N95: Internal | O95: ID | P95: ITTelkom Surabaya | Q95: 6680629 | R95: Ubaidillah Umar | S95: 0727048809 | T95: =J95 -> 0 | U95: Teknik Komputer | X95: FTE | Y95: ITTelkom Surabaya | Z95: 8140 | AA95: 072019 | AK95: 6680633 | AL95: 0717017902 | AM95: Helmy Widyantara | AN95: =T95 -> 0 | AO95: Teknologi Informasi | AP95: Sistem Informasi | AR95: FTII | AS95: ITTelkom Surabaya | BQ95: Proposal | BR95: Laporan Akhir | BS95: MUHAMMAD YANUAR MUHAIMIN | BU95: DANU DININGRAT | CG95: Jurnal Nasional Terakreditasi | CH95: - | CI95: -
A96: 36 | B96: REK.094/PNLT1/REK/III/2021 | C96: - | D96: Implementasi Smart Hybrid PABX di Institut Teknologi Telkom Surabaya | E96: Penelitian Mandiri | F96: 2021 | G96: 2021 | H96: 6 | I96: Teknologi Informasi dan Komunikasi | J96: 0 | K96: Institut Teknologi Telkom Surabaya | L96: 3 | M96: Penelitian Dana Mandiri | N96: Internal | O96: ID | P96: ITTelkom Surabaya | Q96: 6680645 | R96: Walid Maulana Hadiansyah | S96: 0713108902 | T96: =J96 -> 0 | U96: Teknik Telekomunikasi | X96: FTE | Y96: ITTelkom Surabaya | Z96: 8140 | AA96: 072019 | AB96: 6805206 | AC96: 8920230021 | AD96: Agus Sulistya | AE96: =T96 -> 0 | AF96: Sistem Informasi | AI96: FTII | AJ96: ITTelkom Surabaya | AK96: 6680678 | AL96: 0713068702 | AM96: Dwi Edi Setyawan | AN96: =T96 -> 0 | AO96: Teknik Kopmputer | AR96: FTE | AS96: ITTelkom Surabaya | BQ96: Proposal | BR96: Laporan Akhir | BS96: Rayhan Naufaldi | BU96: Tasya Amalia | CG96: Prosiding Internasional, Prototype | CH96: - | CI96: -
A97: 37 | B97: REK.094/PNLT1/REK/III/2021 | C97: - | D97: Optimasi rute optimalberdasarkan waktu, biaya, kondisi cuaca, kejadian lokal, dan jumlah kendaraan dengan menggunakan algoritma fuzzy mandani dan modified hidden markov model | E97: Penelitian Mandiri | F97: 2021 | G97: 2021 | H97: 12 | I97: Transportasi | J97: 0 | K97: Institut Teknologi Telkom Surabaya | L97: 3 | M97: Penelitian Dana Mandiri | N97: Internal | O97: ID | P97: ITTelkom Surabaya | Q97: 6680622 | R97: Dewi RahmawatI | S97: 0709039401 | T97: =J97 -> 0 | U97: Rekayasa Perangkat Lunak | X97: FTII | Y97: ITTelkom Surabaya | Z97: 8140 | AA97: 072019 | AB97: 6680623 | AC97: 0721088602 | AD97: Yupit Sudianto | AE97: =T97 -> 0 | AF97: Sistem Informasi | AI97: FTII | AJ97: ITTelkom Surabaya | AK97: 259781 | AL97: 0710028604 | AM97: Titus Kristanto | AN97: =T97 -> 0 | AO97: Rekayasa Perangkat Lunak | AP97: Sistem Informasi | AR97: FTII | AS97: ITTelkom Surabaya | BQ97: Proposal | BR97: Laporan Akhir | BS97: Reza Arindra Fadhilah | BU97: AMANDA AMALIA | CG97: Jurnal Nasional ber-ISSN | CH97: Submitted | CI97: Hak Cipta (HAKI) | CJ97: Submitted
A98: 38 | B98: REK.094/PNLT1/REK/III/2021 | C98: - | D98: Private Higher Eduction Funding | E98: Penelitian Mandiri | F98: 2021 | G98: 2021 | H98: 6 | I98: Nasional: Sosial Humaniora-Seni Budaya Pendidikan | J98: 0 | K98: Institut Teknologi Telkom Surabaya | L98: Jurnal Internasional Bereputasi | M98: Penelitian Dana Mandiri | N98: Internal | O98: ID | P98: ITTelkom Surabaya | Q98: 6805206 | R98: Agus Sulistya | S98: 8920230021 | T98: =J98 -> 0 | U98: Rekayasa Perangkat Lunak | X98: FTII | Y98: ITTelkom Surabaya | Z98: 8140 | AA98: 072019 | AB98: 6805479 | AC98: 0012059403 | AD98: Rasyidi Faiz Akbar | AE98: =T98 -> 0 | AK98: 6680726 | AL98: 0719069101 | AM98: Arliyanti Nurdin | AN98: =T98 -> 0 | AO98: Teknologi Informasi | AR98: FTE | AS98: ITTelkom Surabaya | BQ98: Proposal | BR98: Laporan Akhir | BS98: DEVYSIKAELO IRA RANTELILI (1202200093) | CG98: Jurnal Internasional Bereputasi | CH98: - | CI98: Jurnal Internal ITTS
A99: 39 | B99: REK.094/PNLT1/REK/III/2021 | C99: - | D99: Pengukuran Kepuasan Mahasiswa terhadap E-learning Institut Teknologi Telkom Surabaya Berdasar Kriteria Usability | E99: Penelitian Mandiri | F99: 2021 | G99: 2021 | H99: 6 | I99: Nasional: Sosial Humaniora-Seni Budaya Pendidikan | J99: 0 | K99: Institut Teknologi Telkom Surabaya | L99: 3 | M99: Penelitian Dana Mandiri | N99: Internal | O99: ID | P99: ITTelkom Surabaya | Q99: 6756289 | R99: Nicko Nur Rakhmaddian | S99: 0725059501 | T99: =J99 -> 0 | U99: Teknik Logistik | X99: FTE | Y99: ITTelkom Surabaya | Z99: 8140 | AA99: 072019 | AB99: 6778519 | AC99: 0712059303 | AD99: Nisa Isrofi | AE99: =T99 -> 0 | AF99: Teknik Logistik | AI99: FTE | AJ99: ITTelkom Surabaya | AK99: 6784457 | AL99: 0723079501 | AM99: Granita Hajar | AN99: =T99 -> 0 | AO99: Teknik Logistik | AR99: FTE | AS99: ITTelkom Surabaya | BQ99: Proposal | BR99: Laporan Akhir | BS99: NABILLA ADINNA CAHYANI | BU99: MUHAMMAD ARKAN FAUZAN WICAKSONO | CG99: Prosiding Internasional | CH99: Submitted | CI99: Jurnal Internal ITTS
A100: 40 | B100: REK.094/PNLT1/REK/III/2021 | C100: - | D100: Pemodelan Rantai Markov untuk Resilensi Rantai pasok Industri manufaktur di Indonesia | E100: Penelitian Mandiri | F100: 2021 | G100: 2021 | H100: 10 | I100: ITTS: Sistem Logistik Cerdas | J100: 0 | K100: Institut Teknologi Telkom Surabaya | L100: 2 | M100: Penelitian Kompetitif Internal | N100: Internal | O100: ID | P100: ITTelkom Surabaya | Q100: 6680643 | R100: Abduh Sayid Albana | S100: 0702039003 | T100: =J100 -> 0 | U100: Teknik Industri | V100: Teknik Logistik | X100: FTII | Y100: ITTelkom Surabaya | Z100: 8140 | AA100: 072019 | AB100: 6680648 | AC100: 0724089201 | AD100: Hawwin Mardhiana | AE100: =T100 -> 0 | AF100: Sistem Informasi | AI100: FTII | AJ100: ITTelkom Surabaya | AK100: 6680618 | AL100: 0725059202 | AM100: Rahaditya Dimas Prihadianto | AN100: =T100 -> 0 | AO100: Teknik Industri | AR100: FTII | AS100: ITTelkom Surabaya | BQ100: Proposal | BR100: Laporan Akhir | BS100: ARDA ERICO YUDA | CG100: Jurnal Nasional Terakreditasi S1 | CH100: - | CI100: -
A101: 41 | B101: REK.094/PNLT1/REK/III/2021 | C101: - | D101: Pendeteksi Informasi Anak Autis Sejak Dini Menggunakan Machine Learning | E101: Penelitian Mandiri | F101: 2021 | G101: 2021 | H101: 10 | I101: ITTS: Teknologi Informasi dan Komunikasi | J101: 0 | K101: Institut Teknologi Telkom Surabaya | L101: 3 | M101: Penelitian Kompetitif Internal | N101: Internal | O101: ID | P101: ITTelkom Surabaya | Q101: 6681032 | R101: Anfazul Faridatul Azizah | S101: 0715039004 | T101: =J101 -> 0 | U101: Sistem Informasi | X101: FTII | Y101: ITTelkom Surabaya | Z101: 8140 | AA101: 072019 | AK101: 6764236 | AL101: 0704068902 | AM101: Rokhmatul Insani | AN101: =T101 -> 0 | AO101: Sistem Informasi | AR101: FTII | AS101: ITTelkom Surabaya | BQ101: Proposal | BR101: Laporan Akhir | BS101: BONNIE FERDINAND AKBAR | BU101: EDRIAND IMENS RAYGRANDI | BW101: IRENE DYAH AYUWATI | CG101: Jurnal Nasional Terakreditasi S4 | CH101: Submitted | CI101: Publikasi Media Massa, HKI
A102: 42 | B102: REK.094/PNLT1/REK/III/2021 | C102: 1819/PNLT1/LPPM/VIII/2021 | D102: Virtual Screening Senyawa Aktif sebagai Inhibitor Meningitis dengan Hybrid Molecular Fingerprint dan Pendekatan Machine Learning | E102: Penelitian Mandiri | F102: 2021 | G102: 2021 | H102: 6 | I102: Nasional: Kesehatan-Obat | J102: 0 | K102: Institut Teknologi Telkom Surabaya | L102: 3 | M102: Penelitian Dana Mandiri | N102: Internal | O102: ID | P102: ITTelkom Surabaya | Q102: 6756318 | R102: Moh.Hamim Zajuli Al Faroby | S102: 0724079501 | T102: =J102 -> 0 | U102: Sains Data | X102: FTII | Y102: ITTelkom Surabaya | Z102: 8140 | AA102: 072019 | AB102: 6793410 | AC102: 0707019501 | AD102: Helisyah Nur Fadhilah | AE102: =T102 -> 0 | AF102: Sains Data | AI102: FTII | AJ102: ITTelkom Surabaya | BQ102: Proposal | BR102: Laporan Akhir | BS102: INDAH RAHMAWATI UTAMI | CG102: Jurnal Internasional Bereputasi | CH102: - | CI102: Seminar Internasional Bereputasi
A103: 43 | B103: REK.094/PNLT1/REK/III/2021 | C103: - | D103: Deteksi Halangan Tangga Turun untuk Penyandang Tuna Netra | E103: Penelitian Mandiri | F103: 2021 | G103: 2021 | H103: 6 | I103: Teknologi Informasi dan Komunikasi | J103: 0 | K103: Institut Teknologi Telkom Surabaya | L103: 3 | M103: Penelitian Dana Mandiri | N103: Internal | O103: ID | P103: ITTelkom Surabaya | Q103: 6767777 | R103: Ahmad Wali Satria Bahari Johan | S103: 0713059501 | T103: =J103 -> 0 | U103: Informatika | X103: FTII | Y103: ITTelkom Surabaya | Z103: 8140 | AA103: 072019 | AB103: 6801989 | AC103: 0704029302 | AD103: Sekar Widyasari Putri | AE103: =T103 -> 0 | AF103: Bisnis Digital | AI103: FTII | AJ103: ITTelkom Surabaya | AK103: 6784457 | AL103: 0723079501 | AM103: Granita Hajar | AN103: =T103 -> 0 | AO103: Teknik Logistik | AR103: FTE | AS103: ITTelkom Surabaya | BQ103: Proposal | BR103: Laporan Akhir | BS103: RAHAYU NUR ROCHMAH | BU103: RAHMAT ANDIKA LAKSANA | CG103: Jurnal Nasional Terakreditasi S2 | CH103: Accepted | CI103: -
...

Sheet PKM AUDIT
A1: No | B1: No. SK | C1: No. Kontrak | D1: Judul Penelitian | E1: Nama Skema | F1: Tahun Usulan | G1: Tahun Pelaksanaan Kegiatan | H1: Lama Kegiatan (bulan) | I1: Bidang Fokus | J1: Dana yang Diusulkan | K1: Dana Disetujui | L1: Nama Institusi Penerima Dana | M1: Target TKT | N1: Nama Program Hibah | O1: Kategori Sumber Dana | P1: Negara Sumber Dana | Q1: Sumber Dana | R1: Sinta ID Ketua | S1: Nama Ketua | T1: NIDN Ketua | U1: DANA KETUA | V1: Prodi | W1: Fakultas | X1: PT | Y1: Sinta ID PT | Z1: Kode PT PDDikti | AA1: Sinta ID Member1 | AB1: NIDN Member1 | AC1: Nama Member1 | AD1: DANA MEMBER 1 | AE1: Prodi2 | AF1: Fakultas3 | AG1: PT4 | AH1: Sinta ID Member2 | AI1: NIDN Member2 | AJ1: Nama Member2 | AK1: DANA MEMBER 2 | AL1: Prodi5 | AM1: Fakultas6 | AN1: PT7 | AO1: Sinta ID Member3 | AP1: NIDN Member3 | AQ1: Nama Member3 | AR1: DANA MEMBER 3 | AS1: Prodi8 | AT1: Fakultas9 | AU1: PT10 | AV1: Sinta ID Member4 | AW1: NIDN Member4 | AX1: Nama Member4 | AY1: DANA MEMBER 4 | AZ1: Prodi11 | BA1: Fakultas12 | BB1: PT13 | BC1: Sinta ID Member5 | BD1: NIDN Member5 | BE1: Nama Member5 | BF1: DANA MEMBER 5 | BG1: Prodi14 | BH1: Fakultas15 | BI1: PT16 | BJ1: Sinta ID Member6 | BK1: NIDN Member6 | BL1: Nama Member6 | BM1: DANA MEMBER 6 | BN1: Prodi17 | BO1: Fakultas18 | BP1: PT19 | BQ1: SDG | BR1: Proposal | BS1: Laporan Akhir | BT1: Nama Mhs1 | BU1: Prodi, Fak, PT Mhs1 | BV1: Nama Mhs2 | BW1: Prodi, Fak, PT Mhs2 | BX1: Nama Mhs3 | BY1: Prodi, Fak, PT Mhs3 | BZ1: Nama Mhs4 | CA1: Prodi Mhs4 | CB1: Nama Mhs5 | CC1: Prodi Mhs5 | CD1: Nama Mhs6 | CE1: Prodi Mhs6 | CF1: Nama Mhs7 | CG1: Prodi Mhs7 | CH1: Nama Mhs8 | CI1: Prodi Mhs8 | CJ1: Publikasi Ilmiah | CK1: Media Massa | CL1: Produk / Jasa | CM1: Capaian Publikasi Ilmiah | CN1: Capaian Luaran Wajib | CO1: Luaran Tambahan | CR1: No | CS1: Pertanyaan | CT1: Jumlah PKM
A2: 1 | B2: REK.024/ABDI3/PPM/III/2020 | C2: - | D2: Penerapan Teknologi Pakan Otomatis Bagi Peternak Ikan di Gresik | E2: Pengmas Dana Internal | F2: 2020 | K2: 6500000 | O2: Internal | Q2: Institut Telknologi Telkom Surabaya | R2: 6680685 | S2: Moch. Iskandar Riansyah | T2: 0721068802 | U2: =K2/3 -> 2166666.7 | V2: Teknik Elektro | W2: FTE | X2: ITTelkom Surabaya | Y2: 8140 | Z2: 072019 | AA2: 6680708 | AB2: 0706069201 | AC2: Lora K. Amifia | AD2: =U2 -> 2166666.7 | AE2: Teknik Elektro | AF2: FTE | AG2: ITTelkom Surabaya | AH2: 6680612 | AI2: 0728059203 | AJ2: Isa Hafidz | AK2: =U2 -> 2166666.7 | AL2: Teknik Elektro | AM2: FTE | AN2: ITTelkom Surabaya | BR2: Proposal | BS2: Laporan Akhir | CR2: 1 | CS2: Jumlah Pengabdian kepada masyarakat yang didanai oleh industri nasional | CT2: =CW4+CW9 -> 4
A3: 2 | B3: REK.024/ABDI3/PPM/III/2020 | C3: - | D3: IPTEK BAGI MASYARAKAT BUDI DAYA IKAN DI BUDURAN SIDOARJO JAWTA TIMUR | E3: Pengmas Dana Internal | F3: 2020 | K3: 6500000 | M3: - | O3: Internal | Q3: Institut Telknologi Telkom Surabaya | R3: 6680683 | S3: Billy Montolalu | T3: 0729088704 | U3: =K3/3 -> 2166666.7 | V3: Sistem Informasi | W3: FTII | X3: ITTelkom Surabaya | Y3: 8140 | Z3: 072019 | AA3: 6680678 | AB3: 0713068702 | AC3: Dwi Edi Setyawan | AD3: =U3 -> 2166666.7 | AE3: Teknik Komputer | AF3: FTE | AG3: ITTelkom Surabaya | AH3: 6680633 | AI3: 0717017902 | AJ3: Helmy Widyantara | AK3: =U3 -> 2166666.7 | AL3: Teknologi Informasi | AM3: FTII | AN3: ITTelkom Surabaya | BR3: Proposal | BS3: Laporan Akhir | CR3: 2 | CS3: jumlah Pengabdian kepada masyarakat yang didanai oleh non-industri nasional/kementrian | CT3: =CW6+CW7+CW8 -> 17 | CV3: Sumber Dana | CW3: Count of Sumber Dana
A4: 3 | C4: - | D4: Workshop on using Braille Embosser and Text Editor Software for the Blind and Visual Impairment Students | E4: Pengmas penugasan | F4: 2020 | G4: 2020 | H4: 4 | I4: Pembedayaan Difabel | K4: 4475000 | M4: - | O4: Internal | Q4: Institut Telknologi Telkom Surabaya | R4: 6681032 | S4: Anfazul Faridatul Azizah | T4: 715039004 | U4: =K4/2 -> 2237500 | V4: Sistem Informasi | W4: FTII | X4: ITTelkom Surabaya | Y4: 8140 | Z4: 072019 | AA4: 6680625 | AB4: 0408067804 | AC4: Nilla Rachmaningrum | AD4: =K4/2 -> 2237500 | AE4: Teknik Telekomunikasi | AF4: FTE | AG4: ITTelkom Surabaya | BR4: Proposal | BS4: Laporan Akhir | CR4: 3 | CS4: jumlah Pengabdian kepada masyarakat yang didanai oleh instansi/lembaga asing/luar negeri | CT4: 0 | CV4: CDC Telkom | CW4: 3
A5: 5 | C5: - | D5: Upaya Penanganan Wabah COVID-19 Terhadap Komunitas Tunarungu di Kota Surabaya | E5: Pengmas penugasan | F5: 2020 | G5: 2020 | K5: 4000000 | M5: - | O5: Internal | Q5: Institut Telknologi Telkom Surabaya | R5: 6681032 | S5: Anfazul Faridatul Azizah | T5: 715039004 | U5: =K5/5 -> 800000 | V5: Sistem Informasi | W5: FTII | X5: ITTelkom Surabaya | Y5: 8140 | Z5: 072019 | AA5: 259781 | AB5: 0710028604 | AC5: Titus Kristanto | AD5: =U5 -> 800000 | AE5: Bisnis Digital | AF5: FTII | AG5: ITTelkom Surabaya | AH5: 6680634 | AI5: 0725059004 | AJ5: Noerma Pudji Istyanto | AK5: =U5 -> 800000 | AL5: Sistem Informasi | AM5: FTII | AN5: ITTelkom Surabaya | AO5: 6680643 | AP5: 0702039003 | AQ5: Abduh Sayid Albana | AR5: =U5 -> 800000 | AS5: Teknik Logistik | AT5: FTE | AU5: ITTelkom Surabaya | AV5: 6724784 | AW5: 722119101 | AX5: FANNUSH SHOFI AKBAR | AY5: =U5 -> 800000 | AZ5: Teknik Telekomunikasi | BA5: FTE | BB5: ITTelkom Surabaya | BR5: Proposal | BS5: Laporan Akhir | CR5: 4 | CS5: jumlah kerjasama non-profit di bidang pengabdian kepada masyarakat | CT5: =6+30+37+44+42+28 -> 187 | CV5: Institut Telknologi Telkom Surabaya | CW5: 138
A6: 6 | C6: - | D6: Pentingnya APD (faceshield) untuk Masyarakat dan UKM | E6: Pengmas penugasan | F6: 2020 | G6: 2020 | H6: 1 | K6: 6400000 | M6: - | O6: Internal | Q6: Institut Telknologi Telkom Surabaya | R6: 6680648 | S6: Hawwin Mardhiana | T6: 0724089201 | U6: =K6/5 -> 1280000 | V6: Sistem Informasi | W6: FTII | X6: ITTelkom Surabaya | Y6: 8140 | Z6: 072019 | AA6: 6665306 | AB6: 0703129001 | AC6: Ully Asfari | AD6: =U6 -> 1280000 | AE6: Sistem Informasi | AF6: FTII | AG6: ITTelkom Surabaya | AH6: 6764236 | AI6: 0704068902 | AJ6: Rokhmatul Insani | AK6: =U6 -> 1280000 | AL6: Sistem Informasi | AM6: FTII | AN6: ITTelkom Surabaya | AO6: 6680627 | AP6: 0703119301 | AQ6: Benazir Imam Arif Muttaqin | AR6: =U6 -> 1280000 | AS6: Teknik Industri | AT6: FTE | AU6: ITTelkom Surabaya | AV6: 6658545 | AW6: 0401078801 | AX6: Ayu Endah Wahyuni | AY6: =U6 -> 1280000 | AZ6: Teknik Industri | BA6: FTE | BB6: ITTelkom Surabaya | BR6: Proposal | BS6: Laporan Akhir | BT6: Aji Triatmojo | BV6: Mohammad Abyan Seifa | BX6: Karina Putri Permatasari | BZ6: Gilang Ahmad Ramadhani Akbar | CJ6: Jurnal Nasional Terakreditasi | CK6: Publikasi Media Massa Online | CM6: Jurnal submitted, artikel media massa publish | CR6: 5 | CS6: jumlah rata-rata dana pengabdian kepada masyarakat per dosen per tahun | CT6: ='KEUANGAN (INT+EKS) AKRE 2025'!AH129 -> #REF! | CV6: Kemendiktisaintek | CW6: 9
CR7: 6 | CS7: jumlah pendanaan pengabdian kepada masyarakat pada bidang seni budaya | CT7: 0 | CV7: Kemenristek Dikti | CW7: 1
A8: 1 | B8: REK.091/ABDI1/REK/III/2021 | C8: 1025/ABDI1/LPPM/III/2021 | D8: Peningkatan Pengawasan Pengunjung Wisata Pasir Putih Dalegan di Masa Pandemi Covid19 dengan Aplikasi Pendeteksi Jarak Berbasis Kecerdasan Buatan | E8: pkm reguler | F8: 2021 | G8: 2021 | H8: 6 | I8: INDUSTRI KREATIF DAN PENGEMBANGAN TEKNOLOGI MAJU | J8: =K8 -> 7000000 | K8: 7000000 | L8: ITTelkom Surabaya | M8: 7 | N8: Pengmas Kompetitif Internal | O8: Internal | P8: ID | Q8: Institut Telknologi Telkom Surabaya | R8: 6680698 | S8: Mohammad Sholik | T8: 0709128101 | U8: =K8/3 -> 2333333.3 | V8: Rekayasa Perangkat Lunak | W8: FTII | X8: ITTelkom Surabaya | Y8: 8140 | Z8: 072019 | AA8: 6680628 | AB8: 0730058702 | AC8: Fidi Wincoko Putro | AD8: =K8/3 -> 2333333.3 | AE8: Rekayasa Perangkat Lunak | AF8: FTE | AG8: ITTelkom Surabaya | AH8: 6680626 | AI8: 0727099201 | AJ8: Ardian Yusuf Wicaksono | AK8: =K8/3 -> 2333333.3 | AL8: Informatika | AM8: FTII | AN8: ITTelkom Surabaya | BR8: Proposal | BS8: Laporan Akhir | BT8: Auliya Rahman Pakarti | BV8: William Kurniawan | BX8: Edo Handoko | CJ8: Jurnal Nasional ber-ISSN | CK8: Publikasi Media Massa Nasional | CL8: Produk TTG Aplikasi Deteksi Jarak | CR8: 7 | CS8: jumlah pendanaan pengabdian kepada masyarakat pada proyek-proyek kemasyarakatan | CT8: 3292660845 | CV8: Kemensos | CW8: 7
A9: 2 | B9: REK.091/ABDI1/REK/III/2021 | C9: 1027/ABDI1/LPPM/III/2021 | D9: Implementasi Metode Rebranding Pada Produk Hasil Urban Farming Masyarakat Lokal di Masa Pandemi | E9: pkm reguler | F9: 2021 | G9: 2021 | H9: 6 | I9: PEMBERDAYAAN DESA/WILAYAH BINAAN | J9: =K9 -> 6750000 | K9: 6750000 | L9: ITTelkom Surabaya | M9: 7 | N9: Pengmas Kompetitif Internal | O9: Internal | P9: ID | Q9: Institut Telknologi Telkom Surabaya | R9: 6682237 | S9: Dominggo Bayu Baskara | T9: 0722069004 | U9: =K9/3 -> 2250000 | V9: Teknik Industri | W9: FTII | X9: ITTelkom Surabaya | Y9: 8140 | Z9: 072019 | AA9: 6680618 | AB9: 0725059202 | AC9: Rahaditya Dimas Prihadianto | AD9: =K9/3 -> 2250000 | AE9: Teknik Industri | AF9: FTE | AG9: ITTelkom Surabaya | AH9: 6681051 | AI9: 0711069301 | AJ9: Rizqa Amelia Zunaidi | AK9: =K9/3 -> 2250000 | AL9: Teknik Industri | AM9: FTE | AN9: ITTelkom Surabaya | BR9: Proposal | BS9: Laporan Akhir | BT9: MUHAMMAD ALFAIRUS HIDAYATULLAH | BV9: INES MULIA NURDIANA | BX9: PUTRI AMELIA FEBRIANTI | CJ9: Jurnal Internal | CK9: Publikasi Media Massa Nasional | CL9: Peningkatan Pemberdayaan Mitra | CM9: Accepted, online | CV9: PT.POS INDONESIA | CW9: 1
A10: 3 | B10: REK.091/ABDI1/REK/III/2021 | C10: 1028/ABDI1/LPPM/III/2021 | D10: Rancang Workbench Ergonomis untuk mendukung aktivitas bank sampah | E10: pkm reguler | F10: 2021 | G10: 2021 | H10: 6 | I10: PEMBERDAYAAN DESA/WILAYAH BINAAN | J10: =K10 -> 6750000 | K10: 6750000 | L10: ITTelkom Surabaya | M10: 7 | N10: Pengmas Kompetitif Internal | O10: Internal | P10: ID | Q10: Institut Telknologi Telkom Surabaya | R10: 6680618 | S10: Rahaditya Dimas Prihadianto | T10: 0725059202 | U10: =K10/3 -> 2250000 | V10: Teknik Industri | W10: FTII | X10: ITTelkom Surabaya | Y10: 8140 | Z10: 072019 | AA10: 6680643 | AB10: 0702039003 | AC10: Abduh Sayid Albana | AD10: =K10/3 -> 2250000 | AE10: Teknik Logistik | AF10: FTII | AG10: ITTelkom Surabaya | AH10: 6658545 | AI10: 0401078801 | AJ10: Ayu Endah Wahyuni | AK10: =K10/3 -> 2250000 | AL10: Teknik Industri | AM10: FTE | AN10: ITTelkom Surabaya | BR10: Proposal | BS10: Laporan Akhir | BT10: ANDHICO WIRYATAMA | BV10: HENDRAWAN ISWIDODO | CJ10: Jurnal Nasional ber-ISSN | CK10: Video Kegiatan | CL10: Peningkatan Pemberdayaan Mitra | CV10: Telkom University | CW10: 27
A11: 4 | B11: REK.091/ABDI1/REK/III/2021 | C11: 1029/ABDI1/LPPM/III/2021 | D11: PKM Peningkatan Branding dan Optimalisasi Manajemen Usaha Pada UKM Handy Craft Az-Zahra, Desa Gubeng, Surabaya | E11: pkm reguler | F11: 2021 | G11: 2021 | H11: 6 | I11: INDUSTRI KREATIF DAN PENGEMBANGAN TEKNOLOGI MAJU | J11: =K11 -> 6750000 | K11: 6750000 | L11: ITTelkom Surabaya | M11: 7 | N11: Pengmas Kompetitif Internal | O11: Internal | P11: ID | Q11: Institut Telknologi Telkom Surabaya | R11: 6680687 | S11: Wahyu Andy Prastyabudi | T11: 702048705 | U11: =K11/3 -> 2250000 | V11: Teknik Industri | W11: FTII | X11: ITTelkom Surabaya | Y11: 8140 | Z11: 072019 | AA11: 6680726 | AB11: 719069101 | AC11: Arliyanti Nurdin | AD11: =K11/3 -> 2250000 | AE11: Teknologi Informasi | AF11: FTII | AG11: ITTelkom Surabaya | AH11: 6778837 | AI11: 711039403 | AJ11: Muhammad Dzulfikar Fauzi | AK11: =K11/3 -> 2250000 | AL11: Informatika | AM11: FTII | AN11: ITTelkom Surabaya | BR11: Proposal | BS11: Laporan Akhir | BT11: Muhammad Arkan Fauzan | BU11: Teknologi Informasi, FTIB, ITTelkom Surabaya | BV11: Farhan Hadi Pratama | BX11: Arda Erico Yuda | BY11: Teknik Industri, FTEIC, ITTelkom Surabaya | CJ11: Prosiding Seminar Nasional ber-ISBN. Jurnal Nasional Terakreditasi Sinta 3 JURNAL PENGABDIAN KEPADA MASYARAKAT | CK11: Publikasi Media Massa Nasional | CL11: Peningkatan Pemberdayaan Mitra Peningkatan signifikan | CM11: Submitted, Published, Peningkatan Signifikan | CV11: (blank)
A12: 5 | B12: REK.091/ABDI1/REK/III/2021 | C12: 1032/ABDI1/LPPM/III/2021 | D12: Pengendali Tingkat Keasaman Air Kolam Untuk Peternak Ikan Lele di Desa Jatirejo, Mojokerto | E12: pkm reguler | F12: 2021 | G12: 2021 | H12: 6 | I12: INDUSTRI KREATIF DAN PENGEMBANGAN TEKNOLOGI MAJU | J12: =K12 -> 6900000 | K12: 6900000 | L12: ITTelkom Surabaya | M12: 7 | N12: Pengmas Kompetitif Internal | O12: Internal | P12: ID | Q12: Institut Telknologi Telkom Surabaya | R12: 258471 | S12: Susijanto Tri Rasmana | T12: 0727097302 | U12: =K12/3 -> 2300000 | V12: Teknik Elektro | W12: FTE | X12: ITTelkom Surabaya | Y12: 8140 | Z12: 072019 | AA12: 6680685 | AB12: 0721068802 | AC12: Moch. Iskandar Riansyah | AD12: =K12/3 -> 2300000 | AE12: Teknik Elektro | AF12: FTE | AG12: ITTelkom Surabaya | AH12: 6853203 | AI12: 0705109006 | AJ12: Chaironi Latif | AK12: =K12/3 -> 2300000 | AL12: Teknik Elektro | AM12: FTE | AN12: ITTelkom Surabaya | BR12: Proposal | BS12: Laporan Akhir | BT12: MUHAMMAD DWI HARIYANTO | BV12: ANAK AGUNG KUSUMA JAYA NINGRAT | BX12: JESICA F NURA | CJ12: Jurnal Nasional Terakreditasi | CK12: Publikasi Media Massa Nasional | CL12: Produk TTG | CM12: Submitted, published, berfungsi dan telah diserahterimakan | CV12: Grand Total | CW12: 186
A13: 6 | B13: REK.091/ABDI1/REK/III/2021 | C13: 1033/ABDI1/LPPM/III/2021 | D13: Pemanfaatan Teknologi Sonar untuk Membantu Nelayan Kedung Cowek, Kec.Bulak | E13: pkm reguler | F13: 2021 | G13: 2021 | H13: 6 | I13: INDUSTRI KREATIF DAN PENGEMBANGAN TEKNOLOGI MAJU | J13: =K13 -> 6900000 | K13: 6900000 | L13: ITTelkom Surabaya | M13: 7 | N13: Pengmas Kompetitif Internal | O13: Internal | P13: ID | Q13: Institut Telknologi Telkom Surabaya | R13: 6680625 | S13: Nilla Rachmaningrum | T13: 0408067804 | U13: =K13/3 -> 2300000 | V13: Teknik Telekomunikasi | W13: FTE | X13: ITTelkom Surabaya | Y13: 8140 | Z13: 072019 | AA13: 6680645 | AB13: 0713108902 | AC13: Walid Maulana Hadiansyah | AD13: =K13/3 -> 2300000 | AE13: Teknik Telekomunikasi | AF13: FTE | AG13: ITTelkom Surabaya | AH13: 6680741 | AI13: 0727059002 | AJ13: Hamzah Ulinuha Mustakim | AK13: =K13/3 -> 2300000 | AL13: Teknik Telekomunikasi | AM13: FTE | AN13: ITTelkom Surabaya | BR13: Proposal | BS13: Laporan Akhir | BT13: Bryan Birzha Marsono | BV13: Rian Gunawan | BX13: Galuh Widya | BZ13: Miscbachul Munir | CJ13: Jurnal Nasional ber-ISSN | CK13: Publikasi Media Massa Nasional | CL13: Peningkatan Pemberdayaan Mitra
A14: 7 | B14: REK.091/ABDI1/REK/III/2021 | C14: 1035/ABDI1/LPPM/III/2021 | D14: Pendayagunaan IT untuk Branding Kampung Ondomohen Sebagai Wisata Edukasi 3R (Reduce, Reuse, dan Recycle) | E14: pkm reguler | F14: 2021 | G14: 2021 | H14: 6 | I14: INDUSTRI KREATIF DAN PENGEMBANGAN TEKNOLOGI MAJU | J14: =K14 -> 6749500 | K14: 6749500 | L14: ITTelkom Surabaya | M14: 7 | N14: Pengmas Kompetitif Internal | O14: Internal | P14: ID | Q14: Institut Telknologi Telkom Surabaya | R14: 6680623 | S14: Yupit Sudianto | T14: 0721088602 | U14: =K14/3 -> 2249833.3 | V14: Sistem Informasi | W14: FTII | X14: ITTelkom Surabaya | Y14: 8140 | Z14: 072019 | AA14: 6680648 | AB14: 0724089201 | AC14: Hawwin Mardhiana | AD14: =K14/3 -> 2249833.3 | AE14: Sistem Informasi | AF14: FTII | AG14: ITTelkom Surabaya | AH14: 6665306 | AI14: 0703129001 | AJ14: Ully Asfari | AK14: =K14/3 -> 2249833.3 | AL14: Sistem Informasi | AM14: FTII | AN14: ITTelkom Surabaya | BR14: Proposal | BS14: Laporan Akhir | BT14: Thania Anindillah Putri | BV14: Tanang Satriyo Adi | BX14: Tanfirul Roibafi Muhammad | CJ14: Jurnal Internal | CK14: Publikasi Media Massa Nasional | CL14: Produk TTG
A15: 8 | B15: REK.091/ABDI1/REK/III/2021 | C15: 1030/ABDI1/LPPM/III/2021 | D15: Sosialisasi Penggunaan "Fingerprint" dan Database untuk Absensi Guru di Yayasan Natanisha, Sekolah Anak Berkebutuhan Khusus "AGCA" | E15: pkm reguler | F15: 2021 | G15: 2021 | H15: 6 | I15: PEMBERDAYAAN DESA/WILAYAH BINAAN | J15: =K15 -> 3400000 | K15: 3400000 | L15: ITTelkom Surabaya | M15: 7 | N15: Pengmas Kompetitif Internal | O15: Internal | P15: ID | Q15: Institut Telknologi Telkom Surabaya | R15: 6681032 | S15: Anfazul Faridatul Azizah | T15: 0715039004 | U15: =K15/2 -> 1700000 | V15: Sistem Informasi | W15: FTII | X15: ITTelkom Surabaya | Y15: 8140 | Z15: 072019 | AA15: 6764236 | AB15: 0704068902 | AC15: Rokhmatul Insani | AD15: =K15/2 -> 1700000 | AE15: Sistem Informasi | AF15: FTII | AG15: ITTelkom Surabaya | BR15: Proposal | BS15: Laporan Akhir | BT15: Tanfirul Roibafi | BV15: Nabilah Monica Hidayat | BX15: Fannijara Enggar Larasati | CJ15: Jurnal Internal | CK15: Publikasi Media Massa Nasional | CL15: Peningkatan Pemberdayaan Mitra | CM15: Media massa published | CN15: Jurnal Pengabdian
A16: 9 | B16: REK.091/ABDI1/REK/III/2021 | C16: 1026/ABDI1/LPPM/III/2021 | D16: PKM SIM Apotek untuk Pengelolaan Data Jual Beli pada Apotek Amel Mojokerto | E16: pkm reguler | F16: 2021 | G16: 2021 | H16: 6 | I16: INDUSTRI KREATIF DAN PENGEMBANGAN TEKNOLOGI MAJU | J16: =K16 -> 6950000 | K16: 6950000 | L16: ITTelkom Surabaya | M16: 7 | N16: Pengmas Kompetitif Internal | O16: Internal | P16: ID | Q16: Institut Telknologi Telkom Surabaya | R16: 6764236 | S16: Rokhmatul Insani | T16: 0704068902 | U16: =K16/2 -> 3475000 | V16: Sistem Informasi | W16: FTII | X16: ITTelkom Surabaya | Y16: 8140 | Z16: 072019 | AA16: 6681032 | AB16: 0715039004 | AC16: Anfazul Faridatul Azizah | AD16: =K16/2 -> 3475000 | AE16: Sistem Informasi | AF16: FTII | AG16: ITTelkom Surabaya | BR16: Proposal | BS16: Laporan Akhir | BT16: ALFONSUS NATHANAEL DAMAR PRISTIANTIO | BV16: M. IQBAL HAFIDZ | BX16: MUHAMMAD DAFFA ADIYATMA YUSUF | CJ16: Jurnal Nasional Terakreditasi | CK16: Video Kegiatan | CL16: Peningkatan Pemberdayaan Mitra | CM16: Jurnal submitted
A17: 10 | B17: REK.091/ABDI1/REK/III/2021 | C17: 1036/ABDI1/LPPM/III/2021 | D17: Sterillisasi Sayur buah Pada Koperasi Hita Loka Tara menggunakan UV Light untuk Meningkatkan Kualitas Produk Hasil Panen Hidroponik dan Buah | E17: pkm berbasis penelitian | F17: 2021 | G17: 2021 | H17: 6 | I17: INDUSTRI KREATIF DAN PENGEMBANGAN TEKNOLOGI MAJU | J17: =K17 -> 15670000 | K17: 15670000 | L17: ITTelkom Surabaya | M17: 7 | N17: Pengmas Kompetitif Internal | O17: Internal | P17: ID | Q17: Institut Telknologi Telkom Surabaya | R17: 6680664 | S17: Farah Zakiyah Rahmanti | T17: 0715128708 | U17: =K17/3 -> 5223333.3 | V17: Teknologi Informasi | W17: FTII | X17: ITTelkom Surabaya | Y17: 8140 | Z17: 072019 | AA17: 6680680 | AB17: 0704039202 | AC17: Bernadus Anggo Seno Aji | AD17: =K17/3 -> 5223333.3 | AE17: Teknologi Informasi | AF17: FTII | AG17: ITTelkom Surabaya | AH17: 6680726 | AI17: 719069101 | AJ17: Arliyanti Nurdin | AK17: =K17/3 -> 5223333.3 | AL17: Teknologi Informasi | AM17: FTII | AN17: ITTelkom Surabaya | BR17: Proposal | BS17: Laporan Akhir | BT17: Mochammad Rafi Adityawarman | BU17: Teknologi Informasi, FTIB, ITTelkom Surabaya | BV17: Muhammad Akbar Ramadhan | BW17: Teknologi Informasi, FTIB, ITTelkom Surabaya | BX17: Muhamad Iqbal Maulana | BY17: Teknologi Informasi, FTIB, ITTelkom Surabaya | BZ17: Wiranti Maharani | CA17: Teknologi Informasi, FTIB, ITTelkom Surabaya | CB17: Riska Aprilia | CC17: Teknologi Informasi, FTIB, ITTelkom Surabaya | CJ17: Jurnal Nasional Terakreditasi | CK17: Video Kegiatan | CL17: Peningkatan Pemberdayaan Mitra | CM17: Video publish youtube, published media massa, pelatihan penggunaan alat | CN17: International Conference | CO17: Accepted
A18: 11 | B18: REK.091/ABDI1/REK/III/2021 | C18: 1037/ABDI1/LPPM/III/2021 | D18: Pemasaran Online Produk Nasi Tiwul di Kabupaten Malang | E18: pkm berbasis penelitian | F18: 2021 | G18: 2021 | H18: 6 | I18: PEMBERDAYAAN DESA/WILAYAH BINAAN | J18: =K18 -> 15300000 | K18: 15300000 | L18: ITTelkom Surabaya | M18: 7 | N18: Pengmas Kompetitif Internal | O18: Internal | P18: ID | Q18: Institut Telknologi Telkom Surabaya | R18: 259781 | S18: Titus Kristanto | T18: 0710028604 | U18: =K18/3 -> 5100000 | V18: Rekayasa Perangkat Lunak | W18: FTII | X18: ITTelkom Surabaya | Y18: 8140 | Z18: 072019 | AA18: 6658545 | AB18: 0401078801 | AC18: Ayu Endah Wahyuni | AD18: =K18/3 -> 5100000 | AE18: Teknik Industri | AF18: FTE | AG18: ITTelkom Surabaya | AH18: 6680622 | AI18: 0709039401 | AJ18: Dewi Rahmawati | AK18: =K18/3 -> 5100000 | AL18: Rekayasa Perangkat Lunak | AM18: FTE | AN18: ITTelkom Surabaya | BR18: Proposal | BS18: Laporan Akhir | BT18: Reza Arindra Fadillah | BV18: Amanda Amalia | CJ18: Jurnal Nasional Terakreditasi | CK18: Publikasi Media Massa Nasional | CL18: Peningkatan Pemberdayaan Mitra | CM18: Jurnal published, published media massa | CN18: Hak Kekayaan Intelektual | CO18: Granted
A19: 12 | B19: REK.092/ABDI1/REK/III/2021 | C19: 1054/ABDI1/LPPM/III/2021 | D19: Peningkatan kapasitas Desa ngeni dengan Penerangan jalan Umum Tenaga Surya dan Pelatihan Keterampilan Teknologi ICT | E19: pkm Penugasan | F19: 2021 | G19: 2021 | H19: 6 | I19: PEMBERDAYAAN DESA/WILAYAH BINAAN | J19: =K19 -> 20000000 | K19: 20000000 | L19: ITTelkom Surabaya | M19: 7 | N19: Pengmas Kompetitif Internal | O19: Internal | P19: ID | Q19: Institut Telknologi Telkom Surabaya | R19: 6680651 | S19: Dimas Adiputra | T19: 0725059301 | U19: =K19/5 -> 4000000 | V19: Teknik Elektro | W19: FTE | X19: ITTelkom Surabaya | Y19: 8140 | Z19: 072019 | AA19: 6680612 | AB19: 0728059203 | AC19: Isa Hafidz | AD19: =K19/5 -> 4000000 | AE19: Teknik Elektro | AF19: FTE | AG19: ITTelkom Surabaya | AH19: 6680708 | AI19: 0706069201 | AJ19: Lora Khaula Amifia | AK19: =K19/5 -> 4000000 | AL19: Teknik Elektro | AM19: FTE | AN19: ITTelkom Surabaya | AO19: 6680641 | AP19: 0714029301 | AQ19: Ardiansyah Al farouq | AR19: =K19/5 -> 4000000 | AS19: Teknik Komputer | AT19: FTII | AU19: ITTelkom Surabaya | AV19: 6682174 | AW19: 0708069202 | AX19: Khodijah Amiroh | AY19: =K19/5 -> 4000000 | AZ19: Teknologi Informasi | BA19: FTII | BB19: ITTelkom Surabaya | BR19: Proposal | BS19: Laporan Akhir | BT19: Bagas Wahyu Prakoso | BV19: Robin Addwiyansyah Alfaro Samrat | BX19: Legowo Budi Prasodjo | BZ19: Nurina Devi Aprilliastuti | CB19: Ahmad Habibi | CD19: Wafa Murtadho Kholid | CF19: Ilham Akbar Maulana | CH19: Aditya Yudhistira | CJ19: Jurnal Nasional ber-ISSN | CK19: Publikasi Media Massa Nasional | CL19: Produk TTG | CM19: Jurnal submitted, publish media massa, PJU | CN19: -
A20: 13 | B20: REK.119/ABDI1/REK/V/2021 | C20: 1276/ABDI1/LPPM/III/2021 | D20: Sosialisasi dan Training Crane Pemulasaran Jenazah secara Terpadu di Rumah Sakit Pendidikan Universitas Airlangga Surabaya | E20: pkm Penugasan | F20: 2021 | G20: 2021 | H20: 3 | I20: PEMBERDAYAAN DESA/WILAYAH BINAAN | J20: =K20 -> 40000000 | K20: 40000000 | L20: ITTelkom Surabaya | M20: 7 | N20: Pengmas Kompetitif Internal | O20: Internal | P20: ID | Q20: Institut Telknologi Telkom Surabaya | R20: 6665306 | S20: Ully Asfari | T20: 0703129001 | U20: =K20/4 -> 10000000 | V20: Sistem Informasi | W20: FTII | X20: ITTelkom Surabaya | Y20: 8140 | Z20: 072019 | AA20: 6680633 | AB20: 0717017902 | AC20: Helmy Widyantara | AD20: =K20/4 -> 10000000 | AE20: Teknologi Informasi | AF20: FTII | AG20: ITTelkom Surabaya | AH20: 6680648 | AI20: 0724089201 | AJ20: Hawwin Mardhiana | AK20: =K20/4 -> 10000000 | AL20: Sistem Informasi | AM20: FTII | AN20: ITTelkom Surabaya | AO20: 6744406 | AP20: 0709059004 | AQ20: Muhammad Nasrullah | AR20: =K20/4 -> 10000000 | AS20: Sistem Informasi | AT20: FTII | AU20: ITTelkom Surabaya | BR20: Proposal | BS20: Laporan Akhir | BT20: Insani Sabilillah | BU20: Sistem Informasi, FTIB, ITTelkom Surabaya | BV20: Siti Aminah | BW20: Sistem Informasi, FTIB, ITTelkom Surabaya | BX20: Meita Betania | CJ20: - | CK20: Publikasi Media Massa Nasional | CL20: - | CM20: Media massa published
A21: 14 | B21: REK.119/ABDI1/REK/V/2021 | C21: 1277/ABDI1/LPPM/III/2021 | D21: Sosialisasi dan Training Crane Pemulasaran Jenazah secara Terpadu di Rumah Sakit Umum Daerah Sidoarjo | E21: pkm Penugasan | F21: 2021 | G21: 2021 | H21: 3 | I21: PEMBERDAYAAN DESA/WILAYAH BINAAN | J21: =K21 -> 40000000 | K21: 40000000 | L21: ITTelkom Surabaya | M21: 7 | N21: Pengmas Kompetitif Internal | O21: Internal | P21: ID | Q21: Institut Telknologi Telkom Surabaya | R21: 6680623 | S21: Yupit Sudianto | T21: 0721088602 | U21: =K21/4 -> 10000000 | V21: Sistem Informasi | W21: FTII | X21: ITTelkom Surabaya | Y21: 8140 | Z21: 072019 | AA21: 6680633 | AB21: 0717017902 | AC21: Helmy Widyantara | AD21: =K21/4 -> 10000000 | AE21: Teknologi Informasi | AF21: FTII | AG21: ITTelkom Surabaya | AH21: 6681051 | AI21: 0711069301 | AJ21: Rizqa Amelia Zunaidi | AK21: =K21/4 -> 10000000 | AL21: Teknik Elektro | AM21: FTE | AN21: ITTelkom Surabaya | AO21: 6764236 | AP21: 0704068902 | AQ21: Rokmatul Insani | AR21: =K21/4 -> 10000000 | AS21: Sistem Informasi | AT21: FTII | AU21: ITTelkom Surabaya | BR21: Proposal | BS21: Laporan Akhir | BT21: Fidelia Adinda Syafani | BU21: Teknik Industri, FTEIC, ITTelkom Surabaya | BV21: Nabilla Adinna Cahyani | BW21: Teknik Industri, FTEIC, ITTelkom Surabaya | BX21: Edriand Imens Raygrandi | CJ21: - | CK21: Video Kegiatan | CL21: -
A22: 15 | B22: REK.119/ABDI1/REK/V/2021 | C22: 1278/ABDI1/LPPM/III/2021 | D22: Sosialisasi dan Training Crane Pemulasaran Jenazah secara Terpadu di Dinas Kesehatan Kabupaten Gresik | E22: pkm Penugasan | F22: 2021 | G22: 2021 | H22: 3 | I22: PEMBERDAYAAN DESA/WILAYAH BINAAN | J22: =K22 -> 40000000 | K22: 40000000 | L22: ITTelkom Surabaya | M22: 7 | N22: Pengmas Kompetitif Internal | O22: Internal | P22: ID | Q22: Institut Telknologi Telkom Surabaya | R22: 6680612 | S22: Isa Hafidz | T22: 0728059203 | U22: =K22/5 -> 8000000 | V22: Teknik Elektro | W22: FTE | X22: ITTelkom Surabaya | Y22: 8140 | Z22: 072019 | AA22: 6680633 | AB22: 0717017902 | AC22: Helmy Widyantara | AD22: =K22/5 -> 8000000 | AE22: Teknologi Informasi | AF22: FTII | AG22: ITTelkom Surabaya | AH22: 6680627 | AI22: 0703119301 | AJ22: Benazir Imam Arif M | AK22: =K22/5 -> 8000000 | AL22: Teknik Elektro | AM22: FTE | AN22: ITTelkom Surabaya | AO22: 6680628 | AP22: 0730058702 | AQ22: Fidi Wincoko Putro | AR22: =K22/5 -> 8000000 | AS22: Rekayasa Perangkat Lunak | AT22: FTE | AU22: ITTelkom Surabaya | AV22: 6680698 | AW22: 0709128101 | AX22: Mohammad Sholik | AY22: =K22/5 -> 8000000 | AZ22: Rekayasa Perangkat Lunak | BA22: FTE | BB22: ITTelkom Surabaya | BR22: Proposal | BS22: Laporan Akhir | BT22: M. MIFTAHUL ABIDIN | BV22: RULLY ROSADI | BW22: Teknologi Informasi, FTIB, ITTelkom Surabaya | BX22: IRFANSAH W. | CJ22: - | CK22: Video Kegiatan | CL22: -
A23: 16 | B23: REK.119/ABDI1/REK/V/2021 | C23: 1278/ABDI1/LPPM/III/2021 | D23: Pelatihan penggunaan mesin braille embosser dengan fitur voice di Balai Literasi Braille Indonesia Abiyoso | E23: pkm Penugasan | F23: 2021 | G23: 2021 | H23: 3 | I23: PEMBERDAYAAN DESA/WILAYAH BINAAN | J23: =K23 -> 450000000 | K23: 450000000 | L23: ITTelkom Surabaya | M23: 7 | N23: Pengmas Kompetitif Internal | O23: Internal | P23: ID | Q23: Institut Telknologi Telkom Surabaya | R23: 6680651 | S23: Dimas Adiputra | T23: 0725059301 | U23: =K23/3 -> 150000000 | V23: Teknik Elektro | W23: FTE | X23: ITTelkom Surabaya | Y23: 8140 | Z23: 072019 | AA23: 6680687 | AB23: 702048705 | AC23: Wahyu Andy Prastyabudi | AD23: =K23/3 -> 150000000 | AH23: 6680623 | AI23: 0721088602 | AJ23: Yupit Sudianto | AK23: =K23/3 -> 150000000 | BR23: Proposal | BS23: Laporan Akhir | BT23: Moch. Bagus Indrastata | BV23: Annisa Putri Pratama | BW23: Teknik Industri, FTEIC, ITTelkom Surabaya | BX23: Sangaji Wicaksono | CK23: Publikasi Media Massa Nasional | CL23: Produk TTG | CM23: Media massa tayang, produk TTG sudah terpasang
A24: 17 | B24: REK.119/ABDI1/REK/V/2021 | C24: 1821/ABDI1/LPPM/VI/2021 | D24: Sosialisasi Crane Pemulasaraan Jenazah di RS Aisyiyah Kudus | E24: pkm Penugasan | F24: 2021 | G24: 2021 | H24: 3 | I24: PEMBERDAYAAN DESA/WILAYAH BINAAN | J24: =K24 -> 40000000 | K24: 40000000 | L24: ITTelkom Surabaya | M24: 7 | N24: Pengmas Kompetitif Internal | O24: Internal | P24: ID | Q24: Institut Telknologi Telkom Surabaya | R24: 6805206 | S24: Agus Sulistya | T24: 8920230021 | U24: =K24/4 -> 10000000 | V24: Rekayasa Perangkat Lunak | W24: FTII | X24: ITTelkom Surabaya | Y24: 8140 | Z24: 072019 | AA24: 6682174 | AB24: 0708069202 | AC24: Khodijah Amiroh | AD24: =K24/4 -> 10000000 | AE24: Teknologi Informasi | AF24: FTII | AG24: ITTelkom Surabaya | AH24: 6680628 | AI24: 0730058702 | AJ24: Fidi Wincoko Putro | AK24: =K24/4 -> 10000000 | AO24: 6680618 | AP24: 0725059202 | AQ24: Rahaditya Dimas Prihadianto | AR24: =K24/4 -> 10000000 | AS24: Teknik Industri | AT24: FTE | AU24: ITTelkom Surabaya | BR24: Proposal | BS24: Laporan Akhir | BT24: Amanda Amalia | BV24: Febri Purnama Putri
A25: 18 | B25: REK.087/SAM4/REK/III/2021 | C25: - | D25: Pengembangan industri dan wisata edukasi Kampung Pintar Suroboyo melalui Penerapan Teknologi Minim Kontak dengan Pendekatan Berbasis Kerakyatan | E25: Hibah BiMA Pemberdayaan Berbasis Masyarakat | F25: 2021 | G25: 2021 | H25: 5 | I25: INDUSTRI KREATIF DAN PENGEMBANGAN TEKNOLOGI MAJU | J25: =K25 -> 48800000 | K25: 48800000 | L25: ITTelkom Surabaya | M25: 7 | N25: Pengmas Kompetitif Internal | O25: Eksternal | Q25: Kemendiktisaintek | R25: 6680627 | S25: Benazir Imam Arif Muttawin | T25: 0703119301 | U25: =K25/2 -> 24400000 | V25: Teknik Industri | W25: FTII | X25: ITTelkom Surabaya | Y25: 8140 | Z25: 072019 | AC25: Anindya Rachma Dwicahyani | AH25: 6680708 | AI25: 0706069201 | AJ25: Lora Khaula Amifia | AK25: =K25/2 -> 24400000 | AL25: Teknik Elektro | AM25: FTE | AN25: ITTelkom Surabaya | BR25: Proposal | BS25: Laporan Akhir
A26: 19 | B26: REK.150/SAM4/REK/VIII/2021 | C26: 1381/ABDI1/LPPM/III/2021 | D26: Pengembangan Computerized Maintenance Management System di RSUD Tongas | E26: pkm reguler | F26: 2021 | G26: 2021 | H26: 5 | I26: INDUSTRI KREATIF DAN PENGEMBANGAN TEKNOLOGI MAJU | J26: =K26 -> 3456000 | K26: 3456000 | L26: ITTelkom Surabaya | M26: 7 | N26: Pengmas Kompetitif Internal | O26: Internal | Q26: Institut Telknologi Telkom Surabaya | R26: 6680683 | S26: Billy Montolalu | T26: 0729088704 | U26: =K26/2 -> 1728000 | V26: Rekayasa Perangkat Lunak | W26: FTII | X26: ITTelkom Surabaya | AA26: 6680629 | AB26: 0727048809 | AC26: Ubaidillah Umar | AD26: =K26/2 -> 1728000 | AE26: Teknik Komputer | AF26: FTE | AG26: ITTelkom Surabaya | BR26: Proposal | BS26: Laporan Akhir | BT26: Ahmad Habibi | BV26: Dimas Mahendra Budi Santosa | CK26: Publikasi Media Massa Nasional | CL26: Produk TTG | CM26: Publish 5 jurnal, produk android
A27: 20 | B27: REK.150/SAM4/REK/VIII/2021 | C27: 1382/ABDI1/LPPM/III/2021 | D27: Pelatihan Software Simulasi Livewire untuk Siswa SMK Telkom Cirebon Secara Online untuk Meningkatkan Sinergi antara Lembaga dibawah Yayasan Pendidikan Telkom | E27: pkm reguler | F27: 2021 | G27: 2021 | H27: 5 | I27: INDUSTRI KREATIF DAN PENGEMBANGAN TEKNOLOGI MAJU | J27: =K27 -> 1000000 | K27: 1000000 | L27: ITTelkom Surabaya | M27: 7 | N27: Pengmas Kompetitif Internal | O27: Internal | Q27: Institut Telknologi Telkom Surabaya | R27: 6680678 | S27: Dwi Edi Setyawan | T27: 0713068702 | U27: =K27/2 -> 500000 | V27: Teknik Komputer | W27: FTE | X27: ITTelkom Surabaya | AA27: 6680683 | AB27: 0729088704 | AC27: Billy Montolalu | AD27: =K27/2 -> 500000 | AE27: Rekayasa Perangkat Lunak | AF27: FTII | AG27: ITTelkom Surabaya | BR27: Proposal | BS27: Laporan Akhir | BT27: Royzaldo Aser Elegius Logo | CJ27: - | CK27: Video Kegiatan | CL27: - | CM27: Publish video youtube
A28: 21 | B28: REK.150/SAM4/REK/VIII/2021 | C28: - | D28: Implementasi Green Marketing pada Produk Urban Farming UMKM Lokal | E28: pkm Mandiri | F28: 2021 | G28: 2021 | H28: 5 | I28: INDUSTRI KREATIF DAN PENGEMBANGAN TEKNOLOGI MAJU | J28: 0 | K28: 5000000 | L28: ITTelkom Surabaya | M28: 7 | N28: Pengmas Kompetitif Internal | O28: Internal | Q28: Institut Telknologi Telkom Surabaya | S28: Tiar Anindya Putri | U28: =K28/2 -> 2500000 | AA28: 6801989 | AB28: 0704029302 | AC28: Sekar Widyasari Putri | AD28: =K28/2 -> 2500000 | AE28: Bisnis Digital | AF28: FTII | AG28: ITTelkom Surabaya | BR28: Proposal | BS28: Laporan Akhir | BT28: Fidelian Adinda Syafani | BU28: Teknik Industri, FTEIC, ITTelkom Surabaya | BV28: Hesti Dita Pramesti | BX28: Muhammad Miftahul Abidin | BY28: Teknik Industri, FTEIC, ITTelkom Surabaya | BZ28: Haifa Puji Rahayuningsih | CB28: Ni Wayan Ditapramesti | CD28: Muchammad Dzulfikar Alfani | CJ28: - | CK28: Publikasi Media Massa Nasional | CL28: Peningkatan Pemberdayaan Mitra | CM28: Media massa sudah terbit, kemasan baru ramah lingkungan
A29: 22 | B29: REK.150/SAM4/REK/VIII/2021 | C29: 1822/ABDI1/LPPM/VIII/2021 | D29: Website Usaha Ice Tube (Kenning Ice Tube) untuk Menunjang Pemasaran di Dunia Digital | E29: pkm Mandiri | F29: 2021 | G29: 2021 | H29: 5 | I29: INDUSTRI KREATIF DAN PENGEMBANGAN TEKNOLOGI MAJU | J29: 0 | K29: 5000000 | L29: ITTelkom Surabaya | M29: 7 | N29: Pengmas Kompetitif Internal | O29: Internal | Q29: Institut Telknologi Telkom Surabaya | R29: 6756318 | S29: Moh.Hamim Zajuli Al Faroby | T29: 0724079501 | U29: =K29/3 -> 1666666.7 | V29: Sains Data | W29: FTII | X29: ITTelkom Surabaya | AA29: 6778519 | AB29: 0712059303 | AC29: Nisa Isrofi | AD29: =K29/3 -> 1666666.7 | AE29: Teknik Logistik | AF29: FTE | AG29: ITTelkom Surabaya | AH29: 6793410 | AI29: 0707019501 | AJ29: Helisyah Nur Fadhilah | AK29: =K29/3 -> 1666666.7 | AL29: Sains Data | AM29: FTII | AN29: ITTelkom Surabaya | BR29: Proposal | BS29: Laporan Akhir | BT29: Rully Rosady | BU29: Teknologi Informasi, FTIB, ITTelkom Surabaya | BV29: Mochamad Fajar Nofriyandri | BW29: Teknologi Informasi, FTIB, ITTelkom Surabaya | BX29: Annisa Ainin Fadilah | BY29: Teknologi Informasi, FTIB, ITTelkom Surabaya | BZ29: Nabila Nur Amalia | CA29: Teknologi Informasi, FTIB, ITTelkom Surabaya | CB29: Berliana Amelia Ariyanti Zein | CC29: Teknologi Informasi, FTIB, ITTelkom Surabaya | CK29: Video Kegiatan, Publikasi Media Internal | CL29: Peningkatan Pemberdayaan Mitra | CM29: Publikasi online | CN29: Website UMKM | CO29: Dapat diakses
A30: 23 | B30: REK.150/SAM4/REK/VIII/2021 | C30: 1823/ABDI1/LPPM/VIII/2021 | D30: Tanda Tangan Elektronik Berbasis QR Code untuk Mempermudah Perizinan pada Masa Pandemi di Kantor Kecamatan Bulak Surabaya | E30: pkm Mandiri | F30: 2021 | G30: 2021 | H30: 5 | I30: PEMBERDAYAAN DESA/WILAYAH BINAAN | J30: 0 | K30: 5000000 | L30: ITTelkom Surabaya | M30: 7 | N30: Pengmas Kompetitif Internal | O30: Internal | Q30: Institut Telknologi Telkom Surabaya | R30: 6756318 | S30: Moh.Hamim Zajuli Al Faroby | T30: 0724079501 | U30: =K30/3 -> 1666666.7 | V30: Sains Data | W30: FTII | X30: ITTelkom Surabaya | AA30: 6778519 | AB30: 0712059303 | AC30: Nisa Isrofi | AD30: =K30/3 -> 1666666.7 | AE30: Teknik Logistik | AF30: FTE | AG30: ITTelkom Surabaya | AH30: 6793410 | AI30: 0707019501 | AJ30: Helisyah Nur Fadhilah | AK30: =K30/3 -> 1666666.7 | AL30: Sains Data | AM30: FTII | AN30: ITTelkom Surabaya | BR30: Proposal | BS30: Laporan Akhir | BT30: Rully Rosady | BU30: Teknologi Informasi, FTIB, ITTelkom Surabaya | BV30: Mochamad Fajar Nofriyandri | BW30: Teknologi Informasi, FTIB, ITTelkom Surabaya | BX30: Annisa Ainin Fadilah | BY30: Teknologi Informasi, FTIB, ITTelkom Surabaya | BZ30: Nabila Nur Amalia | CA30: Teknologi Informasi, FTIB, ITTelkom Surabaya | CB30: Berliana Amelia Ariyanti Zein | CC30: Teknologi Informasi, FTIB, ITTelkom Surabaya | CK30: Video Kegiatan, Publikasi Media Internal | CL30: Peningkatan Pemberdayaan Mitra | CN30: Publikasi Media Internal
