Workbook
Name data: #REF!
Name rapel: #REF!

Sheet Publikasi implementasi
A1: DATA PUBLIKASI | I1: DATA PENULIS KORESPONDING | N1: DATA PENULIS (1) | S1: DATA PENULIS (2) | X1: DATA PENULIS (3) | AC1: DATA PENULIS (4) | AH1: DATA PENULIS (5) | AM1: DATA PENULIS (6) | AR1: DATA PENULIS LAINNYA
A2: Judul Publikasi | B2: Nama Jurnal | C2: Implementasi | D2: Akreditasi/ Index Jurnal | E2: Lembaga Pengindeks | F2: Tahun Submit | G2: Tahun Accepted | H2: Tahun Published | I2: Nama Penulis Koresponding | J2: Sinta ID | K2: NIDN | L2: Prodi | M2: Afiliasi | N2: Nama Penulis (1) | O2: Prodi2 | P2: Afiliasi3 | Q2: Sinta ID4 | R2: NIDN5 | S2: Nama Penulis (2) | T2: Prodi6 | U2: Afiliasi7 | V2: Sinta ID8 | W2: NIDN9 | X2: Nama Penulis (3) | Y2: Prodi10 | Z2: Afiliasi11 | AA2: Sinta ID12 | AB2: NIDN13 | AC2: Nama Penulis (4) | AD2: Prodi14 | AE2: Afiliasi15 | AF2: Sinta ID16 | AG2: NIDN17 | AH2: Nama Penulis (5) | AI2: Prodi18 | AJ2: Afiliasi19 | AK2: Sinta ID20 | AL2: NIDN21 | AM2: Nama Penulis (6) | AN2: Prodi22 | AO2: Afiliasi23 | AP2: Sinta ID24 | AQ2: NIDN25 | AR2: Nama Penulis Lain | AS2: Prodi26 | AT2: Afiliasi27 | AU2: Sinta ID28 | AV2: NIDN29
A3: Low-cost Transverse Electromagnetic (TEM) cell design for radiated emission measurement | B3: IOP Conference Series: Materials Science and Engineering 1073 (1), 012040, 2021 | D3: Prosiding Internasional | H3: 2021 | I3: Muhammad Yanuar Hariawan | L3: TK | M3: ITTELKOM Surabaya | N3: Muhammad Yanuar Hariawan | O3: TK | P3: ITTELKOM Surabaya | S3: Rizadi Sasmita Darwis | U3: Politeknik Caltex Riau | X3: B A Habibi | Z3: Politeknik Caltex Riau
A4: Simulasi Efisiensi dan Akurasi Shielding Effectiveness pada Kabel Coaxial | B4: ABEC Indonesia 9, 1263-1274, 2021 | D4: Prosiding Nasional | H4: 2021 | I4: Putri Cahyanda | M4: Politeknik Caltex Riau | N4: Putri Cahyanda | P4: Politeknik Caltex Riau | S4: Rizadi Sasmita Darwis | U4: Politeknik Caltex Riau | X4: Muhammad Yanuar Hariawan | Y4: TK | Z4: ITTELKOM Surabaya
A5: RANCANG MAGNETIC NEAR FIELD PROBE UNTUK PENGUJIAN RADIATED EMISSION PADA FREKUENSI RENDAH | B5: ABEC Indonesia 9, 1040-1049, 2021 | D5: Prosiding Nasional | H5: 2021 | I5: Yospet Pradika | M5: Politeknik Caltex Riau | N5: Yospet Pradika | P5: Politeknik Caltex Riau | S5: Muhammad Yanuar Hariawan | T5: TK | U5: ITTELKOM Surabaya
A6: RANCANG BANGUN ALAT MONITORING KUALITAS UDARA BERBASIS NODEMCU ESP8266 (HARDWARE) | B6: ABEC Indonesia 9, 837-846, 2021 | D6: Prosiding Nasional | H6: 2021 | I6: Raywanda Affandi Harahap | M6: Politeknik Caltex Riau | N6: Raywanda Affandi Harahap | P6: Politeknik Caltex Riau | S6: Muhammad Yanuar Hariawan | T6: TK | U6: ITTELKOM Surabaya
A7: Filter EMI Aktif menggunakan Op-Amp untuk Mereduksi Near-Field EMI pada PCB | B7: ABEC Indonesia 9, 847-856, 2021 | D7: Prosiding Nasional | H7: 2021 | I7: Wahyudi Nasrianza1 | M7: Politeknik Caltex Riau | N7: Wahyudi Nasrianza1 | P7: Politeknik Caltex Riau | S7: Muhammad Yanuar Hariawan | T7: TK | U7: ITTELKOM Surabaya
A8: SISTEM MONITORING KUALITAS UDARA BERBASIS NODEMCU ESP8266 DENGAN METODE FUZZY LOGIC (SOFTWARE) | B8: ABEC Indonesia 9, 1050-1062, 2021 | D8: Prosiding Nasional | H8: 2021 | I8: Diemas Ibnus Pasedja | M8: Politeknik Caltex Riau | N8: Diemas Ibnus Pasedja | P8: Politeknik Caltex Riau | S8: Muhammad Yanuar Hariawan | T8: TK | U8: ITTELKOM Surabaya
A9: Pengaruh Ketebalan Material Terhadap Shielding effectiveness pada Frekuensi Rendah | B9: Jurnal Elektro dan Mesin Terapan 7 (2), 18-24, 2021 | D9: S4 | E9: SINTA | H9: 2021 | I9: Muhammad Yanuar Hariawan | L9: TK | M9: ITTELKOM Surabaya | N9: Muhammad Yanuar Hariawan | O9: TK | P9: ITTELKOM Surabaya | S9: Rizadi Sasmita Darwis | U9: Politeknik Caltex Riau
A10: Prediksi Jarak Bola Pada Citra Kamera Katadioptrik Menggunakan Metode Artifical Neural Network | B10: ELKOMIKA: Jurnal Teknik Energi Elektrik, Teknik Telekomunikasi, &amp; Teknik Elektronika | D10: S2 | E10: SINTA | H10: 2021 | I10: ZENDI ZAKARIA RAGA PERMANA | M10: Universitas Dinamika | N10: ZENDI ZAKARIA RAGA PERMANA | P10: Universitas Dinamika | S10: Susijanto Tri Rasmana | T10: TE | U10: ITTELKOM Surabaya | X10: IRA PUSPASARI | Z10: Universitas Dinamika
A11: A Systematic Review on the Autonomous Emergency Steering Assessments and Tests Methodology in ASEAN | B11: Journal of the Society of Automotive Engineers Malaysia 5 (2), 185-193, 2021 | D11: Jurnal ber-ISSN | H11: 2021 | I11: M.A.Abdul Rahman | M11: UTM | N11: Susijanto Tri Rasmana | O11: TE | P11: ITTELKOM Surabaya | S11: Dimas Adiputra | T11: TE | U11: ITTELKOM Surabaya | X11: M.A.Abdul Rahman | Z11: UTM | AC11: A.Dwijotomo | AE11: UTM | AH11: M.H.Mohammed Ariff | AJ11: UTM | AM11: N.Abu Husain | AO11: UTM
A12: Pengendali Tingkat Keasaman Air Kolam untuk Peternak Ikan Lele | B12: JMM (Jurnal Masyarakat Mandiri) 5 (6), 3135-3144, 2021 | D12: S3 | E12: SINTA | H12: 2021 | N12: Susijanto Tri Rasmana | O12: TE | P12: ITTELKOM Surabaya | S12: Mochammad Iskandar Riansyah | T12: TE | U12: ITTELKOM Surabaya | X12: Chaironi Latif | Y12: TE | Z12: ITTELKOM Surabaya | AC12: Muhammad Dwi Hariyanto | AD12: TE | AE12: ITTELKOM Surabaya | AH12: Anak Agung Kusuma Jaya Ningrat | AI12: TE | AJ12: ITTELKOM Surabaya | AM12: Jesica Febriani Nura | AN12: TE | AO12: ITTELKOM Surabaya
A13: KINERJA KARYAWAN (KONSEP PENILAIAN KINERJA DI PERUSAHAAN) | B13: CV WIDINA MEDIA UTAMA, 2021 | D13: Buku | H13: 2021 | N13: Hartini Hartini | S13: Alnisa Min Fadlillah | X13: Hetty Ismainar | AC13: Retno Setyorini | AH13: Ahmad Bairizki | AM13: Afdol Muftiasa | AR13: Titus Kristanto | AS13: RPL | AT13: ITTELKOM Surabaya
A14: Kewirausahaan (Teori dan Praktis) | B14: CV WIDINA MEDIA UTAMA, 2021 | D14: Buku | H14: 2021 | N14: Agus Alimuddin | S14: Adih Supriadi | X14: Ujang Enas | AC14: Fauzan Aziz | AH14: Komang Trisna Sari Dewi | AM14: Nikmatul Khoiriyah | AR14: Titus Kristanto | AS14: RPL | AT14: ITTELKOM Surabaya
A15: Marketing Digital Usaha Mikro | B15: CV WIDINA MEDIA UTAMA, 2021 | D15: Buku | H15: 2021 | N15: Rudy Irwansyah | S15: Danil Syahputra | X15: Supiah Ningsih | AC15: Muhammad Hasan | AH15: Titus Kristanto | AI15: RPL | AJ15: ITTELKOM Surabaya | AM15: Lucky Nugroho | AR15: Diana Triwardhani
A16: Pelatihan Dan Pendampingan Pemasaran Online Produk Nasi Tiwul Di Masa Pandemi Covid-19 | B16: JMM (Jurnal Masyarakat Mandiri) 5 (4), 1681-1688, 2021 | D16: S3 | E16: SINTA | H16: 2021 | N16: Titus Kristanto | O16: RPL | P16: ITTELKOM Surabaya | S16: Dewi Rahmawati | T16: RPL | U16: ITTELKOM Surabaya | X16: Ayu Endah Wahyuni | Y16: TI | Z16: ITTELKOM Surabaya | AC16: Muhammad Nasrullah | AD16: SI | AE16: ITTELKOM Surabaya | AH16: Reza Arindra Fadillah | AI16: RPL | AJ16: ITTELKOM Surabaya | AM16: Amanda Amalia | AN16: RPL | AO16: ITTELKOM Surabaya
A17: PELATIHAN PENINGKATAN KEMAMPUAN MENGGUNAKAN MICROSOFT DYNAMICS 365 BUSINESS CENTRAL | B17: Prosiding Konferensi Nasional Pengabdian Kepada Masyarakat dan Corporate &#8230;, 2021 | D17: Prosiding Nasional | H17: 2021 | I17: Muhammad Nasrullah | L17: SI | M17: ITTELKOM Surabaya | N17: Muhammad Nasrullah | O17: SI | P17: ITTELKOM Surabaya | S17: Titus Kristanto | T17: RPL | U17: ITTELKOM Surabaya
A18: Pengujian Black Box Menggunakan Teknik Equivalence Partitions Pada Aplikasi E-Learning Berbasis Web | B18: Building of Informatics, Technology and Science (BITS) 3 (3), 269-274, 2021 | D18: S3 | E18: SINTA | H18: 2021 | I18: Titus Kristanto | L18: RPL | M18: ITTELKOM Surabaya | N18: Titus Kristanto | O18: RPL | P18: ITTELKOM Surabaya | S18: Amanda Amalia | U18: ITTELKOM Surabaya | X18: Salva Wanda Putri Hamidah | Z18: ITTELKOM Surabaya
A19: PENGARUH KREATIVITAS DAN MOTIVASI TERHADAP KARAKTERISTIK KINERJA MANAJERIAL PT PAL INDONESIA (PERSERO) MENGGUNAKAN METODE GRAPHIC RATING SCALE | B19: Prosiding Seminar Nasional MIPATI 1 (1), 2021 | D19: Prosiding Nasional | H19: 2021 | N19: Titus Kristanto | O19: RPL | P19: ITTELKOM Surabaya | S19: Rosdiana Marpaung | U19: Sekolah Tinggi Ilmu Ekonomi Indonesia | X19: Dwi Mustika Kusumawardani | Z19: ITTP | AC19: Dewi Rahmawati | AD19: RPL | AE19: ITTELKOM Surabaya
A20: EndorseGram: Interactive Visualization of Influencer Endorsement Marketplace | B20: 2021 International Conference on Computer Science, Information Technology and Electrical Engineering (ICOMITEE), 2021 | D20: Prosiding Internasional | H20: 2021 | N20: Mochamad Nizar Palefi Ma’Ady | O20: SI | P20: ITTELKOM Surabaya | S20: Shinta Amalia Kusuma Wardhani | U20: Universitas Nahdlatul Ulama Sunan Giri
A21: EFFECTIVE MANAGEMENT OF ONLINE LEARNING DURING PANDEMIC AT SDN 1 TANAH TINGGI | B21: PROGRES PENDIDIKAN 2 (2), 115-118, 2021 | D21: S5 | E21: SINTA | H21: 2021 | I21: Ina Magdalena | M21: Universitas Muhammadiyah Tangerang | N21: Ina Magdalena | P21: Universitas Muhammadiyah Tangerang | S21: Ayu Endah Wahyuni | T21: TI | U21: ITTELKOM Surabaya | X21: Davina Dewi Hartana | Z21: Universitas Muhammadiyah Tangerang
A22: The Development of TRAM Model for Blockchain Use Readiness Among MSMEs in Indonesia | B22: Ninth International Conference on Entrepreneurship and Business Management (ICEBM 2020) | D22: Prosiding Internasional | H22: 2021 | I22: Ayu Endah Wahyuni | L22: TI | M22: ITTELKOM Surabaya | N22: Ayu Endah Wahyuni | O22: TI | P22: ITTELKOM Surabaya | S22: Anita Juraida | U22: Universitas Widyatama | X22: Asep Anwar | Z22: Universitas Widyatama
A23: Readiness factor identification Bandung city MSMEs use blockchain technology | B23: Jurnal Sistem dan Manajemen Industri 5 (2), 53-62, 2021 | D23: S2 | E23: SINTA | H23: 2021 | I23: Ayu Endah Wahyuni | L23: TI | M23: ITTELKOM Surabaya | N23: Ayu Endah Wahyuni | O23: TI | P23: ITTELKOM Surabaya | S23: Anita Juraida | U23: Universitas Widyatama | X23: Asep Anwar | Z23: Universitas Widyatama
A24: Pembuatan Film Animasi Permainan Tradisional Anak-Anak Berbasis 3 Dimensi | B24: eProceeding of TIK 1 (1), 2021 | D24: Jurnal ber-ISSN | H24: 2021 | I24: Ayu Endah Wahyuni | L24: TI | M24: ITTELKOM Surabaya | N24: Ayu Endah Wahyuni | O24: TI | P24: ITTELKOM Surabaya | S24: Mursyidah | U24: Politeknik Negeri Lhokseumawe | X24: Muhammad Nasir | Z24: Politeknik Negeri Lhokseumawe
A25: PEMBUATAN WORKBENCH ERGONOMIS UNTUK MENDUKUNG AKTIVITAS PEMILAHAN, PENGEPRESAN, DAN PENGARUNGAN SAMPAH AIR MINUM DALAM KEMASAN DI KELURAHAN WONKUSUMO SURABAYA | B25: LOGISTA-Jurnal Ilmiah Pengabdian kepada Masyarakat 5 (2), 330-335, 2021 | D25: S4 | E25: SINTA | H25: 2021 | N25: Rahaditya Dimas Prihadianto | O25: TI | P25: ITTELKOM Surabaya | S25: Abduh Sayid Albana | T25: TI | U25: ITTELKOM Surabaya | X25: Ayu Endah Wahyuni | Y25: TI | Z25: ITTELKOM Surabaya | AC25: Hendrawan Widianto | AD25: TI | AE25: ITTELKOM Surabaya
A26: MENGGAGAS MEJA DIGITAL PRIBADI (DIGITALLY PERSONALIZED DESKS) UNTUK ANAK USIA DINI DALAM SISTEM PEMBELAJARAN | B26: Lomba Karya Tulis Ilmiah 2 (1), 109-114, 2021 | D26: Jurnal tidak ber-ISSN | H26: 2021 | N26: Amarrangga Kumara Prada | P26: ITTELKOM Surabaya | S26: Iftitah Kurnia | U26: ITTELKOM Surabaya | X26: Mohammad Robi Maulana | Z26: ITTELKOM Surabaya | AC26: Ayu Endah Wahyuni | AD26: TI | AE26: ITTELKOM Surabaya
A27: Fuzzy Gain Scheduling for Cascaded PI-Control for DC Motor | B27: 2021 IEEE Conference on Energy Conversion (CENCON), 158-162, 2021 | D27: Prosiding Internasional | H27: 2021 | N27: Deany Putri Aulia | P27: Universitas Pertamina | S27: Alfiyah Shaldzabila Yustin | U27: Universitas Pertamina | X27: Amien Marzuq Hilman | Z27: Universitas Pertamina | AC27: Aulia Rahma Annisa | AD27: TK | AE27: ITTELKOM Surabaya | AH27: Eng Wahyu Kunto Wibowo | AJ27: Universitas Pertamina
A28: Rancang Bangun Sistem Alat Fototerapi Untuk Bayi Hiperbilirubinemia Berbasis Internet Of Things (IoT) | B28: Kilat 11 (2), 111-188, 2022 | D28: S4 | E28: SINTA | H28: 2021 | I28: Annida Sakinah Ramadhani | M28: Universitas Pertamina | N28: Annida Sakinah Ramadhani | P28: Universitas Pertamina | S28: Herminarto Nugroho | U28: Universitas Pertamina | X28: Aulia Rahma Annisa | Y28: TK | Z28: ITTELKOM Surabaya
A29: Implementasi Virtual Reality Berbasis Foto 360o Untuk Memvisualisasikan Fasilitas Perguruan Tinggi Surabaya | B29: Jurnal RESTI (Rekayasa Sistem Dan Teknologi Informasi) 5 (1), 155-162, 2021 | D29: S2 | E29: SINTA | H29: 2021 | I29: Nadiah Ratnaduhita | L29: SI | M29: ITTELKOM Surabaya | N29: Nadiah Ratnaduhita | O29: SI | P29: ITTELKOM Surabaya | S29: Ian Mahendra Putra | T29: SI | U29: ITTELKOM Surabaya | X29: Ully Asfari | Y29: SI | Z29: ITTELKOM Surabaya | AC29: Yupit Sudianto | AD29: SI | AE29: ITTELKOM Surabaya | AH29: Benazir Imam Arif Muttaqin | AI29: TI | AJ29: ITTELKOM Surabaya
A30: Modeling of salt supply chains to achieve competitive salt prices | B30: International Journal on Food System Dynamics 12 (1), 51-67, 2021 | D30: Q2 | H30: 2021 | N30: Isnaini Muhandhis | P30: Universitas Wijaya Putra | S30: Budisantoso Wirjodirdjo | U30: ITS | X30: Erma Suryani | Z30: ITS | AC30: Heri Susanto | AE30: Universitas Wijaya Putra | AH30: Ully Asfari | AI30: SI | AJ30: ITTELKOM Surabaya
A31: System Dynamic Framework: Increasing Productivity Of Sugarcane To Support Sustainable Cultivation | B31: Sustainability in Food and Agriculture (SFNA) 2 (2), 105-109, 2021 | D31: Jurnal ber-ISSN | H31: 2021 | I31: Hawwin Mardhiana | L31: SI | M31: ITTELKOM Surabaya | N31: Hawwin Mardhiana | O31: SI | P31: ITTELKOM Surabaya | S31: Erma Suryani | U31: ITS | X31: Ully Asfari | Y31: SI | Z31: ITTELKOM Surabaya | AC31: Muhammad Nasrullah | AD31: SI | AE31: ITTELKOM Surabaya
A32: 3D Virtual prototyping dalam Perbaikan Desain Fasilitas Tempat Kerja: Studi Kasus CV. XYZ | B32: Jurnal IPTEK 25 (1), 69-76, 2021 | D32: S3 | E32: SINTA | H32: 2021 | N32: Benazir Imam Arif Muttaqin | O32: TI | P32: ITTELKOM Surabaya | S32: Ully Asfari | T32: SI | U32: ITTELKOM Surabaya | X32: Hawwin Mardhiana | Y32: SI | Z32: ITTELKOM Surabaya | AC32: Shanggabuana Adhitya Shamaradewa | AD32: TI | AE32: ITTELKOM Surabaya | AH32: Gagas Putra Dawangga | AI32: SI | AJ32: ITTELKOM Surabaya
A33: Faktor yang Mempengaruhi Implementasi Green Human Resource Management pada Ormawa: Model Konseptual: Indonesia | B33: Journal of Advances in Information and Industrial Technology 3 (1), 11-18, 2021 | D33: Jurnal ber-ISSN | H33: 2021 | I33: Moch. Yusuf Fathussalam | L33: SI | M33: ITTELKOM Surabaya | N33: Moch. Yusuf Fathussalam | O33: SI | P33: ITTELKOM Surabaya | S33: I G Ag Kom Agnam M | T33: SI | U33: ITTELKOM Surabaya | X33: Irene Dyah Ayuwati | Y33: SI | Z33: ITTELKOM Surabaya | AC33: Desy Fitri A. L. | AD33: SI | AE33: ITTELKOM Surabaya | AH33: Yuniar Revi A. L | AI33: SI | AJ33: ITTELKOM Surabaya | AM33: Geraldo Brata Hiroshi P. | AN33: SI | AO33: ITTELKOM Surabaya | AR33: Ully Asfari | AS33: SI | AT33: ITTELKOM Surabaya
A34: Pengaruh Pelatihan dan Pengembangan SDM Pada ABA Collection Terhadap Kinerja Pegawai Menggunakan Metode Regresi Linear Berganda | B34: Journal of Advances in Information and Industrial Technology 3 (1), 19-30, 2021 | D34: Jurnal ber-ISSN | H34: 2021 | I34: Nadiah Ratnaduhita | L34: SI | M34: ITTELKOM Surabaya | N34: Nadiah Ratnaduhita | O34: SI | P34: ITTELKOM Surabaya | S34: Rio Armando | T34: SI | U34: ITTELKOM Surabaya | X34: Salsabila Qatrunnada | Y34: SI | Z34: ITTELKOM Surabaya | AC34: Tanang Satriyo Adi | AD34: SI | AE34: ITTELKOM Surabaya | AH34: Tanfirul Roibafi | AI34: SI | AJ34: ITTELKOM Surabaya | AM34: Wan Azizah Sri Nuraini | AN34: SI | AO34: ITTELKOM Surabaya | AR34: Ully Asfari | AS34: SI | AT34: ITTELKOM Surabaya
A35: INOVASI KINERJA PRODUKSI KOPI UNTUK MENINGKATKAN KEUNTUNGAN MELALUI KEGIATAN PENGABDIAN MASYARAKAT KE UKM KOPI ARABICA TRADISIONAL | B35: Prosiding Seminar Nasional &amp; Call for Paper&quot; Peran Perempuan Sebagai &#8230;, 2021 | D35: Prosiding Nasional | H35: 2021 | N35: Ully Asfari | O35: SI | P35: ITTELKOM Surabaya | S35: Isnaini Muhandhis | U35: Universitas Wijaya Putra | X35: Imam Kholik | Z35: Universitas Wijaya Putra
A36: Edge Computing Based Pickup and Delivery Optimization for Warehouse | B36: KICS Winter Conference 2021, 323-324, 2021 | D36: Prosiding Internasional | H36: 2021 | N36: Philip Tobianto Daely | O36: IT | P36: ITTELKOM Surabaya | S36: Jae-Woo Kim | U36: Kumoh National Institute of Technology | X36: Jae Min Lee | Z36: Kumoh National Institute of Technology | AC36: Dong-Seong Kim | AE36: Kumoh National Institute of Technology
A37: Dynamic VRP optimization using discrete PSO in edge computing environment | B37: 2021 International Conference on Information and Communication Technology Convergence (ICTC);, 2021 | D37: Prosiding Internasional | H37: 2021 | N37: Philip Tobianto Daely | O37: IT | P37: ITTELKOM Surabaya | S37: Yohana Jayanti Aruan | U37: Kumoh National Institute of Technology | X37: Jae Min Lee | Z37: Kumoh National Institute of Technology | AC37: Dong-Seong Kim | AE37: Kumoh National Institute of Technology
A38: The design of the emerging 5g using hybrid gpon and xgs-pon technology | B38: 2022 International Conference on Information and Communication Technology Convergence (ICTC);, 2021 | D38: Prosiding Internasional | H38: 2021 | N38: Yohana Jayanti Aruan | P38: Kumoh National Institute of Technology | S38: Philip Tobianto Daely | T38: IT | U38: ITTELKOM Surabaya | X38: Gabriel Avelino Ramos Sampedro | Z38: Kumoh National Institute of Technology | AC38: Jae Min Lee | AE38: Kumoh National Institute of Technology | AH38: Dong-Seong Kim | AJ38: Kumoh National Institute of Technology
A39: Battery Insulation Performance Analysis in Electric Vehicles for the Improvement of Battery Lifetime | B39: Jurnal Ilmiah Teknik Elektro Komputer dan Informatika (JITEKI) 7 (3), 412-422, 2021 | D39: S2 | E39: SINTA | H39: 2021 | I39: Lora Khaula Amifia | L39: TE | M39: ITTELKOM Surabaya | N39: Lora Khaula Amifia | O39: TE | P39: ITTELKOM Surabaya | S39: Nuansa Dipa Bismoko | U39: PT. Telekomunikasi Seluler | X39: Philip Tobianto Daely | Y39: IT | Z39: ITTELKOM Surabaya
A40: Prediction Point of Fault Location on Its Campus Power Grid by using Neural Artificial Method | B40: IOP Conference Series: Materials Science and Engineering 1096 (1), 012068, 2021 | D40: Prosiding Internasional | H40: 2021 | I40: A Syamsudin | M40: ITS | N40: A Syamsudin | P40: ITS | S40: Isa Hafidz | T40: TE | U40: ITTELKOM Surabaya | X40: D Rahmatullah | Z40: Universitas Hang Tuah | AC40: D A Asfani | AE40: ITS | AH40: I M Y Negara | AJ40: ITS
A41: Upaya Peningkatan Kualitas Pendidikan melalui Penerapan ICT di Sekolah Menengah Atas | B41: E-Dimas: Jurnal Pengabdian kepada Masyarakat 12 (2), 329-334, 2021 | D41: S4 | E41: SINTA | H41: 2021 | I41: Isa Hafidz | L41: TE | M41: ITTELKOM Surabaya | N41: Isa Hafidz | O41: TE | P41: ITTELKOM Surabaya | S41: Helmy Widyantara | T41: IT | U41: ITTELKOM Surabaya | X41: Ubaidillah Umar | Y41: TK | Z41: ITTELKOM Surabaya | AC41: Dwi Edi Setyawan | AD41: TK | AE41: ITTELKOM Surabaya | AH41: Billy Montolalu | AI41: TK | AJ41: ITTELKOM Surabaya
A42: Development of Digital Ventilator with Internet of Things for Preparation of the Next Outbreak in Indonesia | B42: Kinetik: Game Technology, Information System, Computer Network, Computing &#8230;, 2021 | D42: S2 | E42: SINTA | H42: 2021 | I42: Dimas Adiputra | L42: TE | M42: ITTELKOM Surabaya | N42: Dimas Adiputra | O42: TE | P42: ITTELKOM Surabaya | S42: Isa Hafidz | T42: TE | U42: ITTELKOM Surabaya | X42: Billy Montolalu | Y42: TK | Z42: ITTELKOM Surabaya | AC42: Fauzan Rasyid | AE42: ITTELKOM Surabaya
A43: Modified Critical Trajectory Algorithm to Determine the Critical Clearing Time for Unbalanced Fault | B43: 2021 International Electronics Symposium (IES), 36-40, 2021 | D43: Prosiding Internasional | H43: 2021 | N43: Isa Hafidz | O43: TE | P43: ITTELKOM Surabaya | S43: Ardyono Priyadi | U43: ITS | X43: Margo Pujiantara | Z43: ITS | AC43: Sjamsjul Anam | AE43: ITS | AH43: Naoto Yorino | AJ43: Hiroshima University | AM43: Mauridhi Hery Purnomo | AO43: ITS
A44: Power Monitoring and Passanger Classification on Logistics Elevator | B44: Elinvo (Electronics, Informatics, and Vocational Education) 6 (2), 2021 | D44: S2 | E44: SINTA | H44: 2021 | I44: Isa Hafidz | L44: TE | M44: ITTELKOM Surabaya | N44: Isa Hafidz | O44: TE | P44: ITTELKOM Surabaya | S44: Aldhitiansyah Putra | U44: ITTELKOM Surabaya | X44: Billy Montolalu | Y44: TK | Z44: ITTELKOM Surabaya | AC44: Dimas Adiputra | AD44: TE | AE44: ITTELKOM Surabaya | AH44: Rifky Dwi Putranto | AI44: TE | AJ44: ITTELKOM Surabaya | AM44: Rafly Daffaldi | AO44: ITTELKOM Surabaya | AR44: Dinda Karisma Ulfa | AT44: ITTELKOM Surabaya
A45: 5G Network as a Technology to Fight Covid-19 Pan-demic in Indonesia: a Review | B45: Journal of Computer, Electronic, and Telecommunication (COMPLETE) 2 (2), 2021 | D45: Jurnal ber-ISSN | H45: 2021 | I45: Hamzah U. Mustakim | L45: TT | M45: ITTELKOM Surabaya | N45: Hamzah U. Mustakim | O45: TT | P45: ITTELKOM Surabaya | S45: Billy Montolalu | T45: TK | U45: ITTELKOM Surabaya | X45: Isa Hafidz | Y45: TE | Z45: ITTELKOM Surabaya
A46: Ulcerative colitis in hemophilia a patient: case report | B46: Materia Socio-medica 33 (1), 75, 2021 | D46: Buku | H46: 2021 | N46: Fauzi Yusuf | P46: Universitas Syiah Kuala | S46: Reno Keumalazia Kamarlis | U46: Universitas Syiah Kuala | X46: Muhsin | Y46: TT | Z46: ITTELKOM Surabaya
A47: Alterations of Gut Microbiota Composition in Severe Acute Respiratory Syndrome Coronavirus 2 Infection: A Brief Review | B47: Annals of the Romanian Society for Cell Biology 25 (6), 13136-13143, 2021 | D47: Q4 | H47: 2021 | I47: Fauzi Yusuf | M47: Universitas Syiah Kuala | N47: Fauzi Yusuf | P47: Universitas Syiah Kuala | S47: Azzaki Abubakar | U47: Universitas Syiah Kuala | X47: Desi Maghfirah | Z47: Universitas Syiah Kuala | AC47: Muhsin | AD47: TT | AE47: ITTELKOM Surabaya | AH47: Marhami Fahriani | AJ47: Universitas Syiah Kuala | AM47: Muhammad Iqhrammullah | AO47: Universitas Syiah Kuala
A48: Anxiety to COVID-19 pandemic amongst university students is related with gastrointestinal symptoms | B48: Bali Medical Journal 10 (2), 847-850, 2021 | D48: Q4 | H48: 2021 | I48: Azzaki Abubakar | M48: Universitas Syiah Kuala | N48: Azzaki Abubakar | P48: Universitas Syiah Kuala | S48: Muhammad Fadhlan Ma'ruf | U48: Universitas Syiah Kuala | X48: Muhammad Mizfaruddin | Z48: Universitas Syiah Kuala | AC48: Fauzi Yusuf | AE48: Universitas Syiah Kuala | AH48: Desi Maghfirah | AJ48: Universitas Syiah Kuala | AM48: Muhsin | AN48: TT | AO48: ITTELKOM Surabaya
A49: Implementasi Process Mining pada Proses Praktik Kerja Lapangan (PKL) | B49: Techno. Com 20 (4), 579-587, 2021 | D49: S3 | E49: SINTA | H49: 2021 | N49: Afina Lina Nurlaili | P49: UPN Veteran Jatim | S49: Muhsin | T49: TT | U49: ITTELKOM Surabaya | X49: Eristya Maya Safitri | Z49: UPN Veteran Jatim
A50: Performance Evaluation of Inductive Miner for Internship Program Workflow | B50: Jurnal Mantik 5 (3), 1619-1624, 2021 | D50: S4 | E50: SINTA | H50: 2021 | N50: Afina Lina Nurlaili | P50: UPN Veteran Jatim | S50: Muhsin | T50: TT | U50: ITTELKOM Surabaya | X50: Dhian Satria Yudha Kartika | Z50: UPN Veteran Jatim
A51: Analisis Desain Eksperimen Perbandingan Aplikasi Pencarian Lokasi | B51: Scan: Jurnal Teknologi Informasi dan Komunikasi 16 (2), 29-33, 2021 | D51: Jurnal ber-ISSN | H51: 2021 | I51: Afina Lina Nurlaili | M51: UPN Veteran Jatim | N51: Afina Lina Nurlaili | P51: UPN Veteran Jatim | S51: Mochammad Arief Ridwan | U51: ITS | X51: Muhsin | Y51: TT | Z51: ITTELKOM Surabaya
A52: Sectoral dual-polarized MIMO antenna for 5G-NR band N77 base station | B52: Indonesian Journal of Electrical Engineering and Computer Sciences 21 (3), 2021 | D52: Q2 | H52: 2021 | I52: Muhsin | L52: TT | M52: ITTELKOM Surabaya | N52: Muhsin | O52: TT | P52: ITTELKOM Surabaya | S52: Afina Lina Nurlaili | U52: UPN Veteran Jatim | X52: Aulia Saharani | Y52: TT | Z52: ITTELKOM Surabaya | AC52: Indah Rahmawati Utami | AD52: TT | AE52: ITTELKOM Surabaya
A53: Anomaly detection using control flow pattern and fuzzy regression in port container handling | B53: Journal of King Saud University-Computer and Information Sciences 33 (1), 11-20, 2021 | D53: Q1 | H53: 2021 | I53: Dewi Rahmawati | L53: RPL | M53: ITTELKOM Surabaya | N53: Dewi Rahmawati | O53: RPL | P53: ITTELKOM Surabaya | S53: Riyanarto Sarno | U53: ITS
A54: A New Hybrid Region-Based Segmentation for 2D Corpus Callosum Segmentation | B54: 2021 5th International Conference on Informatics and Computational Sciences &#8230;, 2021 | D54: Prosiding Internasional | H54: 2021 | N54: Dewi Rahmawati | O54: RPL | P54: ITTELKOM Surabaya | S54: Riyanarto Sarno | U54: ITS | X54: Chastine Fatichah | Z54: ITS
A55: Intelligent System for Fall Prediction Based on Accelerometer and Gyroscope of Fatal Injury in Geriatric | B55: JURNAL NASIONAL TEKNIK ELEKTRO, 2021 | D55: S2 | E55: SINTA | H55: 2021 | I55: Dewi Rahmawati | L55: RPL | M55: ITTELKOM Surabaya | N55: Khodijah Amiroh | O55: IT | P55: ITTELKOM Surabaya | S55: Dewi Rahmawati | T55: RPL | U55: ITTELKOM Surabaya | X55: Ardian Yusuf Wicaksono | Y55: RPL | Z55: ITTELKOM Surabaya
A56: Desain Arsitektur IoT untuk Budidaya Gurami | B56: Jurnal Teknologi Informasi dan Ilmu Komputer 8 (1), 111-118, 2021 | D56: S2 | E56: SINTA | H56: 2021 | I56: Yupit Sudianto | L56: SI | M56: ITTELKOM Surabaya | O56: SI | P56: ITTELKOM Surabaya
A57: Polyaniline-atomic Au modified platinum electrode with ionic liquid as configuration for enhanced electrochemical sensing | B57: 2021 IEEE Sensors, 1-4, 2021 | D57: Prosiding Internasional | H57: 2021 | N57: Parthojit Chakraborty | P57: Tokyo Institute of Technology | S57: Hiroki Kawakami | U57: Tokyo Institute of Technology | X57: Anifatul Faricha | Y57: TE | Z57: ITTELKOM Surabaya | AC57: Tso-Fu Mark Chang | AE57: Tokyo Institute of Technology | AH57: Masato Sone | AJ57: Tokyo Institute of Technology | AM57: Takamichi Nakamoto | AO57: Tokyo Institute of Technology
A58: Study of gas sensing measurement using room temperature ionic liquid coated on interdigitated array electrodes and quartz crystal microbalance | B58: 「センサ・マイクロマシンと応用システム」 シンポジウム論文集 電気学会センサ・マイクロマシン部門 [編] 38 (2021) | D58: Prosiding Internasional | H58: 2021 | N58: Anifatul Faricha | O58: TE | P58: ITTELKOM Surabaya | S58: Parthojit Chakraborty | U58: Tokyo Institute of Technology | X58: Tso-Fu Mark Chang | Z58: Tokyo Institute of Technology | AC58: Masato Sone | AE58: Tokyo Institute of Technology | AH58: Takamichi Nakamoto | AJ58: Tokyo Institute of Technology
A59: Unmanned Aerial Vehicle Robot untuk Pemadam Api dengan Rancangan Alat Pemadam yang Efisien | B59: Jurnal Nasional Teknik Elektro | D59: S2 | E59: SINTA | H59: 2021 | I59: Ardiansyah Al Farouq | L59: TK | M59: ITTELKOM Surabaya | N59: Ardiansyah Al Farouq | O59: TK | P59: ITTELKOM Surabaya | S59: Moch. Iskandar Riansyah | T59: TE | U59: ITTELKOM Surabaya | X59: Ahmad Habibi | Y59: TK | Z59: ITTELKOM Surabaya
A60: Customer rejection to guide lead time quotation and pricing decisions | B60: Journal of the Operational Research Society 72 (6), 1358-1372, 2021 | D60: Q1 | H60: 2021 | I60: Ramzi Hammami | M60: Rennes School of Business | N60: Ramzi Hammami | P60: Rennes School of Business | S60: Yannick Frein | U60: University of Grenoble Alpes | X60: Abduh Sayid Albana | Y60: TI | Z60: ITTELKOM Surabaya
A61: PENGARUH PEMBELAJARAN DIGITAL DENGAN MODEL BLANDED POE2WE BAGI SISWA/MAHASISWA | B61: Lomba Karya Tulis Ilmiah 2 (1), 139-148, 2021 | D61: Jurnal tidak ber-ISSN | H61: 2021 | N61: Yesika Purba | P61: ITTELKOM Surabaya | S61: Nur Rizki Madani | U61: ITTELKOM Surabaya | X61: Farrel Abednego Darea | Z61: ITTELKOM Surabaya | AC61: Abduh Sayid Albana | AD61: TI | AE61: ITTELKOM Surabaya
A62: A Parallel Permutation Flow-Shop Scheduling Model by Using a Two-Step Evolutionary Algorithm to Minimize Intermediate Storage with Tolerable Maximum Completion Time | B62: International Journal of Intelligent Engineering and Systems 14 (6), 464-475, 2021 | D62: Q2 | H62: 2021 | I62: Purba Daru Kusuma | M62: Universitas Telkom | N62: Purba Daru Kusuma | P62: Universitas Telkom | S62: Abduh Sayid Albana | T62: TI | U62: ITTELKOM Surabaya
A63: University course timetabling model in joint courses program to minimize the number of unserved requests | B63: International Journal of Advanced Computer Science and Applications 12 (10), 2021 | D63: Q3 | H63: 2021 | N63: Purba Daru Kusuma | P63: Universitas Telkom | S63: Abduh Sayid Albana | T63: TI | U63: ITTELKOM Surabaya
A64: An improved spectral temporal average method for mitigating Doppler effects in V2V communications | B64: International Journal of Vehicle Information and Communication Systems 6 (3 &#8230;, 2021 | D64: Q4 | H64: 2021 | N64: Wahyu Pamungkas | P64: ITTP | S64: Jans Hendry | U64: UGM | X64: Walid Maulana Hadiansyah | Y64: TE | Z64: ITTELKOM Surabaya
A65: Implementation of Importance-Performance Analysis on Integrated Information System Institut Teknologi Telkom Purwokerto | B65: Jurnal Ilmiah Teknik Industri 20 (2), 184-194, 2021 | D65: S2 | E65: SINTA | H65: 2021 | I65: Dina Rachmawaty | M65: ITTP | N65: Dina Rachmawaty | P65: ITTP | S65: Achmad Zaki Yamani | U65: ITTP | X65: Famila Dwi Winati | Z65: ITTP | AC65: Hawwin Mardhiana | AD65: SI | AE65: ITTELKOM Surabaya
A66: USABILITY TESTING OF THE ONLINE PLATFORM FOR SELLING FOODSTUFFS IN INDONESIA | B66: Journal of Industrial Engineering Management 6 (3), 183-193, 2021 | D66: S3 | E66: SINTA | H66: 2021 | N66: Rizqa Amelia Zunaidi | O66: TI | P66: ITTELKOM Surabaya | S66: Adek Dhea Resmi Purbantari | T66: TI | U66: ITTELKOM Surabaya | X66: Hawwin Mardhiana | Y66: SI | Z66: ITTELKOM Surabaya
A67: Analysis of EMG Signals during Stance and Swing Phases for Controlling Magnetorheological Brake applications | B67: Open Engineering 11 (1), 112-119, 2021 | D67: Q2 | H67: 2021 | I67: Nurhazimah Nazmi | M67: Malaysia-Japan International Institute of Technology | N67: Nurhazimah Nazmi | P67: Malaysia-Japan International Institute of Technolog | S67: Mohd Azizi Abdul Rahman | U67: Malaysia-Japan International Institute of Technolog | X67: Saiful Amri Mazlan | Z67: Malaysia-Japan International Institute of Technolog | AC67: Dimas Adiputra | AD67: TE | AE67: ITTELKOM Surabaya | AH67: Irfan Bahiuddin | AJ67: Malaysia-Japan International Institute of Technolog | AM67: Muhammad Kashfi Shabdin | AO67: Malaysia-Japan International Institute of Technolog | AR67: Nurul Afifah Abdul Razak, Mohd Hatta Mohammed Ariff | AT67: Malaysia-Japan International Institute of Technolog
A68: Sensor number optimization using neural network for ankle foot orthosis equipped with magnetorheological brake | B68: Open Engineering 11 (1), 91-101, 2021 | D68: Q2 | H68: 2021 | I68: Mohd Azizi Abdul Rahman | M68: Malaysia-Japan International Institute of Technology | N68: Dimas Adiputra | O68: TE | P68: ITTELKOM Surabaya | S68: Mohd Azizi Abdul Rahman | U68: Malaysia-Japan International Institute of Technolog | X68: Irfan Bahiuddin | Z68: Malaysia-Japan International Institute of Technolog | AC68: Ubaidillah | AE68: Malaysia-Japan International Institute of Technolog | AH68: Nurhazimah Nazmi | AJ68: Malaysia-Japan International Institute of Technolog
A69: Personalized Gait Treatment Using Passive Controllable Ankle Foot Orthosis | B69: IOP Conference Series: Materials Science and Engineering 1096 (1), 012002, 2021 | D69: Prosiding Internasional | H69: 2021 | N69: Mohd Azizi Abdul Rahman | P69: Malaysia-Japan International Institute of Technology | S69: Dimas Adiputra | T69: TE | U69: ITTELKOM Surabaya
A70: IMPLEMENTASI KAHOOT! DALAM MENUNJANG PEMBELAJARAN DARING INTERAKTIF | B70: Lomba Karya Tulis Ilmiah 2 (1), 123-138, 2021 | D70: Jurnal tidak ber-ISSN | H70: 2021 | N70: Muhammad Nasrulloh Mubarak | P70: ITTELKOM Surabaya | S70: Jesica Febriani Nura | U70: ITTELKOM Surabaya | X70: Dimas Adiputra | Y70: TE | Z70: ITTELKOM Surabaya
A71: Simplified Walking Simulation for Tuning a Passive Controllable Ankle Foot Orthosis | B71: Journal of Computer, Electronic, and Telecommunication (COMPLETE) 2 (2), 2021 | D71: Jurnal ber-ISSN | H71: 2021 | I71: Dimas Adiputra | L71: TE | M71: ITTELKOM Surabaya | N71: Dimas Adiputra | O71: TE | P71: ITTELKOM Surabaya
A72: Dasar Pemrograman Dalam Bahasa C | B72: Deepublish, 2021 | D72: Buku | H72: 2021 | N72: Bernadus Anggo Seno Aji | O72: IT | P72: ITTELKOM Surabaya | S72: Farah Zakiyah Rahmanti | T72: IT | U72: ITTELKOM Surabaya
A73: Undergraduate Thesis System Information Service Evaluation Using UTAUT–5 Factors Based Chatbot | B73: 2021 International Seminar on Application for Technology of Information and Communication (iSemantic) | D73: Prosiding Internasional | H73: 2021 | N73: Septian Enggar Sukmana | P73: Politeknik Negeri Malang | S73: Rokhimatul Wakhidah | U73: Politeknik Negeri Malang | X73: Putri Khoirin Nashiroh | Z73: Universitas Negeri Semarang | AC73: Farah Zakiyah Rahmanti | AD73: IT | AE73: ITTELKOM Surabaya
A74: A Study of Conveyor System with UV Light for Vegetable and Fruit Sterilization for Farmer | B74: 2021 International Conference on Computer Science, Information Technology &#8230;, 2021 | D74: Prosiding Internasional | H74: 2021 | N74: Farah Zakiyah Rahmanti | O74: IT | P74: ITTELKOM Surabaya | S74: Bernadus Anggo Seno Aji | T74: IT | U74: ITTELKOM Surabaya | X74: Arliyanti Nurdin | Y74: IT | Z74: ITTELKOM Surabaya | AC74: Wiranti Maharani | AD74: IT | AE74: ITTELKOM Surabaya | AH74: Riska Aprilia | AI74: IT | AJ74: ITTELKOM Surabaya | AM74: Mochammad Rafi Adityawarman | AN74: IT | AO74: ITTELKOM Surabaya
A75: ANALISIS KONTEN PEMBELAJARAN DIGITAL UNTUK MENGUKUR TINGKAT INTERAKSI DAN PEMAHAMAN MAHASISWA | B75: Lomba Karya Tulis Ilmiah 2 (1), 115-122, 2021 | D75: Jurnal tidak ber-ISSN | H75: 2021 | N75: Muhammad Bayu Prasetyo | P75: ITTELKOM Surabaya | S75: Adrianus Satria Pinandita | U75: ITTELKOM Surabaya | X75: Yakfi Zamzami Achmad | Z75: ITTELKOM Surabaya | AC75: Wahyu Andy Prastyabudi | AD75: TI | AE75: ITTELKOM Surabaya
A76: Penerapan System Thinking Untuk Peningkatan Branding dan Optimalisasi Manajemen Usaha Pada UKM Handy Craft Az-Zahra | B76: Prosiding Konferensi Nasional Pengabdian Kepada Masyarakat dan Corporate &#8230;, 2021 | D76: Prosiding Nasional | H76: 2021 | N76: Arda Erico Yuda | P76: ITTELKOM Surabaya | S76: Wahyu Andy Prastyabudi | T76: TI | U76: ITTELKOM Surabaya | X76: Muhammad Dzulfikar Fauzi | Y76: IF | Z76: ITTELKOM Surabaya | AC76: Arliyanti Nurdin | AD76: IT | AE76: ITTELKOM Surabaya
A77: An Inventory Policy On Agroindustry Supply Chain: A Case Study Of Fruit Seasonal In East Java | B77: Food &amp; Agribusiness Management (FABM) 2 (2), 46-50, 2021 | D77: Jurnal ber-ISSN | H77: 2021 | I77: Paramaditya Arismawati | L77: TI | M77: ITTELKOM Surabaya | N77: Paramaditya Arismawati | O77: TI | P77: ITTELKOM Surabaya | S77: Wahyu Andy Prastyabudi | T77: TI | U77: ITTELKOM Surabaya
A78: A CONCEPTUAL DESIGN OF WASTE MANAGEMENT: SMART BIN DEPLOYMENT IN SURABAYA SMART CITY | B78: Acta Mechanica Malaysia | D78: Jurnal ber-ISSN | H78: 2021 | I78: Wahyu Andy Prastyabudi | L78: TI | M78: ITTELKOM Surabaya | N78: Wahyu Andy Prastyabudi | O78: TI | P78: ITTELKOM Surabaya | S78: Oktavia Ayu Permata | T78: IT | U78: ITTELKOM Surabaya
A79: PERLUASAN PLATFORM E-LEARNING UNTUK MENUNJANG PEMBELAJARAN DI DAERAH TERPENCIL | B79: Lomba Karya Tulis Ilmiah 2 (1), 99-108, 2021 | D79: Jurnal tidak ber-ISSN | H79: 2021 | N79: Rafi Juniar Saputra | P79: ITTELKOM Surabaya | S79: Asri Kartika Dewi | U79: ITTELKOM Surabaya | X79: Era Anzha Naelil Munna | Z79: ITTELKOM Surabaya | AC79: Wahyu Andy Prastyabudi | AD79: TI | AE79: ITTELKOM Surabaya
A80: Notifikasi Real-time Pada Sistem Nurse Call Nirkabel Berbasis Zigbee Menggunakan Protokol WebSocket | B80: SYSTEMIC (Information System and Informatic Journal) 7 (1), 49-54, 2021 | D80: S4 | E80: SINTA | H80: 2021 | N80: Billy Montolalu | O80: TK | P80: ITTELKOM Surabaya | S80: Hamzah Ulinuha Mustakim | T80: TT | U80: ITTELKOM Surabaya | X80: Nilla Rachmaningrum | Y80: TT | Z80: ITTELKOM Surabaya
A81: A Study of Human State Pattern Acquisition Method for Partner Robots | B81: 2021 International Symposium on Micro-NanoMehatronics and Human Science (MHS &#8230;, 2021 | D81: Prosiding Internasional | H81: 2021 | N81: Nao Yamada | P81: Tokyo Metropolitan University | S81: Yani Mohamad | T81: TK | U81: ITTELKOM Surabaya | X81: Naoyuki Kubota | Z81: Tokyo Metropolitan University
A82: Gradient-Free Deep Q-Networks Reinforcement learning: Benchmark and Evaluation | B82: 2021 IEEE Symposium Series on Computational Intelligence (SSCI), 1-5, 2021 | D82: Prosiding Internasional | H82: 2021 | N82: Yani Mohamad | O82: TK | P82: ITTELKOM Surabaya | S82: Fernando Ardilla | U82: PENS | X82: Azhar Aulia Saputra | Z82: Tokyo Metropolitan University | AC82: Naoyuki Kubota | AE82: Tokyo Metropolitan University
A83: Deep Convolutional Networks with Genetic Algorithm for Reinforcement Learning Problem | B83: The 7th International Workshop on Advanced Computational Intelligence and &#8230;, 2021 | D83: Prosiding Internasional | H83: 2021 | N83: Yani Mohamad | O83: TK | P83: ITTELKOM Surabaya | S83: Naoyuki Kubota | U83: Tokyo Metropolitan University
A84: Pengembangan Sistem Penukaran Tiket Suroboyo Bus Melalui Digitalisasi Pencatatan Penukaran Sampah Berbasis Android | B84: JEPIN (Jurnal Edukasi dan Penelitian Informatika) 7 (1), 100-105, 2021 | D84: S2 | E84: SINTA | H84: 2021 | N84: Oktavia Ayu Permata | O84: IT | P84: ITTELKOM Surabaya | S84: Khodijah Amiroh | T84: IT | U84: ITTELKOM Surabaya | X84: Auldy Ansya Rullah | Y84: IT | Z84: ITTELKOM Surabaya
A85: CARITA: PENDIDIKAN KARAKTER ANAK USIA DINI MELALUI SERIAL WEBTOON INTERAKTIF | B85: Lomba Karya Tulis Ilmiah 2 (1), 177-190, 2021 | D85: Jurnal tidak ber-ISSN | H85: 2021 | N85: Berliana Amelia Aryanti Zain | P85: ITTELKOM Surabaya | S85: Alfito De Vaga Mayavanny | U85: ITTELKOM Surabaya | X85: Muhammad Ma`'sum Juniyanto | Z85: ITTELKOM Surabaya | AC85: Oktavia Ayu Permata | AD85: IT | AE85: ITTELKOM Surabaya
A86: Implementation of dosimetry protocol for radionuclide therapy in Indonesia: Collaborative works in nuclear medicine | B86: AIP Conference Proceedings 2346 (1), 030007, 2021 | D86: Prosiding Internasional | H86: 2021 | I86: N. R. Hidayati | M86: Center for Technology of Radiation Safety and Metrology | N86: N. R. Hidayati | P86: Center for Technology of Radiation Safety and Metrology | S86: W. Mailana | U86: Center for Technology of Radiation Safety and Metrology | X86: Pangestu Widodo | Y86: RPL | Z86: ITTELKOM Surabaya | AC86: A. R. Dewi | AE86: Dharmais National Cancer Hospital | AH86: E. Rosilawaty | AJ86: Hasan Sadikin General Hospital | AM86: E. Rosilawaty | AO86: Hasan Sadikin General Hospital | AR86: R. Shintawati H. Budiawan A. H. S. Kartamihardja I. A. S. Mu'minah | AT86: Hasan Sadikin General Hospital Hasan Sadikin General Hospital Hasan Sadikin General Hospital Universitas Indonesia Depok
A87: Sidelobe level suppression and scan-loss compensation in a wide-angular scanning linear array using subarrays amplitude control | B87: 2020 50th European Microwave Conference (EuMC), 352-355, 2021 | D87: Prosiding Internasional | H87: 2021 | N87: Fannush S. Akbar | O87: TT | P87: ITTELKOM Surabaya | S87: Leo Ligthart | U87: Delft University of Technology | X87: Gamantyo Hendrantoro | Z87: ITS | AC87: Ioan E. Lager | AE87: Delft University of Technology
A88: Linear Array Thinning with Cavity backed U-slot Patch Antenna using Genetic Algorithm | B88: Journal of Science and Applicative Technology 5 (1), 9-16, 2021 | D88: S4 | E88: SINTA | H88: 2021 | I88: Novalia Pertiwi | M88: nstitut Teknologi Sumatera | N88: Novalia Pertiwi | P88: Institut Teknologi Sumatera | S88: Fannush S. Akbar | T88: TT | U88: ITTELKOM Surabaya | X88: Eko Setijadi | Z88: ITS | AC88: Gamantyo Hendrantoro | AE88: ITS
A89: A Toolbox of Subarrays for Optimizing Wide-Angular Scanning Arrays Using Trade-Offs Between Scan Loss and Side Lobe Level | B89: IEEE Access 9, 16337-16359, 2021 | D89: Q1 | H89: 2021 | I89: Gamantyo Hendrantoro | M89: ITS | N89: Fannush S. Akbar | O89: TT | P89: ITTELKOM Surabaya | S89: Leo Ligthart | U89: Delft University of Technology | X89: Gamantyo Hendrantoro | Z89: ITS
A90: The Use Of Subarrays In Sparse Phased Array Antenna For Wide-Angular Scanning Radar Applications | B90: Institut Teknologi Sepuluh Nopember, 2021 | D90: Doctoral Thesis | H90: 2021 | I90: Fannush S. Akbar | L90: TT | M90: ITTELKOM Surabaya | N90: Fannush S. Akbar | O90: TT | P90: ITTELKOM Surabaya
A91: Dampak Pandemi Covid-19 Terhadap Pengangguran Di Indonesia | B91: JISIP (Jurnal Ilmu Sosial dan Pendidikan) 5 (4), 2021 | D91: S5 | E91: SINTA | H91: 2021 | I91: Verina Ruth Krisnandika | M91: Sekolah Tinggi Media Nusantara Citra | N91: Verina Ruth Krisnandika | P91: Sekolah Tinggi Media Nusantara Citra | S91: Darlin Aulia | T91: DB | U91: ITTELKOM Surabaya | X91: Luluul Jannah | Z91: Sekolah Tinggi Media Nusantara Citra
A92: Pengaruh Covid-19 Terhadap Perekonomian Di Negara Asean | B92: JISIP (Jurnal Ilmu Sosial Dan Pendidikan) 5 (3), 2021 | D92: S5 | E92: SINTA | H92: 2021 | I92: Azzahra Aulia Dewi | M92: Sekolah Tinggi Media Nusantara Citra | N92: Azzahra Aulia Dewi | P92: Sekolah Tinggi Media Nusantara Citra | S92: Darlin Aulia | T92: DB | U92: ITTELKOM Surabaya | X92: Kurnia Indah Sumunar | Z92: Sekolah Tinggi Media Nusantara Citra | AC92: Erni Hernawati | AE92: Sekolah Tinggi Media Nusantara Citra
A93: Pengaruh Female Independent Directors dan Family Ownership terhadap Financial Reporting Quality dengan Financial Irregulaties sebagai Variabel Moderasi | B93: JISIP (Jurnal Ilmu Sosial dan Pendidikan) 5 (4), 2021 | D93: S5 | E93: SINTA | H93: 2021 | I93: Darlin Aulia | L93: DB | M93: ITTELKOM Surabaya | N93: Darlin Aulia | O93: DB | P93: ITTELKOM Surabaya | S93: Kurnia Indah Sumunar | U93: Sekolah Tinggi Media Nusantara Citra | X93: Luluul Jannah | Z93: Sekolah Tinggi Media Nusantara Citra
A94: Pengaruh Female Tainted Director Terhadap Biaya Audit dan Kualitas Laporan Keuangan dengan Variabel Moderasi Political Connection | B94: JISIP (Jurnal Ilmu Sosial dan Pendidikan) 5 (4), 2021 | D94: S5 | E94: SINTA | H94: 2021 | I94: Budi S. Kramadibrata | M94: Sekolah Tinggi Media Nusantara Citra | N94: Budi S. Kramadibrata | P94: Sekolah Tinggi Media Nusantara Citra | S94: Darlin Aulia | T94: DB | U94: ITTELKOM Surabaya | X94: Rizal Kamsurya | Z94: Sekolah Tinggi Ilmu Keguruan dan Ilmu Pendidikan Media Nusantara Citra
A95: Dampak Financial Technology (Fintech) Dan Intellectual Capital Terhadap Kinerja Keuangan Perbankan Komersial di Indonesia | B95: SEIKO: Journal of Management &amp; Business 4 (2), 198-202, 2021 | D95: S4 | E95: SINTA | H95: 2021 | I95: Muhammad Fauzan Tanjung | M95: Sekolah Tinggi Media Nusantara Citra | N95: Muhammad Fauzan Tanjung | P95: Sekolah Tinggi Media Nusantara Citra | S95: Darlin Aulia | T95: DB | U95: ITTELKOM Surabaya
A96: Kegiatan Pengabdian Masyarakat IT Telkom Purwokerto Berupa Optimasi Produk Kopi Di Desa Melung Pasca Pandemi Corona Virus Disease (COVID-19) | B96: Magistrorum et Scholarium: Jurnal Pengabdian Masyarakat 1 (3), 347-360, 2021 | D96: Jurnal ber-ISSN | H96: 2021 | I96: Kholidiyah Masykuroh | M96: ITTP | N96: Nanda Iryani | O96: TK | P96: ITTELKOM Surabaya | S96: Sarah Astiti | U96: ITTP | X96: Kholidiyah Masykuroh | Z96: ITTP
A97: Prototype smart door lock by using wireless network based on arduino uno | B97: 2021 IEEE International Conference on Communication, Networks and Satellite &#8230;, 2021 | D97: Prosiding Internasional | H97: 2021 | N97: Kholidiyah Masykuroh | P97: ITTP | S97: Fikra Titan Syifa | U97: ITTP | X97: Gatot Rizky Setiyanto | Z97: ITTP | AC97: Afifah Dwi Ramadhani | AE97: ITTP | AH97: Danny Kurnianto | AJ97: ITTP | AM97: Nanda Iryani | AN97: TK | AO97: ITTELKOM Surabaya
A98: Analisis Performansi Routing OSPF menggunakan RYU Controller dan POX Controller pada Software Defined Networking | B98: InComTech: Jurnal Telekomunikasi dan Komputer 11 (1), 73-84, 2021 | D98: S3 | E98: SINTA | H98: 2021 | I98: Nanda Iryani | L98: TK | M98: ITTELKOM Surabaya | N98: Nanda Iryani | O98: TK | P98: ITTELKOM Surabaya | S98: Afifah Dwi Ramadhani | U98: ITTP | X98: Mayang Karmila Sari | Z98: ITTP
A99: Analisis Performansi Dynamic Multipoint Virtual Private Network pada Routing Protocol BGP dengan FRRouting. 6 (1) | B99: JTERA (Jurnal Teknologi Rekayasa), 6(1), 61-66 | D99: S3 | E99: SINTA | H99: 2021 | I99: Nanda Iryani | L99: TK | M99: ITTELKOM Surabaya | N99: Nanda Iryani | O99: TK | P99: ITTELKOM Surabaya | S99: Dyas Dendi Andika | U99: ITTP
A100: Analisis Perbandingan Performansi Eksternal Border Gateway Protocol (EBGP) pada Jaringan Konvensional dan Jaringan Software Defined Network | B100: RESISTOR (Elektronika Kendali Telekomunikasi Tenaga Listrik Komputer) 4 (2 &#8230;, 2021 | D100: S4 | E100: SINTA | H100: 2021 | N100: Lu’lu’ Hasna’ Mahdiyah | P100: ITTP | S100: Jafaruddin Gusti Amri Ginting | U100: ITTP | X100: Nanda Iryani | Y100: TK | Z100: ITTELKOM Surabaya
...

Sheet DATA PNLT KHUSUS AKRE 2025
A1: No | B1: No. SK | C1: No. Kontrak | D1: Judul Penelitian | E1: Nama Skema | F1: Tahun Usulan | G1: Tahun Pelaksanaan Kegiatan | H1: Lama Kegiatan (bulan) | I1: Bidang Fokus | J1: Dana Disetujui | K1: Nama Institusi Penerima Dana | L1: Target TKT | M1: Nama Program Hibah | N1: Kategori Sumber Dana | O1: Negara Sumber Dana | P1: Sumber Dana | Q1: Sinta ID Ketua | R1: Nama Ketua | S1: NIDN Ketua | T1: DANA KETUA | U1: Prodi Ketua | V1: Prodi Ketua (2) | W1: Prodi Ketua (3) | X1: Fakultas Ketua | Y1: Institusi Ketua | Z1: Sinta ID Institusi Ketua | AA1: Kode PT Ketua | AB1: Sinta ID Member1 | AC1: NIDN Member1 | AD1: Nama Anggota 1 | AE1: Dana Anggota 1 | AF1: Prodi Member 1 | AG1: Prodi Member 1 (2) | AH1: Prodi Anggota 1 (3) | AI1: Fakultas | AJ1: PT | AK1: Sinta ID Member2 | AL1: NIDN Member2 | AM1: Nama Anggota 2 | AN1: Dana Anggota 2 | AO1: Prodi Anggota 2 | AP1: Prodi Anggota 2 (2) | AQ1: Prodi Anggota 2 (3) | AR1: Fakultas3 | AS1: PT4 | AT1: Sinta ID Member3 | AU1: NIDN Member3 | AV1: Nama Anggota 3 | AW1: Dana Anggota 3 | AX1: Prodi Anggota 3 | AY1: Prodi Anggota 3 (2) | AZ1: Fakultas Anggota 3 | BA1: PT Anggota 3 | BB1: Sinta ID Member4 | BC1: NIDN Member4 | BD1: Nama Member4 | BE1: Dana Anggota 4 | BF1: Prodi Anggota 4 | BG1: Prodi Anggota 4 (2) | BH1: Fakultas Anggota 4 | BI1: PT Anggota 4 | BJ1: Sinta ID Member5 | BK1: NIDN Member5 | BL1: Nama Member5 | BM1: Prodi Anggota 5 | BN1: Fakultas Anggota 5 | BO1: Dana Anggota 5 | BP1: SDG | BQ1: Proposal | BR1: Laporan Akhir | BS1: Nama Mh | BT1: Prodi, Fak, PT Mhs1 | BU1: Nama Mhs2 | BV1: Prodi, Fak, PT Mhs2 | BW1: Nama Mhs3 | BX1: Prodi, Fak, PT Mhs3 | BY1: Nama Mhs4 | BZ1: Prodi Mhs4 | CA1: Nama Mhs5 | CB1: Prodi Mhs5 | CC1: Nama Mhs6 | CD1: Prodi Mhs6 | CE1: Nama Mhs7 | CF1: Prodi Mhs7 | CG1: Luaran Wajib | CH1: Capaian Luaran Wajib | CI1: Luaran Tambahan | CJ1: Capaian Luaran Tambahan
C2: 10/KP/LPPM-UWP/K-1/II/2018 | D2: RANCANGAN TEORI BAPAKISME TERHADAP PRODUKTIFITAS KADER POSYANDU SEBAGAI PENGGUNA SISTEM INFORMASI KMS | E2: Penelitian Hibah Eksternal | F2: 2018 | G2: 2018 | I2: Teknologi Informasi dan Komunikasi | J2: 16750000 | K2: Institut Teknologi Telkom Surabaya | O2: ID | P2: ITTelkom Surabaya | R2: Ully Asfari | T2: =J2 -> 16750000 | U2: Sistem Informasi | X2: FTII | AD2: Ir SUBADERI M.M | AE2: =J2 -> 16750000
C4: 214/PNLT3/PPM/III/2019 | D4: PENGEMBANGAN SISTEM KENDALI KUANTITAS AIR PADA TANAMAN HIDROPONIK BERBASIS INTERNET OF THINGS (IOT) | E4: Penelitian Dana Internal (PDI) | F4: 2019 | G4: 2019 | H4: 10 | J4: 8880000 | K4: Institut Teknologi Telkom Surabaya | L4: 4 | M4: Penelitian Kompetitif Internal | N4: Internal | O4: ID | P4: ITTelkom Surabaya | R4: Ubaidillah Umar | T4: =J4 -> 8880000 | U4: Teknik Komputer | X4: FTE | AD4: Helmy Widyantara | AE4: =J4 -> 8880000 | AF4: Teknologi Informasi | AG4: Sistem Informasi | AI4: FTII | BQ4: Proposal | BR4: Laporan Akhir | BS4: Rizal Fathurrahman | BU4: Alfrido Ramadhana KP
C5: 214/PNLT3/PPM/III/2019 | D5: Superposisi Gelombang Sinus Sebagai Media Pembelajaran Gelombang Dan Bunyi Pada Matakuliah Fisika Dasar Screen reader support enabled. | E5: Penelitian Dana Internal (PDI) | F5: 2019 | G5: 2019 | H5: 6 | J5: 4114000 | K5: Institut Teknologi Telkom Surabaya | L5: 3 | M5: Penelitian Kompetitif Internal | N5: Internal | O5: ID | P5: ITTelkom Surabaya | R5: Dwi Edi Setyawan | T5: =J5 -> 4114000 | U5: Teknik Komputer | X5: FTE | AD5: Billy Montolalu | AE5: =J5 -> 4114000 | AF5: Teknik Komputer | AI5: FTE | BQ5: Proposal | BR5: Laporan Akhir | BS5: Danang Taufik Kurnianto | BU5: Muhammad Syaiful Islam
C6: 214/PNLT3/PPM/III/2019 | D6: Rancang Bangun Modul Praktikum Harmonisasi Nada Sebagai Media Pembelajaran Gelombang Dan Bunyi Pada Matakuliah Fisika Dasar | E6: Penelitian Dana Internal (PDI) | F6: 2019 | G6: 2019 | H6: 6 | J6: 4752000 | K6: Institut Teknologi Telkom Surabaya | L6: 3 | M6: Penelitian Kompetitif Internal | N6: Internal | O6: ID | P6: ITTelkom Surabaya | R6: Dwi Edi Setyawan | T6: =J6 -> 4752000 | U6: Teknik Komputer | X6: FTE | AD6: Ardiansyah Al farouq | AE6: =J6 -> 4752000 | AF6: Teknik Komputer | AI6: FTE | BQ6: Proposal | BR6: Laporan Akhir | BS6: Muhammad Yanuar Muhaimin | BU6: Muhammad Huzaimi Maulana
C7: 214/PNLT3/PPM/III/2019 | D7: Analisis Kepuasan Pelanggan Terhadap Layanan Penyedia Jasa Transportasi Online Menggunakan Fuzzy Service Quality | E7: Penelitian Dana Internal (PDI) | F7: 2019 | G7: 2019 | H7: 8 | J7: 9627000 | K7: Institut Teknologi Telkom Surabaya | M7: Penelitian Kompetitif Internal | N7: Internal | O7: ID | P7: ITTelkom Surabaya | R7: Hawwin Mardhiana | T7: =J7 -> 9627000 | U7: Sistem Informasi | X7: FTII | AD7: Ully Asfari | AE7: =J7 -> 9627000 | AF7: Sistem Informasi | AI7: FTII | AM7: Anfazul Faridatul Azizah | AN7: =J7 -> 9627000 | AO7: Sistem Informasi | AR7: FTII | AV7: Rizqa Amelia Zunaidi | AW7: =J7 -> 9627000 | AX7: Teknik Industri | AZ7: FTII | BQ7: Proposal | BR7: Laporan Akhir | BS7: Tanang Satrio Adi
C8: 214/PNLT3/PPM/III/2019 | D8: Sistem Akuaponik Berbasis IOT pada Urban Farming | E8: Penelitian Dana Internal (PDI) | F8: 2019 | G8: 2019 | H8: 6 | J8: 11120000 | K8: Institut Teknologi Telkom Surabaya | L8: 6 | M8: Penelitian Kompetitif Internal | N8: Internal | O8: ID | P8: ITTelkom Surabaya | R8: Yupit Sudianto | T8: =J8 -> 11120000 | U8: Sistem Informasi | X8: FTII | AD8: Dimas Adiputra | AE8: =J8 -> 11120000 | AF8: Teknik Elektro | AI8: FTE | AM8: Fidi Wincoko Putro | AN8: =J8 -> 11120000 | AO8: Rekayasa Perangkat Lunak | AR8: FTII | AV8: Dominggo Bayu Baskara | AW8: =J8 -> 11120000 | AX8: Teknik Industri | AZ8: FTII | BD8: Noerma Pudji Istyanto | BE8: =J8 -> 11120000 | BF8: Sistem Informasi | BH8: FTII | BQ8: Proposal | BR8: Laporan Akhir | BS8: Tanfirul Roibafi Muhammad | BT8: SI, FTII, ITTS | BU8: Dhimas Bintang Bagaskara | BV8: RPL, FTII, ITTS
C9: 214/PNLT3/PPM/III/2019 | D9: Antena Dengan Beamforming Sederhana Untuk Komunikasi Robot Bergerak | E9: Penelitian Dana Internal (PDI) | F9: 2019 | G9: 2019 | H9: 9 | J9: 11400000 | K9: Institut Teknologi Telkom Surabaya | L9: 4 | M9: Penelitian Kompetitif Internal | N9: Internal | O9: ID | P9: ITTelkom Surabaya | R9: Muhsin | T9: =J9 -> 11400000 | U9: Teknik Telekomunikasi | V9: Teknik Elektro | X9: FTE | AD9: Walid Maulana Hadiansyah | AE9: =J9 -> 11400000 | AF9: Teknik Telekomunikasi | AI9: FTE | AM9: Tri Agus Djoko Kuntjoro | AN9: =J9 -> 11400000 | AO9: Teknik Telekomunikasi | AR9: FTE | BQ9: Proposal | BR9: Laporan Akhir | BS9: Aulia Putri Pramita | BU9: Riski Dwi Nur Cahyanti | BW9: Prasasti Desta Srihadi
C10: 214/PNLT3/PPM/III/2019 | D10: Identifikasi Posisi Kapal Mengunakan Internet Of Thing Sistem Untuk Mengurangi Antrian Kendaraan Truk Di Pelabuhan | E10: Penelitian Dana Internal (PDI) | F10: 2019 | G10: 2019 | H10: 10 | J10: 10125000 | K10: Institut Teknologi Telkom Surabaya | L10: Publikasi paper seminar | M10: Penelitian Kompetitif Internal | N10: Internal | O10: ID | P10: ITTelkom Surabaya | R10: Nilla Rachmaningrum | T10: =J10 -> 10125000 | U10: Teknik Telekomunikasi | X10: FTE | AD10: Hamzah Ulinuha Mustakim | AE10: =J10 -> 10125000 | AF10: Teknik Telekomunikasi | AI10: FTE | AM10: Tri Agus Djoko Kuntjoro | AN10: =J10 -> 10125000 | AO10: Teknik Telekomunikasi | AR10: FTE | BQ10: Proposal | BR10: Laporan Akhir | BS10: RM. Bagastyo Anggoro | BU10: Utami Ika Sulistya Rini
C11: 214/PNLT3/PPM/III/2019 | D11: Transporter Logistik Cerdas "SROBOT" | E11: Penelitian Dana Internal (PDI) | F11: 2019 | G11: 2019 | H11: 5 | J11: 11875000 | K11: Institut Teknologi Telkom Surabaya | L11: 4 | M11: Penelitian Kompetitif Internal | N11: Internal | O11: ID | P11: ITTelkom Surabaya | R11: Moch. Iskandar Riansyah | T11: =J11 -> 11875000 | U11: Teknik Elektro | X11: FTE | AD11: Lora Khaula Amifia | AE11: =J11 -> 11875000 | AF11: Teknik Elektro | AI11: FTE | BQ11: Proposal | BR11: Laporan Akhir | BS11: Putu Duta Hasta Putra | BU11: Getsemani Adi Bagus Maranata H
C12: 214/PNLT3/PPM/III/2019 | D12: Analisis Dan Deteksi Anomali Pada Perubahan Total Electron Content (Tec) Di Lapisan Ionosphare Sebelum Terjadi Gempa Bumi Menggunakan Ensemble Method. (Studi Kasus Gempa Bumi Palu Dan Lombok) | E12: Penelitian Dana Internal (PDI) | F12: 2019 | G12: 2019 | H12: 8 | J12: 3748000 | K12: Institut Teknologi Telkom Surabaya | L12: Jurnal Nasional Terakreditasi | M12: Penelitian Kompetitif Internal | N12: Internal | O12: ID | P12: ITTelkom Surabaya | R12: Bernadus Anggo Seno Aji | T12: =J12 -> 3748000 | U12: Teknologi Informasi | X12: FTII | AD12: Pangestu Widodo | AE12: =J12 -> 3748000 | AF12: Teknik Komputer | AI12: FTE | AM12: Arliyanti Nurdin | AN12: =J12 -> 3748000 | AO12: Teknologi Informasi | AR12: FTII | BQ12: Proposal | BR12: Laporan Akhir | BS12: Muhamad Rizal Dwi Adhipramana
C13: 214/PNLT3/PPM/III/2019 | D13: Simple Digital Wireless Transmitter & Receiver | E13: Penelitian Dana Internal (PDI) | F13: 2019 | G13: 2019 | H13: 10 | J13: 9400000 | K13: Institut Teknologi Telkom Surabaya | L13: HAKI | M13: Penelitian Kompetitif Internal | N13: Internal | O13: ID | P13: ITTelkom Surabaya | R13: Hamzah Ulinuha Mustakim | T13: =J13 -> 9400000 | U13: Teknik Telekomunikasi | X13: FTE | AD13: Nilla Rachmaningrum | AE13: =J13 -> 9400000 | AF13: Teknik Telekomunikasi | AI13: FTE | AM13: Walid Maulana Hadiansyah | AN13: =J13 -> 9400000 | AO13: Teknik Telekomunikasi | AR13: FTE | BQ13: Proposal | BR13: Laporan Akhir | BS13: Ahmad Maulana Rozaq
C14: 214/PNLT3/PPM/III/2019 | D14: Model Lokasi Spatial Dengan Fungsi Permintaan Yang Bergantung Pada Harga, Lokasi, Dan Diskon | E14: Penelitian Dana Internal (PDI) | F14: 2019 | G14: 2019 | H14: 8 | J14: 5296000 | K14: Institut Teknologi Telkom Surabaya | L14: 3 | M14: Penelitian Kompetitif Internal | N14: Internal | O14: ID | P14: ITTelkom Surabaya | R14: Abduh Sayid Albana | T14: =J14 -> 5296000 | U14: Teknik Industri | V14: Teknik Logistik | X14: FTII | AD14: Rahaditya Dimas Prihadianto | AE14: =J14 -> 5296000 | AF14: Teknik Industri | AI14: FTII | AM14: Sinta Dewi | AN14: =J14 -> 5296000 | BQ14: Proposal | BR14: Laporan Akhir | BS14: Muhammad Narendroduto Rokhyadi
C15: 214/PNLT3/PPM/III/2019 | D15: Pengawasan Dan Klasifikasi Kualitas Air Pdam Surabaya Berbasis Internet Of Things | E15: Penelitian Dana Internal (PDI) | F15: 2019 | G15: 2019 | H15: 6 | J15: 10250000 | K15: Institut Teknologi Telkom Surabaya | L15: 4 | M15: Penelitian Kompetitif Internal | N15: Internal | O15: ID | P15: ITTelkom Surabaya | R15: Dimas Adiputra | T15: =J15 -> 10250000 | U15: Teknik Elektro | X15: FTE | AD15: Anifatul Faricha | AE15: =J15 -> 10250000 | AF15: Teknik Elektro | AI15: FTE | AM15: Moch. Iskandar Riansyah | AN15: =J15 -> 10250000 | AO15: Teknik Elektro | AR15: FTE | AV15: Billy Montolalu | AW15: =J15 -> 10250000 | AX15: Teknik Komputer | AZ15: FTE | BQ15: Proposal | BR15: Laporan Akhir | BS15: Fauzan Abdul Rasyid | BU15: Moch. Bagus Indrastata
C16: 214/PNLT3/PPM/III/2019 | D16: Permodelan Permintaan Yang Mempertimbangkan Harga, Lokasi Dan Rebate | E16: Penelitian Dana Internal (PDI) | F16: 2019 | G16: 2019 | H16: 6 | J16: 6800000 | K16: Institut Teknologi Telkom Surabaya | L16: 2 | M16: Penelitian Kompetitif Internal | N16: Internal | O16: ID | P16: ITTelkom Surabaya | R16: Wahyu Andy Prastyabudi | T16: =J16 -> 6800000 | U16: Teknik Industri | X16: FTII | AD16: Sinta Dewi | AE16: =J16 -> 6800000 | AM16: Rizqa Amelia Zunaidi | AN16: =J16 -> 6800000 | AO16: Teknik Industri | AR16: FTII | BQ16: Proposal | BR16: Laporan Akhir | BS16: Nisrina Salsabila
C17: 214/PNLT3/PPM/III/2019 | D17: Koordinasi vd Kompetisi: Aplikasi Hotelling Model Pada Pelabuhan Peti Kemas Surabaya | E17: Penelitian Dana Internal (PDI) | F17: 2019 | G17: 2019 | H17: 10 | J17: 4800000 | K17: Institut Teknologi Telkom Surabaya | L17: 3 | M17: Penelitian Kompetitif Internal | N17: Internal | O17: ID | P17: ITTelkom Surabaya | R17: Rahaditya Dimas Prihadianto | T17: =J17 -> 4800000 | U17: Teknik Industri | X17: FTII | AD17: Abduh Sayid Albana | AE17: =J17 -> 4800000 | AF17: Teknik Industri | AG17: Teknik Logistik | AI17: FTII | AM17: Dominggo Bayu Baskara | AN17: =J17 -> 4800000 | AO17: Teknik Industri | AR17: FTII | BQ17: Proposal | BR17: Laporan Akhir | BS17: Shanggabuana Adhitya Shamaradewa
C18: 214/PNLT3/PPM/III/2019 | D18: Rancang Bangun Sistem Informasi Transportasi Umum Di Surabaya Mengguanakan Google Maps APIs Dan Firebase Pada Perangkat | E18: Penelitian Dana Internal (PDI) | F18: 2019 | G18: 2019 | H18: 10 | J18: 10748000 | K18: Institut Teknologi Telkom Surabaya | L18: Aplikasi Android, Jurnal Nasional Terakreditasi, Seminar Internasional Terindeks IEEE | M18: Penelitian Kompetitif Internal | N18: Internal | O18: ID | P18: ITTelkom Surabaya | R18: Farah Zakiyah Rahmanti | T18: =J18 -> 10748000 | U18: Teknologi Informasi | X18: FTII | AD18: Khodijah Amiroh | AE18: =J18 -> 10748000 | AF18: Teknologi Informasi | AI18: FTII | AM18: Oktavia Ayu Permata | AN18: =J18 -> 10748000 | AO18: Teknologi Informasi | AR18: FTII | AV18: Philip Tobianto Daely | AW18: =J18 -> 10748000 | AX18: Teknologi Informasi | AZ18: FTII | BQ18: Proposal | BR18: Laporan Akhir | BS18: Anas Ittaqullah
C19: 214/PNLT3/PPM/III/2019 | D19: Voice Command Dalam Rumah Pintar Berbasis Internet Of Things | E19: Penelitian Dana Internal (PDI) | F19: 2019 | G19: 2019 | H19: 3 | J19: 8681500 | K19: Institut Teknologi Telkom Surabaya | L19: Artikel Ilmiah dimuat di Jurnal | M19: Penelitian Kompetitif Internal | N19: Internal | O19: ID | P19: ITTelkom Surabaya | R19: Billy Montolalu | T19: =J19 -> 8681500 | U19: Teknik Komputer | X19: FTE | AD19: Ardiansyah Al farouq | AE19: =J19 -> 8681500 | AF19: Teknik Komputer | AI19: FTE | BQ19: Proposal | BR19: Laporan Akhir | BS19: Danu Diningrat | BU19: Alvin Tamado Cahaya
C20: 214/PNLT3/PPM/III/2019 | D20: Pengembangan Sistem Cerdas Untuk Prediksi Jatuh Berbasis Accelerometer Dan Gyroscope Dalam Rangka Pencegahan Cedera Fatal Pada Geriatri | E20: Penelitian Dana Internal (PDI) | F20: 2019 | G20: 2019 | H20: 10 | J20: 10025000 | K20: Institut Teknologi Telkom Surabaya | L20: 3 | M20: Penelitian Kompetitif Internal | N20: Internal | O20: ID | P20: ITTelkom Surabaya | R20: Dewi Rahmawati | T20: =J20 -> 10025000 | U20: Rekayasa Perangkat Lunak | X20: FTII | AD20: Ardian Yusuf Wicaksono | AE20: =J20 -> 10025000 | AF20: Informatika | AI20: FTII | AM20: Khodijah Amiroh | AN20: =J20 -> 10025000 | AO20: Teknologi Informasi | AR20: FTII | AV20: Titus Kristanto | AW20: =J20 -> 10025000 | AX20: Rekayasa Perangkat Lunak | AY20: Sistem Informasi | AZ20: FTII | BQ20: Proposal | BR20: Laporan Akhir
C21: 214/PNLT3/PPM/III/2019 | D21: Manajemen Energi Menggunakan Internet Of Things Untuk Smart Home | E21: Penelitian Dana Internal (PDI) | F21: 2019 | G21: 2019 | H21: 6 | J21: 6574000 | K21: Institut Teknologi Telkom Surabaya | L21: Paper Scopus | M21: Penelitian Kompetitif Internal | N21: Internal | O21: ID | P21: ITTelkom Surabaya | R21: Isa Hafidz | T21: =J21 -> 6574000 | U21: Teknik Elektro | X21: FTE | AD21: Moch. Iskandar Riansyah | AE21: =J21 -> 6574000 | AF21: Teknik Elektro | AI21: FTE | AM21: Dimas Adiputra | AN21: =J21 -> 6574000 | AO21: Teknik Elektro | AR21: FTE | BQ21: Proposal | BR21: Laporan Akhir | BS21: Fathur Alfariz | BU21: Nova H. M. Soetarno
A23: 1 | B23: REK.623/PNLT3/PPM/III/2020 | C23: 544/PNLT3/PPM/III/2020 | D23: PENGARUH TIPE MEDIA SOSIAL TERHADAP HUBUNGAN ANTARA INFORMASI PADA IKLAN PRODUK UKM INDUSTRI SANDANG DENGAN INTENSI MEMBELI PADA INFORMATION ACCEPTANCE MODEL (IACM) | E23: Penelitian Dana Internal (PDI) | F23: 2020 | G23: 2020 | H23: 10 | I23: Manajemen Industri | J23: 4563200 | K23: Institut Teknologi Telkom Surabaya | L23: 1 | N23: Internal | O23: ID | P23: ITTelkom Surabaya | Q23: 6681051 | R23: Rizqa Amelia Zunaidi | S23: 0711069301 | T23: =J23 -> 4563200 | U23: Teknik Industri | X23: FTEIC | AB23: 6680627 | AC23: 0703119301 | AD23: Benazir Imam Arif Muttaqin | AE23: =J23 -> 4563200 | AF23: Teknik Industri | AI23: FTEIC | AJ23: ITTelkom Surabaya | BQ23: Proposal | BR23: Laporan Akhir | CG23: Jurnal Nasional Terakreditasi | CI23: Seminar Internasional
A24: 2 | B24: REK.623/PNLT3/PPM/III/2020 | C24: 545/PNLT3/PPM/III/2020 | D24: Studi Kelayakan Teknologi Klasifikasi Otomatis Berbasis Convolutional Neural Network Pada Sistem Penerimaan Mahasiswa Baru | E24: Penelitian Dana Internal (PDI) | F24: 2020 | G24: 2020 | H24: 10 | I24: Studi Kelayakan | J24: 5820000 | K24: Institut Teknologi Telkom Surabaya | L24: 3 | N24: Internal | O24: ID | P24: ITTelkom Surabaya | Q24: 6682237 | R24: Dominggo Bayu Baskara | S24: 0722069004 | T24: =J24 -> 5820000 | U24: Bisnis Digital | X24: FTIB | AB24: 6680626 | AC24: 0727099201 | AD24: Ardian Yusuf Wicaksono | AE24: =J24 -> 5820000 | AF24: Informatika | AI24: FTIB | AJ24: ITTelkom Surabaya | AK24: 6680628 | AL24: 0730058702 | AM24: Fidi Wincoko Putro | AN24: =J24 -> 5820000 | AO24: Rekayasa Perangkat Lunak | AR24: FTIB | AS24: ITTelkom Surabaya | BQ24: Proposal | BR24: Laporan Akhir | CG24: Jurnal Nasional
A25: 3 | B25: REK.623/PNLT3/PPM/III/2020 | C25: 546/PNLT3/PPM/III/2020 | D25: 2D TO 3D MRI BRAIN SEGMENTATION MENGGUNAKAN U-NET AND MASK R-CNN METHOD UNTUK PENDUDUK DAERAH MARITIM | E25: Penelitian Dana Internal (PDI) | F25: 2020 | G25: 2020 | H25: 10 | I25: Machine Learning | J25: 13337500 | K25: Institut Teknologi Telkom Surabaya | L25: 3 | M25: Penelitian Kompetitif Internal | N25: Internal | O25: ID | P25: ITTelkom Surabaya | Q25: 6680622 | R25: Dewi Rahmawati | S25: 0709039401 | T25: =J25 -> 13337500 | U25: Rekayasa Perangkat Lunak | X25: FTIB | Y25: ITTelkom Surabaya | Z25: 8140 | AA25: 072019 | AB25: 6680626 | AC25: 0727099201 | AD25: Ardian Yusuf Wicaksono | AE25: =J25 -> 13337500 | AF25: Informatika | AI25: FTIB | AJ25: ITTelkom Surabaya | BQ25: Proposal | BR25: Laporan Akhir | CG25: Jurnal Nasional Terakreditasi | CI25: Seminar Internasional
A26: 4 | B26: REK.623/PNLT3/PPM/III/2020 | C26: 547/PNLT3/PPM/III/2020 | D26: Water Monitoring Using Internet of Things (IoT) Gen. 1 | E26: Penelitian Dana Internal (PDI) | F26: 2020 | G26: 2020 | H26: 10 | I26: Kemaritiman | J26: 15883750 | K26: Institut Teknologi Telkom Surabaya | L26: 4 | N26: Internal | O26: ID | P26: ITTelkom Surabaya | Q26: 6680651 | R26: Dimas Adiputra | S26: 0725059301 | T26: =J26 -> 15883750 | U26: Teknik Elektro | X26: FTEIC | AB26: 6680631 | AC26: 0704069202 | AD26: Anifatul Faricha | AE26: =J26 -> 15883750 | AF26: Teknik Elektro | AI26: FTEIC | AJ26: ITTelkom Surabaya | AK26: 6680685 | AL26: 0721068802 | AM26: Moch. Iskandar Riansyah | AN26: =J26 -> 15883750 | AO26: Teknik Elektro | AR26: FTEIC | AS26: ITTelkom Surabaya | BQ26: Proposal | BR26: Laporan Akhir | CG26: Jurnal | CI26: Proseding internasional, Prototype
A27: 5 | B27: REK.623/PNLT3/PPM/III/2020 | C27: 548/PNLT3/PPM/III/2020 | D27: Simulasi Model Hoteliing Pada Pelabuhan Peti Kemas Surabaya | E27: Penelitian Dana Internal (PDI) | F27: 2020 | G27: 2020 | H27: 10 | I27: Simulasi Industri | J27: 5796000 | K27: Institut Teknologi Telkom Surabaya | L27: 3 | N27: Internal | O27: ID | P27: ITTelkom Surabaya | Q27: 6680618 | R27: Rahaditya Dimas Prihadianto | S27: 0725059202 | T27: =J27 -> 5796000 | U27: Teknik Industri | X27: FTEIC | AB27: 6680643 | AC27: 0702039003 | AD27: Abduh Sayid Albana | AE27: =J27 -> 5796000 | AF27: Teknik Logistik | AG27: Teknik Industri | AI27: FTEIC | AJ27: ITTelkom Surabaya | AK27: 6682237 | AL27: 722069004 | AM27: Dominggo Bayu | AN27: =J27 -> 5796000 | AO27: Bisnis Digital | AR27: FTIB | AS27: ITTelkom Surabaya | BQ27: Proposal | BR27: Laporan Akhir | CG27: Jurnal Nasional Terakreditasi | CI27: Seminar Internasional
A28: 6 | B28: REK.623/PNLT3/PPM/III/2020 | C28: 549/PNLT3/PPM/III/2020 | D28: Desain Sistem Monitoring Solar Farm dengan Menggunakan PV Inverter pada Bangunan | E28: Penelitian Dana Internal (PDI) | F28: 2020 | G28: 2020 | H28: 10 | I28: Teknologi Informasi dan Komunikasi | J28: 15035000 | K28: Institut Teknologi Telkom Surabaya | L28: 2 | N28: Internal | O28: ID | P28: ITTelkom Surabaya | Q28: 6680612 | R28: Isa Hafidz | S28: 0728059203 | T28: =J28 -> 15035000 | U28: Teknik Elektro | X28: FTEIC | AB28: 6680683 | AC28: 0729088704 | AD28: Billy Montolalu | AE28: =J28 -> 15035000 | AF28: Rekayasa Perangkat Lunak | AI28: FTIB | AJ28: ITTelkom Surabaya | AK28: 6680741 | AL28: 727059002 | AM28: Hamzah Ulinuha Mustakim | AN28: =J28 -> 15035000 | AO28: Teknik Telekomunikasi | AR28: FTEIC | AS28: ITTelkom Surabaya | BQ28: Proposal | BR28: Laporan Akhir | CG28: Jurnal | CI28: Modul Pelatihan, Modul Praktikum
A29: 7 | B29: REK.623/PNLT3/PPM/III/2020 | C29: 550/PNLT3/PPM/III/2020 | D29: EVAN (Emergency Vehiche Automatic Notification) | E29: Penelitian Dana Internal (PDI) | F29: 2020 | G29: 2020 | H29: 10 | I29: Transportasi | J29: 12530400 | K29: Institut Teknologi Telkom Surabaya | L29: 2 | N29: Internal | O29: ID | P29: ITTelkom Surabaya | Q29: 6682174 | R29: Khodijah Amiroh | S29: 0708069202 | T29: =J29 -> 12530400 | U29: Teknologi Informasi | X29: FTIB | AB29: 6680664 | AC29: 0715128708 | AD29: Farah Zakiyah Rahmanti | AE29: =J29 -> 12530400 | AF29: Teknologi Informasi | AI29: FTIB | AJ29: ITTelkom Surabaya | AK29: 6680680 | AL29: 704039202 | AM29: Bernadus Anggo Seno Aji | AN29: =J29 -> 12530400 | AO29: Teknologi Informasi | AR29: FTIB | AS29: ITTelkom Surabaya | BQ29: Proposal | BR29: Laporan Akhir | CG29: Jurnal Nasional Terakreditasi | CI29: HKI
A30: 8 | B30: REK.623/PNLT3/PPM/III/2020 | C30: 551/PNLT3/PPM/III/2020 | D30: Analisis Karakteristik Peniaian Kinerja Manajerial Terhadap Pengaruh Motivasi Dan Kreativitas Menggunakan Metode Graphic Rating Scale Pada Instansi XYZ | E30: Penelitian Dana Internal (PDI) | F30: 2020 | G30: 2020 | H30: 10 | I30: Teknologi Informasi dan Komunikasi | J30: 6661475 | K30: Institut Teknologi Telkom Surabaya | L30: 3 | N30: Internal | O30: ID | P30: ITTelkom Surabaya | Q30: 259781 | R30: Titus Kristanto | S30: 0710028604 | T30: =J30 -> 6661475 | U30: Bisnis Digital | V30: Sistem Informasi | X30: FTIB | AB30: 6680698 | AC30: 0709128101 | AD30: Mohammad Sholik | AE30: =J30 -> 6661475 | AF30: Rekayasa Perangkat Lunak | AI30: FTIB | AJ30: ITTelkom Surabaya | AK30: 6744406 | AL30: 0709059004 | AM30: Muhamad Nasrullah | AN30: =J30 -> 6661475 | AO30: Sistem Informasi | AR30: FTIB | AS30: ITTelkom Surabaya | BQ30: Proposal | BR30: Laporan Akhir | CG30: Jurnal Nasional Terakreditasi | CI30: Seminar Internasional, Hak Cipta
A31: 9 | B31: REK.623/PNLT3/PPM/III/2020 | C31: 552/PNLT3/PPM/III/2020 | D31: Perancangan Data Warehouse untuk Menunjang Akreditasi Program Studi | E31: Penelitian Dana Internal (PDI) | F31: 2020 | G31: 2020 | H31: 6 | I31: Warehouse Management System | J31: 4600000 | K31: Institut Teknologi Telkom Surabaya | L31: 3 | N31: Internal | O31: ID | P31: ITTelkom Surabaya | Q31: 6764236 | R31: Rokhmatul Insani | S31: 0704068902 | T31: =J31 -> 4600000 | U31: Sistem Informasi | X31: FTIB | AB31: 6665306 | AC31: 0703129001 | AD31: Ully Asfari | AE31: =J31 -> 4600000 | AF31: Sistem Informasi | AI31: FTIB | AJ31: ITTelkom Surabaya | BQ31: Proposal | BR31: Laporan Akhir | CG31: Jurnal Sinta 2 | CI31: Seminar Internasional
A32: 10 | B32: REK.623/PNLT3/PPM/III/2020 | C32: 553/PNLT3/PPM/III/2020 | D32: Penelusuran Sumber Gas Pada Kondisi Turbulensi Mekanis Menggunakan Mobile Robot | E32: Penelitian Dana Internal (PDI) | F32: 2020 | G32: 2020 | H32: 7 | I32: Transportasi | J32: 11932940 | K32: Institut Teknologi Telkom Surabaya | L32: 4 | N32: Internal | O32: ID | P32: ITTelkom Surabaya | Q32: 6680633 | R32: Helmy Widyantara | S32: 0717017902 | T32: =J32 -> 11932940 | U32: Teknologi Informasi | V32: Sistem Informasi | X32: FTIB | AB32: 6680629 | AC32: 0727048809 | AD32: Ubaidillah Umar | AE32: =J32 -> 11932940 | AF32: Teknik Komputer | AI32: FTEIC | AJ32: ITTelkom Surabaya | BQ32: Proposal | BR32: Laporan Akhir | CG32: Jurnal Internasional
A33: 11 | B33: REK.623/PNLT3/PPM/III/2020 | C33: 554/PNLT3/PPM/III/2020 | D33: Antenna MIMO 5G-NR Band N77 dengan Korelasi Rendah untuk Base Station Komunikasi Robot Bergerak | E33: Penelitian Dana Internal (PDI) | F33: 2020 | G33: 2020 | H33: 10 | I33: Teknologi Informasi dan Komunikasi | J33: 11270000 | K33: Institut Teknologi Telkom Surabaya | L33: 4 | N33: Internal | O33: ID | P33: ITTelkom Surabaya | Q33: 6680615 | R33: Muhsin | S33: 0703049401 | T33: =J33 -> 11270000 | U33: Teknik Telekomunikasi | V33: Teknik Elektro | X33: FTEIC | AB33: 6680645 | AC33: 0713108902 | AD33: Walid Maulana Hadiansyah | AE33: =J33 -> 11270000 | AF33: Teknik Telekomunikasi | AI33: FTEIC | AJ33: ITTelkom Surabaya | BQ33: Proposal | BR33: Laporan Akhir | CG33: Jurnal Internasional
A34: 12 | B34: REK.623/PNLT3/PPM/III/2020 | C34: 555/PNLT3/PPM/III/2020 | D34: Transporter Logistik Cerdas dengan Kemampuan Obstacle Avoidance dan Path Planning | E34: Penelitian Dana Internal (PDI) | F34: 2020 | G34: 2020 | H34: 10 | I34: Transportasi | J34: 13337500 | K34: Institut Teknologi Telkom Surabaya | L34: 4 | N34: Internal | O34: ID | P34: ITTelkom Surabaya | Q34: 6680685 | R34: Moch. Iskandar Riansyah | S34: 0721068802 | T34: =J34 -> 13337500 | U34: Teknik Elektro | X34: FTEIC | AB34: 6680708 | AC34: 0706069201 | AD34: Lora Khaula Amifia | AE34: =J34 -> 13337500 | AF34: Teknik Elektro | AI34: FTEIC | AJ34: ITTelkom Surabaya | BQ34: Proposal | BR34: Laporan Akhir | CG34: Jurnal | CI34: Proseding internasional, Prototype
A35: 13 | B35: REK.623/PNLT3/PPM/III/2020 | C35: 556/PNLT3/PPM/III/2020 | D35: Sistem Pelacakan Aset Menggunakan RFID pada ITTelkom Surabaya | E35: Penelitian Dana Internal (PDI) | F35: 2020 | G35: 2020 | H35: 10 | I35: Logistik | J35: 13579200 | K35: Institut Teknologi Telkom Surabaya | L35: 2 | N35: Internal | O35: ID | P35: ITTelkom Surabaya | Q35: 6680664 | R35: Farah Zakiyah Rahmanti | S35: 0715128708 | T35: =J35 -> 13579200 | U35: Teknologi Informasi | X35: FTIB | AB35: 6682174 | AC35: 0708069202 | AD35: Khodijah Amiroh | AE35: =J35 -> 13579200 | AF35: Teknologi Informasi | AI35: FTIB | AJ35: ITTelkom Surabaya | AK35: 6679083 | AL35: 0728069401 | AM35: Philip Tobianto Daely | AN35: =J35 -> 13579200 | AO35: Teknologi Informasi | AR35: FTIB | AS35: ITTelkom Surabaya | BQ35: Proposal | BR35: Laporan Akhir | CG35: Jurnal Nasional Terakreditasi | CI35: HKI
A36: 14 | B36: REK.623/PNLT3/PPM/III/2020 | C36: 557/PNLT3/PPM/III/2020 | D36: Menyelidiki Hasil Pembelajaran dan Menghasilkan Subyektif Mendalam Dalam Pengalaman Logistic Dengan Video 360 | E36: Penelitian Dana Internal (PDI) | F36: 2020 | G36: 2020 | H36: 10 | I36: Virtual Reality, Budaya Organisasi | J36: 8320250 | K36: Institut Teknologi Telkom Surabaya | L36: 2 | N36: Internal | O36: ID | P36: ITTelkom Surabaya | Q36: 6665306 | R36: Ully Asfari | S36: 0703129001 | T36: =J36 -> 8320250 | U36: Sistem Informasi | X36: FTIB | AB36: 6680623 | AC36: 0721088602 | AD36: Yupit Sudianto | AE36: =J36 -> 8320250 | AF36: Sistem Informasi | AI36: FTIB | AJ36: ITTelkom Surabaya | AK36: 6680627 | AL36: 0703119301 | AM36: Benazir Imam Arif Muttaqin | AN36: =J36 -> 8320250 | AO36: Teknik Industri | AR36: FTEIC | AS36: ITTelkom Surabaya | BQ36: Proposal | BR36: Laporan Akhir | CG36: Jurnal Nasional | CI36: Hak Cipta
A37: 15 | B37: REK.661/PNLT3/PPM/III/2020 | C37: 534/SAM4/PPM/III/2020 | D37: Pengembangan sistem kendali kuantitas air pada tanaman hidroponik berbasis Internet of Things (IoT) | E37: Penelitian Dosen Pemula (PDP) | F37: 2020 | G37: 2020 | H37: 10 | I37: Kemaritiman | J37: 19765000 | K37: Institut Teknologi Telkom Surabaya | L37: 2 | M37: Penelitian Kompetitif Nasional | N37: eksternal | O37: ID | Q37: 6680629 | R37: Ubaidillah Umar | S37: 0727048809 | T37: =J37 -> 19765000 | U37: Teknik Komputer | X37: FTEIC | AB37: 6680633 | AC37: 0717017902 | AD37: Helmy Widyantara | AE37: =J37 -> 19765000 | AF37: Teknologi Informasi | AG37: Sistem Informasi | AI37: FTIB | AJ37: ITTelkom Surabaya | BQ37: Proposal | BR37: Proposal | CG37: Jurnal | CI37: Proseding internasional, Prototype
A38: 16 | B38: REK.661/PNLT3/PPM/III/2020 | C38: 535/SAM4/PPM/III/2020 | D38: Implementasi Framework Performance System (PMS) pada Perusahaan Penyedia Jasa Logistik di Indonesia | E38: Penelitian Dosen Pemula (PDP) | F38: 2020 | G38: 2020 | H38: 12 | J38: 19355000 | K38: Institut Teknologi Telkom Surabaya | L38: 2 | N38: eksternal | O38: ID | Q38: 6681051 | R38: Rizqa Amelia Zunaidi | S38: 0711069301 | T38: =J38 -> 19355000 | U38: Teknik Industri | X38: FTEIC | AB38: 6680687 | AC38: 0702048705 | AD38: Wahyu Andy Prastyabudi | AE38: =J38 -> 19355000 | AF38: Teknik Industri | AI38: FTEIC | AJ38: ITTelkom Surabaya | BQ38: Proposal | BR38: Laporan Akhir | CG38: Jurnal Nasional Terakreditasi | CI38: Seminar Internasional,
A39: 17 | B39: REK.661/PNLT3/PPM/III/2020 | C39: 536/SAM4/PPM/III/2020 | D39: Adopsi dan Implementasi I-Gracias di Lemdikti Yayasan Pendidikan Telkom berbasis Knowledge Management System (Studi Kasus: ITTelkom Surabaya) | E39: Penelitian Dosen Pemula (PDP) | F39: 2020 | G39: 2020 | H39: 12 | J39: 18860000 | K39: Institut Teknologi Telkom Surabaya | L39: 2 | N39: eksternal | O39: ID | Q39: 6680634 | R39: Noerma Pudji Istyanto | S39: 0725059004 | T39: =J39 -> 18860000 | U39: Sistem Informasi | X39: FTIB | AB39: 6680622 | AC39: 0709039401 | AD39: Dewi Rahmawati | AE39: =J39 -> 18860000 | AF39: Rekayasa Perangkat Lunak | AI39: FTIB | AJ39: ITTelkom Surabaya | BQ39: Proposal | BR39: Laporan Akhir | CG39: Jurnal Nasional Terakreditasi
A40: 18 | B40: REK.661/PNLT3/PPM/III/2020 | C40: 537/SAM4/PPM/III/2020 | D40: Analisis dan Perancangan Framewrork Sistem Informasi Manajemen Data Perguruan Tinggi di Surabaya | E40: Penelitian Dosen Pemula (PDP) | F40: 2020 | G40: 2020 | H40: 12 | J40: 19721000 | K40: Institut Teknologi Telkom Surabaya | L40: 2 | N40: eksternal | O40: ID | Q40: 259781 | R40: Titus Kristanto | S40: 0710028604 | T40: =J40 -> 19721000 | U40: Bisnis Digital | V40: Sistem Informasi | X40: FTIB | AB40: 6680645 | AC40: 0713108902 | AD40: Walid Maulana Hadiansyah | AE40: =J40 -> 19721000 | AF40: Teknik Telekomunikasi | AI40: FTEIC | AJ40: ITTelkom Surabaya | BQ40: Proposal | BR40: Laporan Akhir | CG40: Jurnal Nasional Terakreditasi | CI40: Buku (berupa buku ajar, monograf, atau buku referensi)
A41: 19 | B41: REK.661/PNLT3/PPM/III/2020 | C41: 538/SAM4/PPM/III/2020 | D41: Deteksi Kerusakan Jalan Raya secara Real Time berbasis perangkat bergerak dengan convolutional neural network | E41: Penelitian Dosen Pemula (PDP) | F41: 2020 | G41: 2020 | H41: 12 | J41: 16000000 | K41: Institut Teknologi Telkom Surabaya | N41: eksternal | O41: ID | Q41: 6680628 | R41: Fidi Wincoko Putro | S41: 0730058702 | T41: =J41 -> 16000000 | U41: Rekayasa Perangkat Lunak | X41: FTIB | Y41: ITTelkom Surabaya | Z41: 8140 | AA41: 072019 | AB41: 6680626 | AC41: 0727099201 | AD41: Ardian Yusuf Wicaksono | AE41: =J41 -> 16000000 | AF41: Informatika | AI41: FTIB | AJ41: ITTelkom Surabaya | AK41: 6680698 | AL41: 0709128101 | AM41: Mohammad Sholik | AN41: =J41 -> 16000000 | AO41: Rekayasa Perangkat Lunak | AR41: FTIB | AS41: ITTelkom Surabaya | BQ41: Proposal | BR41: Laporan Akhir
A42: 20 | B42: REK.661/PNLT3/PPM/III/2020 | C42: 539/SAM4/PPM/III/2020 | D42: Pengembangan sistem penukaran tiket suroboyobus melalui digitalisasi pencatatan penukaran sampah berbasis android | E42: Penelitian Dosen Pemula (PDP) | F42: 2020 | G42: 2020 | J42: 19770000 | K42: Institut Teknologi Telkom Surabaya | N42: eksternal | O42: ID | Q42: 6681205 | R42: Oktavia Ayu Permata | S42: 0705109002 | T42: =J42 -> 19770000 | U42: Teknologi Informasi | X42: FTIB | AB42: 6682174 | AC42: 0708069202 | AD42: Khodijah Amiroh | AE42: =J42 -> 19770000 | AF42: Teknologi Informasi | AI42: FTIB | AJ42: ITTelkom Surabaya | BQ42: Proposal | BR42: Laporan Akhir
A43: 21 | B43: REK.661/PNLT3/PPM/III/2020 | C43: 540/SAM4/PPM/III/2020 | D43: Pengembangan Sistem Nurse Call Nirkabael Berbasis ZigBee untuk Pasien Rawat Inap di RS Umum Daerah Tongas | E43: Penelitian Dosen Pemula (PDP) | F43: 2020 | G43: 2020 | H43: 12 | I43: Teknologi Informasi dan Komunikasi | J43: 16097000 | K43: Institut Teknologi Telkom Surabaya | L43: 2 | N43: eksternal | O43: ID | Q43: 6680683 | R43: Billy Montolalu | S43: 0729088704 | T43: =J43 -> 16097000 | U43: Rekayasa Perangkat Lunak | X43: FTIB | Y43: ITTelkom Surabaya | Z43: 8140 | AA43: 072019 | AB43: 6680741 | AC43: 0727059002 | AD43: Hamzah Ulinuha Mustakim | AE43: =J43 -> 16097000 | AF43: Teknik Telekomunikasi | AI43: FTEIC | AJ43: ITTelkom Surabaya | BQ43: Proposal | BR43: Laporan Akhir | CG43: Jurnal Nasional Terakreditasi
A44: 22 | B44: REK.661/PNLT3/PPM/III/2020 | C44: 541/SAM4/PPM/III/2020 | D44: Pemanfaatan VR dalam perancangan desain tempat kerja dan pengaruhnya terhadap produktivitas | E44: Penelitian Dosen Pemula (PDP) | F44: 2020 | G44: 2020 | H44: 12 | I44: Kemaritiman | J44: 19431000 | K44: Institut Teknologi Telkom Surabaya | L44: 3 | N44: eksternal | O44: ID | Q44: 6680627 | R44: Benazir Imam Arif Muttaqin | S44: 0703119301 | T44: =J44 -> 19431000 | U44: Teknik Industri | X44: FTEIC | AB44: 6665306 | AC44: 0703129001 | AD44: Ully Asfari | AE44: =J44 -> 19431000 | AF44: Sistem Informasi | AI44: FTIB | AJ44: ITTelkom Surabaya | AK44: 6680648 | AL44: 724089201 | AM44: Hawwin Mardhiana | AN44: =J44 -> 19431000 | AO44: Sistem Informasi | AR44: FTIB | AS44: ITTelkom Surabaya | BQ44: Proposal | BR44: Laporan Akhir | CG44: Jurnal Nasional Terakreditasi | CI44: Karya arsitektur
A45: 23 | B45: REK.661/PNLT3/PPM/III/2020 | C45: 542/SAM4/PPM/III/2020 | D45: Deteksi Kecelakaan Lalu Lintas pada Real Time Video | E45: Penelitian Dosen Pemula (PDP) | F45: 2020 | G45: 2020 | H45: 12 | I45: Transportasi | J45: 19990000 | K45: Institut Teknologi Telkom Surabaya | L45: 2 | N45: eksternal | O45: ID | Q45: 6680726 | R45: Arliyanti Nurdin | S45: 0719069101 | T45: =J45 -> 19990000 | U45: Teknologi Informasi | X45: FTIB | AB45: 6680680 | AC45: 0704039202 | AD45: Bernandus Anggo Seno Aji | AE45: =J45 -> 19990000 | AF45: Teknologi Informasi | AI45: FTIB | AJ45: ITTelkom Surabaya | AK45: 6680623 | AL45: 721088602 | AM45: Yupit Sudianto | AN45: =J45 -> 19990000 | AO45: Sistem Informasi | AR45: FTIB | AS45: ITTelkom Surabaya | BQ45: Proposal | BR45: Laporan Akhir | CG45: Jurnal Nasional Terakreditasi
A46: 24 | B46: REK.661/PNLT3/PPM/III/2020 | C46: 543/SAM4/PPM/III/2020 | D46: Pengembangan robot pesawat tanpa awak untuk pemadam kebakaran di lingkungan yang berbahaya | E46: Penelitian Dosen Pemula (PDP) | F46: 2020 | G46: 2020 | H46: 12 | J46: 19800000 | K46: Institut Teknologi Telkom Surabaya | L46: 3 | N46: eksternal | O46: ID | Q46: 6680641 | R46: Ardiansyah Al Farouq | S46: 0714029301 | T46: =J46 -> 19800000 | U46: Teknik Komputer | X46: FTEIC | AB46: 6680685 | AC46: 0721068802 | AD46: Moch.Iskandar Riansyah | AE46: =J46 -> 19800000 | AF46: Teknik Elektro | AI46: FTEIC | AJ46: ITTelkom Surabaya | BQ46: Proposal | BR46: Laporan Akhir | CG46: Jurnal Nasional Terakreditasi | CI46: Program Komputer
A47: 25 | B47: REK. 754/PNLT1/WRI/IV/2020 | C47: 1298/PNLT3/LPPM/VIII/2020 | D47: Lorong Sterilisasi Untuk Membersihkan Virus Corona pada Pakaian Luar Tubuh Manusia | E47: Penelitian Penugasan | F47: 2020 | G47: 2020 | H47: 12 | J47: 85000000 | K47: Institut Teknologi Telkom Surabaya | N47: Internal | O47: ID | Q47: 6680628 | R47: Fidi Wincoko Putro | S47: 0730058702 | T47: =J47 -> 85000000 | U47: Rekayasa Perangkat Lunak | X47: FTIB | Y47: ITTelkom Surabaya | Z47: 8140 | AA47: 072019 | AB47: 6680685 | AC47: 0721068802 | AD47: Moch.Iskandar Riansyah | AE47: =J47 -> 85000000 | AF47: Teknik Elektro | AI47: FTEIC | AJ47: ITTelkom Surabaya | AK47: 6680648 | AL47: 724089201 | AM47: Hawwin Mardhiana | AN47: =J47 -> 85000000 | AO47: Sistem Informasi | AR47: FTIB | AS47: ITTelkom Surabaya | AT47: 6680678 | AU47: 0713068702 | AV47: Dwi Edi Setyawan | AW47: =J47 -> 85000000 | AX47: Teknik Komputer | AZ47: FTEIC | BA47: ITTelkom Surabaya | BQ47: Proposal | BR47: Laporan Akhir
A48: 26 | B48: REK. 754/PNLT1/WRI/IV/2020 | C48: 1299/PNLT3/LPPM/VIII/2020 | D48: Rancang bangun sterillisasi chamber untuk meminimalisir risiko paparan virus COVID-19 | E48: Penelitian Penugasan | F48: 2020 | G48: 2020 | H48: 5 | J48: 50000000 | K48: Institut Teknologi Telkom Surabaya | L48: 3 | N48: Internal | O48: ID | Q48: 6680678 | R48: Dwi Edi Setyawan | S48: 0713068702 | T48: =J48 -> 50000000 | U48: Teknik Komputer | X48: FTEIC | AB48: 6680741 | AC48: 727059002 | AD48: Hamzah Ulinuha Mustakim | AE48: =J48 -> 50000000 | AF48: Teknik Telekomunikasi | AI48: FTEIC | AJ48: ITTelkom Surabaya | AK48: 6682794 | AL48: 721058310 | AM48: Pangestu Widodo | AN48: =J48 -> 50000000 | AO48: Teknik Komputer | AR48: FTEIC | AS48: ITTelkom Surabaya | AT48: 6764236 | AU48: 0704068902 | AV48: Rokhmatul Insani | AW48: =J48 -> 50000000 | AX48: Sistem Informasi | AZ48: FTIB | BA48: ITTelkom Surabaya | BQ48: Proposal | BR48: Laporan Akhir | CG48: Produk
A49: 27 | B49: REK. 754/PNLT1/WRI/IV/2020 | C49: 1300/PNLT3/LPPM/VIII/2020 | D49: Desain Robot Logistik Pembantu Tenaga Medis di Rumah Sakit | E49: Penelitian Penugasan | F49: 2020 | G49: 2020 | H49: 10 | I49: Teknologi Informasi dan Komunikasi | J49: 7500000 | K49: Institut Teknologi Telkom Surabaya | L49: 2 | N49: Internal | O49: ID | Q49: 6680683 | R49: Billy Montolalu | S49: 0729088704 | T49: =J49 -> 7500000 | U49: Rekayasa Perangkat Lunak | X49: FTIB | Y49: ITTelkom Surabaya | Z49: 8140 | AA49: 072019 | AB49: 6680612 | AC49: 728059203 | AD49: Isa Hafidz | AE49: =J49 -> 7500000 | AF49: Teknik Elektro | AI49: FTEIC | AJ49: ITTelkom Surabaya | AK49: 6680633 | AL49: 0717017902 | AM49: Helmy Widyantara | AN49: =J49 -> 7500000 | AO49: Teknologi Informasi | AP49: Sistem Informasi | AR49: FTIB | AS49: ITTelkom Surabaya | BQ49: Proposal | BR49: Laporan Akhir | CG49: Jurnal
A50: 28 | B50: REK. 754/PNLT1/WRI/IV/2020 | C50: 1301/PNLT3/LPPM/VIII/2020 | D50: Robot Sterillisasi Ruang Isolasi/ICU | E50: Penelitian Penugasan | F50: 2020 | G50: 2020 | H50: 3 | J50: 45000000 | K50: Institut Teknologi Telkom Surabaya | L50: 2 | N50: Internal | O50: ID | Q50: 6680633 | R50: Helmy Widyantara | S50: 0717017902 | T50: =J50 -> 45000000 | U50: Teknologi Informasi | V50: Sistem Informasi | X50: FTIB | AB50: 6680685 | AC50: 0721068802 | AD50: Moch.Iskandar Riansyah | AE50: =J50 -> 45000000 | AF50: Teknik Elektro | AI50: FTEIC | AJ50: ITTelkom Surabaya | AK50: 6680683 | AL50: 729088704 | AM50: Billy Montolalu | AN50: =J50 -> 45000000 | AO50: Rekayasa Perangkat Lunak | AR50: FTIB | AS50: ITTelkom Surabaya | BQ50: Proposal | BR50: Laporan Akhir | CG50: HAKI | CI50: Jurnal
A51: 29 | B51: REK. 754/PNLT1/WRI/IV/2020 | C51: 1302/PNLT3/LPPM/VIII/2020 | D51: Swab Chamber untuk Pencegahan Penularan COVID-19 pada Petugas Medis | E51: Penelitian Penugasan | F51: 2020 | G51: 2020 | H51: 12 | I51: Elektronika | J51: 40000000 | K51: Institut Teknologi Telkom Surabaya | N51: Internal | O51: ID | Q51: 6680741 | R51: Hamzah Ulinuha Mustakim | S51: 0727059002 | T51: =J51 -> 40000000 | U51: Teknik Telekomunikasi | X51: FTEIC | AB51: 6680627 | AC51: 0703119301 | AD51: Benazir Imam Arif Muttaqin | AE51: =J51 -> 40000000 | AF51: Teknik Industri | AI51: FTEIC | AJ51: ITTelkom Surabaya | BQ51: Proposal | BR51: Laporan Akhir | CG51: Prototype, HKI
A52: 30 | B52: REK. 754/PNLT1/WRI/IV/2020 | C52: 1303/PNLT3/LPPM/VIII/2020 | D52: Pengembangan portable Non-Invasive Ventilator untuk menghadapi wabah COVID-19 di Jawa Timur, Indonesia | E52: Penelitian Penugasan | F52: 2020 | G52: 2020 | H52: 5 | I52: COVID-19 | J52: 23317000 | K52: Institut Teknologi Telkom Surabaya | L52: 4 | N52: Internal | O52: ID | Q52: 6680651 | R52: Dimas Adiputra | S52: 0725059301 | T52: =J52 -> 23317000 | U52: Teknik Elektro | X52: FTEIC | AB52: 6680633 | AC52: 0717017902 | AD52: Helmy Widyantara | AE52: =J52 -> 23317000 | AF52: Teknologi Informasi | AG52: Sistem Informasi | AI52: FTIB | AJ52: ITTelkom Surabaya | AK52: 6680683 | AL52: 729088704 | AM52: Billy Montolalu | AN52: =J52 -> 23317000 | AO52: Rekayasa Perangkat Lunak | AR52: FTIB | AT52: 6680627 | AU52: 0703119301 | AV52: Benazir Imam Arif Muttaqin | AW52: =J52 -> 23317000 | AX52: Teknik Industri | AZ52: FTEIC | BA52: ITTelkom Surabaya | BB52: 6680612 | BC52: 0728059203 | BD52: Isa Hafidz | BE52: =J52 -> 23317000 | BF52: Teknik Industri | BH52: FTEIC | BI52: ITTelkom Surabaya | BQ52: Proposal | BR52: Laporan Akhir | CG52: Prototype
A53: 31 | B53: REK. 754/PNLT1/WRI/IV/2020 | C53: 1304/PNLT3/LPPM/VIII/2020 | D53: Pengembangan desain APD Face Shield dengan teknologi cetak tridimensi untuk mengatasi kekurangan APD Tenaga Medis COVID-19 | E53: Penelitian Penugasan | F53: 2020 | G53: 2020 | H53: 2 | J53: 2067000 | K53: Institut Teknologi Telkom Surabaya | L53: 6 | N53: Internal | O53: ID | Q53: 6680627 | R53: Benazir Imam Arif Muttaqin | S53: 0703119301 | T53: =J53 -> 2067000 | U53: Teknik Industri | X53: FTEIC | AB53: 6682237 | AC53: 0722069004 | AD53: Dominggo Bayu Baskara | AE53: =J53 -> 2067000 | AF53: Bisnis Digital | AI53: FTIB | AJ53: ITTelkom Surabaya | AK53: 6681051 | AL53: 711069301 | AM53: Rizqa Amelia Zunaidi | AN53: =J53 -> 2067000 | AO53: Teknik Industri | AR53: FTEIC | AT53: 6665306 | AU53: 0703129001 | AV53: Ully Asfari | AW53: =J53 -> 2067000 | AX53: Sistem Informasi | AZ53: FTIB | BA53: ITTelkom Surabaya | BQ53: Proposal | BR53: Laporan Akhir | CG53: Hak Cipta | CI53: Desain Industri
A54: 32 | B54: REK. 941/SAM4/REK/VI/2020 | D54: Cairan Antiseptik untuk Pencegahan Penyebaran Covid -19 | E54: Penelitian kerjasama | F54: 2020 | G54: 2020 | J54: 100000000 | K54: Institut Teknologi Telkom Surabaya | N54: eksternal | O54: ID | Q54: 6680651 | R54: Dimas Adiputra | S54: 0725059301 | T54: =J54 -> 100000000 | U54: Teknik Elektro | X54: FTEIC | AB54: 6805206 | AC54: 8920230021 | AD54: Agus Sulistya | AE54: =J54 -> 100000000 | AF54: Sistem Informasi | AI54: FTIB | AJ54: ITTelkom Surabaya | AT54: 6859016 | AU54: 0727069503 | AV54: Rifki Dwi Putranto | AW54: =J54 -> 100000000 | AX54: Teknik Elektro | AZ54: FTEIC | BA54: ITTelkom Surabaya | BQ54: Proposal | BR54: Laporan Akhir
A55: 33 | B55: REK.1287/PNLT3/REK/VIII/2020 | C55: 1305/PNLT3/LPPM/VIII/2020 | D55: Sterilisasi Udara Pada Ruangan Tertutup Menggunakan Filter Aktif | E55: Penelitian Penugasan | F55: 2020 | G55: 2020 | H55: 3 | J55: 10055000 | K55: Institut Teknologi Telkom Surabaya | N55: Internal | O55: ID | Q55: 6682174 | R55: Khodijah Amiroh | S55: 0708069202 | T55: =J55 -> 10055000 | U55: Teknologi Informasi | X55: FTIB | BQ55: Proposal | BR55: Laporan Akhir | CG55: Prototype | CI55: HAKI
A56: 34 | B56: REK.1287/PNLT3/REK/VIII/2020 | C56: 1306/PNLT3/LPPM/VIII/2020 | D56: Sterilisasi Udara pada AC Untuk Menghadapi Kondisi New Normal | E56: Penelitian Penugasan | F56: 2020 | G56: 2020 | H56: 3 | J56: 9145000 | K56: Institut Teknologi Telkom Surabaya | N56: Internal | O56: ID | Q56: 6680633 | R56: Helmy Widyantara | S56: 0717017902 | T56: =J56 -> 9145000 | U56: Teknologi Informasi | V56: Sistem Informasi | X56: FTIB | BQ56: Proposal | BR56: Laporan Akhir | CG56: Prototype
A57: 35 | B57: REK.1287/PNLT3/REK/VIII/2020 | C57: 1307/PNLT3/LPPM/VIII/2020 | D57: Sterilisasi Udara Portable Untuk Olahragawan Menggunakan Filter Aktif | E57: Penelitian Penugasan | F57: 2020 | G57: 2020 | H57: 3 | J57: 8555000 | K57: Institut Teknologi Telkom Surabaya | N57: Internal | O57: ID | Q57: 6680680 | R57: Bernadus Anggo Seno Aji | S57: 0704039202 | T57: =J57 -> 8555000 | U57: Teknologi Informasi | X57: FTIB | BQ57: Proposal | BR57: Laporan Akhir | CG57: Prototype
A58: 36 | B58: REK. 2031/SAM4/REK/VI/2020 | D58: Penelitian dan Pengembangan Digital Ventilator | E58: Penelitian kerjasama | F58: 2020 | G58: 2020 | J58: 86400000 | K58: Institut Teknologi Telkom Surabaya | N58: eksternal | O58: ID | Q58: 6665306 | R58: Ully Asfari | S58: 0703129001 | T58: =J58 -> 86400000 | U58: Sistem Informasi | X58: FTIB | AK58: 6859016 | AL58: 0727069503 | AM58: Rifki Dwi Putranto | AN58: =J58 -> 86400000 | AO58: Teknik Elektro | AR58: FTEIC | AS58: ITTelkom Surabaya | BQ58: Proposal | BR58: Laporan Akhir
A59: 37 | B59: REK. 925/SAM4/REK/VI/2020 | D59: Crane Pemulasaraan Jenazah Pasien COVID-19 | E59: Penelitian kerjasama | F59: 2020 | G59: 2020 | J59: 200000000 | K59: Institut Teknologi Telkom Surabaya | N59: eksternal | O59: ID | Q59: 6680633 | R59: Helmy Widyantara | S59: 0717017902 | T59: =J59 -> 200000000 | U59: Teknologi Informasi | V59: Sistem Informasi | X59: FTIB | AB59: 6665306 | AC59: 0703129001 | AD59: Ully Asfari | AE59: =T59 -> 200000000 | AF59: Sistem Informasi | AI59: FTIB | AJ59: ITTelkom Surabaya | AT59: 6665306 | AU59: 0703129001 | AV59: Ully Asfari | AW59: =J59 -> 200000000 | AX59: Sistem Informasi | AZ59: FTIB | BA59: ITTelkom Surabaya | BQ59: Proposal | BR59: Laporan Akhir
A61: 1 | B61: REK.086/PNLT1/REK/III/2021 | C61: 997/PNLT1/LPPM/III/2021 | D61: Evaluasi Platform Penjualan Produk Hidroponik dan Aqua ponik | E61: Penelitian Dasar | F61: 2021 | G61: 2021 | H61: 12 | I61: Teknologi Informasi dan Komunikasi | J61: 6750000 | K61: Institut Teknologi Telkom Surabaya | L61: 1 | M61: Penelitian Kompetitif Internal | N61: Internal | O61: ID | P61: ITTelkom Surabaya | Q61: 6681051 | R61: Rizqa Amelia Zunaidi | S61: 0711069301 | T61: =J61 -> 6750000 | U61: Teknik Industri | X61: FTII | Y61: ITTelkom Surabaya | Z61: 8140 | AA61: 072019 | AB61: 6680648 | AC61: 0724089201 | AD61: Hawwin Mardhiana | AE61: =T61 -> 6750000 | AF61: Sistem Informasi | AI61: FTII | AJ61: ITTelkom Surabaya | BQ61: Proposal | BR61: Laporan Akhir | BS61: ADEK DHEA RESMI PURBANTARI | CG61: Jurnal Nasional Terakreditasi | CH61: Accepted | CI61: Seminar Internasional | CJ61: Presented
A62: 2 | B62: REK.086/PNLT1/REK/III/2021 | C62: 998/PNLT1/LPPM/III/2021 | D62: Penerapan Data Mining untuk Menunjang Proses Seleksi Calon Mahasiswa pada ITTelkom Surabaya | E62: Penelitian Dasar | F62: 2021 | G62: 2021 | H62: 10 | I62: Teknologi Informasi dan Komunikasi | J62: 3750000 | K62: Institut Teknologi Telkom Surabaya | L62: 3 | M62: Penelitian Kompetitif Internal | N62: Internal | O62: ID | P62: ITTelkom Surabaya | Q62: 6764236 | R62: Rokhmatul Insani | S62: 0704068902 | T62: =J62 -> 3750000 | U62: Sistem Informasi | X62: FTII | Y62: ITTelkom Surabaya | Z62: 8140 | AA62: 072019 | AB62: 6744406 | AC62: 0709059004 | AD62: Muhammad Nasrullah | AE62: =T62 -> 3750000 | AF62: Sistem Informasi | AI62: FTII | AJ62: ITTelkom Surabaya | AK62: 6681032 | AL62: 0715039004 | AM62: Anfazul Faridatul Azizah | AN62: =T62 -> 3750000 | AO62: Sistem Informasi | AR62: FTII | AS62: ITTelkom Surabaya | BQ62: Proposal | BR62: Laporan Akhir | BS62: BONNIE FERDINAND AKBAR | BU62: EDRIAND IMENS RAYGRANDI | BW62: RAHMAT ANDIKA LAKSANA | CG62: Jurnal Nasional Terakreditasi | CH62: - | CI62: HKI
A63: 3 | B63: REK.086/PNLT1/REK/III/2021 | C63: 999/PNLT1/LPPM/III/2021 | D63: Strategi Optimalisasi Kegiatan Petani Garam dan Peningkatan Produktivitas Garam dengan Pendekatan Simulasi Sistem Dinamik (Studi kasus: Kawasan Tambak Cemandi Sidoarjo) | E63: Penelitian Dasar | F63: 2021 | G63: 2021 | H63: 10 | I63: Kemaritiman | J63: 7000000 | K63: Institut Teknologi Telkom Surabaya | L63: 1 | M63: Penelitian Kompetitif Internal | N63: Internal | O63: ID | P63: ITTelkom Surabaya | Q63: 6680648 | R63: Hawwin Mardhiana | S63: 0724089201 | T63: =J63 -> 7000000 | U63: Sistem Informasi | X63: FTII | Y63: ITTelkom Surabaya | Z63: 8140 | AA63: 072019 | AB63: 6681051 | AC63: 0711069301 | AD63: Rizqa Amelia Zunaidi | AE63: =T63 -> 7000000 | AF63: Teknik Industri | AI63: FTII | AJ63: ITTelkom Surabaya | AK63: 6680627 | AL63: 0703119301 | AM63: Benazir Imam Arif Muttaqin | AN63: =T63 -> 7000000 | AO63: Teknik Industri | AR63: FTII | AS63: ITTelkom Surabaya | BQ63: Proposal | BR63: Laporan Akhir | BS63: SITI AMINAH | BU63: WIDAYATULLAH RA | BW63: ACHMAD DAFA FIRDAUS | CG63: - | CH63: - | CI63: -
A64: 4 | B64: REK.086/PNLT1/REK/III/2021 | C64: 1000/PNLT1/LPPM/III/2021 | D64: Pakan Ikan Otomatis Menggunakan Fuzzy Logic Berbasis IoT | E64: Penelitian Dasar | F64: 2021 | G64: 2021 | H64: 10 | I64: Pangan-Pertanian | J64: 6995000 | K64: Institut Teknologi Telkom Surabaya | L64: 3 | M64: Penelitian Kompetitif Internal | N64: Internal | O64: ID | P64: ITTelkom Surabaya | Q64: 6680680 | R64: Bernadus Anggo Seno Aji | S64: 0704039202 | T64: =J64 -> 6995000 | U64: Teknologi Informasi | X64: FTII | Y64: ITTelkom Surabaya | Z64: 8140 | AA64: 072019 | AB64: 6681205 | AC64: 0705109002 | AD64: Oktavia Ayu Permata | AE64: =T64 -> 6995000 | AF64: Teknologi Informasi | AI64: FTII | AJ64: ITTelkom Surabaya | AK64: 6680664 | AL64: 0715128708 | AM64: Farah Zakiyah Rahmanti | AN64: =T64 -> 6995000 | AO64: Teknologi Informasi | AR64: FTII | AS64: ITTelkom Surabaya | BQ64: Proposal | BR64: Laporan Akhir | BS64: CHINTYA TRIBHUANA UTAMI | BU64: BAYU KRISNA MUKTI | CG64: Jurnal Nasional S3 | CH64: -
A65: 5 | B65: REK.086/PNLT1/REK/III/2021 | C65: 1001/PNLT1/LPPM/III/2021 | D65: Analisis Efektivitas Pembelajaran Daring Pada Anak Usia Sekolah Dasar Hingga Perguruan Tinggi | E65: Penelitian Dasar | F65: 2021 | G65: 2021 | H65: 10 | I65: Teknologi Informasi dan Komunikasi | J65: 6316000 | K65: Institut Teknologi Telkom Surabaya | L65: 3 | M65: Penelitian Kompetitif Internal | N65: Internal | O65: ID | P65: ITTelkom Surabaya | Q65: 6744406 | R65: Muhammad Nasrullah | S65: 0709059004 | T65: =J65 -> 6316000 | U65: Sistem Informasi | X65: FTII | Y65: ITTelkom Surabaya | Z65: 8140 | AA65: 072019 | AB65: 6764236 | AC65: 0704068902 | AD65: Rokhmatul Insani | AE65: =T65 -> 6316000 | AF65: Sistem Informasi | AI65: FTII | AJ65: ITTelkom Surabaya | AK65: 6680634 | AL65: 0725059004 | AM65: Noerma Pudji Istyanto | AN65: =T65 -> 6316000 | AO65: Sistem Informasi | AR65: FTII | AS65: ITTelkom Surabaya | BQ65: Proposal | BR65: Laporan Akhir | BS65: RIO ARMANDO | BU65: RAIHAN FEBRIANTO GRAHADI | BW65: NATASYA AMELIA SUKMAWATI | CG65: Jurnal Nasional Terakreditasi | CH65: Submitted | CI65: Seminar Internasional | CJ65: Submit Abstrak
A66: 6 | B66: REK.086/PNLT1/REK/III/2021 | C66: 1004/PNLT1/LPPM/III/2021 | D66: Model Prediksi Point of Interest Berdasarkan Data Log Perjalanan Taksi | E66: Penelitian Dasar | F66: 2021 | G66: 2021 | H66: 10 | I66: Teknologi Informasi dan Komunikasi | J66: 6750000 | K66: Institut Teknologi Telkom Surabaya | L66: 3 | M66: Penelitian Kompetitif Internal | N66: Internal | O66: ID | P66: ITTelkom Surabaya | Q66: 6680687 | R66: Wahyu Andy Prastyabudi | S66: 0702048705 | T66: =J66 -> 6750000 | U66: Teknik Industri | X66: FTE | Y66: ITTelkom Surabaya | Z66: 8140 | AA66: 072019 | AB66: 6778837 | AC66: 0711039403 | AD66: Muhammad Dzulfikar Fauzi | AE66: =T66 -> 6750000 | AF66: Informatika | AI66: FTII | AJ66: ITTelkom Surabaya | BQ66: Proposal | BR66: Laporan Akhir | BS66: ARDA ERICO YUDA | BU66: AYU PREMA LAKSMI | CG66: Publikasi Jurnal Internasional | CH66: - | CI66: -
A67: 7 | B67: REK.086/PNLT1/REK/III/2021 | C67: 1005/PNLT1/LPPM/III/2021 | D67: Segmentasi Jalan Raya dengan CNN Unet untuk Asisten Pengemudi | E67: Penelitian Dasar | F67: 2021 | G67: 2021 | H67: 12 | I67: ITTS: Transportasi | J67: 6800000 | K67: Institut Teknologi Telkom Surabaya | L67: 3 | M67: Penelitian Kompetitif Internal | N67: Internal | O67: ID | P67: ITTelkom Surabaya | Q67: 6680626 | R67: Ardian Yusuf Wicaksono | S67: 0727099201 | T67: =J67 -> 6800000 | U67: Rekayasa Perangkat Lunak | X67: FTII | Y67: ITTelkom Surabaya | Z67: 8140 | AA67: 072019 | AB67: 6680628 | AC67: 0730058702 | AD67: Fidi Wincoko Putro | AE67: =T67 -> 6800000 | AF67: Rekayasa Perangkat Lunak | AI67: FTII | AJ67: ITTelkom Surabaya | AK67: 6767777 | AL67: 0713059501 | AM67: Ahmad Wali Satria | AN67: =T67 -> 6800000 | AO67: Informatika | AR67: FTII | AS67: ITTelkom Surabaya | BQ67: Proposal | BR67: Laporan Akhir | BS67: MOCH YUSUF FAISAL AKBAR ANWARI | BU67: SYAHFRIL NIZAMMUDIN | BW67: AULIYA RAHMAN PAKARTI | CG67: Jurnal Nasional S3 | CH67: - | CI67: -
A68: 8 | B68: REK.086/PNLT1/REK/III/2021 | C68: 1006/PNLT1/LPPM/III/2021 | D68: Analisis Pengaruh Adopsi Teknologi Big Data terhadap Keunggulan Bersaing dan Performansi pada UMKM (Study case: UMKM Kota Surabaya) | E68: Penelitian Dasar | F68: 2021 | G68: 2021 | H68: 12 | I68: Teknologi Informasi dan Komunikasi | J68: 6750000 | K68: Institut Teknologi Telkom Surabaya | L68: 3 | M68: Penelitian Kompetitif Internal | N68: Internal | O68: ID | P68: ITTelkom Surabaya | Q68: 6658545 | R68: Ayu Endah Wahyuni | S68: 0401078801 | T68: =J68 -> 6750000 | U68: Teknik Industri | X68: FTII | Y68: ITTelkom Surabaya | Z68: 8140 | AA68: 072019 | AB68: 6658545 | AC68: 0401078801 | AD68: Ayu Endah Wahyuni | AE68: =T68 -> 6750000 | AF68: Teknik Industri | AI68: FTII | AJ68: ITTelkom Surabaya | AK68: 6682237 | AL68: 0722069004 | AM68: Dominggo Bayu Baskara | AN68: =T68 -> 6750000 | AO68: Bisnis Digital | AR68: FTII | AS68: ITTelkom Surabaya | BQ68: Proposal | BR68: Laporan Akhir | BS68: ABIYYAS DAFFA SURYADI | BU68: MUHAMMAD HANIF RAIHAN | BW68: YAKFI ZAMZAMI ACHMAD | CG68: Jurnal Nasional Terakreditasi | CH68: Submitted | CI68: Seminar Internasional
A69: 9 | B69: REK.086/PNLT1/REK/III/2021 | C69: 1009/PNLT1/LPPM/III/2021 | D69: Hydroponic Monitoring System Based On LoRa Technology | E69: Penelitian Dasar | F69: 2021 | G69: 2021 | H69: 8 | I69: Teknologi Informasi dan Komunikasi | J69: 6750000 | K69: Institut Teknologi Telkom Surabaya | L69: 2 | M69: Penelitian Kompetitif Internal | N69: Internal | O69: ID | P69: ITTelkom Surabaya | Q69: 6681205 | R69: Oktavia Ayu Permata | S69: 0705109002 | T69: =J69 -> 6750000 | U69: Teknologi Informasi | X69: FTII | Y69: ITTelkom Surabaya | Z69: 8140 | AA69: 072019 | AB69: 6680664 | AC69: 0715128708 | AD69: Farah Zakiyah Rahmanti | AE69: =T69 -> 6750000 | AF69: Teknologi Informasi | AI69: FTII | AJ69: ITTelkom Surabaya | AK69: 6680680 | AL69: 0704039202 | AM69: Bernadus Anggo Seno Aji | AN69: =T69 -> 6750000 | AO69: Teknologi Informasi | AR69: FTII | AS69: ITTelkom Surabaya | BQ69: Proposal | BR69: Laporan Akhir | BS69: RISKA APRILIA | BU69: GALIH DIMAS PRASTOWO | CG69: Publikasi Jurnal Internasional | CH69: - | CI69: HKI
A70: 10 | B70: REK.086/PNLT1/REK/III/2021 | C70: 1010/PNLT1/LPPM/III/2021 | D70: Integrasi IT dengan Proses Bisnis dengan Studi Kasus di Institut Teknologi Telkom Surabaya | E70: Penelitian Dasar | F70: 2021 | G70: 2021 | H70: 10 | I70: Teknologi Informasi dan Komunikasi | J70: 6500000 | K70: Institut Teknologi Telkom Surabaya | L70: 1 | M70: Penelitian Kompetitif Internal | N70: Internal | O70: ID | P70: ITTelkom Surabaya | Q70: 6680623 | R70: Yupit Sudianto | S70: 0721088602 | T70: =J70 -> 6500000 | U70: Sistem Informasi | X70: FTII | Y70: ITTelkom Surabaya | Z70: 8140 | AA70: 072019 | AB70: 6680626 | AC70: 0727099201 | AD70: Ardian Yusuf Wicaksono | AE70: =T70 -> 6500000 | AF70: Rekayasa Perangkat Lunak | AI70: FTII | AJ70: ITTelkom Surabaya | AK70: 6787821 | AL70: 0707029303 | AM70: Desinta Nur Rachmaniar | AN70: =T70 -> 6500000 | AO70: Teknik Logistik | AR70: FTE | AS70: ITTelkom Surabaya | BQ70: Proposal | BR70: Laporan Akhir | BS70: ARDA ERICO YUDA | BU70: ARDANU ADANG SAPUTRA | BW70: REKSA ALDIAN RAHMANDY PUTRA | CG70: Jurnal Nasional S4 | CH70: - | CI70: -
A71: 11 | B71: REK.086/PNLT1/REK/III/2021 | C71: 1008/PNLT1/LPPM/III/2021 | D71: Evaluasi Efektivitas Penerapan metode Pengenalan marka Jalan Raya Untuk Mengenali Rel Listrik pada Jalan Raya Berlistrik | E71: Penelitian Dasar | F71: 2021 | G71: 2021 | H71: 10 | I71: ITTS: Transportasi | J71: 6750000 | K71: Institut Teknologi Telkom Surabaya | L71: 2 | M71: Penelitian Kompetitif Internal | N71: Internal | O71: ID | P71: ITTelkom Surabaya | Q71: 6682794 | R71: Pangestu Widodo | S71: 0721058310 | T71: =J71 -> 6750000 | U71: Rekayasa Perangkat Lunak | X71: FTII | Y71: ITTelkom Surabaya | Z71: 8140 | AA71: 072019 | AB71: 6778837 | AC71: 0711039403 | AD71: Muhammad Dzulfikar Fauzi | AE71: =T71 -> 6750000 | AF71: Informatika | AI71: FTII | AJ71: ITTelkom Surabaya | BQ71: Proposal | BR71: Laporan Akhir | BS71: MOCH YUSUF FAISAL AKBAR ANWARI | CG71: Jurnal Nasional Terakreditasi | CH71: - | CI71: -
A72: 12 | B72: REK.086/PNLT1/REK/III/2021 | C72: 1011/PNLT1/LPPM/III/2021 | D72: Monitoring Daya Cargo Elevator berbasis IoT | E72: Penelitian Terapan | F72: 2021 | G72: 2021 | H72: 6 | I72: ITTS: Sistem Logistik Cerdas | J72: 12137500 | K72: Institut Teknologi Telkom Surabaya | L72: 3 | M72: Penelitian Kompetitif Internal | N72: Internal | O72: ID | P72: ITTelkom Surabaya | Q72: 6680612 | R72: Isa Hafidz | S72: 0728059203 | T72: =J72 -> 12137500 | U72: Teknik Elektro | X72: FTE | Y72: ITTelkom Surabaya | Z72: 8140 | AA72: 072019 | AB72: 6680683 | AC72: 0729088704 | AD72: Billy Montolalu | AE72: =T72 -> 12137500 | AF72: Teknik Kopmputer | AI72: FTE | AJ72: ITTelkom Surabaya | AK72: 6859016 | AL72: 0727069503 | AM72: Rifki Dwi Putranto | AN72: =T72 -> 12137500 | AO72: Teknik Elektro | AR72: FTE | AS72: ITTelkom Surabaya | BQ72: Proposal | BR72: Laporan Akhir | BS72: ALDHITIANSYAH PUTRA | BU72: MOCHAMMAD RAFLY PUTRA DAFFALDI | BV72: Teknik Elektro,FTEIC, ITTelkom Surabaya | BW72: DINDA KARISMA ULFA | BX72: Teknik Komputer, FTEIC, ITTelkom Surabaya | CG72: JURNAL NASIONAL TERINDEKS | CH72: Submitted | CI72: -
A73: 13 | B73: REK.086/PNLT1/REK/III/2021 | C73: 1012/PNLT1/LPPM/III/2021 | D73: Smart BLDC Motor Control for Smooth Efficient Initial Movement of an Electric Vehicle | E73: Penelitian Terapan | F73: 2021 | G73: 2021 | H73: 12 | I73: ITTS: Transportasi | J73: 16750000 | K73: Institut Teknologi Telkom Surabaya | L73: 5 | M73: Penelitian Kompetitif Internal | N73: Internal | O73: ID | P73: ITTelkom Surabaya | Q73: 6680651 | R73: Dimas Adiputra | S73: 0725059301 | T73: =J73 -> 16750000 | U73: Teknik Elektro | X73: FTE | Y73: ITTelkom Surabaya | Z73: 8140 | AA73: 072019 | AB73: 6682794 | AC73: 0721058310 | AD73: Pangestu Widodo | AE73: =T73 -> 16750000 | AF73: Rekaqyasa Perangkat Lunak | AI73: FTII | AJ73: ITTelkom Surabaya | BQ73: Proposal | BR73: Laporan Akhir | BS73: Aldo Juan Widodo | BT73: Teknik Elektro, FTEIC, ITTelkom Surabaya | BU73: YOSEFAN ALFEUS BAYUAJI | BV73: Teknik Elektro,FTEIC, ITTelkom Surabaya | BW73: NADIA DINDA PRATAMA PUTRI_x000D_ | BX73: Teknik Elektro,FTEIC, ITTelkom Surabaya | CG73: JURNAL NASIONAL TERINDEKS | CH73: Submitted | CI73: HAKI Prototype | CJ73: Submitted
A74: 14 | B74: REK.086/PNLT1/REK/III/2021 | C74: 1014/PNLT1/LPPM/III/2021 | D74: Desain dan Verifikasi keamanan Sistem Manajemen Baterai sebagai Pendukung Kendaraan Listrik | E74: Penelitian Terapan | F74: 2021 | G74: 2021 | H74: 12 | I74: ITTS: Transportasi | J74: 17000000 | K74: Institut Teknologi Telkom Surabaya | L74: 3 | M74: Penelitian Kompetitif Internal | N74: Internal | O74: ID | P74: ITTelkom Surabaya | Q74: 6680708 | R74: Lora Khaula Amifia | S74: 0706069201 | T74: =J74 -> 17000000 | U74: Teknik Elektro | X74: FTE | Y74: ITTelkom Surabaya | Z74: 8140 | AA74: 072019 | AB74: 6680685 | AC74: 0721068802 | AD74: Moch. Iskandar Riansyah | AE74: =T74 -> 17000000 | AF74: Teknik Elektro | AI74: FTE | AJ74: ITTelkom Surabaya | AK74: 6680627 | AL74: 0703119301 | AM74: Benazir Imam Arif Muttaqin | AN74: =T74 -> 17000000 | AO74: Teknik Induustri | AR74: FTE | AS74: ITTelkom Surabaya | BQ74: Proposal | BR74: Laporan Akhir | BS74: Adellia Puspita Ratri_x000D_ | BT74: Teknik Elektro, FTEIC, ITTelkom Surabaya | BU74: Bagas Wahyu Prakoso_x000D_ | BV74: Teknik Elektro, FTEIC, ITTelkom Surabaya | BW74: Firman Adi Rifansyah | BX74: Teknik Elektro, FTEIC, ITTelkom Surabaya | CG74: Jurnal Internasional Terindeks | CH74: In Review | CI74: Jurnal Nasional S2 | CJ74: Accepted
A75: 15 | B75: REK.086/PNLT1/REK/III/2021 | C75: 1015/PNLT1/LPPM/III/2021 | D75: Desain Antena Phased Array untuk Radar Kendaraan Otonom | E75: Penelitian Terapan | F75: 2021 | G75: 2021 | H75: 12 | I75: ITTS: Transportasi | J75: 17000000 | K75: Institut Teknologi Telkom Surabaya | L75: 6 | M75: Penelitian Kompetitif Internal | N75: Internal | O75: ID | P75: ITTelkom Surabaya | Q75: 6680645 | R75: Walid Maulana Hadiansyah | S75: 0713108902 | T75: =J75 -> 17000000 | U75: Teknik Telekomunikasi | X75: FTE | Y75: ITTelkom Surabaya | Z75: 8140 | AA75: 072019 | AB75: 6724784 | AC75: 0722119101 | AD75: Fannush Shofi Akbar | AE75: =T75 -> 17000000 | AF75: Teknik Telekomunikasi | AI75: FTE | AJ75: ITTelkom Surabaya | AK75: 6680741 | AL75: 0727059002 | AM75: Hamzah Ulinuha Mustakim | AN75: =T75 -> 17000000 | AO75: Teknik Telekomunikasi | AR75: FTE | AS75: ITTelkom Surabaya | BQ75: Proposal | BR75: Laporan Akhir | CG75: 1 Jurnal Terindeks | CH75: Submitted | CI75: -
A76: 16 | B76: REK.086/PNLT1/REK/III/2021 | C76: 1017/PNLT1/LPPM/III/2021 | D76: Simultanous Localization and Mapping pada Robot Cerdas Pemadam Kebakaran di Gudang | E76: Penelitian Terapan | F76: 2021 | G76: 2021 | H76: 12 | I76: ITTS: Kebencanaan | J76: 16976100 | K76: Institut Teknologi Telkom Surabaya | L76: 4 | M76: Penelitian Kompetitif Internal | N76: Internal | O76: ID | P76: ITTelkom Surabaya | Q76: 258471 | R76: Susijanto Tri Rasmana | S76: 0727097302 | T76: =J76 -> 16976100 | U76: Teknik Elektro | X76: FTE | Y76: ITTelkom Surabaya | Z76: 8140 | AA76: 072019 | AB76: 6680641 | AC76: 0714029301 | AD76: Ardiansyah Al farouq | AE76: =T76 -> 16976100 | AF76: Teknik Kopmputer | AI76: FTE | AJ76: ITTelkom Surabaya | BQ76: Proposal | BR76: Laporan Akhir | BS76: Moch Syamfallah Anwar | BT76: Teknik Elektro, FTEIC, ITTelkom Surabaya | BU76: Verina Elista Malik | BV76: Teknik Elektro, FTEIC, ITTelkom Surabaya | BW76: Rizqika Ibnu Khattab | CG76: Jurnal Nasional Terakreditasi Sinta | CH76: - | CI76: HAKI (Hak Cipta)
A77: 17 | B77: REK.086/PNLT1/REK/III/2021 | C77: 1018/PNLT1/LPPM/III/2021 | D77: Built in Scale For Estimating Truck Capacity | E77: Penelitian Terapan | F77: 2021 | G77: 2021 | H77: 12 | I77: ITTS: Transportasi | J77: 14500000 | K77: Institut Teknologi Telkom Surabaya | L77: 4 | M77: Penelitian Kompetitif Internal | N77: Internal | O77: ID | P77: ITTelkom Surabaya | Q77: 6680618 | R77: Rahaditya Dimas Prihadianto | S77: 0725059202 | T77: =J77 -> 14500000 | U77: Teknik Industri | X77: FTII | Y77: ITTelkom Surabaya | Z77: 8140 | AA77: 072019 | AB77: 6680651 | AC77: 0725059301 | AD77: Dimas Adiputra | AE77: =T77 -> 14500000 | AF77: Teknik Elektro | AI77: FTE | AJ77: ITTelkom Surabaya | AK77: 6658545 | AL77: 0401078801 | AM77: Ayu Endah Wahyuni | AN77: =T77 -> 14500000 | AO77: Teknik Industri | AR77: FTE | AS77: ITTelkom Surabaya | BQ77: Proposal | BR77: Laporan Akhir | BS77: SULAIMAN ASHARI | BU77: M. BAGUS INDRASTATA_x000D_ | CG77: Jurnal Nasional Terakreditasi Sinta 4_x000D_ | CH77: - | CI77: Prosiding Seminar Nasional
A78: 18 | B78: REK.086/PNLT1/REK/III/2021 | C78: 1019/PNLT1/LPPM/III/2021 | D78: Pemodelan Machine Learning untuk Analisis Kredit Pembayaran Biaya Kuliah | E78: Penelitian Terapan | F78: 2021 | G78: 2021 | H78: 12 | I78: ITTS: Teknologi Informasi dan Komunikasi | J78: 16750000 | K78: Institut Teknologi Telkom Surabaya | L78: 3 | M78: Penelitian Kompetitif Internal | N78: Internal | O78: ID | P78: ITTelkom Surabaya | Q78: 6680726 | R78: Arliyanti Nurdin | S78: 0719069101 | T78: =J78 -> 16750000 | U78: Teknologi Informasi | X78: FTE | Y78: ITTelkom Surabaya | Z78: 8140 | AA78: 072019 | AB78: 6681051 | AC78: 0711069301 | AD78: Rizqa Amelia Zunaidi | AE78: =T78 -> 16750000 | AF78: Teknik Industri | AI78: FTE | AJ78: ITTelkom Surabaya | AM78: Rasyidi Faiz Akbar | BQ78: Proposal | BR78: Laporan Akhir | BS78: MUHAMMAD ARKAN FAUZAN WICAKSONO | BU78: DONI FRIANDY | BW78: AGI LOBITA JAPTARA MARTADINATA | CG78: Jurnal Nasional Terakreditasi | CH78: - | CI78: HKI
A79: 19 | B79: REK.086/PNLT1/REK/III/2021 | C79: 1021/PNLT1/LPPM/III/2021 | D79: Feasibility Study for Conversion of Diesel Powered into Electric Truck | E79: Penelitian Terapan | F79: 2021 | G79: 2021 | H79: 12 | I79: ITTS: Transportasi | J79: 13980000 | K79: Institut Teknologi Telkom Surabaya | L79: 3 | M79: Penelitian Kompetitif Internal | N79: Internal | O79: ID | P79: ITTelkom Surabaya | Q79: 6680627 | R79: Benazir Imam Arif Muttawin | S79: 0703119301 | T79: =J79 -> 13980000 | U79: Teknik Industri | X79: FTII | Y79: ITTelkom Surabaya | Z79: 8140 | AA79: 072019 | AB79: 6682237 | AC79: 0722069004 | AD79: Dominggo Bayu Baskara | AE79: =T79 -> 13980000 | AF79: Bisnis Digital | AI79: FTII | AJ79: ITTelkom Surabaya | BQ79: Proposal | BR79: Laporan Akhir | BS79: TERRESA INDRAJANI KUSUMA | BU79: HENDRAWAN WIDIANTO | BW79: MUHAMMAD MIFTAHUL ABIDIN | BY79: YUDITH IQBAL DIKA PERMANA | CG79: 1 Jurnal Nasional S3; 1 Prosiding Internasional_x000D_ | CH79: Published | CI79: 1 Blueprint KI
A80: 20 | B80: REK.086/PNLT1/REK/III/2021 | C80: 1825/PNLT1/LPPM/III/2021 | D80: Optimalisasi Daya Turbin Angin Proses Vertikal Menggunakan Sistem Kendli Adaptif Pada Diffusert Penyearah Angin | E80: Penelitian Terapan | F80: 2021 | G80: 2021 | H80: 24 | I80: Nasional: Energi-Energi Baru dan Terbarukan | J80: 17000000 | K80: Institut Teknologi Telkom Surabaya | L80: 3 | M80: Penelitian Kompetitif Internal | N80: Internal | O80: ID | P80: ITTelkom Surabaya | Q80: 6680633 | R80: Helmy Widyantara | S80: 0717017902 | T80: =J80 -> 17000000 | U80: Teknologi Informasi | V80: Sistem Informasi | X80: FTII | Y80: ITTelkom Surabaya | Z80: 8140 | AA80: 072019 | BQ80: Proposal | BR80: Laporan Akhir | CG80: Prototype | CH80: - | CI80: Jurnal Internasional | CJ80: Submitted
A81: 21 | B81: REK.086/PNLT1/REK/III/2021 | C81: 1020/PNLT1/LPPM/III/2021 | D81: Desain dan Impelementasi Sistem Informasi Manajemen Cerdas Kerja Praktik dan Magang Mahasiswa dengan Decision Tree (Study kasus: ITTelkom Surabaya) | E81: Penelitian Terapan | F81: 2021 | G81: 2021 | H81: 12 | I81: ITTS: Teknologi Informasi dan Komunikasi | J81: 14500000 | K81: Institut Teknologi Telkom Surabaya | L81: 6 | M81: Penelitian Kompetitif Internal | N81: Internal | O81: ID | P81: ITTelkom Surabaya | Q81: 6680628 | R81: Fidi Wincoko Putro | S81: 0730058702 | T81: =J81 -> 14500000 | U81: Rekayasa Perangkat Lunak | X81: FTII | Y81: ITTelkom Surabaya | Z81: 8140 | AA81: 072019 | AB81: 6682174 | AC81: 0708069202 | AD81: Khodijah Amiroh | AE81: =T81 -> 14500000 | AF81: Teknologi Informasi | AI81: FTII | AJ81: ITTelkom Surabaya | AK81: 6764236 | AL81: 0704068902 | AM81: Rokhmatul Insani | AN81: =T81 -> 14500000 | AO81: Sistem Informasi | AR81: FTII | AS81: ITTelkom Surabaya | BQ81: Proposal | BR81: Laporan Akhir | BS81: ZULKARNAIN (1201190004) | BU81: AQIL MUSTAQIM (1201190017) | BW81: MUHAMAD IQBAL MAULANA (1202190023) | CG81: Jurnal Nasional S3; HAKI | CH81: - | CI81: Seminar Internasional
A82: 22 | B82: REK.086/PNLT1/REK/III/2021 | C82: 1024/PNLT1/LPPM/III/2021 | D82: Hybrid Renewble Energy and Smart Management for Office Building | E82: Penelitian Pengembangan | F82: 2021 | G82: 2021 | H82: 6 | I82: Nasional: Energi-Energi Baru dan Terbarukan | J82: 23600000 | K82: Institut Teknologi Telkom Surabaya | L82: 6 | M82: Penelitian Kompetitif Internal | N82: Internal | O82: ID | P82: ITTelkom Surabaya | Q82: 6680683 | R82: Billy Montolalu | S82: 0729088704 | T82: =J82 -> 23600000 | U82: Teknik Komputer | X82: FTE | Y82: ITTelkom Surabaya | Z82: 8140 | AA82: 072019 | AB82: 6680651 | AC82: 0725059301 | AD82: Dimas Adiputra | AE82: =T82 -> 23600000 | AF82: Teknik Elektro | AI82: FTE | AJ82: ITTelkom Surabaya | AK82: 6859016 | AL82: 0727069503 | AM82: Rifki Dwi Putranto | AN82: =T82 -> 23600000 | AO82: Teknik Elektro | AR82: FTE | AS82: ITTelkom Surabaya | AT82: 6680612 | AU82: 728059203 | AV82: Isa Hafidz | AW82: =T82 -> 23600000 | AX82: Teknik Elektro | AZ82: FTEIC | BA82: ITTelkom Surabaya | BQ82: Proposal | BR82: Laporan Akhir | BS82: Muh Syahwal M | BU82: Jesica F Nura | BW82: Royzaldo Aser Elegius Logo | CG82: Submit Jurnal Ber-ISSN | CH82: - | CI82: -
A83: 23 | B83: REK.136/PNLT1/REK/V/2021 | C83: 1275/PNLT1/LPPM/IV/2021 | D83: Pembuatan Prototipe Anjungan Kesehatan mandiri | E83: Penelitian Kerjasama Institusi | F83: 2021 | G83: 2021 | H83: 8 | I83: Nasional: Kesehatan-Obat | J83: 40000000 | K83: Institut Teknologi Telkom Surabaya | L83: 4 | M83: Penelitian Kemitraan | N83: Internal | O83: ID | P83: ITTelkom Surabaya | Q83: 258471 | R83: Susijanto Tri Rasmana | S83: 0727097302 | T83: =J83 -> 40000000 | U83: Teknik Elektro | X83: FTE | Y83: ITTelkom Surabaya | Z83: 8140 | AA83: 072019 | BQ83: Proposal | BR83: Laporan Akhir | BS83: Nova Herlina Mila Soetarno | BT83: Teknik Elektro, FTEIC, ITTelkom Surabaya | BU83: Muhammad Dwi Hariyanto | BV83: Teknik Elektro, FTEIC, ITTelkom Surabaya | BW83: Andi Nur Halisyah | BX83: Teknik Elektro, FTEIC, ITTelkom Surabaya | BY83: Riyo Oktavian Pradana | BZ83: Teknik Elektro, FTEIC, ITTelkom Surabaya | CA83: Robin Addwiyansyah Alvaro | CB83: Teknik Elektro, FTEIC, ITTelkom Surabaya | CC83: Bagas Wahyu Prakoso | CD83: Teknik Elektro, FTEIC, ITTelkom Surabaya | CG83: Anjungan Pemeriksa Kesehatan | CH83: Submitted | CI83: PATEN | CJ83: Diterima
A84: 24 | B84: REK.136/PNLT1/REK/V/2021 | C84: - | D84: Implementasi Java Interface Pada Anjungan Kesehatan Mandiri | E84: Penelitian Kerjasama Institusi | F84: 2021 | G84: 2021 | H84: 12 | I84: Nasional: Kesehatan-Obat | J84: 40000000 | K84: Institut Teknologi Telkom Surabaya | L84: 4 | M84: Penelitian Kemitraan | N84: Internal | O84: ID | P84: ITTelkom Surabaya | Q84: 6680683 | R84: Billy Montolalu | S84: 0729088704 | T84: =J84 -> 40000000 | U84: Teknik Komputer | X84: FTE | Y84: ITTelkom Surabaya | Z84: 8140 | AA84: 072019 | AB84: 6778837 | AC84: 0711039403 | AD84: Muhammad Dzulfikar Fauzi | AE84: =T84 -> 40000000 | AF84: Informatika | AI84: FTII | AJ84: ITTelkom Surabaya | AK84: 6767777 | AL84: 0713059501 | AM84: Ahmad Wali Satria Bhari Johan | AN84: =T84 -> 40000000 | AO84: Informatika | AR84: FTII | AS84: ITTelkom Surabaya | BQ84: Proposal | BR84: Laporan Akhir | BS84: Dimas Bagas Wicaksono | BT84: Teknik Elektro, FTEIC, ITTelkom Surabaya | BU84: Fathur Alfariz | BV84: Teknik Elektro, FTEIC, ITTelkom Surabaya | BW84: Adellia Puspita Ratri | BX84: Teknik Elektro, FTEIC, ITTelkom Surabaya | BY84: Getsemani Adi Bagus Maranata Hartono | BZ84: Teknik Elektro, FTEIC, ITTelkom Surabaya | CA84: Abdullaoh Hamid Nushfi | CB84: Teknik Elektro, FTEIC, ITTelkom Surabaya | CD84: Teknik Elektro, FTEIC, ITTelkom Surabaya | CG84: Prototipe perangkat lunak berupa program untukmembaca alat ukur, mengolah data pengukuran, menyajikan informasi ke perangkat luara, dan transferdata ke database rumah sakit. | CH84: - | CI84: Publikasi ilmiah yang diterbitkan pada jurnal nasionalatau internasional terindek
A85: 25 | B85: REK.139/PNLT1/REK/V/2021 | C85: 1274/PNLT1/LPPM/V/2021 | D85: Perbaikan Sustem I-gracias Institut Teknologi Telkom Purwokerto dengan Metode Quality Function Deployment (QFD) | E85: Penelitian Kerjasama Perguruan Tinggi (PEKERTI) | F85: 2021 | G85: 2021 | H85: 8 | I85: Teknologi Informasi dan Komunikasi | J85: =8103000+12474000 -> 20577000 | K85: Institut Teknologi Telkom Surabaya | L85: 2 | N85: Internal | Q85: 6070770 | R85: Achmad Zaki Yamani | S85: 0613118701 | T85: =J85 -> 20577000 | U85: Teknik Industri | Y85: ITTelkom Purwokerto | Z85: 228 | AA85: 062003 | AB85: 6699792 | AC85: 0615089201 | AD85: Dina Rachmawaty | AF85: Teknik Industri | AJ85: ITTelkom Purwokerto | AK85: 6753293 | AL85: 0601049501 | AM85: Famila Dwi Winati | AO85: Teknik Industri | AS85: ITTelkom Purwokerto | AT85: 6680648 | AU85: 0724089201 | AV85: Hawwin Mardhiana | AW85: =J85 -> 20577000 | AX85: Sistem Informasi | AZ85: FTII | BA85: ITTelkom Surabaya | BQ85: Proposal | BR85: Laporan Akhir | CG85: 2 Jurnal Nasional Terakreditasi S2 | CH85: Submitted – In review | CI85: Seminar Internasional | CJ85: Accepted, Presented
A86: 26 | B86: REK.001/PNLT1/REK/I/2021 | C86: 1273/PNLT1/LPPM/I/2021 | D86: Pengembangan Metode Advanced Feature Selection Untuk Sensor Array Optimization Pada Electronic Nose (Tel U) | E86: Penelitian Kerjasama Perguruan Tinggi (PEKERTI) | F86: 2021 | G86: 2021 | H86: 12 | I86: - | J86: 40000000 | K86: Institut Teknologi Telkom Surabaya | L86: 4 | N86: Internal | Q86: 6680622 | R86: Dewi RahmawatI | S86: 0709039401 | T86: =J86 -> 40000000 | U86: Rekayasa Perangkat Lunak | X86: FTII | Y86: ITTelkom Surabaya | Z86: 8140 | AA86: 072019 | BQ86: Proposal | BR86: Laporan Akhir | BS86: Zaki Al Faridzi | BU86: Muhammad Abizard Al Thareq | BW86: Indah Mayang Sari | CG86: Jurnal Internasional | CH86: - | CI86: Prosiding Internasional
A87: 27 | B87: REK.193/PNLT1/REK/IX/2021 | C87: 1660/PNLT1/LPPM/X/2021 | D87: Mengkonstruksi Defini dari Startup (Sebuah Kajian Systematic Literatur Review) | E87: Penelitian Kerjasama Perguruan Tinggi (PEKERTI) | F87: 2021 | G87: 2021 | H87: 11 | I87: - | J87: =16750000*2 -> 33500000 | L87: 6 | N87: Internal | R87: Kiki Sudiana | T87: =J87 -> 33500000 | AD87: Fajar Sidiq Prabowo | AM87: Agus Sulistya | AV87: Riza Akhsani Setyo Prayoga | BQ87: Proposal | BR87: Laporan Akhir | BS87: MUHAMMAD RAFLI RAMADHAN | CG87: Jurnal Internasional, Prosiding conference, Hak Cipta | CH87: - | CI87: -
A88: 28 | B88: REK.090/PNLT1/REK/III/2021 | C88: 1110/PNLT1/LPPM/IV/2021 | D88: Pengembangan Purwarupa truk bertenaga listrik | E88: Penelitian Research Center | F88: 2021 | G88: 2021 | H88: 12 | I88: Nasional: Transportasi | J88: 100000000 | K88: Institut Teknologi Telkom Surabaya | L88: 4 | M88: Penelitian Kompetitif Internal | N88: Internal | O88: ID | P88: ITTelkom Surabaya | Q88: 6680685 | R88: Moch. Iskandar Riansyah | S88: 0721068802 | T88: =J88 -> 100000000 | U88: Teknik Elektro | X88: FTE | Y88: ITTelkom Surabaya | Z88: 8140 | AA88: 072019 | BQ88: Proposal | BR88: Laporan Akhir | BS88: Aditya Yudhistira | BT88: Teknologi Informasi, FTIB, ITTelkom Surabaya | BU88: Moch. Syamfallah Anwar | BW88: Nova Herlina Mila Soetarno | BY88: M Fariz Rahmadany | BZ88: Teknik Elektro, FTEIC, ITTelkom Surabaya | CA88: Muhammad Fauzan Rasyid | CC88: Henko kholima | CE88: Ishak Rizaldy Eka Kurnia | CG88: Jurnal Nasional Sinta2 | CH88: - | CI88: Prototype, HKI
A89: 29 | B89: REK.090/PNLT1/REK/III/2021 | C89: 1111/PNLT1/LPPM/IV/2021 | D89: Sistem Pemberdayaan Rooftop Terintegrasi | E89: Penelitian Research Center | F89: 2021 | G89: 2021 | H89: 12 | I89: Nasional: Pangan-Pertanian | J89: 100000000 | K89: Institut Teknologi Telkom Surabaya | L89: 4 | M89: Penelitian Kompetitif Internal | N89: Internal | O89: ID | P89: ITTelkom Surabaya | Q89: 6680633 | R89: Helmy Widyantara | S89: 0717017902 | T89: =J89 -> 100000000 | U89: Teknologi Informasi | V89: Sistem Informasi | X89: FTII | Y89: ITTelkom Surabaya | Z89: 8140 | AA89: 072019 | BQ89: Proposal | BR89: Laporan Akhir | BS89: Muhammad Rafi Irzam | BT89: Teknologi Informasi, FTIB, ITTelkom Surabaya | BU89: Danang Taufik Kurnianto | BW89: Denza Tanzilda | BX89: Teknologi Informasi, FTIB, ITTelkom Surabaya | BY89: Muhammad Yanuar Muhaimin | CA89: Danu Diningrat | CB89: Teknik Komputer, FTEIC, ITTelkom Surabaya | CC89: Naufal Ammar Badr | CD89: Teknologi Informasi, FTIB, ITTelkom Surabaya | CG89: Jurnal Internasional | CH89: - | CI89: Prototype sistem monitoring dan pengendalian green house berbasis IoT dan Prototype sistem monitoring dan pengendalian kualitas air pada pemijahan wader
A90: 30 | B90: REK.086/PNLT1/REK/III/2021 | C90: 1038/PNLT1/LPPM/III/2021 | D90: Pengantar Teknik Industri | E90: Penulisan Buku Ajar | F90: 2021 | G90: 2021 | H90: 10 | I90: Nasional: Sosial Humaniora-Seni Budaya Pendidikan | J90: 3500000 | K90: Institut Teknologi Telkom Surabaya | L90: Terbit | M90: Penelitian Kompetitif Internal | N90: Internal | O90: ID | P90: ITTelkom Surabaya | Q90: 6682237 | R90: Dominggo Bayu Baskara | S90: 0722069004 | T90: =J90 -> 3500000 | U90: Teknik Industri | X90: FTII | Y90: ITTelkom Surabaya | Z90: 8140 | AA90: 072019 | AB90: 6680618 | AC90: 0725059202 | AD90: Rahaditya Dimas Prihadianto | AE90: =T90 -> 3500000 | AF90: Teknik Industri | AI90: FTE | AJ90: ITTelkom Surabaya | AK90: 6680627 | AL90: 0703119301 | AM90: Benazir Imam Arif Muttawin | AN90: =T90 -> 3500000 | AO90: Teknik Industri | AR90: FTE | AS90: ITTelkom Surabaya | BQ90: Proposal | BR90: Laporan Akhir | CG90: Buku Ajar | CH90: - | CI90: -
A91: 31 | B91: REK.086/PNLT1/REK/III/2021 | C91: 1039/PNLT1/LPPM/III/2021 | D91: Pengenalan Sistem Enterprise Menggunkan Odoo (Studi Kasus:Logistik) | E91: Penulisan Buku Ajar | F91: 2021 | G91: 2021 | H91: 8 | I91: ITTS: Sistem Logistik Cerdas | J91: 3000000 | K91: Institut Teknologi Telkom Surabaya | L91: - | M91: Penelitian Kompetitif Internal | N91: Internal | O91: ID | P91: ITTelkom Surabaya | Q91: 6665306 | R91: Ully Asfari | S91: 0703129001 | T91: =J91 -> 3000000 | U91: Sistem Informasi | X91: FTII | Y91: ITTelkom Surabaya | Z91: 8140 | AA91: 072019 | AB91: 6680648 | AC91: 0724089201 | AD91: Hawwin Mardhiana | AE91: =T91 -> 3000000 | AF91: Sistem Informasi | AI91: FTII | AJ91: ITTelkom Surabaya | AK91: 6744406 | AL91: 0709059004 | AM91: Muhammad Nasrullah | AN91: =T91 -> 3000000 | AO91: Sistem Informasi | AR91: FTII | AS91: ITTelkom Surabaya | BQ91: Proposal | BR91: Laporan Akhir | CG91: Buku Ajar ISSBN | CH91: Terealisasi | CI91: -
A92: 32 | B92: REK.086/PNLT1/REK/III/2021 | C92: 1013/PNLT1/LPPM/III/2021 | D92: Prototype Sistem Kendali Cerdas untuk Ground Vehicle di Jalan Raya | E92: Penelitian Terapan | F92: 2021 | G92: 2021 | H92: 12 | I92: ITTS: Transportasi | J92: 16800000 | K92: Institut Teknologi Telkom Surabaya | L92: 3 | M92: Penelitian Kompetitif Internal | N92: Internal | O92: ID | P92: ITTelkom Surabaya | Q92: 6680641 | R92: Ardiansyah Al Farouq | S92: 0714029301 | T92: =J92 -> 16800000 | U92: Teknik Komputer | X92: FTE | Y92: ITTelkom Surabaya | Z92: 8140 | AA92: 072019 | AB92: 6680678 | AC92: 0713068702 | AD92: Dwi Edi Setyawan | AE92: =T92 -> 16800000 | AF92: Teknik Kopmputer | AI92: FTE | AJ92: ITTelkom Surabaya | BQ92: Proposal | BR92: Laporan Akhir | BS92: Ahmad Habibi | BT92: Teknik Komputer, FTEIC, ITTelkom Surabaya | BU92: Dito Hewi Julianto | BV92: Teknik Komputer, FTEIC, ITTelkom Surabaya | CG92: Konference | CH92: Accepted | CI92: Prototype Robot UGV
A93: 33 | B93: REK.094/PNLT1/REK/III/2021 | C93: - | D93: TEKNIK KOMPUTASI DENGAN MEMPERTIMBANGKAN STABILITAS TRANSIEN PADA SMART GRID | E93: Penelitian Mandiri | F93: 2021 | G93: 2021 | H93: 6 | I93: ITTS: Sistem Logistik Cerdas | J93: 0 | K93: Institut Teknologi Telkom Surabaya | L93: 2 | M93: Penelitian Dana Mandiri | N93: Internal | O93: ID | P93: ITTelkom Surabaya | Q93: 6680612 | R93: Isa Hafidz | S93: 0728059203 | T93: =J93 -> 0 | U93: Teknik Elektro | X93: FTE | Y93: ITTelkom Surabaya | Z93: 8140 | AA93: 072019 | BQ93: Proposal | BR93: Laporan Akhir | BS93: ALDHITIANSYAH PUTRA | BT93: Teknik Elektro, FTEIC, ITTelkom Surabaya | BU93: Rafly Daffaldi | BV93: Teknik Elektro, FTEIC, ITTelkom Surabaya | CG93: Seminar Internasional | CH93: Accepted | CI93: -
A94: 34 | B94: REK.094/PNLT1/REK/III/2021 | C94: - | D94: Aplying Machine Learning Algorithm in Time Series Forecasting on Financial Prediction | E94: Penelitian Mandiri | F94: 2021 | G94: 2021 | H94: 6 | I94: Teknologi Informasi dan Komunikasi | J94: 0 | K94: Institut Teknologi Telkom Surabaya | L94: 3 | M94: Penelitian Dana Mandiri | N94: Internal | O94: ID | P94: ITTelkom Surabaya | Q94: 6680631 | R94: Anifatul Faricha | S94: 0704069202 | T94: =J94 -> 0 | U94: Teknik Elektro | X94: FTE | Y94: ITTelkom Surabaya | Z94: 8140 | AA94: 072019 | AB94: 6680648 | AC94: 0724089201 | AD94: Hawwin Mardhiana | AE94: =T94 -> 0 | AF94: Sistem Informasi | AI94: FTII | AJ94: ITTelkom Surabaya | AK94: 6718390 | AL94: 0001069203 | AM94: Siti Maghfirotul Ulyah | AN94: =T94 -> 0 | AO94: Statistika | AR94: FST | AS94: Universitas Airlangga | AT94: 5999348 | AU94: 0031077602 | AV94: Rika Susanti | AW94: =T94 -> 0 | AX94: Obstetori dan Gineklogi Peminatan | AZ94: FK | BA94: Universitas Andalas | BQ94: Proposal | BR94: Laporan Akhir | BS94: Christoper Andreas | BU94: Firman Adi Rifansyah | BV94: Teknik Elektro, FTEIC, ITTelkom Surabaya | CG94: Jurnal Sinta 1 | CH94: Submitted | CI94: Procsiding Internasional | CJ94: Accepted
A95: 35 | B95: REK.094/PNLT1/REK/III/2021 | C95: - | D95: Sistem Kendali dan Monitoring Suhu Kolam Pemijahan Wader Pari Ikan Wader berbasis IoT | E95: Penelitian Mandiri | F95: 2021 | G95: 2021 | H95: 12 | I95: ITTS: Teknologi Informasi dan Komunikasi | J95: 0 | K95: Institut Teknologi Telkom Surabaya | L95: 3 | M95: Penelitian Dana Mandiri | N95: Internal | O95: ID | P95: ITTelkom Surabaya | Q95: 6680629 | R95: Ubaidillah Umar | S95: 0727048809 | T95: =J95 -> 0 | U95: Teknik Komputer | X95: FTE | Y95: ITTelkom Surabaya | Z95: 8140 | AA95: 072019 | AK95: 6680633 | AL95: 0717017902 | AM95: Helmy Widyantara | AN95: =T95 -> 0 | AO95: Teknologi Informasi | AP95: Sistem Informasi | AR95: FTII | AS95: ITTelkom Surabaya | BQ95: Proposal | BR95: Laporan Akhir | BS95: MUHAMMAD YANUAR MUHAIMIN | BU95: DANU DININGRAT | CG95: Jurnal Nasional Terakreditasi | CH95: - | CI95: -
A96: 36 | B96: REK.094/PNLT1/REK/III/2021 | C96: - | D96: Implementasi Smart Hybrid PABX di Institut Teknologi Telkom Surabaya | E96: Penelitian Mandiri | F96: 2021 | G96: 2021 | H96: 6 | I96: Teknologi Informasi dan Komunikasi | J96: 0 | K96: Institut Teknologi Telkom Surabaya | L96: 3 | M96: Penelitian Dana Mandiri | N96: Internal | O96: ID | P96: ITTelkom Surabaya | Q96: 6680645 | R96: Walid Maulana Hadiansyah | S96: 0713108902 | T96: =J96 -> 0 | U96: Teknik Telekomunikasi | X96: FTE | Y96: ITTelkom Surabaya | Z96: 8140 | AA96: 072019 | AB96: 6805206 | AC96: 8920230021 | AD96: Agus Sulistya | AE96: =T96 -> 0 | AF96: Sistem Informasi | AI96: FTII | AJ96: ITTelkom Surabaya | AK96: 6680678 | AL96: 0713068702 | AM96: Dwi Edi Setyawan | AN96: =T96 -> 0 | AO96: Teknik Kopmputer | AR96: FTE | AS96: ITTelkom Surabaya | BQ96: Proposal | BR96: Laporan Akhir | BS96: Rayhan Naufaldi | BU96: Tasya Amalia | CG96: Prosiding Internasional, Prototype | CH96: - | CI96: -
A97: 37 | B97: REK.094/PNLT1/REK/III/2021 | C97: - | D97: Optimasi rute optimalberdasarkan waktu, biaya, kondisi cuaca, kejadian lokal, dan jumlah kendaraan dengan menggunakan algoritma fuzzy mandani dan modified hidden markov model | E97: Penelitian Mandiri | F97: 2021 | G97: 2021 | H97: 12 | I97: Transportasi | J97: 0 | K97: Institut Teknologi Telkom Surabaya | L97: 3 | M97: Penelitian Dana Mandiri | N97: Internal | O97: ID | P97: ITTelkom Surabaya | Q97: 6680622 | R97: Dewi RahmawatI | S97: 0709039401 | T97: =J97 -> 0 | U97: Rekayasa Perangkat Lunak | X97: FTII | Y97: ITTelkom Surabaya | Z97: 8140 | AA97: 072019 | AB97: 6680623 | AC97: 0721088602 | AD97: Yupit Sudianto | AE97: =T97 -> 0 | AF97: Sistem Informasi | AI97: FTII | AJ97: ITTelkom Surabaya | AK97: 259781 | AL97: 0710028604 | AM97: Titus Kristanto | AN97: =T97 -> 0 | AO97: Rekayasa Perangkat Lunak | AP97: Sistem Informasi | AR97: FTII | AS97: ITTelkom Surabaya | BQ97: Proposal | BR97: Laporan Akhir | BS97: Reza Arindra Fadhilah | BU97: AMANDA AMALIA | CG97: Jurnal Nasional ber-ISSN | CH97: Submitted | CI97: Hak Cipta (HAKI) | CJ97: Submitted
A98: 38 | B98: REK.094/PNLT1/REK/III/2021 | C98: - | D98: Private Higher Eduction Funding | E98: Penelitian Mandiri | F98: 2021 | G98: 2021 | H98: 6 | I98: Nasional: Sosial Humaniora-Seni Budaya Pendidikan | J98: 0 | K98: Institut Teknologi Telkom Surabaya | L98: Jurnal Internasional Bereputasi | M98: Penelitian Dana Mandiri | N98: Internal | O98: ID | P98: ITTelkom Surabaya | Q98: 6805206 | R98: Agus Sulistya | S98: 8920230021 | T98: =J98 -> 0 | U98: Rekayasa Perangkat Lunak | X98: FTII | Y98: ITTelkom Surabaya | Z98: 8140 | AA98: 072019 | AB98: 6805479 | AC98: 0012059403 | AD98: Rasyidi Faiz Akbar | AE98: =T98 -> 0 | AK98: 6680726 | AL98: 0719069101 | AM98: Arliyanti Nurdin | AN98: =T98 -> 0 | AO98: Teknologi Informasi | AR98: FTE | AS98: ITTelkom Surabaya | BQ98: Proposal | BR98: Laporan Akhir | BS98: DEVYSIKAELO IRA RANTELILI (1202200093) | CG98: Jurnal Internasional Bereputasi | CH98: - | CI98: Jurnal Internal ITTS
A99: 39 | B99: REK.094/PNLT1/REK/III/2021 | C99: - | D99: Pengukuran Kepuasan Mahasiswa terhadap E-learning Institut Teknologi Telkom Surabaya Berdasar Kriteria Usability | E99: Penelitian Mandiri | F99: 2021 | G99: 2021 | H99: 6 | I99: Nasional: Sosial Humaniora-Seni Budaya Pendidikan | J99: 0 | K99: Institut Teknologi Telkom Surabaya | L99: 3 | M99: Penelitian Dana Mandiri | N99: Internal | O99: ID | P99: ITTelkom Surabaya | Q99: 6756289 | R99: Nicko Nur Rakhmaddian | S99: 0725059501 | T99: =J99 -> 0 | U99: Teknik Logistik | X99: FTE | Y99: ITTelkom Surabaya | Z99: 8140 | AA99: 072019 | AB99: 6778519 | AC99: 0712059303 | AD99: Nisa Isrofi | AE99: =T99 -> 0 | AF99: Teknik Logistik | AI99: FTE | AJ99: ITTelkom Surabaya | AK99: 6784457 | AL99: 0723079501 | AM99: Granita Hajar | AN99: =T99 -> 0 | AO99: Teknik Logistik | AR99: FTE | AS99: ITTelkom Surabaya | BQ99: Proposal | BR99: Laporan Akhir | BS99: NABILLA ADINNA CAHYANI | BU99: MUHAMMAD ARKAN FAUZAN WICAKSONO | CG99: Prosiding Internasional | CH99: Submitted | CI99: Jurnal Internal ITTS
A100: 40 | B100: REK.094/PNLT1/REK/III/2021 | C100: - | D100: Pemodelan Rantai Markov untuk Resilensi Rantai pasok Industri manufaktur di Indonesia | E100: Penelitian Mandiri | F100: 2021 | G100: 2021 | H100: 10 | I100: ITTS: Sistem Logistik Cerdas | J100: 0 | K100: Institut Teknologi Telkom Surabaya | L100: 2 | M100: Penelitian Kompetitif Internal | N100: Internal | O100: ID | P100: ITTelkom Surabaya | Q100: 6680643 | R100: Abduh Sayid Albana | S100: 0702039003 | T100: =J100 -> 0 | U100: Teknik Industri | V100: Teknik Logistik | X100: FTII | Y100: ITTelkom Surabaya | Z100: 8140 | AA100: 072019 | AB100: 6680648 | AC100: 0724089201 | AD100: Hawwin Mardhiana | AE100: =T100 -> 0 | AF100: Sistem Informasi | AI100: FTII | AJ100: ITTelkom Surabaya | AK100: 6680618 | AL100: 0725059202 | AM100: Rahaditya Dimas Prihadianto | AN100: =T100 -> 0 | AO100: Teknik Industri | AR100: FTII | AS100: ITTelkom Surabaya | BQ100: Proposal | BR100: Laporan Akhir | BS100: ARDA ERICO YUDA | CG100: Jurnal Nasional Terakreditasi S1 | CH100: - | CI100: -
A101: 41 | B101: REK.094/PNLT1/REK/III/2021 | C101: - | D101: Pendeteksi Informasi Anak Autis Sejak Dini Menggunakan Machine Learning | E101: Penelitian Mandiri | F101: 2021 | G101: 2021 | H101: 10 | I101: ITTS: Teknologi Informasi dan Komunikasi | J101: 0 | K101: Institut Teknologi Telkom Surabaya | L101: 3 | M101: Penelitian Kompetitif Internal | N101: Internal | O101: ID | P101: ITTelkom Surabaya | Q101: 6681032 | R101: Anfazul Faridatul Azizah | S101: 0715039004 | T101: =J101 -> 0 | U101: Sistem Informasi | X101: FTII | Y101: ITTelkom Surabaya | Z101: 8140 | AA101: 072019 | AK101: 6764236 | AL101: 0704068902 | AM101: Rokhmatul Insani | AN101: =T101 -> 0 | AO101: Sistem Informasi | AR101: FTII | AS101: ITTelkom Surabaya | BQ101: Proposal | BR101: Laporan Akhir | BS101: BONNIE FERDINAND AKBAR | BU101: EDRIAND IMENS RAYGRANDI | BW101: IRENE DYAH AYUWATI | CG101: Jurnal Nasional Terakreditasi S4 | CH101: Submitted | CI101: Publikasi Media Massa, HKI
A102: 42 | B102: REK.094/PNLT1/REK/III/2021 | C102: 1819/PNLT1/LPPM/VIII/2021 | D102: Virtual Screening Senyawa Aktif sebagai Inhibitor Meningitis dengan Hybrid Molecular Fingerprint dan Pendekatan Machine Learning | E102: Penelitian Mandiri | F102: 2021 | G102: 2021 | H102: 6 | I102: Nasional: Kesehatan-Obat | J102: 0 | K102: Institut Teknologi Telkom Surabaya | L102: 3 | M102: Penelitian Dana Mandiri | N102: Internal | O102: ID | P102: ITTelkom Surabaya | Q102: 6756318 | R102: Moh.Hamim Zajuli Al Faroby | S102: 0724079501 | T102: =J102 -> 0 | U102: Sains Data | X102: FTII | Y102: ITTelkom Surabaya | Z102: 8140 | AA102: 072019 | AB102: 6793410 | AC102: 0707019501 | AD102: Helisyah Nur Fadhilah | AE102: =T102 -> 0 | AF102: Sains Data | AI102: FTII | AJ102: ITTelkom Surabaya | BQ102: Proposal | BR102: Laporan Akhir | BS102: INDAH RAHMAWATI UTAMI | CG102: Jurnal Internasional Bereputasi | CH102: - | CI102: Seminar Internasional Bereputasi
A103: 43 | B103: REK.094/PNLT1/REK/III/2021 | C103: - | D103: Deteksi Halangan Tangga Turun untuk Penyandang Tuna Netra | E103: Penelitian Mandiri | F103: 2021 | G103: 2021 | H103: 6 | I103: Teknologi Informasi dan Komunikasi | J103: 0 | K103: Institut Teknologi Telkom Surabaya | L103: 3 | M103: Penelitian Dana Mandiri | N103: Internal | O103: ID | P103: ITTelkom Surabaya | Q103: 6767777 | R103: Ahmad Wali Satria Bahari Johan | S103: 0713059501 | T103: =J103 -> 0 | U103: Informatika | X103: FTII | Y103: ITTelkom Surabaya | Z103: 8140 | AA103: 072019 | AB103: 6801989 | AC103: 0704029302 | AD103: Sekar Widyasari Putri | AE103: =T103 -> 0 | AF103: Bisnis Digital | AI103: FTII | AJ103: ITTelkom Surabaya | AK103: 6784457 | AL103: 0723079501 | AM103: Granita Hajar | AN103: =T103 -> 0 | AO103: Teknik Logistik | AR103: FTE | AS103: ITTelkom Surabaya | BQ103: Proposal | BR103: Laporan Akhir | BS103: RAHAYU NUR ROCHMAH | BU103: RAHMAT ANDIKA LAKSANA | CG103: Jurnal Nasional Terakreditasi S2 | CH103: Accepted | CI103: -
...

Sheet PKM AUDIT
A1: No | B1: No. SK | C1: No. Kontrak | D1: Judul Penelitian | E1: Nama Skema | F1: Tahun Usulan | G1: Tahun Pelaksanaan Kegiatan | H1: Lama Kegiatan (bulan) | I1: Bidang Fokus | J1: Dana yang Diusulkan | K1: Dana Disetujui | L1: Nama Institusi Penerima Dana | M1: Target TKT | N1: Nama Program Hibah | O1: Kategori Sumber Dana | P1: Negara Sumber Dana | Q1: Sumber Dana | R1: Sinta ID Ketua | S1: Nama Ketua | T1: NIDN Ketua | U1: DANA KETUA | V1: Prodi | W1: Fakultas | X1: PT | Y1: Sinta ID PT | Z1: Kode PT PDDikti | AA1: Sinta ID Member1 | AB1: NIDN Member1 | AC1: Nama Member1 | AD1: DANA MEMBER 1 | AE1: Prodi2 | AF1: Fakultas3 | AG1: PT4 | AH1: Sinta ID Member2 | AI1: NIDN Member2 | AJ1: Nama Member2 | AK1: DANA MEMBER 2 | AL1: Prodi5 | AM1: Fakultas6 | AN1: PT7 | AO1: Sinta ID Member3 | AP1: NIDN Member3 | AQ1: Nama Member3 | AR1: DANA MEMBER 3 | AS1: Prodi8 | AT1: Fakultas9 | AU1: PT10 | AV1: Sinta ID Member4 | AW1: NIDN Member4 | AX1: Nama Member4 | AY1: DANA MEMBER 4 | AZ1: Prodi11 | BA1: Fakultas12 | BB1: PT13 | BC1: Sinta ID Member5 | BD1: NIDN Member5 | BE1: Nama Member5 | BF1: DANA MEMBER 5 | BG1: Prodi14 | BH1: Fakultas15 | BI1: PT16 | BJ1: Sinta ID Member6 | BK1: NIDN Member6 | BL1: Nama Member6 | BM1: DANA MEMBER 6 | BN1: Prodi17 | BO1: Fakultas18 | BP1: PT19 | BQ1: SDG | BR1: Proposal | BS1: Laporan Akhir | BT1: Nama Mhs1 | BU1: Prodi, Fak, PT Mhs1 | BV1: Nama Mhs2 | BW1: Prodi, Fak, PT Mhs2 | BX1: Nama Mhs3 | BY1: Prodi, Fak, PT Mhs3 | BZ1: Nama Mhs4 | CA1: Prodi Mhs4 | CB1: Nama Mhs5 | CC1: Prodi Mhs5 | CD1: Nama Mhs6 | CE1: Prodi Mhs6 | CF1: Nama Mhs7 | CG1: Prodi Mhs7 | CH1: Nama Mhs8 | CI1: Prodi Mhs8 | CJ1: Publikasi Ilmiah | CK1: Media Massa | CL1: Produk / Jasa | CM1: Capaian Publikasi Ilmiah | CN1: Capaian Luaran Wajib | CO1: Luaran Tambahan | CR1: No | CS1: Pertanyaan | CT1: Jumlah PKM
A2: 1 | B2: REK.024/ABDI3/PPM/III/2020 | C2: - | D2: Penerapan Teknologi Pakan Otomatis Bagi Peternak Ikan di Gresik | E2: Pengmas Dana Internal | F2: 2020 | K2: 6500000 | O2: Internal | Q2: Institut Telknologi Telkom Surabaya | R2: 6680685 | S2: Moch. Iskandar Riansyah | T2: 0721068802 | U2: =K2/3 -> 2166666.7 | V2: Teknik Elektro | W2: FTE | X2: ITTelkom Surabaya | Y2: 8140 | Z2: 072019 | AA2: 6680708 | AB2: 0706069201 | AC2: Lora K. Amifia | AD2: =U2 -> 2166666.7 | AE2: Teknik Elektro | AF2: FTE | AG2: ITTelkom Surabaya | AH2: 6680612 | AI2: 0728059203 | AJ2: Isa Hafidz | AK2: =U2 -> 2166666.7 | AL2: Teknik Elektro | AM2: FTE | AN2: ITTelkom Surabaya | BR2: Proposal | BS2: Laporan Akhir | CR2: 1 | CS2: Jumlah Pengabdian kepada masyarakat yang didanai oleh industri nasional | CT2: =CW4+CW9 -> 4
A3: 2 | B3: REK.024/ABDI3/PPM/III/2020 | C3: - | D3: IPTEK BAGI MASYARAKAT BUDI DAYA IKAN DI BUDURAN SIDOARJO JAWTA TIMUR | E3: Pengmas Dana Internal | F3: 2020 | K3: 6500000 | M3: - | O3: Internal | Q3: Institut Telknologi Telkom Surabaya | R3: 6680683 | S3: Billy Montolalu | T3: 0729088704 | U3: =K3/3 -> 2166666.7 | V3: Sistem Informasi | W3: FTII | X3: ITTelkom Surabaya | Y3: 8140 | Z3: 072019 | AA3: 6680678 | AB3: 0713068702 | AC3: Dwi Edi Setyawan | AD3: =U3 -> 2166666.7 | AE3: Teknik Komputer | AF3: FTE | AG3: ITTelkom Surabaya | AH3: 6680633 | AI3: 0717017902 | AJ3: Helmy Widyantara | AK3: =U3 -> 2166666.7 | AL3: Teknologi Informasi | AM3: FTII | AN3: ITTelkom Surabaya | BR3: Proposal | BS3: Laporan Akhir | CR3: 2 | CS3: jumlah Pengabdian kepada masyarakat yang didanai oleh non-industri nasional/kementrian | CT3: =CW6+CW7+CW8 -> 17 | CV3: Sumber Dana | CW3: Count of Sumber Dana
A4: 3 | C4: - | D4: Workshop on using Braille Embosser and Text Editor Software for the Blind and Visual Impairment Students | E4: Pengmas penugasan | F4: 2020 | G4: 2020 | H4: 4 | I4: Pembedayaan Difabel | K4: 4475000 | M4: - | O4: Internal | Q4: Institut Telknologi Telkom Surabaya | R4: 6681032 | S4: Anfazul Faridatul Azizah | T4: 715039004 | U4: =K4/2 -> 2237500 | V4: Sistem Informasi | W4: FTII | X4: ITTelkom Surabaya | Y4: 8140 | Z4: 072019 | AA4: 6680625 | AB4: 0408067804 | AC4: Nilla Rachmaningrum | AD4: =K4/2 -> 2237500 | AE4: Teknik Telekomunikasi | AF4: FTE | AG4: ITTelkom Surabaya | BR4: Proposal | BS4: Laporan Akhir | CR4: 3 | CS4: jumlah Pengabdian kepada masyarakat yang didanai oleh instansi/lembaga asing/luar negeri | CT4: 0 | CV4: CDC Telkom | CW4: 3
A5: 5 | C5: - | D5: Upaya Penanganan Wabah COVID-19 Terhadap Komunitas Tunarungu di Kota Surabaya | E5: Pengmas penugasan | F5: 2020 | G5: 2020 | K5: 4000000 | M5: - | O5: Internal | Q5: Institut Telknologi Telkom Surabaya | R5: 6681032 | S5: Anfazul Faridatul Azizah | T5: 715039004 | U5: =K5/5 -> 800000 | V5: Sistem Informasi | W5: FTII | X5: ITTelkom Surabaya | Y5: 8140 | Z5: 072019 | AA5: 259781 | AB5: 0710028604 | AC5: Titus Kristanto | AD5: =U5 -> 800000 | AE5: Bisnis Digital | AF5: FTII | AG5: ITTelkom Surabaya | AH5: 6680634 | AI5: 0725059004 | AJ5: Noerma Pudji Istyanto | AK5: =U5 -> 800000 | AL5: Sistem Informasi | AM5: FTII | AN5: ITTelkom Surabaya | AO5: 6680643 | AP5: 0702039003 | AQ5: Abduh Sayid Albana | AR5: =U5 -> 800000 | AS5: Teknik Logistik | AT5: FTE | AU5: ITTelkom Surabaya | AV5: 6724784 | AW5: 722119101 | AX5: FANNUSH SHOFI AKBAR | AY5: =U5 -> 800000 | AZ5: Teknik Telekomunikasi | BA5: FTE | BB5: ITTelkom Surabaya | BR5: Proposal | BS5: Laporan Akhir | CR5: 4 | CS5: jumlah kerjasama non-profit di bidang pengabdian kepada masyarakat | CT5: =6+30+37+44+42+28 -> 187 | CV5: Institut Telknologi Telkom Surabaya | CW5: 138
A6: 6 | C6: - | D6: Pentingnya APD (faceshield) untuk Masyarakat dan UKM | E6: Pengmas penugasan | F6: 2020 | G6: 2020 | H6: 1 | K6: 6400000 | M6: - | O6: Internal | Q6: Institut Telknologi Telkom Surabaya | R6: 6680648 | S6: Hawwin Mardhiana | T6: 0724089201 | U6: =K6/5 -> 1280000 | V6: Sistem Informasi | W6: FTII | X6: ITTelkom Surabaya | Y6: 8140 | Z6: 072019 | AA6: 6665306 | AB6: 0703129001 | AC6: Ully Asfari | AD6: =U6 -> 1280000 | AE6: Sistem Informasi | AF6: FTII | AG6: ITTelkom Surabaya | AH6: 6764236 | AI6: 0704068902 | AJ6: Rokhmatul Insani | AK6: =U6 -> 1280000 | AL6: Sistem Informasi | AM6: FTII | AN6: ITTelkom Surabaya | AO6: 6680627 | AP6: 0703119301 | AQ6: Benazir Imam Arif Muttaqin | AR6: =U6 -> 1280000 | AS6: Teknik Industri | AT6: FTE | AU6: ITTelkom Surabaya | AV6: 6658545 | AW6: 0401078801 | AX6: Ayu Endah Wahyuni | AY6: =U6 -> 1280000 | AZ6: Teknik Industri | BA6: FTE | BB6: ITTelkom Surabaya | BR6: Proposal | BS6: Laporan Akhir | BT6: Aji Triatmojo | BV6: Mohammad Abyan Seifa | BX6: Karina Putri Permatasari | BZ6: Gilang Ahmad Ramadhani Akbar | CJ6: Jurnal Nasional Terakreditasi | CK6: Publikasi Media Massa Online | CM6: Jurnal submitted, artikel media massa publish | CR6: 5 | CS6: jumlah rata-rata dana pengabdian kepada masyarakat per dosen per tahun | CT6: =#REF! -> #REF! | CV6: Kemendiktisaintek | CW6: 9
CR7: 6 | CS7: jumlah pendanaan pengabdian kepada masyarakat pada bidang seni budaya | CT7: 0 | CV7: Kemenristek Dikti | CW7: 1
A8: 1 | B8: REK.091/ABDI1/REK/III/2021 | C8: 1025/ABDI1/LPPM/III/2021 | D8: Peningkatan Pengawasan Pengunjung Wisata Pasir Putih Dalegan di Masa Pandemi Covid19 dengan Aplikasi Pendeteksi Jarak Berbasis Kecerdasan Buatan | E8: pkm reguler | F8: 2021 | G8: 2021 | H8: 6 | I8: INDUSTRI KREATIF DAN PENGEMBANGAN TEKNOLOGI MAJU | J8: =K8 -> 7000000 | K8: 7000000 | L8: ITTelkom Surabaya | M8: 7 | N8: Pengmas Kompetitif Internal | O8: Internal | P8: ID | Q8: Institut Telknologi Telkom Surabaya | R8: 6680698 | S8: Mohammad Sholik | T8: 0709128101 | U8: =K8/3 -> 2333333.3 | V8: Rekayasa Perangkat Lunak | W8: FTII | X8: ITTelkom Surabaya | Y8: 8140 | Z8: 072019 | AA8: 6680628 | AB8: 0730058702 | AC8: Fidi Wincoko Putro | AD8: =K8/3 -> 2333333.3 | AE8: Rekayasa Perangkat Lunak | AF8: FTE | AG8: ITTelkom Surabaya | AH8: 6680626 | AI8: 0727099201 | AJ8: Ardian Yusuf Wicaksono | AK8: =K8/3 -> 2333333.3 | AL8: Informatika | AM8: FTII | AN8: ITTelkom Surabaya | BR8: Proposal | BS8: Laporan Akhir | BT8: Auliya Rahman Pakarti | BV8: William Kurniawan | BX8: Edo Handoko | CJ8: Jurnal Nasional ber-ISSN | CK8: Publikasi Media Massa Nasional | CL8: Produk TTG Aplikasi Deteksi Jarak | CR8: 7 | CS8: jumlah pendanaan pengabdian kepada masyarakat pada proyek-proyek kemasyarakatan | CT8: 3292660845 | CV8: Kemensos | CW8: 7
A9: 2 | B9: REK.091/ABDI1/REK/III/2021 | C9: 1027/ABDI1/LPPM/III/2021 | D9: Implementasi Metode Rebranding Pada Produk Hasil Urban Farming Masyarakat Lokal di Masa Pandemi | E9: pkm reguler | F9: 2021 | G9: 2021 | H9: 6 | I9: PEMBERDAYAAN DESA/WILAYAH BINAAN | J9: =K9 -> 6750000 | K9: 6750000 | L9: ITTelkom Surabaya | M9: 7 | N9: Pengmas Kompetitif Internal | O9: Internal | P9: ID | Q9: Institut Telknologi Telkom Surabaya | R9: 6682237 | S9: Dominggo Bayu Baskara | T9: 0722069004 | U9: =K9/3 -> 2250000 | V9: Teknik Industri | W9: FTII | X9: ITTelkom Surabaya | Y9: 8140 | Z9: 072019 | AA9: 6680618 | AB9: 0725059202 | AC9: Rahaditya Dimas Prihadianto | AD9: =K9/3 -> 2250000 | AE9: Teknik Industri | AF9: FTE | AG9: ITTelkom Surabaya | AH9: 6681051 | AI9: 0711069301 | AJ9: Rizqa Amelia Zunaidi | AK9: =K9/3 -> 2250000 | AL9: Teknik Industri | AM9: FTE | AN9: ITTelkom Surabaya | BR9: Proposal | BS9: Laporan Akhir | BT9: MUHAMMAD ALFAIRUS HIDAYATULLAH | BV9: INES MULIA NURDIANA | BX9: PUTRI AMELIA FEBRIANTI | CJ9: Jurnal Internal | CK9: Publikasi Media Massa Nasional | CL9: Peningkatan Pemberdayaan Mitra | CM9: Accepted, online | CV9: PT.POS INDONESIA | CW9: 1
A10: 3 | B10: REK.091/ABDI1/REK/III/2021 | C10: 1028/ABDI1/LPPM/III/2021 | D10: Rancang Workbench Ergonomis untuk mendukung aktivitas bank sampah | E10: pkm reguler | F10: 2021 | G10: 2021 | H10: 6 | I10: PEMBERDAYAAN DESA/WILAYAH BINAAN | J10: =K10 -> 6750000 | K10: 6750000 | L10: ITTelkom Surabaya | M10: 7 | N10: Pengmas Kompetitif Internal | O10: Internal | P10: ID | Q10: Institut Telknologi Telkom Surabaya | R10: 6680618 | S10: Rahaditya Dimas Prihadianto | T10: 0725059202 | U10: =K10/3 -> 2250000 | V10: Teknik Industri | W10: FTII | X10: ITTelkom Surabaya | Y10: 8140 | Z10: 072019 | AA10: 6680643 | AB10: 0702039003 | AC10: Abduh Sayid Albana | AD10: =K10/3 -> 2250000 | AE10: Teknik Logistik | AF10: FTII | AG10: ITTelkom Surabaya | AH10: 6658545 | AI10: 0401078801 | AJ10: Ayu Endah Wahyuni | AK10: =K10/3 -> 2250000 | AL10: Teknik Industri | AM10: FTE | AN10: ITTelkom Surabaya | BR10: Proposal | BS10: Laporan Akhir | BT10: ANDHICO WIRYATAMA | BV10: HENDRAWAN ISWIDODO | CJ10: Jurnal Nasional ber-ISSN | CK10: Video Kegiatan | CL10: Peningkatan Pemberdayaan Mitra | CV10: Telkom University | CW10: 27
A11: 4 | B11: REK.091/ABDI1/REK/III/2021 | C11: 1029/ABDI1/LPPM/III/2021 | D11: PKM Peningkatan Branding dan Optimalisasi Manajemen Usaha Pada UKM Handy Craft Az-Zahra, Desa Gubeng, Surabaya | E11: pkm reguler | F11: 2021 | G11: 2021 | H11: 6 | I11: INDUSTRI KREATIF DAN PENGEMBANGAN TEKNOLOGI MAJU | J11: =K11 -> 6750000 | K11: 6750000 | L11: ITTelkom Surabaya | M11: 7 | N11: Pengmas Kompetitif Internal | O11: Internal | P11: ID | Q11: Institut Telknologi Telkom Surabaya | R11: 6680687 | S11: Wahyu Andy Prastyabudi | T11: 702048705 | U11: =K11/3 -> 2250000 | V11: Teknik Industri | W11: FTII | X11: ITTelkom Surabaya | Y11: 8140 | Z11: 072019 | AA11: 6680726 | AB11: 719069101 | AC11: Arliyanti Nurdin | AD11: =K11/3 -> 2250000 | AE11: Teknologi Informasi | AF11: FTII | AG11: ITTelkom Surabaya | AH11: 6778837 | AI11: 711039403 | AJ11: Muhammad Dzulfikar Fauzi | AK11: =K11/3 -> 2250000 | AL11: Informatika | AM11: FTII | AN11: ITTelkom Surabaya | BR11: Proposal | BS11: Laporan Akhir | BT11: Muhammad Arkan Fauzan | BU11: Teknologi Informasi, FTIB, ITTelkom Surabaya | BV11: Farhan Hadi Pratama | BX11: Arda Erico Yuda | BY11: Teknik Industri, FTEIC, ITTelkom Surabaya | CJ11: Prosiding Seminar Nasional ber-ISBN. Jurnal Nasional Terakreditasi Sinta 3 JURNAL PENGABDIAN KEPADA MASYARAKAT | CK11: Publikasi Media Massa Nasional | CL11: Peningkatan Pemberdayaan Mitra Peningkatan signifikan | CM11: Submitted, Published, Peningkatan Signifikan | CV11: (kosong)
A12: 5 | B12: REK.091/ABDI1/REK/III/2021 | C12: 1032/ABDI1/LPPM/III/2021 | D12: Pengendali Tingkat Keasaman Air Kolam Untuk Peternak Ikan Lele di Desa Jatirejo, Mojokerto | E12: pkm reguler | F12: 2021 | G12: 2021 | H12: 6 | I12: INDUSTRI KREATIF DAN PENGEMBANGAN TEKNOLOGI MAJU | J12: =K12 -> 6900000 | K12: 6900000 | L12: ITTelkom Surabaya | M12: 7 | N12: Pengmas Kompetitif Internal | O12: Internal | P12: ID | Q12: Institut Telknologi Telkom Surabaya | R12: 258471 | S12: Susijanto Tri Rasmana | T12: 0727097302 | U12: =K12/3 -> 2300000 | V12: Teknik Elektro | W12: FTE | X12: ITTelkom Surabaya | Y12: 8140 | Z12: 072019 | AA12: 6680685 | AB12: 0721068802 | AC12: Moch. Iskandar Riansyah | AD12: =K12/3 -> 2300000 | AE12: Teknik Elektro | AF12: FTE | AG12: ITTelkom Surabaya | AH12: 6853203 | AI12: 0705109006 | AJ12: Chaironi Latif | AK12: =K12/3 -> 2300000 | AL12: Teknik Elektro | AM12: FTE | AN12: ITTelkom Surabaya | BR12: Proposal | BS12: Laporan Akhir | BT12: MUHAMMAD DWI HARIYANTO | BV12: ANAK AGUNG KUSUMA JAYA NINGRAT | BX12: JESICA F NURA | CJ12: Jurnal Nasional Terakreditasi | CK12: Publikasi Media Massa Nasional | CL12: Produk TTG | CM12: Submitted, published, berfungsi dan telah diserahterimakan | CV12: Total Keseluruhan | CW12: 186
A13: 6 | B13: REK.091/ABDI1/REK/III/2021 | C13: 1033/ABDI1/LPPM/III/2021 | D13: Pemanfaatan Teknologi Sonar untuk Membantu Nelayan Kedung Cowek, Kec.Bulak | E13: pkm reguler | F13: 2021 | G13: 2021 | H13: 6 | I13: INDUSTRI KREATIF DAN PENGEMBANGAN TEKNOLOGI MAJU | J13: =K13 -> 6900000 | K13: 6900000 | L13: ITTelkom Surabaya | M13: 7 | N13: Pengmas Kompetitif Internal | O13: Internal | P13: ID | Q13: Institut Telknologi Telkom Surabaya | R13: 6680625 | S13: Nilla Rachmaningrum | T13: 0408067804 | U13: =K13/3 -> 2300000 | V13: Teknik Telekomunikasi | W13: FTE | X13: ITTelkom Surabaya | Y13: 8140 | Z13: 072019 | AA13: 6680645 | AB13: 0713108902 | AC13: Walid Maulana Hadiansyah | AD13: =K13/3 -> 2300000 | AE13: Teknik Telekomunikasi | AF13: FTE | AG13: ITTelkom Surabaya | AH13: 6680741 | AI13: 0727059002 | AJ13: Hamzah Ulinuha Mustakim | AK13: =K13/3 -> 2300000 | AL13: Teknik Telekomunikasi | AM13: FTE | AN13: ITTelkom Surabaya | BR13: Proposal | BS13: Laporan Akhir | BT13: Bryan Birzha Marsono | BV13: Rian Gunawan | BX13: Galuh Widya | BZ13: Miscbachul Munir | CJ13: Jurnal Nasional ber-ISSN | CK13: Publikasi Media Massa Nasional | CL13: Peningkatan Pemberdayaan Mitra
A14: 7 | B14: REK.091/ABDI1/REK/III/2021 | C14: 1035/ABDI1/LPPM/III/2021 | D14: Pendayagunaan IT untuk Branding Kampung Ondomohen Sebagai Wisata Edukasi 3R (Reduce, Reuse, dan Recycle) | E14: pkm reguler | F14: 2021 | G14: 2021 | H14: 6 | I14: INDUSTRI KREATIF DAN PENGEMBANGAN TEKNOLOGI MAJU | J14: =K14 -> 6749500 | K14: 6749500 | L14: ITTelkom Surabaya | M14: 7 | N14: Pengmas Kompetitif Internal | O14: Internal | P14: ID | Q14: Institut Telknologi Telkom Surabaya | R14: 6680623 | S14: Yupit Sudianto | T14: 0721088602 | U14: =K14/3 -> 2249833.3 | V14: Sistem Informasi | W14: FTII | X14: ITTelkom Surabaya | Y14: 8140 | Z14: 072019 | AA14: 6680648 | AB14: 0724089201 | AC14: Hawwin Mardhiana | AD14: =K14/3 -> 2249833.3 | AE14: Sistem Informasi | AF14: FTII | AG14: ITTelkom Surabaya | AH14: 6665306 | AI14: 0703129001 | AJ14: Ully Asfari | AK14: =K14/3 -> 2249833.3 | AL14: Sistem Informasi | AM14: FTII | AN14: ITTelkom Surabaya | BR14: Proposal | BS14: Laporan Akhir | BT14: Thania Anindillah Putri | BV14: Tanang Satriyo Adi | BX14: Tanfirul Roibafi Muhammad | CJ14: Jurnal Internal | CK14: Publikasi Media Massa Nasional | CL14: Produk TTG
A15: 8 | B15: REK.091/ABDI1/REK/III/2021 | C15: 1030/ABDI1/LPPM/III/2021 | D15: Sosialisasi Penggunaan "Fingerprint" dan Database untuk Absensi Guru di Yayasan Natanisha, Sekolah Anak Berkebutuhan Khusus "AGCA" | E15: pkm reguler | F15: 2021 | G15: 2021 | H15: 6 | I15: PEMBERDAYAAN DESA/WILAYAH BINAAN | J15: =K15 -> 3400000 | K15: 3400000 | L15: ITTelkom Surabaya | M15: 7 | N15: Pengmas Kompetitif Internal | O15: Internal | P15: ID | Q15: Institut Telknologi Telkom Surabaya | R15: 6681032 | S15: Anfazul Faridatul Azizah | T15: 0715039004 | U15: =K15/2 -> 1700000 | V15: Sistem Informasi | W15: FTII | X15: ITTelkom Surabaya | Y15: 8140 | Z15: 072019 | AA15: 6764236 | AB15: 0704068902 | AC15: Rokhmatul Insani | AD15: =K15/2 -> 1700000 | AE15: Sistem Informasi | AF15: FTII | AG15: ITTelkom Surabaya | BR15: Proposal | BS15: Laporan Akhir | BT15: Tanfirul Roibafi | BV15: Nabilah Monica Hidayat | BX15: Fannijara Enggar Larasati | CJ15: Jurnal Internal | CK15: Publikasi Media Massa Nasional | CL15: Peningkatan Pemberdayaan Mitra | CM15: Media massa published | CN15: Jurnal Pengabdian
A16: 9 | B16: REK.091/ABDI1/REK/III/2021 | C16: 1026/ABDI1/LPPM/III/2021 | D16: PKM SIM Apotek untuk Pengelolaan Data Jual Beli pada Apotek Amel Mojokerto | E16: pkm reguler | F16: 2021 | G16: 2021 | H16: 6 | I16: INDUSTRI KREATIF DAN PENGEMBANGAN TEKNOLOGI MAJU | J16: =K16 -> 6950000 | K16: 6950000 | L16: ITTelkom Surabaya | M16: 7 | N16: Pengmas Kompetitif Internal | O16: Internal | P16: ID | Q16: Institut Telknologi Telkom Surabaya | R16: 6764236 | S16: Rokhmatul Insani | T16: 0704068902 | U16: =K16/2 -> 3475000 | V16: Sistem Informasi | W16: FTII | X16: ITTelkom Surabaya | Y16: 8140 | Z16: 072019 | AA16: 6681032 | AB16: 0715039004 | AC16: Anfazul Faridatul Azizah | AD16: =K16/2 -> 3475000 | AE16: Sistem Informasi | AF16: FTII | AG16: ITTelkom Surabaya | BR16: Proposal | BS16: Laporan Akhir | BT16: ALFONSUS NATHANAEL DAMAR PRISTIANTIO | BV16: M. IQBAL HAFIDZ | BX16: MUHAMMAD DAFFA ADIYATMA YUSUF | CJ16: Jurnal Nasional Terakreditasi | CK16: Video Kegiatan | CL16: Peningkatan Pemberdayaan Mitra | CM16: Jurnal submitted
A17: 10 | B17: REK.091/ABDI1/REK/III/2021 | C17: 1036/ABDI1/LPPM/III/2021 | D17: Sterillisasi Sayur buah Pada Koperasi Hita Loka Tara menggunakan UV Light untuk Meningkatkan Kualitas Produk Hasil Panen Hidroponik dan Buah | E17: pkm berbasis penelitian | F17: 2021 | G17: 2021 | H17: 6 | I17: INDUSTRI KREATIF DAN PENGEMBANGAN TEKNOLOGI MAJU | J17: =K17 -> 15670000 | K17: 15670000 | L17: ITTelkom Surabaya | M17: 7 | N17: Pengmas Kompetitif Internal | O17: Internal | P17: ID | Q17: Institut Telknologi Telkom Surabaya | R17: 6680664 | S17: Farah Zakiyah Rahmanti | T17: 0715128708 | U17: =K17/3 -> 5223333.3 | V17: Teknologi Informasi | W17: FTII | X17: ITTelkom Surabaya | Y17: 8140 | Z17: 072019 | AA17: 6680680 | AB17: 0704039202 | AC17: Bernadus Anggo Seno Aji | AD17: =K17/3 -> 5223333.3 | AE17: Teknologi Informasi | AF17: FTII | AG17: ITTelkom Surabaya | AH17: 6680726 | AI17: 719069101 | AJ17: Arliyanti Nurdin | AK17: =K17/3 -> 5223333.3 | AL17: Teknologi Informasi | AM17: FTII | AN17: ITTelkom Surabaya | BR17: Proposal | BS17: Laporan Akhir | BT17: Mochammad Rafi Adityawarman | BU17: Teknologi Informasi, FTIB, ITTelkom Surabaya | BV17: Muhammad Akbar Ramadhan | BW17: Teknologi Informasi, FTIB, ITTelkom Surabaya | BX17: Muhamad Iqbal Maulana | BY17: Teknologi Informasi, FTIB, ITTelkom Surabaya | BZ17: Wiranti Maharani | CA17: Teknologi Informasi, FTIB, ITTelkom Surabaya | CB17: Riska Aprilia | CC17: Teknologi Informasi, FTIB, ITTelkom Surabaya | CJ17: Jurnal Nasional Terakreditasi | CK17: Video Kegiatan | CL17: Peningkatan Pemberdayaan Mitra | CM17: Video publish youtube, published media massa, pelatihan penggunaan alat | CN17: International Conference | CO17: Accepted
A18: 11 | B18: REK.091/ABDI1/REK/III/2021 | C18: 1037/ABDI1/LPPM/III/2021 | D18: Pemasaran Online Produk Nasi Tiwul di Kabupaten Malang | E18: pkm berbasis penelitian | F18: 2021 | G18: 2021 | H18: 6 | I18: PEMBERDAYAAN DESA/WILAYAH BINAAN | J18: =K18 -> 15300000 | K18: 15300000 | L18: ITTelkom Surabaya | M18: 7 | N18: Pengmas Kompetitif Internal | O18: Internal | P18: ID | Q18: Institut Telknologi Telkom Surabaya | R18: 259781 | S18: Titus Kristanto | T18: 0710028604 | U18: =K18/3 -> 5100000 | V18: Rekayasa Perangkat Lunak | W18: FTII | X18: ITTelkom Surabaya | Y18: 8140 | Z18: 072019 | AA18: 6658545 | AB18: 0401078801 | AC18: Ayu Endah Wahyuni | AD18: =K18/3 -> 5100000 | AE18: Teknik Industri | AF18: FTE | AG18: ITTelkom Surabaya | AH18: 6680622 | AI18: 0709039401 | AJ18: Dewi Rahmawati | AK18: =K18/3 -> 5100000 | AL18: Rekayasa Perangkat Lunak | AM18: FTE | AN18: ITTelkom Surabaya | BR18: Proposal | BS18: Laporan Akhir | BT18: Reza Arindra Fadillah | BV18: Amanda Amalia | CJ18: Jurnal Nasional Terakreditasi | CK18: Publikasi Media Massa Nasional | CL18: Peningkatan Pemberdayaan Mitra | CM18: Jurnal published, published media massa | CN18: Hak Kekayaan Intelektual | CO18: Granted
A19: 12 | B19: REK.092/ABDI1/REK/III/2021 | C19: 1054/ABDI1/LPPM/III/2021 | D19: Peningkatan kapasitas Desa ngeni dengan Penerangan jalan Umum Tenaga Surya dan Pelatihan Keterampilan Teknologi ICT | E19: pkm Penugasan | F19: 2021 | G19: 2021 | H19: 6 | I19: PEMBERDAYAAN DESA/WILAYAH BINAAN | J19: =K19 -> 20000000 | K19: 20000000 | L19: ITTelkom Surabaya | M19: 7 | N19: Pengmas Kompetitif Internal | O19: Internal | P19: ID | Q19: Institut Telknologi Telkom Surabaya | R19: 6680651 | S19: Dimas Adiputra | T19: 0725059301 | U19: =K19/5 -> 4000000 | V19: Teknik Elektro | W19: FTE | X19: ITTelkom Surabaya | Y19: 8140 | Z19: 072019 | AA19: 6680612 | AB19: 0728059203 | AC19: Isa Hafidz | AD19: =K19/5 -> 4000000 | AE19: Teknik Elektro | AF19: FTE | AG19: ITTelkom Surabaya | AH19: 6680708 | AI19: 0706069201 | AJ19: Lora Khaula Amifia | AK19: =K19/5 -> 4000000 | AL19: Teknik Elektro | AM19: FTE | AN19: ITTelkom Surabaya | AO19: 6680641 | AP19: 0714029301 | AQ19: Ardiansyah Al farouq | AR19: =K19/5 -> 4000000 | AS19: Teknik Komputer | AT19: FTII | AU19: ITTelkom Surabaya | AV19: 6682174 | AW19: 0708069202 | AX19: Khodijah Amiroh | AY19: =K19/5 -> 4000000 | AZ19: Teknologi Informasi | BA19: FTII | BB19: ITTelkom Surabaya | BR19: Proposal | BS19: Laporan Akhir | BT19: Bagas Wahyu Prakoso | BV19: Robin Addwiyansyah Alfaro Samrat | BX19: Legowo Budi Prasodjo | BZ19: Nurina Devi Aprilliastuti | CB19: Ahmad Habibi | CD19: Wafa Murtadho Kholid | CF19: Ilham Akbar Maulana | CH19: Aditya Yudhistira | CJ19: Jurnal Nasional ber-ISSN | CK19: Publikasi Media Massa Nasional | CL19: Produk TTG | CM19: Jurnal submitted, publish media massa, PJU | CN19: -
A20: 13 | B20: REK.119/ABDI1/REK/V/2021 | C20: 1276/ABDI1/LPPM/III/2021 | D20: Sosialisasi dan Training Crane Pemulasaran Jenazah secara Terpadu di Rumah Sakit Pendidikan Universitas Airlangga Surabaya | E20: pkm Penugasan | F20: 2021 | G20: 2021 | H20: 3 | I20: PEMBERDAYAAN DESA/WILAYAH BINAAN | J20: =K20 -> 40000000 | K20: 40000000 | L20: ITTelkom Surabaya | M20: 7 | N20: Pengmas Kompetitif Internal | O20: Internal | P20: ID | Q20: Institut Telknologi Telkom Surabaya | R20: 6665306 | S20: Ully Asfari | T20: 0703129001 | U20: =K20/4 -> 10000000 | V20: Sistem Informasi | W20: FTII | X20: ITTelkom Surabaya | Y20: 8140 | Z20: 072019 | AA20: 6680633 | AB20: 0717017902 | AC20: Helmy Widyantara | AD20: =K20/4 -> 10000000 | AE20: Teknologi Informasi | AF20: FTII | AG20: ITTelkom Surabaya | AH20: 6680648 | AI20: 0724089201 | AJ20: Hawwin Mardhiana | AK20: =K20/4 -> 10000000 | AL20: Sistem Informasi | AM20: FTII | AN20: ITTelkom Surabaya | AO20: 6744406 | AP20: 0709059004 | AQ20: Muhammad Nasrullah | AR20: =K20/4 -> 10000000 | AS20: Sistem Informasi | AT20: FTII | AU20: ITTelkom Surabaya | BR20: Proposal | BS20: Laporan Akhir | BT20: Insani Sabilillah | BU20: Sistem Informasi, FTIB, ITTelkom Surabaya | BV20: Siti Aminah | BW20: Sistem Informasi, FTIB, ITTelkom Surabaya | BX20: Meita Betania | CJ20: - | CK20: Publikasi Media Massa Nasional | CL20: - | CM20: Media massa published
A21: 14 | B21: REK.119/ABDI1/REK/V/2021 | C21: 1277/ABDI1/LPPM/III/2021 | D21: Sosialisasi dan Training Crane Pemulasaran Jenazah secara Terpadu di Rumah Sakit Umum Daerah Sidoarjo | E21: pkm Penugasan | F21: 2021 | G21: 2021 | H21: 3 | I21: PEMBERDAYAAN DESA/WILAYAH BINAAN | J21: =K21 -> 40000000 | K21: 40000000 | L21: ITTelkom Surabaya | M21: 7 | N21: Pengmas Kompetitif Internal | O21: Internal | P21: ID | Q21: Institut Telknologi Telkom Surabaya | R21: 6680623 | S21: Yupit Sudianto | T21: 0721088602 | U21: =K21/4 -> 10000000 | V21: Sistem Informasi | W21: FTII | X21: ITTelkom Surabaya | Y21: 8140 | Z21: 072019 | AA21: 6680633 | AB21: 0717017902 | AC21: Helmy Widyantara | AD21: =K21/4 -> 10000000 | AE21: Teknologi Informasi | AF21: FTII | AG21: ITTelkom Surabaya | AH21: 6681051 | AI21: 0711069301 | AJ21: Rizqa Amelia Zunaidi | AK21: =K21/4 -> 10000000 | AL21: Teknik Elektro | AM21: FTE | AN21: ITTelkom Surabaya | AO21: 6764236 | AP21: 0704068902 | AQ21: Rokmatul Insani | AR21: =K21/4 -> 10000000 | AS21: Sistem Informasi | AT21: FTII | AU21: ITTelkom Surabaya | BR21: Proposal | BS21: Laporan Akhir | BT21: Fidelia Adinda Syafani | BU21: Teknik Industri, FTEIC, ITTelkom Surabaya | BV21: Nabilla Adinna Cahyani | BW21: Teknik Industri, FTEIC, ITTelkom Surabaya | BX21: Edriand Imens Raygrandi | CJ21: - | CK21: Video Kegiatan | CL21: -
A22: 15 | B22: REK.119/ABDI1/REK/V/2021 | C22: 1278/ABDI1/LPPM/III/2021 | D22: Sosialisasi dan Training Crane Pemulasaran Jenazah secara Terpadu di Dinas Kesehatan Kabupaten Gresik | E22: pkm Penugasan | F22: 2021 | G22: 2021 | H22: 3 | I22: PEMBERDAYAAN DESA/WILAYAH BINAAN | J22: =K22 -> 40000000 | K22: 40000000 | L22: ITTelkom Surabaya | M22: 7 | N22: Pengmas Kompetitif Internal | O22: Internal | P22: ID | Q22: Institut Telknologi Telkom Surabaya | R22: 6680612 | S22: Isa Hafidz | T22: 0728059203 | U22: =K22/5 -> 8000000 | V22: Teknik Elektro | W22: FTE | X22: ITTelkom Surabaya | Y22: 8140 | Z22: 072019 | AA22: 6680633 | AB22: 0717017902 | AC22: Helmy Widyantara | AD22: =K22/5 -> 8000000 | AE22: Teknologi Informasi | AF22: FTII | AG22: ITTelkom Surabaya | AH22: 6680627 | AI22: 0703119301 | AJ22: Benazir Imam Arif M | AK22: =K22/5 -> 8000000 | AL22: Teknik Elektro | AM22: FTE | AN22: ITTelkom Surabaya | AO22: 6680628 | AP22: 0730058702 | AQ22: Fidi Wincoko Putro | AR22: =K22/5 -> 8000000 | AS22: Rekayasa Perangkat Lunak | AT22: FTE | AU22: ITTelkom Surabaya | AV22: 6680698 | AW22: 0709128101 | AX22: Mohammad Sholik | AY22: =K22/5 -> 8000000 | AZ22: Rekayasa Perangkat Lunak | BA22: FTE | BB22: ITTelkom Surabaya | BR22: Proposal | BS22: Laporan Akhir | BT22: M. MIFTAHUL ABIDIN | BV22: RULLY ROSADI | BW22: Teknologi Informasi, FTIB, ITTelkom Surabaya | BX22: IRFANSAH W. | CJ22: - | CK22: Video Kegiatan | CL22: -
A23: 16 | B23: REK.119/ABDI1/REK/V/2021 | C23: 1278/ABDI1/LPPM/III/2021 | D23: Pelatihan penggunaan mesin braille embosser dengan fitur voice di Balai Literasi Braille Indonesia Abiyoso | E23: pkm Penugasan | F23: 2021 | G23: 2021 | H23: 3 | I23: PEMBERDAYAAN DESA/WILAYAH BINAAN | J23: =K23 -> 450000000 | K23: 450000000 | L23: ITTelkom Surabaya | M23: 7 | N23: Pengmas Kompetitif Internal | O23: Internal | P23: ID | Q23: Institut Telknologi Telkom Surabaya | R23: 6680651 | S23: Dimas Adiputra | T23: 0725059301 | U23: =K23/3 -> 150000000 | V23: Teknik Elektro | W23: FTE | X23: ITTelkom Surabaya | Y23: 8140 | Z23: 072019 | AA23: 6680687 | AB23: 702048705 | AC23: Wahyu Andy Prastyabudi | AD23: =K23/3 -> 150000000 | AH23: 6680623 | AI23: 0721088602 | AJ23: Yupit Sudianto | AK23: =K23/3 -> 150000000 | BR23: Proposal | BS23: Laporan Akhir | BT23: Moch. Bagus Indrastata | BV23: Annisa Putri Pratama | BW23: Teknik Industri, FTEIC, ITTelkom Surabaya | BX23: Sangaji Wicaksono | CK23: Publikasi Media Massa Nasional | CL23: Produk TTG | CM23: Media massa tayang, produk TTG sudah terpasang
A24: 17 | B24: REK.119/ABDI1/REK/V/2021 | C24: 1821/ABDI1/LPPM/VI/2021 | D24: Sosialisasi Crane Pemulasaraan Jenazah di RS Aisyiyah Kudus | E24: pkm Penugasan | F24: 2021 | G24: 2021 | H24: 3 | I24: PEMBERDAYAAN DESA/WILAYAH BINAAN | J24: =K24 -> 40000000 | K24: 40000000 | L24: ITTelkom Surabaya | M24: 7 | N24: Pengmas Kompetitif Internal | O24: Internal | P24: ID | Q24: Institut Telknologi Telkom Surabaya | R24: 6805206 | S24: Agus Sulistya | T24: 8920230021 | U24: =K24/4 -> 10000000 | V24: Rekayasa Perangkat Lunak | W24: FTII | X24: ITTelkom Surabaya | Y24: 8140 | Z24: 072019 | AA24: 6682174 | AB24: 0708069202 | AC24: Khodijah Amiroh | AD24: =K24/4 -> 10000000 | AE24: Teknologi Informasi | AF24: FTII | AG24: ITTelkom Surabaya | AH24: 6680628 | AI24: 0730058702 | AJ24: Fidi Wincoko Putro | AK24: =K24/4 -> 10000000 | AO24: 6680618 | AP24: 0725059202 | AQ24: Rahaditya Dimas Prihadianto | AR24: =K24/4 -> 10000000 | AS24: Teknik Industri | AT24: FTE | AU24: ITTelkom Surabaya | BR24: Proposal | BS24: Laporan Akhir | BT24: Amanda Amalia | BV24: Febri Purnama Putri
A25: 18 | B25: REK.087/SAM4/REK/III/2021 | C25: - | D25: Pengembangan industri dan wisata edukasi Kampung Pintar Suroboyo melalui Penerapan Teknologi Minim Kontak dengan Pendekatan Berbasis Kerakyatan | E25: Hibah BiMA Pemberdayaan Berbasis Masyarakat | F25: 2021 | G25: 2021 | H25: 5 | I25: INDUSTRI KREATIF DAN PENGEMBANGAN TEKNOLOGI MAJU | J25: =K25 -> 48800000 | K25: 48800000 | L25: ITTelkom Surabaya | M25: 7 | N25: Pengmas Kompetitif Internal | O25: Eksternal | Q25: Kemendiktisaintek | R25: 6680627 | S25: Benazir Imam Arif Muttawin | T25: 0703119301 | U25: =K25/2 -> 24400000 | V25: Teknik Industri | W25: FTII | X25: ITTelkom Surabaya | Y25: 8140 | Z25: 072019 | AC25: Anindya Rachma Dwicahyani | AH25: 6680708 | AI25: 0706069201 | AJ25: Lora Khaula Amifia | AK25: =K25/2 -> 24400000 | AL25: Teknik Elektro | AM25: FTE | AN25: ITTelkom Surabaya | BR25: Proposal | BS25: Laporan Akhir
A26: 19 | B26: REK.150/SAM4/REK/VIII/2021 | C26: 1381/ABDI1/LPPM/III/2021 | D26: Pengembangan Computerized Maintenance Management System di RSUD Tongas | E26: pkm reguler | F26: 2021 | G26: 2021 | H26: 5 | I26: INDUSTRI KREATIF DAN PENGEMBANGAN TEKNOLOGI MAJU | J26: =K26 -> 3456000 | K26: 3456000 | L26: ITTelkom Surabaya | M26: 7 | N26: Pengmas Kompetitif Internal | O26: Internal | Q26: Institut Telknologi Telkom Surabaya | R26: 6680683 | S26: Billy Montolalu | T26: 0729088704 | U26: =K26/2 -> 1728000 | V26: Rekayasa Perangkat Lunak | W26: FTII | X26: ITTelkom Surabaya | AA26: 6680629 | AB26: 0727048809 | AC26: Ubaidillah Umar | AD26: =K26/2 -> 1728000 | AE26: Teknik Komputer | AF26: FTE | AG26: ITTelkom Surabaya | BR26: Proposal | BS26: Laporan Akhir | BT26: Ahmad Habibi | BV26: Dimas Mahendra Budi Santosa | CK26: Publikasi Media Massa Nasional | CL26: Produk TTG | CM26: Publish 5 jurnal, produk android
A27: 20 | B27: REK.150/SAM4/REK/VIII/2021 | C27: 1382/ABDI1/LPPM/III/2021 | D27: Pelatihan Software Simulasi Livewire untuk Siswa SMK Telkom Cirebon Secara Online untuk Meningkatkan Sinergi antara Lembaga dibawah Yayasan Pendidikan Telkom | E27: pkm reguler | F27: 2021 | G27: 2021 | H27: 5 | I27: INDUSTRI KREATIF DAN PENGEMBANGAN TEKNOLOGI MAJU | J27: =K27 -> 1000000 | K27: 1000000 | L27: ITTelkom Surabaya | M27: 7 | N27: Pengmas Kompetitif Internal | O27: Internal | Q27: Institut Telknologi Telkom Surabaya | R27: 6680678 | S27: Dwi Edi Setyawan | T27: 0713068702 | U27: =K27/2 -> 500000 | V27: Teknik Komputer | W27: FTE | X27: ITTelkom Surabaya | AA27: 6680683 | AB27: 0729088704 | AC27: Billy Montolalu | AD27: =K27/2 -> 500000 | AE27: Rekayasa Perangkat Lunak | AF27: FTII | AG27: ITTelkom Surabaya | BR27: Proposal | BS27: Laporan Akhir | BT27: Royzaldo Aser Elegius Logo | CJ27: - | CK27: Video Kegiatan | CL27: - | CM27: Publish video youtube
A28: 21 | B28: REK.150/SAM4/REK/VIII/2021 | C28: - | D28: Implementasi Green Marketing pada Produk Urban Farming UMKM Lokal | E28: pkm Mandiri | F28: 2021 | G28: 2021 | H28: 5 | I28: INDUSTRI KREATIF DAN PENGEMBANGAN TEKNOLOGI MAJU | J28: 0 | K28: 5000000 | L28: ITTelkom Surabaya | M28: 7 | N28: Pengmas Kompetitif Internal | O28: Internal | Q28: Institut Telknologi Telkom Surabaya | S28: Tiar Anindya Putri | U28: =K28/2 -> 2500000 | AA28: 6801989 | AB28: 0704029302 | AC28: Sekar Widyasari Putri | AD28: =K28/2 -> 2500000 | AE28: Bisnis Digital | AF28: FTII | AG28: ITTelkom Surabaya | BR28: Proposal | BS28: Laporan Akhir | BT28: Fidelian Adinda Syafani | BU28: Teknik Industri, FTEIC, ITTelkom Surabaya | BV28: Hesti Dita Pramesti | BX28: Muhammad Miftahul Abidin | BY28: Teknik Industri, FTEIC, ITTelkom Surabaya | BZ28: Haifa Puji Rahayuningsih | CB28: Ni Wayan Ditapramesti | CD28: Muchammad Dzulfikar Alfani | CJ28: - | CK28: Publikasi Media Massa Nasional | CL28: Peningkatan Pemberdayaan Mitra | CM28: Media massa sudah terbit, kemasan baru ramah lingkungan
A29: 22 | B29: REK.150/SAM4/REK/VIII/2021 | C29: 1822/ABDI1/LPPM/VIII/2021 | D29: Website Usaha Ice Tube (Kenning Ice Tube) untuk Menunjang Pemasaran di Dunia Digital | E29: pkm Mandiri | F29: 2021 | G29: 2021 | H29: 5 | I29: INDUSTRI KREATIF DAN PENGEMBANGAN TEKNOLOGI MAJU | J29: 0 | K29: 5000000 | L29: ITTelkom Surabaya | M29: 7 | N29: Pengmas Kompetitif Internal | O29: Internal | Q29: Institut Telknologi Telkom Surabaya | R29: 6756318 | S29: Moh.Hamim Zajuli Al Faroby | T29: 0724079501 | U29: =K29/3 -> 1666666.7 | V29: Sains Data | W29: FTII | X29: ITTelkom Surabaya | AA29: 6778519 | AB29: 0712059303 | AC29: Nisa Isrofi | AD29: =K29/3 -> 1666666.7 | AE29: Teknik Logistik | AF29: FTE | AG29: ITTelkom Surabaya | AH29: 6793410 | AI29: 0707019501 | AJ29: Helisyah Nur Fadhilah | AK29: =K29/3 -> 1666666.7 | AL29: Sains Data | AM29: FTII | AN29: ITTelkom Surabaya | BR29: Proposal | BS29: Laporan Akhir | BT29: Rully Rosady | BU29: Teknologi Informasi, FTIB, ITTelkom Surabaya | BV29: Mochamad Fajar Nofriyandri | BW29: Teknologi Informasi, FTIB, ITTelkom Surabaya | BX29: Annisa Ainin Fadilah | BY29: Teknologi Informasi, FTIB, ITTelkom Surabaya | BZ29: Nabila Nur Amalia | CA29: Teknologi Informasi, FTIB, ITTelkom Surabaya | CB29: Berliana Amelia Ariyanti Zein | CC29: Teknologi Informasi, FTIB, ITTelkom Surabaya | CK29: Video Kegiatan, Publikasi Media Internal | CL29: Peningkatan Pemberdayaan Mitra | CM29: Publikasi online | CN29: Website UMKM | CO29: Dapat diakses
A30: 23 | B30: REK.150/SAM4/REK/VIII/2021 | C30: 1823/ABDI1/LPPM/VIII/2021 | D30: Tanda Tangan Elektronik Berbasis QR Code untuk Mempermudah Perizinan pada Masa Pandemi di Kantor Kecamatan Bulak Surabaya | E30: pkm Mandiri | F30: 2021 | G30: 2021 | H30: 5 | I30: PEMBERDAYAAN DESA/WILAYAH BINAAN | J30: 0 | K30: 5000000 | L30: ITTelkom Surabaya | M30: 7 | N30: Pengmas Kompetitif Internal | O30: Internal | Q30: Institut Telknologi Telkom Surabaya | R30: 6756318 | S30: Moh.Hamim Zajuli Al Faroby | T30: 0724079501 | U30: =K30/3 -> 1666666.7 | V30: Sains Data | W30: FTII | X30: ITTelkom Surabaya | AA30: 6778519 | AB30: 0712059303 | AC30: Nisa Isrofi | AD30: =K30/3 -> 1666666.7 | AE30: Teknik Logistik | AF30: FTE | AG30: ITTelkom Surabaya | AH30: 6793410 | AI30: 0707019501 | AJ30: Helisyah Nur Fadhilah | AK30: =K30/3 -> 1666666.7 | AL30: Sains Data | AM30: FTII | AN30: ITTelkom Surabaya | BR30: Proposal | BS30: Laporan Akhir | BT30: Rully Rosady | BU30: Teknologi Informasi, FTIB, ITTelkom Surabaya | BV30: Mochamad Fajar Nofriyandri | BW30: Teknologi Informasi, FTIB, ITTelkom Surabaya | BX30: Annisa Ainin Fadilah | BY30: Teknologi Informasi, FTIB, ITTelkom Surabaya | BZ30: Nabila Nur Amalia | CA30: Teknologi Informasi, FTIB, ITTelkom Surabaya | CB30: Berliana Amelia Ariyanti Zein | CC30: Teknologi Informasi, FTIB, ITTelkom Surabaya | CK30: Video Kegiatan, Publikasi Media Internal | CL30: Peningkatan Pemberdayaan Mitra | CN30: Publikasi Media Internal
A31: 24 | B31: REK.150/SAM4/REK/VIII/2021 | C31: - | D31: REDI (Rebranding dan Digitalisasi Pemasaran UMKM Mahda Collection) | E31: pkm Mandiri | F31: 2021 | G31: 2021 | H31: 5 | I31: INDUSTRI KREATIF DAN PENGEMBANGAN TEKNOLOGI MAJU | J31: 0 | K31: 4850000 | L31: ITTelkom Surabaya | M31: 7 | N31: Pengmas Kompetitif Internal | O31: Internal | Q31: Institut Telknologi Telkom Surabaya | R31: 6784457 | S31: Granita Hajar | T31: 0723079501 | V31: Teknik Logistik | W31: FTE | X31: ITTelkom Surabaya | AC31: Mawanda Almuhayar | BR31: Proposal | BS31: Laporan Akhir | BT31: Deny Satria Ardi | BU31: Teknologi Informasi, FTIB, ITTelkom Surabaya | BV31: Fitria Rahma Wulandari | BW31: Teknologi Informasi, FTIB, ITTelkom Surabaya | BX31: Alfito De Vega Mayavanny | BY31: Teknologi Informasi, FTIB, ITTelkom Surabaya | BZ31: Densa Tanzild Widyawantara D | CA31: Teknologi Informasi, FTIB, ITTelkom Surabaya | CB31: Naufal Ammar Badri | CC31: Teknologi Informasi, FTIB, ITTelkom Surabaya | CJ31: Jurnal Internal | CK31: Video Kegiatan | CL31: Peningkatan Pemberdayaan Mitra | CM31: Jurnal Accepted, video online, logo dan produk terlaksana
A32: 25 | B32: REK.150/SAM4/REK/VIII/2021 | C32: - | D32: Implementasi E-Marketing dengan Memanfaatkan E-Commerce dan Social Media dalam Transformasi Strategi Pemasaran untuk Urban Farming pada UMKM Lokal | E32: pkm Mandiri | F32: 2021 | G32: 2021 | H32: 5 | I32: INDUSTRI KREATIF DAN PENGEMBANGAN TEKNOLOGI MAJU | J32: 0 | K32: 5000000 | L32: ITTelkom Surabaya | M32: 7 | N32: Pengmas Kompetitif Internal | O32: Internal | Q32: Institut Telknologi Telkom Surabaya | S32: Bagas Putra Pradana | AC32: Rasyidi Faiz Akbar | BR32: Proposal | BS32: Laporan Akhir | BT32: Muhammad Faiq Farhan Rajwa | BV32: Yudith IqbalDika Permana | BX32: Annisa Rahma Ayuningtyas | BZ32: Emi Damayanti | CB32: Zara Hawiningrum | CD32: Nurul Hikmah Wildyansya | CJ32: - | CK32: Publikasi Media Massa Nasional | CL32: Peningkatan Pemberdayaan Mitra | CM32: Publikasi sudah terbit, e-commerce & social media account untuk mitra
A33: 26 | B33: REK.150/SAM4/REK/VIII/2021 | C33: - | D33: Rebranding Produk pada UMKM Ukusno Stemboat untuk Memperluas Area Pemasaran Saat Kondisi Pandemi COVID-19 | E33: pkm Mandiri | F33: 2021 | G33: 2021 | H33: 5 | I33: INDUSTRI KREATIF DAN PENGEMBANGAN TEKNOLOGI MAJU | J33: 0 | K33: 5000000 | L33: ITTelkom Surabaya | M33: 7 | N33: Pengmas Kompetitif Internal | O33: Internal | Q33: Institut Telknologi Telkom Surabaya | S33: Almira Ivah Edina | AA33: 6787821 | AB33: 0707029303 | AC33: Desita Nur Rachmaniar | AE33: Teknik Logistik | AF33: FTE | AG33: ITTelkom Surabaya | BR33: Proposal | BS33: Laporan Akhir | BT33: Durrotul Faiqoh | BU33: Sistem Informasi, FTIB, ITTelkom Surabaya | BV33: Siti Aminah | BW33: Sistem Informasi, FTIB, ITTelkom Surabaya | BX33: Desy Fitri Aulia Latuconsina | BY33: Sistem Informasi, FTIB, ITTelkom Surabaya | BZ33: Tyrela Disya Arivani | CA33: Sistem Informasi, FTIB, ITTelkom Surabaya | CB33: Nadiah Ratnaduhita | CC33: Sistem Informasi, FTIB, ITTelkom Surabaya | CD33: Adela Dewi Fortuna | CE33: Sistem Informasi, FTIB, ITTelkom Surabaya | CJ33: Jurnal Internal | CK33: Video Kegiatan | CL33: Peningkatan Pemberdayaan Mitra | CM33: Jurnal Accepted, video online, peningkatan besar pemberdayaan mitra
A34: 27 | B34: REK.150/SAM4/REK/VIII/2021 | C34: 1824/ABDI1/LPPM/VIII/2021 | D34: Bersihkan Hati dengan Berbagi, Kembangkan Masyarakat dari Faktor Ekonomi pada Bubur Ayam Teteh Lina | E34: pkm Mandiri | F34: 2021 | G34: 2021 | H34: 5 | I34: PEMBERDAYAAN DESA/WILAYAH BINAAN | J34: 0 | K34: 5575000 | L34: ITTelkom Surabaya | M34: 7 | N34: Pengmas Kompetitif Internal | O34: Internal | Q34: Institut Telknologi Telkom Surabaya | R34: 6760392 | S34: Amalia Nur Alifah | T34: 0729129403 | V34: Sains Data | W34: FTII | X34: ITTelkom Surabaya | AA34: 6756289 | AB34: 0725059501 | AC34: Nicko Nur Rakhmaddian | AE34: Teknik Logistik | AF34: FTEIC | AG34: ITTelkom Surabaya | BR34: Proposal | BS34: Laporan Akhir | BT34: Aisyah Pinky Marshanda | BV34: Beivenly Andrea Jayadiva S | BX34: Ihda Fauziyah | BZ34: Rahayu Nur Rochmah | CB34: Rimbi Titi Pinasti | CD34: Yulia Wahyu Ningsih | CJ34: Jurnal Internal | CK34: Video Kegiatan | CL34: Peningkatan Pemberdayaan Mitra | CM34: Video online
A35: 28 | B35: REK.150/SAM4/REK/VIII/2021 | C35: - | D35: Pembuatan Sistem Pengarsipan Posyandu Dinoyo Berbasis Website | E35: pkm Mandiri | F35: 2021 | G35: 2021 | H35: 5 | I35: PEMBERDAYAAN DESA/WILAYAH BINAAN | J35: 0 | K35: 5000000 | L35: ITTelkom Surabaya | M35: 7 | N35: Pengmas Kompetitif Internal | O35: Internal | Q35: Institut Telknologi Telkom Surabaya | R35: 6767777 | S35: Ahmad Wali Satria Bahari Johan | T35: 0713059501 | V35: Informatika | W35: FTII | X35: ITTelkom Surabaya | AA35: 6768348 | AB35: 0714079701 | AC35: Rizky Fenaldo Maulana | AE35: Informatika | AF35: FTII | AG35: ITTelkom Surabaya | AH35: 6773159 | AI35: 0706089501 | AJ35: Kharisma Monika Dian Pertiwi | AL35: Informatika | AM35: FTII | AN35: ITTelkom Surabaya | BR35: Proposal | BS35: Laporan Akhir | BT35: Akbar Tiar Afta Prabowo | BV35: Andhika Muhammad Prabowo | BX35: Kuncoro Manik Dharma Putra | BZ35: Anggara Widan Striawan | CB35: Thomas Adi Kusuma | CD35: Diana Puspita | CJ35: Jurnal Internal | CK35: Publikasi Media Massa Nasional | CL35: Produk TTG | CM35: Jurnal accepted, video online, produk website | CN35: Media massa | CO35: Published
A36: 29 | B36: REK.022/SAM4/REK/II/2021 | D36: Sistem Sterilisasi Udara pada Ruangan Tertutup Berbasis IOT | E36: Hibah Ayo Bikin Nyata (ABN) | F36: 2021 | G36: 2021 | H36: 8 | I36: PEMBERDAYAAN DESA/WILAYAH BINAAN | J36: 45000000 | K36: 45000000 | L36: ITTelkom Surabaya | M36: 7 | O36: Eksternal | Q36: CDC Telkom | R36: 6682174 | S36: Khodijah Amiroh | T36: 0708069202 | U36: =K36/3 -> 15000000 | V36: Teknologi Informasi | W36: FTII | X36: ITTelkom Surabaya | Y36: 8140 | Z36: 072019 | AA36: 6680633 | AB36: 0717017902 | AC36: Helmy Widyantara | AD36: =K36/3 -> 15000000 | AE36: Teknologi Informasi | AF36: FTII | AG36: ITTelkom Surabaya | AH36: 6681205 | AI36: 0705109002 | AJ36: Oktavia Ayu Permata | AK36: =K36/3 -> 15000000 | AL36: Teknologi Informasi | AM36: FTII | AN36: ITTelkom Surabaya | BR36: Proposal | BS36: Laporan Akhir
A37: 30 | B37: REK. 220/SAM4/REK/X/2021 | D37: Perancangan Mesin Pengering Rumpur Laut (Part of Smart Aquaculture Monitoring and Control System) untuk budidaya Rumput Laut di Kampung Rumput Laut Dusun Tanjungsari, Kabupaten Sidoarjo, Provinsi Jawa Timur | E37: pkm kerjasama | F37: 2021 | G37: 2021 | H37: 2 | I37: PEMBERDAYAAN DESA/WILAYAH BINAAN | J37: - | K37: 17500000 | L37: ITTelkom Surabaya | M37: 7 | O37: Eksternal | Q37: Institut Telknologi Telkom Surabaya | R37: 6680726 | S37: Arliyanti Nurdin | T37: 719069101 | BR37: Proposal | BS37: Laporan Akhir | BT37: Naufal Ammar Badri | BU37: Teknologi Informasi, FTIB, ITTelkom Surabaya | BV37: Mochamad Fajar Nofriyandri | BW37: Teknologi Informasi, FTIB, ITTelkom Surabaya | BX37: Alfito De Vaga Mayavanny | BY37: Teknologi Informasi, FTIB, ITTelkom Surabaya
A39: 1 | B39: REK.070/ABDI1/REK/II/2022 | C39: 385/ABDI1/LPPM/II/2022 | D39: Sistem Pengawasan Kualitas Air Tambak Budidaya Lobster Untuk Meningkatkan Perkembangbiakan Lobster Berbasis IoT Sebagai Upaya Pengembangan Pusat Riset UMKM Budidaya Lebster di Jawa Timur | E39: Pengmas Berbasis Penelitian | F39: 2022 | G39: 2022 | I39: INDUSTRI KREATIF DAN PENERAPAN TEKNOLOGI MAJU | K39: 16408500 | L39: ITTelkom Surabaya | M39: 7 | N39: Pengmas Kompetitif Internal | O39: Internal | P39: ID | Q39: Institut Telknologi Telkom Surabaya | R39: 6099359 | S39: Mochamad Nizar Palefi Ma'ady | T39: 0708119103 | U39: =K39/4 -> 4102125 | V39: Sistem Informasi | W39: FTIB | X39: ITTelkom Surabaya | AA39: 6680623 | AB39: 0721088602 | AC39: Yupit Sudianto | AD39: =U39 -> 4102125 | AE39: Sistem Informasi | AF39: FTIB | AG39: ITTelkom Surabaya | AH39: 6680633 | AI39: 0717017902 | AJ39: Helmy Widyantara | AK39: =U39 -> 4102125 | AL39: Teknologi Informasi | AM39: FTIB | AN39: ITTelkom Surabaya | AO39: 6680629 | AP39: 0727048809 | AQ39: Ubaidillah Umar | AR39: =U39 -> 4102125 | AS39: Teknik Komputer | AT39: FTEIC | BR39: Proposal | BS39: Laporan Akhir | BT39: Denny Daffa Rizaldy | BV39: Bintang Marwan Putra Pradana | CJ39: Prosiding Internasional (ICAITI) | CM39: Accepted
A40: 2 | B40: REK.070/ABDI1/REK/II/2022 | C40: 386/ABDI1/LPPM/II/2022 | D40: PENGEMBANGAN WEBSITE KAMPUNG WISATA EDUKASI (STUDI KASUS KAMPUNG ONDOMOHEN SURABAYA) | E40: pkm reguler | F40: 2022 | G40: 2022 | I40: INDUSTRI KREATIF DAN PENERAPAN TEKNOLOGI MAJU | K40: 6000000 | L40: ITTelkom Surabaya | M40: 7 | N40: Pengmas Kompetitif Internal | O40: Internal | P40: ID | Q40: Institut Telknologi Telkom Surabaya | R40: 6768348 | S40: Rizky Fenaldo Maulana | T40: 0714079701 | U40: =K40/3 -> 2000000 | V40: Informatika | W40: FTIB | X40: ITTelkom Surabaya | AA40: 6773159 | AB40: 0706089501 | AC40: Kharisma Monika Dian Pertiwi | AD40: =U40 -> 2000000 | AE40: Informatika | AF40: FTIB | AG40: ITTelkom Surabaya | AH40: 6785861 | AI40: 0730049402 | AJ40: Riza Akhsani Setyo Prayoga | AK40: =U40 -> 2000000 | AL40: Sistem Informasi | AM40: FTIB | AN40: ITTelkom Surabaya | BR40: Proposal | BS40: Laporan Akhir | BT40: Taufiqur Rahman | BU40: Bisnis Digital, FTIB, ITTelkom Surabaya | BV40: Elma Saskia Mawardi | BW40: Informatika, FTIB, ITTelkom Surabaya | BX40: Daniel Dabra Pasongli | BY40: Informatika, FTIB, ITTelkom Surabaya | CJ40: Jurnal Nasional Terakreditasi | CK40: Publikasi Media Massa Nasional | CL40: Peningkatan Pemberdayaan Mitra | CM40: Jurnal Published
A41: 3 | B41: REK.070/ABDI1/REK/II/2022 | C41: 387/ABDI1/LPPM/II/2022 | D41: Optimalisasi Panel Surya sebagai Pembangkit Listrik Alternatif untuk Meleyani Kebutuhan Listrik Masyarakat Kampung Oase Ondomohen | E41: pkm reguler | F41: 2022 | G41: 2022 | I41: PEMBERDAYAAN DESA ATAU WILAYAH BINAAN | K41: 7000000 | L41: ITTelkom Surabaya | M41: 7 | N41: Pengmas Kompetitif Internal | O41: Internal | P41: ID | Q41: Institut Telknologi Telkom Surabaya | R41: 6680708 | S41: Lora Khaula Amifia | T41: 0706069201 | U41: =K41/3 -> 2333333.3 | V41: Teknik Elektro | W41: FTEIC | X41: ITTelkom Surabaya | AA41: 258471 | AB41: 0727097302 | AC41: Susijanto Tri Rasmana | AD41: =U41 -> 2333333.3 | AE41: Teknik Elektro | AF41: FTEIC | AG41: ITTelkom Surabaya | AH41: 6680685 | AI41: 0721068802 | AJ41: Moch. Iskandar Riansyah | AK41: =U41 -> 2333333.3 | AL41: Teknik Elektro | AM41: FTEIC | AN41: ITTelkom Surabaya | BR41: Proposal | BS41: Laporan Akhir | BT41: Tiur Imanuela Ayu Larasati Wibowo | BV41: Mohammad Fahmi Ilmi Yogianto | BX41: Hernadimas Alfattah | CJ41: Jurnal Nasional ber-ISSN | CK41: Publikasi Media Massa Nasional | CL41: Produk TTG | CM41: Jurnal published, publikasi media massa online, produk finished | CN41: HKI
A42: 4 | B42: REK.070/ABDI1/REK/II/2022 | C42: 388/ABDI1/LPPM/II/2022 | D42: Pembuatan Sistem Manajemen Aset Wakaf Untuk Yayasan Al-Manar 1989 Babatan Pilang Wiyung Surabaya | E42: pkm reguler | F42: 2022 | G42: 2022 | I42: PEMBERDAYAAN DESA ATAU WILAYAH BINAAN | K42: 6425000 | L42: ITTelkom Surabaya | M42: 7 | N42: Pengmas Kompetitif Internal | O42: Internal | P42: ID | Q42: Institut Telknologi Telkom Surabaya | R42: 6681205 | S42: Oktavia Ayu Permata | T42: 0705109002 | U42: =K42/3 -> 2141666.7 | V42: Teknologi Informasi | W42: FTIB | X42: ITTelkom Surabaya | AA42: 6680664 | AB42: 0715128708 | AC42: Farah Zakiyah Rahmanti | AD42: =U42 -> 2141666.7 | AE42: Teknologi Informasi | AF42: FTIB | AG42: ITTelkom Surabaya | AH42: 6680680 | AI42: 0704039202 | AJ42: Bernadus Anggo Seno Aji | AK42: =U42 -> 2141666.7 | AL42: Teknologi Informasi | AM42: FTIB | AN42: ITTelkom Surabaya | BR42: Proposal | BS42: Laporan Akhir | BT42: Naufal Ammar Badri | BU42: Teknologi Informasi, FTIB, ITTelkom Surabaya | BV42: Muhammad Ma'sum Juniyanto | BW42: Teknologi Informasi, FTIB, ITTelkom Surabaya | BX42: Alfito De Vaga Mayavanny | BY42: Teknologi Informasi, FTIB, ITTelkom Surabaya | CJ42: Jurnal Nasional Terakreditasi | CK42: Publikasi Media Massa Nasional | CL42: Peningkatan Pemberdayaan Mitra | CM42: Akhir Pelunasan: TW II
A43: 5 | B43: REK.070/ABDI1/REK/II/2022 | C43: 389/ABDI1/LPPM/II/2022 | D43: Pendampingan Penyusunan Pembukuan Dan Laporan Keuangan Untuk UKM Di Kota Surabaya | E43: pkm reguler | F43: 2022 | G43: 2022 | I43: INDUSTRI KREATIF DAN PENERAPAN TEKNOLOGI MAJU | K43: 7000000 | L43: ITTelkom Surabaya | M43: 7 | N43: Pengmas Kompetitif Internal | O43: Internal | P43: ID | Q43: Institut Telknologi Telkom Surabaya | R43: 6681051 | S43: Rizqa Amelia Zunaidi | T43: 0711069301 | U43: =K43/3 -> 2333333.3 | V43: Teknik Industri | W43: FTEIC | X43: ITTelkom Surabaya | AA43: 6658545 | AB43: 0401078801 | AC43: Ayu Endah Wahyuni | AD43: =U43 -> 2333333.3 | AE43: Teknik Industri | AF43: FTEIC | AG43: ITTelkom Surabaya | AH43: 6680618 | AI43: 0725059202 | AJ43: Rahaditya Dimas Prihadianto | AK43: =U43 -> 2333333.3 | AL43: Teknik Industri | AM43: FTEIC | AN43: ITTelkom Surabaya | BR43: Proposal | BS43: Laporan Akhir | BT43: Yashmine Mela Ardianto | BV43: Hendrawan Widianto | BW43: Teknik Industri, FTEIC, ITTelkom Surabaya | BX43: Firli Tajtibra | CJ43: Jurnal Nasional ber-ISSN | CK43: Publikasi Media Massa Nasional | CL43: Peningkatan Pemberdayaan Mitra | CM43: Publikasi published, produk finished
A44: 6 | B44: REK.070/ABDI1/REK/II/2022 | C44: 390/ABDI1/LPPM/II/2022 | D44: Pengembangan Wisata Kampung Hijau Dan Pengelolahan Sampah Makanan Warga Untuk Budidaya Magot Menjadi Pakan Ikan Di Kampung Ondomohen Magersari Surabaya | E44: pkm reguler | F44: 2022 | G44: 2022 | I44: PEMBERDAYAAN DESA ATAU WILAYAH BINAAN | K44: 7000000 | L44: ITTelkom Surabaya | M44: 7 | N44: Pengmas Kompetitif Internal | O44: Internal | P44: ID | Q44: Institut Telknologi Telkom Surabaya | R44: 6680641 | S44: Ardiansyah Al Farouq | T44: 0714029301 | U44: =K44/3 -> 2333333.3 | V44: Teknik Komputer | W44: FTEIC | X44: ITTelkom Surabaya | AA44: 6680618 | AB44: 0725059202 | AC44: Rahaditya Dimas Prihadianto | AD44: =U44 -> 2333333.3 | AE44: Teknik Industri | AF44: FTEIC | AG44: ITTelkom Surabaya | AH44: 6680678 | AI44: 0713068702 | AJ44: Dwi Edi Setyawan | AK44: =U44 -> 2333333.3 | AL44: Teknik Komputer | AM44: FTEIC | AN44: ITTelkom Surabaya | BR44: Proposal | BS44: Laporan Akhir | BT44: Ahmad Habibi | BV44: Dimas Mahendra | BX44: Silvi Prastiwi | CJ44: Jurnal Nasional ber-ISSN | CK44: Publikasi Media Massa Nasional | CL44: Produk TTG | CM44: Jurnal Published, Video kegiatan dan media massa published, peningkatan keterampilan mitra
A45: 7 | B45: REK.070/ABDI1/REK/II/2022 | C45: 391/ABDI1/LPPM/II/2022 | D45: PKM Aplikasi Bergerak Untuk Pemesanan Air Minum Isi Ulang Pada Depo Bahagia | E45: pkm reguler | F45: 2022 | G45: 2022 | I45: INDUSTRI KREATIF DAN PENERAPAN TEKNOLOGI MAJU | K45: 6900000 | L45: ITTelkom Surabaya | M45: 7 | N45: Pengmas Kompetitif Internal | O45: Internal | P45: ID | Q45: Institut Telknologi Telkom Surabaya | R45: 6764236 | S45: Rokhmatul Insani | T45: 0704068902 | U45: =K45/3 -> 2300000 | V45: Sistem Informasi | W45: FTIB | X45: ITTelkom Surabaya | AA45: 6744406 | AB45: 0709059004 | AC45: Muhammad Nasrullah | AD45: =U45 -> 2300000 | AE45: Sistem Informasi | AF45: FTIB | AG45: ITTelkom Surabaya | AH45: 6680634 | AI45: 0725059004 | AJ45: Noerma Pudji Istyanto | AK45: =U45 -> 2300000 | AL45: Sistem Informasi | AM45: FTIB | AN45: ITTelkom Surabaya | BR45: Proposal | BS45: Laporan Akhir | BT45: Tyrela Disya Arivani | BU45: Sistem Informasi, FTIB, ITTelkom Surabaya | BV45: Tasya Andini Tesalonika | CJ45: Jurnal Nasional Terakreditasi | CK45: Publikasi Media Massa Nasional | CL45: Produk TTG | CM45: Jurnal published, publikasi media massa published
A46: 8 | B46: REK.070/ABDI1/REK/II/2022 | C46: 392/ABDI1/LPPM/II/2022 | D46: Pelatihan Online Streaming Pengajian Bagi Pengurus Langgar Al-Qodir | E46: pkm reguler | F46: 2022 | G46: 2022 | I46: INDUSTRI KREATIF DAN PENERAPAN TEKNOLOGI MAJU | K46: 6000000 | L46: ITTelkom Surabaya | M46: 7 | N46: Pengmas Kompetitif Internal | O46: Internal | P46: ID | Q46: Institut Telknologi Telkom Surabaya | R46: 6682794 | S46: Pangestu Widodo | T46: 0721058310 | U46: =K46/2 -> 3000000 | V46: Rekayasa Perangkat Lunak | W46: FTIB | X46: ITTelkom Surabaya | AA46: 6680626 | AB46: 0727099201 | AC46: Ardian Yusuf Wicaksono | AD46: =U46 -> 3000000 | AE46: Informatika | AF46: FTIB | AG46: ITTelkom Surabaya | BR46: Proposal | BS46: Laporan Akhir | BT46: Muhammad Nafi Udin | BU46: Rekayasa Perangkat Lunak, FTIB, ITTelkom Surabaya | BV46: Damasya Ine Larisa | BW46: Rekayasa Perangkat Lunak, FTIB, ITTelkom Surabaya | CJ46: Jurnal Nasional ber-ISSN | CK46: Publikasi Media Massa Nasional | CL46: Produk TTG | CM46: Jurnal published, publikasi media massa published | CN46: Video dokumentasi | CO46: Published
A47: 9 | B47: REK.070/ABDI1/REK/II/2022 | C47: 393/ABDI1/LPPM/II/2022 | D47: Pemanfaatan Teknologi Smart Farming Untuk Meningkatkan Efisiensi Budidaya Janur Di Kelompok Tani Elok Mekar Sari Surabaya | E47: pkm reguler | F47: 2022 | G47: 2022 | I47: PEMBERDAYAAN DESA ATAU WILAYAH BINAAN | K47: 7000000 | L47: ITTelkom Surabaya | M47: 7 | N47: Pengmas Kompetitif Internal | O47: Internal | P47: ID | Q47: Institut Telknologi Telkom Surabaya | R47: 6680625 | S47: Nilla Rachmaningrum | T47: 0408067804 | U47: =K47/3 -> 2333333.3 | V47: Teknik Telekomunikasi | W47: FTEIC | X47: ITTelkom Surabaya | AA47: 6724784 | AB47: 722119101 | AC47: Fannush Shofi Akbar | AD47: =U47 -> 2333333.3 | AE47: Teknik Telekomunikasi | AF47: FTEIC | AG47: ITTelkom Surabaya | AH47: 6680741 | AI47: 0727059002 | AJ47: Hamzah Ulinuha Mustakim | AK47: =U47 -> 2333333.3 | AL47: Teknik Telekomunikasi | AM47: FTEIC | AN47: ITTelkom Surabaya | BR47: Proposal | BS47: Laporan Akhir | BT47: Rizky Maulana Syafi' Zamhari | BV47: Syammas Muhyiddin | CJ47: Jurnal Nasional ber-ISSN | CK47: Publikasi Media Massa Nasional | CL47: Peningkatan Pemberdayaan Mitra | CM47: Jurnal published, Media massa published
A48: 10 | B48: REK.070/ABDI1/REK/II/2022 | C48: 394/ABDI1/LPPM/II/2022 | D48: Pemanfaatan Teknologi Gelombang Bunyi Sebagai Salah Satu Alternatif Penambahan Hotspot Berkumpulnya Ikan Bagi Nelayan Pesisir Pantai Kenjeran, Kota Surabaya | E48: pkm reguler | F48: 2022 | G48: 2022 | I48: PEMBERDAYAAN DESA ATAU WILAYAH BINAAN | K48: 6500000 | L48: ITTelkom Surabaya | M48: 7 | N48: Pengmas Kompetitif Internal | O48: Internal | P48: ID | Q48: Institut Telknologi Telkom Surabaya | R48: 6680645 | S48: Walid Maulana Hadiansyah | T48: 0713108902 | U48: =K48/3 -> 2166666.7 | V48: Teknik Telekomunikasi | W48: FTEIC | X48: ITTelkom Surabaya | AA48: 6680625 | AB48: 0408067804 | AC48: Nilla Rachmaningrum | AD48: =U48 -> 2166666.7 | AE48: Teknik Telekomunikasi | AF48: FTEIC | AG48: ITTelkom Surabaya | AH48: 6829130 | AI48: 0720019102 | AJ48: Risdilah Mimma Untsa | AK48: =U48 -> 2166666.7 | AL48: Teknik Telekomunikasi | AM48: FTEIC | AN48: ITTelkom Surabaya | BR48: Proposal | BS48: Laporan Akhir | BT48: Rian Gunawan | CJ48: Jurnal Nasional ber-ISSN | CK48: Publikasi Media Massa Nasional | CL48: Peningkatan Pemberdayaan Mitra | CM48: Akhir pelunasan: TW II, Publikasi published, produk finished
A49: 11 | B49: REK.070/ABDI1/REK/II/2022 | C49: 395/ABDI1/LPPM/II/2022 | D49: Pengembangan Aplikasi Penjualan Dan Proyek Pada Koperasi Pegawai Institut Teknologi Telkom Hita Loka Tara | E49: pkm reguler | F49: 2022 | G49: 2022 | I49: INDUSTRI KREATIF DAN PENERAPAN TEKNOLOGI MAJU | K49: 6955000 | L49: ITTelkom Surabaya | M49: 7 | N49: Pengmas Kompetitif Internal | O49: Internal | P49: ID | Q49: Institut Telknologi Telkom Surabaya | R49: 6680628 | S49: Fidi Wincoko Putro | T49: 0730058702 | U49: =K49/1 -> 6955000 | V49: Rekayasa Perangkat Lunak | W49: FTIB | X49: ITTelkom Surabaya | BR49: Proposal | BS49: Laporan Akhir | BT49: Muhammad Ath Thariq Luqmana | BU49: Rekayasa Perangkat Lunak, FTIB, ITTelkom Surabaya | BV49: Mochammad Ihza Rizky Karim | BW49: Sistem Informasi, FTIB, ITTelkom Surabaya | BX49: Bagus Cahyo Sulistiyo | CJ49: Jurnal Nasional ber-ISSN | CM49: Akhir Pelunasan: TW III
A50: 12 | B50: REK.070/ABDI1/REK/II/2022 | C50: 396/ABDI1/LPPM/II/2022 | D50: Pelatihan Implementasi Green Marketing Dan Digital Marketing Memanfaatkan Social Media dan E- Comerce Untuk UMKM | E50: pkm reguler | F50: 2022 | G50: 2022 | I50: INDUSTRI KREATIF DAN PENERAPAN TEKNOLOGI MAJU | K50: 6671000 | L50: ITTelkom Surabaya | M50: 7 | N50: Pengmas Kompetitif Internal | O50: Internal | P50: ID | Q50: Institut Telknologi Telkom Surabaya | R50: 6801989 | S50: Sekar Widyasari Putri | T50: 0704029302 | U50: =K50/3 -> 2223666.7 | V50: Bisnis Digital | W50: FTIB | X50: ITTelkom Surabaya | AC50: Tiar Anindya Putri | AD50: =U50 -> 2223666.7 | AG50: ITTelkom Surabaya | AH50: 6767777 | AI50: 0713059501 | AJ50: Ahmad Wali Satria Bahari Johan | AK50: =U50 -> 2223666.7 | AL50: Informatika | AM50: FTIB | AN50: ITTelkom Surabaya | BR50: Proposal | BS50: Laporan Akhir | BT50: Jenny Ghifrina Putri S. | BV50: M. Ghouzul A'Dhom | BW50: Bisnis Digital, FTIB, ITTelkom Surabaya | BX50: Vagnes Angela F. | CJ50: Jurnal Nasional Terakreditasi | CK50: Publikasi Media Massa Nasional | CL50: Peningkatan Pemberdayaan Mitra | CM50: Jurnal published, Publikasi published
A51: 13 | B51: REK.070/ABDI1/REK/II/2022 | C51: 397/ABDI1/LPPM/II/2022 | D51: PKM EYED ( EDUCATION YOUTH OF ENTREPRENEURS) PROGRAM PEMANFAATAN IT UNTUK MENINGKATKAN PRODUKTIF DAN EKONOMI MASYARAKAT DI SEPANJANG ASRI PASKA PANDEMI COVID-19 | E51: pkm reguler | F51: 2022 | G51: 2022 | I51: PEMBERDAYAAN DESA ATAU WILAYAH BINAAN | K51: 7000000 | L51: ITTelkom Surabaya | M51: 7 | N51: Pengmas Kompetitif Internal | O51: Internal | P51: ID | Q51: Institut Telknologi Telkom Surabaya | R51: 6680634 | S51: Noerma Pudji Istyanto | T51: 0725059004 | U51: =K51/3 -> 2333333.3 | V51: Sistem Informasi | W51: FTIB | X51: ITTelkom Surabaya | AA51: 6744406 | AB51: 0709059004 | AC51: Muhammad Nasrullah | AD51: =U51 -> 2333333.3 | AE51: Sistem Informasi | AF51: FTIB | AG51: ITTelkom Surabaya | AH51: 6764236 | AI51: 0704068902 | AJ51: Rokhmatul Insani | AK51: =U51 -> 2333333.3 | AL51: Sistem Informasi | AM51: FTIB | AN51: ITTelkom Surabaya | BR51: Proposal | BS51: Laporan Akhir | BT51: Yuni Qoriah Verdiana | BU51: Sistem Informasi, FTIB, ITTelkom Surabaya | BV51: Rizki Afifatus Sa'diyah | BX51: M Dawud Emerulloh | CJ51: Jurnal Nasional ber-ISSN | CK51: Publikasi Media Massa Nasional | CL51: Peningkatan Pemberdayaan Mitra | CM51: Jurnal published, media massa published, peningkatan mitra
A52: 14 | B52: REK.070/ABDI1/REK/II/2022 | C52: 398/ABDI1/LPPM/II/2022 | D52: Penerapan QRcode Pada Sistem Digitalisasi Produk Dan Hasil Inovasi Dan Tanaman Di Kampung Oase Odomohen | E52: pkm reguler | F52: 2022 | G52: 2022 | I52: INDUSTRI KREATIF DAN PENERAPAN TEKNOLOGI MAJU | K52: 5570000 | L52: ITTelkom Surabaya | M52: 7 | N52: Pengmas Kompetitif Internal | O52: Internal | P52: ID | Q52: Institut Telknologi Telkom Surabaya | R52: 6680648 | S52: Hawwin Mardhiana | T52: 0724089201 | U52: =K52/3 -> 1856666.7 | V52: Sistem Informasi | W52: FTIB | X52: ITTelkom Surabaya | AA52: 6665306 | AB52: 0703129001 | AC52: Ully Asfari | AD52: =U52 -> 1856666.7 | AE52: Sistem Informasi | AF52: FTIB | AG52: ITTelkom Surabaya | AH52: 6801883 | AI52: 0720088905 | AJ52: Aris Kusumawati | AK52: =U52 -> 1856666.7 | AL52: Sistem Informasi | AM52: FTIB | AN52: ITTelkom Surabaya | BR52: Proposal | BS52: Laporan Akhir | BT52: Ahmad Ihsan Fuady | BV52: Nauvaldy Virgiawan | CJ52: Jurnal Nasional Terakreditasi | CK52: Video Kegiatan | CL52: Peningkatan Pemberdayaan Mitra | CM52: Akhir pelunasan: April 2023, minggu 2. submit ulang
A53: 15 | B53: REK.070/ABDI1/REK/II/2022 | C53: 399/ABDI1/LPPM/II/2022 | D53: Strategi Peningkatan Pemasaran dan Penjualan Produk Olahan Buah Mangrove Melalui Pembuatan Website | E53: pkm reguler | F53: 2022 | G53: 2022 | I53: INDUSTRI KREATIF DAN PENERAPAN TEKNOLOGI MAJU | K53: 7000000 | L53: ITTelkom Surabaya | M53: 7 | N53: Pengmas Kompetitif Internal | O53: Internal | P53: ID | Q53: Institut Telknologi Telkom Surabaya | R53: 6680629 | S53: Ubaidillah Umar | T53: 0727048809 | U53: =K53/3 -> 2333333.3 | V53: Teknik Komputer | W53: FTEIC | X53: ITTelkom Surabaya | AA53: 6663582 | AB53: 0303069102 | AC53: Aulia Rahma Annisa | AD53: =U53 -> 2333333.3 | AE53: Teknik Komputer | AF53: FTEIC | AG53: ITTelkom Surabaya | AH53: 6680633 | AI53: 0717017902 | AJ53: Helmy Widyantara | AK53: =U53 -> 2333333.3 | AL53: Teknologi Informasi | AM53: FTIB | AN53: ITTelkom Surabaya | BR53: Proposal | BS53: Laporan Akhir | BT53: Gempar Alamsyah | BV53: Ari Candra Rahmanaga | BX53: Aliffianto Nur Huda | CJ53: - | CK53: Publikasi Media Massa Nasional | CL53: Peningkatan Pemberdayaan Mitra | CM53: Akhir pelunasan: TW III, Publikasi published
A54: 16 | B54: REK.070/ABDI1/REK/II/2022 | C54: - | D54: Pelatihan Pengembangan Inovasi Bisnis Digital Berbasis Web Untuk Meningkatkan Daya Saing SMK Di Jatim | E54: pkm Penugasan | F54: 2022 | G54: 2022 | I54: INDUSTRI KREATIF DAN PENERAPAN TEKNOLOGI MAJU | K54: 10000000 | L54: ITTelkom Surabaya | M54: 7 | N54: Pengmas Kompetitif Internal | O54: Internal | P54: ID | Q54: Institut Telknologi Telkom Surabaya | R54: 6680687 | S54: Wahyu Andy Prastyabudi | T54: 0702048705 | U54: =K54/3 -> 3333333.3 | V54: Teknik Industri | W54: FTEIC | X54: ITTelkom Surabaya | AA54: 6680698 | AB54: 0709128101 | AC54: Mohammad Sholik | AD54: =U54 -> 3333333.3 | AE54: Rekayasa Perangkat Lunak | AF54: FTIB | AG54: ITTelkom Surabaya | AH54: 259781 | AI54: 0710028604 | AJ54: Titus Kristanto | AK54: =U54 -> 3333333.3 | AL54: Rekayasa Perangkat Lunak | AM54: FTIB | AN54: ITTelkom Surabaya | BR54: Proposal | BS54: Laporan Akhir | CJ54: Jurnal Nasional ber-ISSN | CM54: Jurnal published
A55: 17 | B55: REK.070/ABDI1/REK/II/2022 | C55: 925/ABDI1/LPPM/VII/2022 | D55: Pembentukan Kelompok Usaha dan Strategi Branding untuk Membentuk Identitas Brand | E55: pkm reguler | F55: 2022 | G55: 2022 | I55: PEMBERDAYAAN DESA/WILAYAH BINAAN | K55: 6971250 | L55: ITTelkom Surabaya | M55: 7 | N55: Pengmas Kompetitif Internal | O55: Internal | P55: ID | Q55: Institut Telknologi Telkom Surabaya | R55: 6787821 | S55: Desita Nur Rachmaniar | T55: 0707029303 | U55: =K55/2 -> 3485625 | V55: Teknik Logistik | W55: FTEIC | X55: ITTelkom Surabaya | AA55: 6778519 | AB55: 0712059303 | AC55: Nisa Isrofi | AD55: =U55 -> 3485625 | AE55: Teknik Logistik | AF55: FTEIC | AG55: ITTelkom Surabaya | BR55: Proposal | BS55: Laporan Akhir | BT55: Riris Ainur Rosidah | BV55: Lovina Amil Hasanah | BX55: Muhammad Farhan Abdillah Sholeh | CJ55: Jurnal Internal | CK55: Video Kegiatan | CL55: Peningkatan Pemberdayaan Mitra | CM55: Jurnal published
A56: 18 | B56: REK.124/ABDI1/REK/VII/2022 | C56: 926/ABDI1/LPPM/VII/2022 | D56: Pelatihan Pemanfaatan Fintech Lending Dan Payment pada UMKM | E56: pkm reguler | F56: 2022 | G56: 2022 | I56: INDUSTRI KREATIF DAN PENGEMBANGAN TEKNOLOGI MAJU | K56: 6941000 | L56: ITTelkom Surabaya | M56: 7 | N56: Pengmas Kompetitif Internal | O56: Internal | P56: ID | Q56: Institut Telknologi Telkom Surabaya | R56: 6727245 | S56: Darlin Aulia | T56: 0309069201 | U56: =K56/2 -> 3470500 | V56: Bisnis Digital | W56: FTIB | X56: ITTelkom Surabaya | AA56: 6843682 | AB56: 0708128901 | AC56: Caesareano Lafado Yesa | AD56: =U56 -> 3470500 | AE56: Sains Data | AF56: FTIB | AG56: ITTelkom Surabaya | AJ56: Achmad Yanu Alif Fianto | AK56: 0 | BR56: Proposal | BS56: Laporan Akhir | BT56: Tsalits Agnita Ulfatun Nisa | BV56: Gadis Artha Mevia Eka Agusty | BX56: Nada’ Alfi Nabila | BZ56: Tsabita Imtiyaz | CJ56: Jurnal Nasional ber-ISSN | CK56: Video Kegiatan | CL56: Peningkatan Pemberdayaan Mitra | CM56: Jurnal published, media massa published, ekosistem fintech berkelanjutan
A57: 19 | B57: REK.124/ABDI1/REK/VII/2022 | C57: 927/ABDI1/LPPM/VII/2022 | D57: Pengembangan Kampung Wisata Edukasi dengan Penerapan Teknologi dan Pemberdayaan Masyarakat Di Kampoeng Songo Surabaya | E57: pkm reguler | F57: 2022 | G57: 2022 | I57: INDUSTRI KREATIF DAN PENGEMBANGAN TEKNOLOGI MAJU | K57: 7000000 | L57: ITTelkom Surabaya | M57: 7 | N57: Pengmas Kompetitif Internal | O57: Internal | P57: ID | Q57: Institut Telknologi Telkom Surabaya | R57: 6680698 | S57: Mohammad Sholik | T57: 0709128101 | U57: =K57/3 -> 2333333.3 | V57: Rekayasa Perangkat Lunak | W57: FTIB | X57: ITTelkom Surabaya | AA57: 259781 | AB57: 0710028604 | AC57: Titus Kristanto | AD57: =U57 -> 2333333.3 | AE57: Rekayasa Perangkat Lunak | AF57: FTIB | AG57: ITTelkom Surabaya | AH57: 6680622 | AI57: 0709039401 | AJ57: Dewi Rahmawati | AK57: =U57 -> 2333333.3 | AL57: Rekayasa Perangkat Lunak | AM57: FTIB | AN57: ITTelkom Surabaya | BR57: Proposal | BS57: Laporan Akhir | BT57: Nursyahjaya Ramadaniputra | BV57: Rizky Agung Prayogi | BX57: M Syarif Hidayatullah | CJ57: Jurnal Nasional ber-ISSN | CK57: Publikasi Media Massa Nasional | CL57: Peningkatan Pemberdayaan Mitra
A58: 20 | B58: REK.124/ABDI1/REK/VII/2022 | C58: 928/ABDI1/LPPM/VII/2022 | D58: Pengembangan WebProfile pada Usaha Furniture Surabaya (Studi Kasus UD. Rozi Rohmad) | E58: pkm reguler | F58: 2022 | G58: 2022 | I58: INDUSTRI KREATIF DAN PENGEMBANGAN TEKNOLOGI MAJU | K58: 6000000 | L58: ITTelkom Surabaya | M58: 7 | N58: Pengmas Kompetitif Internal | O58: Internal | P58: ID | Q58: Institut Telknologi Telkom Surabaya | R58: 6785861 | S58: Riza Akhsani Setyo Prayoga | T58: 0730049402 | U58: =K58/3 -> 2000000 | V58: Bisnis Digital | W58: FTIB | X58: ITTelkom Surabaya | AA58: 6768348 | AB58: 0714079701 | AC58: Rizky Fenaldo Maulana | AD58: =U58 -> 2000000 | AE58: Informatika | AF58: FTIB | AG58: ITTelkom Surabaya | AH58: 6756289 | AI58: 0725059501 | AJ58: Nicko Nur Rakhmaddian | AK58: =U58 -> 2000000 | AL58: Teknik Logistik | AM58: FTEIC | AN58: ITTelkom Surabaya | BR58: Proposal | BS58: Laporan Akhir | BT58: Tracy Olivia | BV58: Fajrul Fallah Arrafi | BX58: Devandro Alifiano | CJ58: Jurnal Nasional Terakreditasi | CM58: Jurnal published
